Workbook

Sheet Reports
A1: Aton Aire Trading Corporation
A2: 2026 | B2: January | C2: February | D2: March | E2: April
A3: Operation
A4: Sales | B4: ='2026 IS'!C5 -> 405325.97 | C4: ='2026 IS'!D5 -> 314994.6 | D4: ='2026 IS'!E5 -> 676068 | E4: ='2026 IS'!F5 -> 664972.26
A5: Cost of Sales | B5: ='2026 IS'!C6 -> -280718.4 | C5: ='2026 IS'!D6 -> -206326.08 | D5: ='2026 IS'!E6+'2026 IS'!E7 -> -527192.8 | E5: ='2026 IS'!F6 -> -500048.32
A6: Gross Margin | B6: ='2026 IS'!C8 -> 124607.57 | C6: ='2026 IS'!D8 -> 108668.52 | D6: ='2026 IS'!E8 -> 148875.2 | E6: ='2026 IS'!F8 -> 164923.94
A7: Opex | B7: =-'2026 IS'!C35 -> -86778.602 | C7: =-'2026 IS'!D35 -> -95045.817 | D7: =-'2026 IS'!E35 -> -149782.08 | E7: =-'2026 IS'!F35 -> -86517.733
A8: Net Income (Loss) | B8: ='2026 IS'!C39 -> 30263.174 | C8: ='2026 IS'!D39 -> 10898.162 | D8: ='2026 IS'!E36 -> -906.88333 | E8: ='2026 IS'!F39 -> 62724.965
A10: Inventory
A11: Beg Balance | B11: ='2026 Purch'!K2 -> 582521.5 | C11: =B14 -> 563271.1 | D11: =C14 -> 576346.62
A12: Purchases | B12: ='2026 Purch'!H20 -> 261468 | C12: ='2026 Purch'!H34 -> 219401.6 | D12: ='2026 Purch'!H53 -> 548340.12
A13: Sold | B13: =-'2026 Purch'!I20 -> -280718.4 | C13: =-'2026 Purch'!I34 -> -206326.08 | D13: =-'2026 Purch'!I53 -> -521692.8
A14: End Balance | B14: =sum(B11:B13) -> 563271.1 | C14: =sum(C11:C13) -> 576346.62 | D14: =sum(D11:D13) -> 602993.94 | E14: =sum(E11:E13) -> 0
A16: Payable
A17: Beg Balance | B17: ='2026 AP'!J15 -> 534000.2 | C17: =B20 -> 462098.8 | D17: =C20 -> 462705.6
A18: Purchases | B18: ='2026 Purch'!H20 -> 261468 | C18: ='2026 Purch'!H34 -> 219401.6 | D18: =D12 -> 548340.12
A19: Payments | B19: =-sum('2026 AP'!H16:H50) -> -333369.4 | C19: =-sum('2026 AP'!H51:H74) -> -218794.8 | D19: =-sum('2026 AP'!H75:H93) -> -504266.72
A20: End Balance | B20: =sum(B17:B19) -> 462098.8 | C20: =sum(C17:C19) -> 462705.6 | D20: =sum(D17:D19) -> 506779 | E20: =sum(E17:E19) -> 0
A22: Receivable
A23: Beg Balance
A24: Additions
A25: Collected
A26: End Balance

Sheet 2026CF
E1: 17329.53
A2: Date | B2: Description | C2: In | D2: Out | E2: Balance | F2: Remarks
C3: =SUM(C5:C1048649) -> 1398388.6 | D3: =SUM(D5:#REF!) -> 1817994.9 | E3: =E1+C3-D3 -> -402276.77
A4: 2026 | B4: Beginning Balance
E5: =E1 -> 17329.53
A6: 46053 | B6: January Cash Sales | C6: 405325.97 | E6: =E5+C6-D6 -> 422655.5
A7: 46029 | B7: Cash Purchase | D7: 15600 | E7: =E6+C7-D7 -> 407055.5 | F7: Uniwestech 2 tanks 134A
A8: 46030 | B8: Expenses for the month | D8: 20538 | E8: =E7+C8-D8 -> 386517.5 | F8: Lalamove from Cubao
A9: 46037 | B9: Salaries Jan 15 2026 | D9: 6000 | E9: =E8+C9-D9 -> 380517.5 | F9: Jocelyn
A10: 46037 | B10: Salaries Jan 15 2026 | D10: 6600 | E10: =E9+C10-D10 -> 373917.5 | F10: Pastor Jun
A11: 46037 | B11: Salaries Jan 15 2026 | D11: 500 | E11: =E10+C11-D11 -> 373417.5 | F11: Christia
A12: 46037 | B12: Salaries Jan 15 2026 | D12: 2500 | E12: =E11+C12-D12 -> 370917.5 | F12: Ishabella JC
A13: 46044 | B13: Payment | D13: 26928 | E13: =E12+C13-D13 -> 343989.5 | F13: Entalpia replacement for check #942972
A14: 46042 | B14: Payment | D14: 20000 | E14: =E13+C14-D14 -> 323989.5 | F14: 938017 Centralworld
A15: 45669 | B15: Payment | D15: 11800 | E15: =E14+C15-D15 -> 312189.5 | F15: 938046 JYQL
A16: 45670 | B16: Payment | D16: 13800 | E16: =E15+C16-D16 -> 298389.5 | F16: 942956 JYQL
A17: 45670 | B17: Payment | D17: 16300 | E17: =E16+C17-D17 -> 282089.5 | F17: 942957 JYQL
A18: 46041 | B18: Payment | D18: 5310 | E18: =E17+C18-D18 -> 276779.5 | F18: 917636 STAL
... A32: 46048 | B32: Payment | D32: 25600 | E32: =E31+C32-D32 -> 10620.1 | F32: 938036 Uniwestech
E33: =E32+C33-D33 -> 10620.1
E34: =E33+C34-D34 -> 10620.1
A35: 46052 | B35: Business Permit | D35: 34000 | E35: =E34+C35-D35 -> -23379.9
A36: 46052 | B36: Salaries Jan 30 2026 | D36: 6600 | E36: =E35+C36-D36 -> -29979.9 | F36: Pastor Jun
A37: 46052 | B37: Salaries Jan 30 2026 | D37: 5000 | E37: =E36+C37-D37 -> -34979.9 | F37: Jocelyn
A38: 46052 | B38: Salaries Jan 30 2026 | D38: 1000 | E38: =E37+C38-D38 -> -35979.9 | F38: Christia
A39: 46052 | B39: Salaries Jan 30 2026 | D39: 5000 | E39: =E38+C39-D39 -> -40979.9 | F39: Rocky
A40: 46055 | B40: LTO Renewal | D40: 9000 | E40: =E39+C40-D40 -> -49979.9 | F40: OR Renewal Suzuki with penalty (2023-2025)
A41: 46056 | B41: Payment | D41: 9854.8 | E41: =E40+C41-D41 -> -59834.7 | F41: Ishabella full payment 4 pcs korea pump
A42: 46058 | B42: Delivery Expense | D42: 531 | E42: =E41+C42-D42 -> -60365.7 | F42: Lalamove from Cubao
A43: 46058 | B43: Cash Collection / Sales | C43: 17839.29 | E43: =E42+C43-D43 -> -42526.41 | F43: Drench, check payment
A44: 46058 | B44: Payment | D44: 27450 | E44: =E43+C44-D44 -> -69976.41 | F44: JYQL
A45: 46058 | B45: Payment | D45: 18610 | E45: =E44+C45-D45 -> -88586.41 | F45: JYQL
A46: 46059 | B46: Payment | D46: 35000 | E46: =E45+C46-D46 -> -123586.41 | F46: Uniwestech replacement for check #942952
A47: 46059 | B47: Bank Charges | D47: 2600 | E47: =E46+C47-D47 -> -126186.41 | F47: JYQL bounced check
A48: 46059 | B48: Delivery Expense | D48: 364 | E48: =E47+C48-D48 -> -126550.41 | F48: Lalamove from Cubao
A49: 46060 | B49: Payment | D49: 12850 | E49: =E48+C49-D49 -> -139400.41 | F49: JYQL replacement for check #942982
A50: 46065 | B50: Delivery Expense | D50: 1000 | E50: =E49+C50-D50 -> -140400.41 | F50: Lalamove from Cubao
A51: 46065 | B51: Cash Collection / Sales | C51: 8000 | E51: =E50+C51-D51 -> -132400.41 | F51: Drench, check payment
A52: 46065 | B52: Payment | D52: 23500 | E52: =E51+C52-D52 -> -155900.41 | F52: JYQL
A53: 46065 | B53: Bank Charges | D53: 2200 | E53: =E52+C53-D53 -> -158100.41 | F53: Winterpine bounced check
A54: 46066 | B54: Delivery Expense | D54: 221 | E54: =E53+C54-D54 -> -158321.41 | F54: Lalamove from Cubao
A55: 46066 | B55: Payment | D55: 10290 | E55: =E54+C55-D55 -> -168611.41 | F55: JYQL
A56: 46066 | B56: Payment | D56: 9400 | E56: =E55+C56-D56 -> -178011.41 | F56: JYQL
A57: 46067 | B57: Salaries Feb 14 2026 | D57: 1000 | E57: =E56+C57-D57 -> -179011.41 | F57: Christia
A58: 46067 | B58: Salaries Feb 14 2026 | D58: 2500 | E58: =E57+C58-D58 -> -181511.41 | F58: Ishabella JC
A59: 46067 | B59: Salaries Feb 14 2026 | D59: 5000 | E59: =E58+C59-D59 -> -186511.41 | F59: Jocelyn
A60: 46067 | B60: Salaries Feb 14 2026 | D60: 6000 | E60: =E59+C60-D60 -> -192511.41 | F60: Pastor Jun
A61: 46067 | B61: Salaries Feb 14 2026 | D61: 5000 | E61: =E60+C61-D61 -> -197511.41 | F61: Rocky
A62: 46067 | B62: Delivery Expense | D62: 500 | E62: =E61+C62-D62 -> -198011.41 | F62: Lalamove from Cubao
A63: 46069 | B63: Borrowings | C63: 16000 | E63: =E62+C63-D63 -> -182011.41 | F63: Lazada
A64: 46070 | B64: Payment | D64: 7000 | E64: =E63+C64-D64 -> -189011.41 | F64: Nonoy (30 less 15k, less 7k balance 8k)
A65: 46071 | B65: Cash Collection / Sales | C65: 5100 | E65: =E63+C65-D65 -> -176911.41 | F65: from Pastor Jun
A66: 46072 | B66: Cash Collection / Sales | C66: 6900 | E66: =E65+C66-D66 -> -170011.41 | F66: From Ikot Feb 19 2026
A67: 46072 | B67: Cash Collection / Sales | C67: 21000 | E67: =E66+C67-D67 -> -149011.41 | F67: From Ikot Feb 19 2026
A68: 46073 | B68: Solicitation to Drench | D68: 500 | E68: =E67+C68-D68 -> -149511.41 | F68: Edison
A69: 46073 | B69: Payment | D69: 16600 | E69: =E68+C69-D69 -> -166111.41 | F69: Uniwestech 2 tanks 134A (cash purchase)
A70: 46078 | B70: Payment | D70: 19240 | E70: =E69+C70-D70 -> -185351.41 | F70: 91780 JYQL
A71: 46078 | B71: Bank Charges | D71: 2200 | E71: =E70+C71-D71 -> -187551.41 | F71: Stal bounced check 31,300
A72: 46078 | B72: Delivery Expense | D72: 350 | E72: =E71+C72-D72 -> -187901.41 | F72: Lalamove Jayson to Cubao
A73: 46079 | B73: Cash Collection / Sales | C73: 9420 | E73: =E71+C73-D73 -> -178131.41 | F73: Gcash from Ikot Feb 26 2026
A74: 46079 | B74: Cash Collection / Sales | C74: 4000 | E74: =E73+C74-D74 -> -174131.41 | F74: Gcash from Ikot Feb 26 2026
A75: 46079 | B75: Cash Collection / Sales | C75: 19000 | E75: =E73+C75-D75 -> -159131.41 | F75: Cash deposit from Ikot Feb 26 2026
A76: 46079 | B76: Cash Collection / Sales | C76: 9000 | E76: =E75+C76-D76 -> -150131.41 | F76: Transfer from Ikot Feb 26 2026
A77: 46080 | B77: Payment | D77: 16000 | E77: =E76+C77-D77 -> -166131.41 | F77: 942973 Uniwestech
A78: 46080 | B78: Salaries Feb 27 2026 | D78: 1000 | E78: =E77+C78-D78 -> -167131.41 | F78: Christia
A79: 46080 | B79: Salaries Feb 27 2026 | D79: 5000 | E79: =E78+C79-D79 -> -172131.41 | F79: Jocelyn
A80: 46080 | B80: Salaries Feb 27 2026 | D80: 6000 | E80: =E79+C80-D80 -> -178131.41 | F80: Pastor Jun
A81: 46080 | B81: Salaries Feb 27 2026 | D81: 5000 | E81: =E80+C81-D81 -> -183131.41 | F81: Rocky
A82: 46080 | B82: Cash Collection / Sales | C82: 200735.31 | E82: =E81+C82-D82 -> 17603.9
A83: 46080 | B83: Expenses for the month | D83: =16737.34-2833.34+3230 -> 17134 | E83: =E82+C83-D83 -> 469.9
A84: 46080 | B84: Payment | D84: 20000 | E84: =E83+C84-D84 -> -19530.1 | F84: 938018 Centralworld
E85: =E84+C85-D85 -> -19530.1
A86: 46083 | B86: Payment | D86: 16926.8 | E86: =E85+C86-D86 -> -36456.9 | F86: Ishabella
A87: 46083 | B87: Payment | D87: 9200 | E87: =E86+C87-D87 -> -45656.9 | F87: 943002 JYQL
A88: 46085 | B88: Payment | D88: 12150 | E88: =E87+C88-D88 -> -57806.9 | F88: 938002 STAL
A89: 46087 | B89: Payment | D89: 22500 | E89: =E88+C89-D89 -> -80306.9 | F89: 943003 JYQL
A90: 46087 | B90: Payment | D90: 6385 | E90: =E89+C90-D90 -> -86691.9 | F90: 943005 JYQL
A91: 46091 | B91: Payment | D91: 35360 | E91: =E90+C91-D91 -> -122051.9 | F91: Ishabella
A92: 45728 | B92: Payment | D92: 25230.8 | E92: =E91+C92-D92 -> -147282.7 | F92: 942954 Winterpine
A93: 46094 | B93: Salaries Mar 15 2026 | D93: 1000 | E93: =E92+C93-D93 -> -148282.7 | F93: Christia
A94: 46094 | B94: Salaries Mar 15 2026 | D94: 2500 | E94: =E93+C94-D94 -> -150782.7 | F94: Ishabella JC
A95: 46094 | B95: Salaries Mar 15 2026 | D95: 5000 | E95: =E94+C95-D95 -> -155782.7 | F95: Jocelyn
A96: 46094 | B96: Salaries Mar 15 2026 | D96: 6000 | E96: =E95+C96-D96 -> -161782.7 | F96: Pastor Jun
A97: 46094 | B97: Salaries Mar 15 2026 | D97: 5000 | E97: =E96+C97-D97 -> -166782.7 | F97: Rocky
A98: 46098 | B98: Cash Collection / Sales | C98: 100000 | E98: =E97+C98-D98 -> -66782.7 | F98: DP Decasio
A99: 46099 | B99: Payment | D99: 16400 | E99: =E98+C99-D99 -> -83182.7 | F99: Uniwestech
A100: 46099 | B100: Payment | D100: 20660 | E100: =E99+C100-D100 -> -103842.7 | F100: 917639 STAL
A101: 46099 | B101: Payment | D101: 20730 | E101: =E100+C101-D101 -> -124572.7 | F101: 943006JYQL
A102: 46099 | B102: Payment | D102: 19680 | E102: =E101+C102-D102 -> -144252.7 | F102: 938003 STAL
A103: 46099 | B103: Bank Charges | D103: 2400 | E103: =E102+C103-D103 -> -146652.7 | F103: bounced check Hisys
A104: 46102 | B104: Payment | D104: 7530 | E104: =E103+C104-D104 -> -154182.7 | F104: 943008JYQL | G104: JYQL
A105: 46099 | B105: Payment | D105: 60000 | E105: =E104+C105-D105 -> -214182.7 | F105: 943017HISYS | G105: KM Aire Alliance Corporation
A106: 46105 | B106: Payment | D106: 20000 | E106: =E105+C106-D106 -> -234182.7 | F106: 938019Central Word | G106: Centralworld Enterprises
A107: 46108 | B107: Payment | D107: 22500 | E107: =E106+C107-D107 -> -256682.7 | F107: 943004JYQL | G107: 44561 JYQL
A108: 46108 | B108: Payment | D108: 19070 | E108: =E107+C108-D108 -> -275752.7 | F108: 938047STAL | G108: Jambon / Cash
A109: 46108 | B109: Payment | D109: 21250 | E109: =E108+C109-D109 -> -297002.7 | F109: 938048STAL | G109: Jambon / Cash
A110: 46110 | B110: Payment | D110: 17050 | E110: =E109+C110-D110 -> -314052.7 | F110: 943009JYQL | G110: JYQL
A111: 46112 | B111: Payment | D111: 131644.12 | E111: =E110+C111-D111 -> -445696.82 | F111: 943018HISYS | G111: KM Aire Alliance Corporation
A112: 46112 | B112: Hospitaization | D112: 70000 | E112: =E111+C112-D112 -> -515696.82 | F112: Papa
A113: 46112 | B113: Salaries Mar 15 2026 | D113: 1000 | E113: =E112+C113-D113 -> -516696.82 | F113: Christia
...

Sheet 2026 IS
A1: Aton Aire Trading Corporation
A2: Monthly Income/Loss
A3: For the Year 2026
C4: January | D4: February | E4: March | F4: April | G4: May | H4: June | I4: July | J4: August | K4: September | L4: October | M4: November | N4: December | O4: Total
B5: Sales | C5: ='2026 DS'!$F$3 -> 405325.97 | D5: ='2026 DS'!F44 -> 314994.6 | E5: ='2026 DS'!F103 -> 676068 | F5: ='2026 DS'!F170 -> 664972.26 | G5: ='2026 DS'!F239 -> 341484.6 | H5: ='2026 DS'!F291 -> 461234 | I5: ='2026 DS'!F358 -> 799834.6 | O5: =SUM(C5:N5) -> 3663914
B6: Cost of Sales | C6: =-'2026 DS'!$G$3 -> -280718.4 | D6: =-'2026 DS'!G44 -> -206326.08 | E6: =-'2026 DS'!G103 -> -521692.8 | F6: =-'2026 DS'!G170 -> -500048.32 | G6: =-'2026 DS'!G239 -> -222972 | H6: =-'2026 DS'!G291 -> -319265.8 | I6: =-'2026 DS'!G358 -> -593187 | O6: =SUM(C6:N6) -> -2644210.4
B7: Expenses Related to Sales | C7: =-'2026 DS'!$H$3 -> 0 | D7: =-'2026 DS'!H44 -> 0 | E7: =-'2026 DS'!H103 -> -5500 | F7: =-'2026 DS'!H170 -> 0 | G7: =-'2026 DS'!H239 -> 0 | H7: =-'2026 DS'!H291 -> 0 | I7: =-'2026 DS'!H358 -> 0 | O7: =SUM(C7:N7) -> -5500
B8: Gross Margin | C8: =SUM(C5:C7) -> 124607.57 | D8: =SUM(D5:D7) -> 108668.52 | E8: =SUM(E5:E7) -> 148875.2 | F8: =SUM(F5:F7) -> 164923.94 | G8: =SUM(G5:G7) -> 118512.6 | H8: =SUM(H5:H7) -> 141968.2 | I8: =SUM(I5:I7) -> 206647.6 | J8: =SUM(J5:J7) -> 0 | ... O8: =SUM(O5:O7) -> 1014203.6
B9: Gross Profit Ratio | C9: =C8/C5 -> 0.30742558 | D9: =D8/D5 -> 0.34498534 | E9: =E8/E5 -> 0.22020743 | F9: =F8/F5 -> 0.24801627 | G9: =G8/G5 -> 0.34705108 | H9: =H8/H5 -> 0.30780081 | I9: =I8/I5 -> 0.25836292 | J9: =J8/J5 -> #DIV/0! | ... O9: =O8/O5 -> 0.2768088
B11: Operating Expenses (cash)
B13: Salaries | C13: ='2026 Exp'!C6 -> 33200 | D13: ='2026 Exp'!C29 -> 36500 | E13: ='2026 Exp'!C52 -> 37700 | F13: ='2026 Exp'!C76 -> 40000 | G13: ='2026 Exp'!C100 -> 41000 | H13: ='2026 Exp'!C124 -> 40489.62 | I13: ='2026 Exp'!C148 -> 43250 | O13: =SUM(C13:N13) -> 272139.62
B14: 13th Month | C14: ='2026 Exp'!C7 -> 3000 | D14: ='2026 Exp'!C30 -> 3000 | E14: ='2026 Exp'!C53 -> 3000 | F14: ='2026 Exp'!C77 -> 3000 | G14: ='2026 Exp'!C101 -> 3000 | H14: ='2026 Exp'!C125 -> 3000 | I14: ='2026 Exp'!C149 -> 3000 | O14: =SUM(C14:N14) -> 21000
B15: Christmas Expenses | C15: ='2026 Exp'!C8 -> 2000 | D15: ='2026 Exp'!C31 -> 2000 | E15: ='2026 Exp'!C54 -> 2000 | F15: ='2026 Exp'!C78 -> 2000 | G15: ='2026 Exp'!C102 -> 2000 | H15: ='2026 Exp'!C126 -> 2000 | I15: ='2026 Exp'!C150 -> 2000 | O15: =SUM(C15:N15) -> 14000
B16: Business Permit | C16: ='2026 Exp'!C9 -> 2833.3333 | D16: ='2026 Exp'!C32 -> 2833.3333 | E16: ='2026 Exp'!C55 -> 2833.3333 | F16: ='2026 Exp'!C79 -> 2833.3333 | G16: ='2026 Exp'!C103 -> 2833.3333 | H16: ='2026 Exp'!C127 -> 2833.3333 | I16: ='2026 Exp'!C151 -> 2833.3333 | O16: =SUM(C16:N16) -> 19833.333
B17: Percentage tax | C17: ='2026 Exp'!C10 -> 13548.149 | D17: ='2026 Exp'!C33 -> 1855.5 | E17: ='2026 Exp'!C56 -> 11692.65 | F17: ='2026 Exp'!C80 -> 5000 | G17: ='2026 Exp'!C104 -> 5000 | H17: ='2026 Exp'!C128 -> 5000 | I17: ='2026 Exp'!C152 -> 5000 | O17: =SUM(C17:N17) -> 47096.299
B18: Rent | C18: ='2026 Exp'!C11 -> 5000 | D18: ='2026 Exp'!C34 -> 5000 | E18: ='2026 Exp'!C57 -> 5000 | F18: ='2026 Exp'!C81 -> 5000 | G18: ='2026 Exp'!C105 -> 5000 | H18: ='2026 Exp'!C129 -> 5000 | I18: ='2026 Exp'!C153 -> 5000 | O18: =SUM(C18:N18) -> 35000
B19: LTO Renewal | C19: ='2026 Exp'!C12 -> 0 | D19: ='2026 Exp'!C35 -> 9000 | E19: ='2026 Exp'!C58 -> 0 | F19: ='2026 Exp'!C82 -> 0 | G19: ='2026 Exp'!C106 -> 0 | H19: ='2026 Exp'!C130 -> 0 | I19: ='2026 Exp'!C154 -> 0 | O19: =SUM(C19:N19) -> 9000
B20: Electicity & Water | C20: ='2026 Exp'!C13 -> 0 | D20: ='2026 Exp'!C36 -> 0 | E20: ='2026 Exp'!C59 -> 0 | F20: ='2026 Exp'!C83 -> 0 | G20: ='2026 Exp'!C107 -> 0 | H20: ='2026 Exp'!C131 -> 0 | I20: ='2026 Exp'!C155 -> 0 | O20: =SUM(C20:N20) -> 0
B21: Internet | C21: ='2026 Exp'!C14 -> 2500 | D21: ='2026 Exp'!C37 -> 2500 | E21: ='2026 Exp'!C60 -> 2500 | F21: ='2026 Exp'!C84 -> 2500 | G21: ='2026 Exp'!C108 -> 2500 | H21: ='2026 Exp'!C132 -> 2500 | I21: ='2026 Exp'!C156 -> 2500 | O21: =SUM(C21:N21) -> 17500
B22: SSS Contribution | C22: ='2026 Exp'!C15 -> 1210 | D22: ='2026 Exp'!C38 -> 1210 | E22: ='2026 Exp'!C61 -> 1210 | F22: ='2026 Exp'!C85 -> 1210 | G22: ='2026 Exp'!C109 -> 1210 | H22: ='2026 Exp'!C133 -> 1210 | I22: ='2026 Exp'!C157 -> 1210 | O22: =SUM(C22:N22) -> 8470
B23: PHIC Contribution | C23: ='2026 Exp'!C16 -> 300 | D23: ='2026 Exp'!C39 -> 300 | E23: ='2026 Exp'!C62 -> 300 | F23: ='2026 Exp'!C86 -> 300 | G23: ='2026 Exp'!C110 -> 300 | H23: ='2026 Exp'!C134 -> 300 | I23: ='2026 Exp'!C158 -> 300 | O23: =SUM(C23:N23) -> 2100
B24: HDMF Contribution | C24: ='2026 Exp'!C17 -> 200 | D24: ='2026 Exp'!C40 -> 200 | E24: ='2026 Exp'!C63 -> 200 | F24: ='2026 Exp'!C87 -> 200 | G24: ='2026 Exp'!C111 -> 200 | H24: ='2026 Exp'!C135 -> 200 | I24: ='2026 Exp'!C159 -> 200 | O24: =SUM(C24:N24) -> 1400
... B32: Commissions | C32: ='2026 Exp'!C25 -> 7449.12 | D32: ='2026 Exp'!C48 -> 8046.984 | E32: ='2026 Exp'!C71 -> 3061.1 | F32: ='2026 Exp'!C95 -> 6234.4 | G32: ='2026 Exp'!C119 -> 6360.22 | H32: ='2026 Exp'!C143 -> 11371.94 | I32: ='2026 Exp'!C167 -> 11635.78 | O32: =SUM(C32:N32) -> 54159.544
B33: Allowances (Hospitalization) | E33: ='2026 Exp'!C72 -> 60000 | F33: ='2026 Exp'!C96 -> 0 | G33: ='2026 Exp'!C120 -> 0 | H33: ='2026 Exp'!C144 -> 0 | I33: ='2026 Exp'!C168 -> 45224.44 | O33: =SUM(C33:N33) -> 105224.44
B35: Total Opex (cash) | C35: =SUM(C12:C34) -> 86778.602 | D35: =SUM(D12:D34) -> 95045.817 | E35: =SUM(E12:E34) -> 149782.08 | F35: =SUM(F12:F34) -> 86517.733 | G35: =SUM(G12:G34) -> 84063.553 | H35: =SUM(H12:H34) -> 94864.893 | I35: =SUM(I12:I34) -> 153443.55 | J35: =SUM(J12:J34) -> 0 | ... O35: =SUM(O12:O34) -> 750496.24
B36: Income/(Loss) | C36: =C8-C35 -> 37828.968 | D36: =D8-D35 -> 13622.703 | E36: =E8-E35 -> -906.88333 | F36: =F8-F35 -> 78406.207 | G36: =G8-G35 -> 34449.047 | H36: =H8-H35 -> 47103.307 | I36: =I8-I35 -> 53204.047 | J36: =J8-J35 -> 0 | ... O36: =O8-O35 -> 263707.39
B37: Depreciation
B38: Income Tax (20%) | C38: =(C36-C37)*0.2 -> 7565.7935 | D38: =(D36-D37)*0.2 -> 2724.5405 | E38: 0 | F38: =(F36-F37)*0.2 -> 15681.241 | G38: =(G36-G37)*0.2 -> 6889.8093 | H38: =(H36-H37)*0.2 -> 9420.6613 | I38: =(I36-I37)*0.2 -> 10640.809 | J38: =(J36-J37)*0.2 -> 0 | K38: =(K36-K37)*0.2 -> 0 | L38: =(L36-L37)*0.2 -> 0 | M38: =(M36-M37)*0.2 -> 0 | ... O38: =(O36-O37)*0.2 -> 52741.479
B39: Final Net Income/(Loss) | C39: =C36-C37-C38 -> 30263.174 | D39: =D36-D37-D38 -> 10898.162 | E39: =E36-E37-E38 -> -906.88333 | F39: =F36-F37-F38 -> 62724.965 | G39: =G36-G37-G38 -> 27559.237 | H39: =H36-H37-H38 -> 37682.645 | I39: =I36-I37-I38 -> 42563.237 | J39: =J36-J37-J38 -> 0 | ... O39: =O36-O37-O38 -> 210965.91
B40: Net Profit Ratio

Sheet 2026 Exp
B1: Aton Aire Trading Corporation
B2: 2026 Expenses
A3: Month | C3: Total | D3: 1 | E3: 2 | F3: 3 | G3: 4 | H3: 5 | I3: 6 | J3: 7 | K3: 8 | L3: 9 | M3: 10 | N3: 11 | O3: 12 | P3: 13 | Q3: 14 | R3: 15 | S3: 16 | T3: 17 | U3: 18 | V3: 19 | W3: 20 | X3: 21 | Y3: 22 | Z3: 23 | AA3: 24 | AB3: 25 | AC3: 26 | AD3: 27 | AE3: 28 | AF3: 29 | AG3: 30 | AH3: 31
A4: January | B4: Total for the Month | C4: =SUM(C5:C26) -> 86778.602 | D4: =SUM(D5:D26) -> 0 | E4: =SUM(E5:E26) -> 500 | F4: =SUM(F5:F26) -> 0 | G4: =SUM(G5:G26) -> 0 | H4: =SUM(H5:H26) -> 1225 | I4: =SUM(I5:I26) -> 0 | J4: =SUM(J5:J26) -> 2025 | ... AH4: =SUM(AH5:AH26) -> 0
A5: January | B5: Cash | C5: =SUM(D5:AH5) -> 0
A6: January | B6: Salaries | C6: =SUM(D6:AH6) -> 33200 | R6: 15600 | AG6: 17600
A7: January | B7: 13th Month | C7: =SUM(D7:AH7) -> 3000 | AG7: 3000
A8: January | B8: Christmas Expenses | C8: =SUM(D8:AH8) -> 2000 | AG8: 2000
A9: January | B9: Business Permit | C9: =SUM(D9:AH9) -> 2833.3333 | AG9: =34000/12 -> 2833.3333
A10: January | B10: Percentage tax | C10: =SUM(D10:AH10) -> 13548.149 | AG10: ='2026 DS'!N3 -> 13548.149
A11: January | B11: Rent | C11: =SUM(D11:AH11) -> 5000 | AG11: 5000
A12: January | B12: LTO Renewal | C12: =SUM(D12:AH12) -> 0
A13: January | B13: Electicity & Water | C13: =SUM(D13:AH13) -> 0 | AG13: 0
A14: January | B14: Internet | C14: =SUM(D14:AH14) -> 2500 | AG14: 2500
A15: January | B15: SSS Contribution | C15: =SUM(D15:AH15) -> 1210 | AG15: 1210
A16: January | B16: PHIC Contribution | C16: =SUM(D16:AH16) -> 300 | AG16: =12000*0.025 -> 300
A17: January | B17: HDMF Contribution | C17: =SUM(D17:AH17) -> 200 | AG17: 200
A18: January | B18: Store supplies | C18: =SUM(D18:AH18) -> 0
A19: January | B19: Repairs & Maintenance | C19: =SUM(D19:AH19) -> 0
A20: January | B20: Bank Charges | C20: =SUM(D20:AH20) -> 5040 | E20: =500 -> 500 | H20: 25 | J20: 25 | R20: 30 | V20: 20 | Y20: 10 | AC20: =10+2200 -> 2210 | AF20: 2200 | AG20: 20
A21: January | B21: Communication | C21: =SUM(D21:AH21) -> 35 | W21: 35
A22: January | B22: Meals | C22: =SUM(D22:AH22) -> 1700 | J22: 800 | K22: 500 | O22: 100 | Q22: 300
A23: January | B23: Gasoline | C23: =SUM(D23:AH23) -> 4200 | H23: =1000+200 -> 1200 | J23: 1200 | K23: 800 | O23: 100 | R23: 600 | W23: 100 | AG23: 200
A24: January | B24: Deliveries | C24: =SUM(D24:AH24) -> 4563 | K24: 380 | Q24: =650+130 -> 780 | S24: =343+900 -> 1243 | V24: 250 | AD24: =100+720 -> 820 | AE24: =310+780 -> 1090
A25: January | B25: Commissions | C25: =SUM(D25:AH25) -> 7449.12 | AG25: ='2026 Comm'!C4 -> 7449.12
A27: February | B27: Total for the Month | C27: =SUM(C28:C49) -> 95045.817 | D27: =SUM(D28:D49) -> 0 | E27: =SUM(E28:E49) -> 10120 | F27: =SUM(F28:F49) -> 100 | G27: =SUM(G28:G49) -> 0 | H27: =SUM(H28:H49) -> 250 | I27: =SUM(I28:I49) -> 2610 | J27: =SUM(J28:J49) -> 0 | ... AH27: =SUM(AH28:AH49) -> 0
A28: February | B28: Cash | C28: =SUM(D28:AH28) -> 0
A29: February | B29: Salaries | C29: =SUM(D29:AH29) -> 36500 | Q29: 19500 | AE29: 17000
A30: February | B30: 13th Month | C30: =SUM(D30:AH30) -> 3000 | AE30: 3000
A31: February | B31: Christmas Expenses | C31: =SUM(D31:AH31) -> 2000 | AE31: 2000
A32: February | B32: Business Permit | C32: =SUM(D32:AH32) -> 2833.3333 | AE32: =34000/12 -> 2833.3333
A33: February | B33: Percentage tax | C33: =SUM(D33:AH33) -> 1855.5 | AE33: ='2026 DS'!N44 -> 1855.5
A34: February | B34: Rent | C34: =SUM(D34:AH34) -> 5000 | AE34: 5000
A35: February | B35: LTO Renewal | C35: =SUM(D35:AH35) -> 9000 | E35: 9000
A36: February | B36: Electicity & Water | C36: =SUM(D36:AH36) -> 0
A37: February | B37: Internet | C37: =SUM(D37:AH37) -> 2500 | AG37: 2500
A38: February | B38: SSS Contribution | C38: =SUM(D38:AH38) -> 1210 | AG38: 1210
A39: February | B39: PHIC Contribution | C39: =SUM(D39:AH39) -> 300 | AG39: =12000*0.025 -> 300
A40: February | B40: HDMF Contribution | C40: =SUM(D40:AH40) -> 200 | AG40: 200
A41: February | B41: Store supplies | C41: =SUM(D41:AH41) -> 0
A42: February | B42: Repairs & Maintenance | C42: =SUM(D42:AH42) -> 0
A43: February | B43: Bank Charges | C43: =SUM(D43:AH43) -> 10230 | E43: 500 | I43: =2600+10 -> 2610 | L43: 10 | M43: 10 | O43: =2200+10 -> 2210 | S43: =10+10 -> 20 | U43: 10 | W43: =10+2600 -> 2610 | Z43: =10+10 -> 20 | AB43: =10+2200 -> 2210 | AD43: =10+10 -> 20
A44: February | B44: Communication | C44: =SUM(D44:AH44) -> 0
A45: February | B45: Meals | C45: =SUM(D45:AH45) -> 2400 | O45: 800 | V45: 800 | AC45: 800
A46: February | B46: Gasoline | C46: =SUM(D46:AH46) -> 5700 | E46: 200 | F46: 100 | N46: 200 | O46: =200+1200 -> 1400 | Q46: 200 | U46: 200 | V46: =200+1200 -> 1400 | W46: 200 | AA46: 250 | AC46: =50+1200 -> 1250 | AE46: 300
A47: February | B47: Deliveries | C47: =SUM(D47:AH47) -> 4270 | E47: =100+320 -> 420 | H47: 250 | O47: =800+300 -> 1100 | U47: =300+650 -> 950 | AC47: =350+1000 -> 1350 | AE47: 200
A48: February | B48: Commissions | C48: =SUM(D48:AH48) -> 8046.984 | AE48: ='2026 DS'!K44 -> 8046.984
A50: March | B50: Total for the Month | C50: =SUM(C51:C72) -> 149782.08 | D50: =SUM(D51:D72) -> 500 | E50: =SUM(E51:E72) -> 10 | F50: =SUM(F51:F72) -> 1550 | G50: =SUM(G51:G72) -> 0 | H50: =SUM(H51:H72) -> 710 | I50: =SUM(I51:I72) -> 0 | J50: =SUM(J51:J72) -> 10 | ... AH50: =SUM(AH51:AH72) -> 51422.083
A51: March | B51: Cash | C51: =SUM(D51:AH51) -> 0
A52: March | B52: Salaries | C52: =SUM(D52:AH52) -> 37700 | R52: 19500 | AH52: 18200
A53: March | B53: 13th Month | C53: =SUM(D53:AH53) -> 3000 | AH53: 3000
A54: March | B54: Christmas Expenses | C54: =SUM(D54:AH54) -> 2000 | AH54: 2000
A55: March | B55: Business Permit | C55: =SUM(D55:AH55) -> 2833.3333 | AH55: =34000/12 -> 2833.3333
A56: March | B56: Percentage tax | C56: =SUM(D56:AH56) -> 11692.65 | AH56: =13548.15-1855.5 -> 11692.65
A57: March | B57: Rent | C57: =SUM(D57:AH57) -> 5000 | AH57: 5000
A58: March | B58: LTO Renewal | C58: =SUM(D58:AH58) -> 0
A59: March | B59: Electicity & Water | C59: =SUM(D59:AH59) -> 0
A60: March | B60: Internet | C60: =SUM(D60:AH60) -> 2500 | AH60: 2500
A61: March | B61: SSS Contribution | C61: =SUM(D61:AH61) -> 1210 | AH61: 1210
A62: March | B62: PHIC Contribution | C62: =SUM(D62:AH62) -> 300 | AH62: =12000*0.025 -> 300
A63: March | B63: HDMF Contribution | C63: =SUM(D63:AH63) -> 200 | AH63: 200
A64: March | B64: Store supplies | C64: =SUM(D64:AH64) -> 0
A65: March | B65: Repairs & Maintenance | C65: =SUM(D65:AH65) -> 500 | F65: 500
A66: March | B66: Bank Charges | C66: =SUM(D66:AH66) -> 5880 | D66: 500 | E66: 10 | J66: 10 | K66: 10 | M66: 10 | O66: =10+10 -> 20 | P66: =10+10+10+10+10+10 -> 60 | S66: =10+10 -> 20 | U66: 2400 | X66: 20 | AA66: 10 | AC66: 2800 | AG66: 10
A67: March | B67: Communication | C67: =SUM(D67:AH67) -> 0
A68: March | B68: Meals | C68: =SUM(D68:AH68) -> 710 | V68: =500+210 -> 710
A69: March | B69: Gasoline | C69: =SUM(D69:AH69) -> 3650 | F69: 200 | M69: 200 | O69: 200 | S69: 150 | V69: 1500 | X69: 1000 | AG69: 200 | AH69: 200
A70: March | B70: Deliveries | C70: =SUM(D70:AH70) -> 9545 | F70: =300+550 -> 850 | H70: =150+560 -> 710 | N70: 1000 | S70: 1000 | U70: =380+600 -> 980 | X70: 700 | AB70: 1180 | AC70: =350+750 -> 1100 | AE70: 800 | AH70: =125+1100 -> 1225
A71: March | B71: Commissions | C71: =SUM(D71:AH71) -> 3061.1 | AH71: ='2026 DS'!K103 -> 3061.1
A72: March | B72: Allowances (Hospitalization) | C72: =SUM(D72:AH72) -> 60000 | AG72: 60000
A74: April | B74: Total for the Month | C74: =SUM(C75:C96) -> 86517.733 | D74: =SUM(D75:D96) -> 0 | E74: =SUM(E75:E96) -> 0 | F74: =SUM(F75:F96) -> 0 | G74: =SUM(G75:G96) -> 1410 | H74: =SUM(H75:H96) -> 0 | I74: =SUM(I75:I96) -> 600 | J74: =SUM(J75:J96) -> 700 | ... AH74: =SUM(AH75:AH96) -> 0
A75: April | B75: Cash | C75: =SUM(D75:AH75) -> 0
A76: April | B76: Salaries | C76: =SUM(D76:AH76) -> 40000 | R76: 21250 | AG76: 18750
A77: April | B77: 13th Month | C77: =SUM(D77:AH77) -> 3000 | AG77: 3000
A78: April | B78: Christmas Expenses | C78: =SUM(D78:AH78) -> 2000 | AG78: 2000
A79: April | B79: Business Permit | C79: =SUM(D79:AH79) -> 2833.3333 | AG79: =34000/12 -> 2833.3333
A80: April | B80: Percentage tax | C80: =SUM(D80:AH80) -> 5000 | AG80: 5000
A81: April | B81: Rent | C81: =SUM(D81:AH81) -> 5000 | AG81: 5000
A82: April | B82: LTO Renewal | C82: =SUM(D82:AH82) -> 0
A83: April | B83: Electicity & Water | C83: =SUM(D83:AH83) -> 0
A84: April | B84: Internet | C84: =SUM(D84:AH84) -> 2500 | AG84: 2500
A85: April | B85: SSS Contribution | C85: =SUM(D85:AH85) -> 1210 | AG85: 1210
A86: April | B86: PHIC Contribution | C86: =SUM(D86:AH86) -> 300 | AG86: =12000*0.025 -> 300
A87: April | B87: HDMF Contribution | C87: =SUM(D87:AH87) -> 200 | AG87: 200
A88: April | B88: Store supplies | C88: =SUM(D88:AH88) -> 0
A89: April | B89: Repairs & Maintenance | C89: =SUM(D89:AH89) -> 500 | P89: 500
A90: April | B90: Bank Charges | C90: =SUM(D90:AH90) -> 780 | K90: 10 | M90: 20 | P90: 610 | Q90: 10 | R90: 30 | U90: 10 | Y90: 30 | AD90: 40 | AG90: 20
A91: April | B91: Communication | C91: =SUM(D91:AH91) -> 0
A92: April | B92: Meals | C92: =SUM(D92:AH92) -> 2910 | G92: 210 | K92: 700 | S92: 1000 | Z92: 1000
A93: April | B93: Gasoline | C93: =SUM(D93:AH93) -> 7900 | G93: 1200 | K93: 2400 | S93: 2300 | Z93: 2000
A94: April | B94: Deliveries | C94: =SUM(D94:AH94) -> 6150 | I94: 600 | J94: 700 | Q94: 350 | R94: =300+750 -> 1050 | W94: 800 | Y94: 1000 | AD94: 950 | AE94: 700
A95: April | B95: Commissions | C95: =SUM(D95:AH95) -> 6234.4 | AG95: ='2026 DS'!K170 -> 6234.4
A96: April | B96: Allowances (Hospitalization) | C96: =SUM(D96:AH96) -> 0
A98: May | B98: Total for the Month | C98: =SUM(C99:C120) -> 84063.553 | D98: =SUM(D99:D120) -> 0 | E98: =SUM(E99:E120) -> 0 | F98: =SUM(F99:F120) -> 0 | G98: =SUM(G99:G120) -> 1220 | H98: =SUM(H99:H120) -> 10 | I98: =SUM(I99:I120) -> 0 | J98: =SUM(J99:J120) -> 2000 | ... AH98: =SUM(AH99:AH120) -> 28403.553
A99: May | B99: Cash | C99: =SUM(D99:AH99) -> 0
A100: May | B100: Salaries | C100: =SUM(D100:AH100) -> 41000 | R100: =16750+5000 -> 21750 | AG100: =14250+5000 -> 19250
A101: May | B101: 13th Month | C101: =SUM(D101:AH101) -> 3000 | AH101: 3000
A102: May | B102: Christmas Expenses | C102: =SUM(D102:AH102) -> 2000 | AH102: 2000
A103: May | B103: Business Permit | C103: =SUM(D103:AH103) -> 2833.3333 | AH103: =34000/12 -> 2833.3333
A104: May | B104: Percentage tax | C104: =SUM(D104:AH104) -> 5000 | AH104: 5000
...

Sheet 2026 DS
A1: Date | B1: DR # | C1: Customer Name | D1: Sales Agent | E1: Mode | F1: Sales | G1: Capital | H1: Sales related Exp | I1: Margin | J1: GPR | K1: Agents Comm | L1: Remarks | M1: BIR Sales | N1: Percentage Tax
I2: =F:F-G:G-H:H -> 0
A3: For the month of January 2026 | F3: =SUM(F4:F42) -> 405325.97 | G3: =SUM(G4:G42) -> 280718.4 | H3: =SUM(H4:H42) -> 0 | I3: =SUM(I4:I42) -> 124607.57 | J3: =I3/F3 -> 0.30742558 | K3: =SUM(K4:K42) -> 7449.12 | L3: Q1 2026 | M3: 451604.97 | N3: =M3*0.03 -> 13548.149
A4: 46037 | B4: 1559 | C4: TECHPRO | D4: Rocky | E4: Gcash | F4: 2400 | G4: 1500 | I4: =F:F-G:G-H:H -> 900 | J4: =I4/F4 -> 0.375 | K4: =I4*0.2 -> 180
B5: 1560 | C5: 46054 | I5: =F:F-G:G-H:H -> 0 | J5: =I5/F5 -> #DIV/0!
A6: 46030 | B6: 1612 | C6: Subic GS Auto | D6: Store | F6: 68880 | G6: 44145 | I6: =F:F-G:G-H:H -> 24735 | J6: =I6/F6 -> 0.35910279
A7: 46030 | B7: 1613 | C7: Drench | D7: Ikot | F7: 17600 | G7: 8000 | I7: =F:F-G:G-H:H -> 9600 | J7: =I7/F7 -> 0.54545455 | K7: =F7*0.01 -> 176
A8: 46030 | B8: 1614 | C8: RAJ | D8: Ikot | F8: 6600 | G8: 3625 | I8: =F:F-G:G-H:H -> 2975 | J8: =I8/F8 -> 0.45075758 | K8: =F8*0.01 -> 66
A9: 46030 | B9: 1615 | C9: D7A | D9: Ikot | F9: 17900 | G9: 13104 | I9: =F:F-G:G-H:H -> 4796 | J9: =I9/F9 -> 0.26793296 | K9: =F9*0.01 -> 179
A10: 46030 | B10: 1616 | C10: Vhong | D10: Ikot | F10: 7500 | G10: 6234 | I10: =F:F-G:G-H:H -> 1266 | J10: =I10/F10 -> 0.1688 | K10: =F10*0.01 -> 75
A11: 46031 | B11: 1617 | C11: Vhong | D11: Ikot | F11: 12100 | G11: 8620 | I11: =F:F-G:G-H:H -> 3480 | J11: =I11/F11 -> 0.28760331 | K11: =F11*0.01 -> 121
A12: 46034 | B12: 1618 | C12: RAJ | D12: Ikot | F12: 1500 | G12: 800 | I12: =F:F-G:G-H:H -> 700 | J12: =I12/F12 -> 0.46666667 | K12: =F12*0.01 -> 15
A13: 46037 | B13: 1619 | C13: Buenafe | D13: Ikot | F13: 4500 | G13: 2700 | I13: =F:F-G:G-H:H -> 1800 | J13: =I13/F13 -> 0.4 | K13: =F13*0.01 -> 45
A14: 46037 | B14: 1620 | C14: 2011 | D14: Ikot | F14: 800 | G14: 520 | I14: =F:F-G:G-H:H -> 280 | J14: =I14/F14 -> 0.35 | K14: =F14*0.01 -> 8
A15: 46037 | B15: 1621 | C15: D7A | D15: Ikot | F15: 16200 | G15: 12150 | I15: =F:F-G:G-H:H -> 4050 | J15: =I15/F15 -> 0.25 | K15: =F15*0.01 -> 162
A16: 46037 | B16: 1622 | C16: Drench | D16: Ikot | F16: 22600 | G16: =16000+2700 -> 18700 | I16: =F:F-G:G-H:H -> 3900 | J16: =I16/F16 -> 0.17256637 | K16: =F16*0.01 -> 226
A17: 46037 | B17: 1623 | C17: RAJ | D17: Ikot | F17: 1700 | G17: 1200 | I17: =F:F-G:G-H:H -> 500 | J17: =I17/F17 -> 0.29411765 | K17: =F17*0.01 -> 17
A18: 46037 | B18: 1624 | C18: Vhong | D18: Ikot | F18: 1700 | G18: 1400 | I18: =F:F-G:G-H:H -> 300 | J18: =I18/F18 -> 0.17647059 | K18: =F18*0.01 -> 17
A19: 46041 | B19: 1625 | C19: Auto Aire | D19: Ikot | F19: 5000 | G19: 3600 | I19: =F:F-G:G-H:H -> 1400 | J19: =I19/F19 -> 0.28 | K19: =F19*0.01 -> 50
A20: 46043 | B20: 1626 | C20: Buenafe | D20: Ikot | F20: 3000 | G20: 2180 | I20: =F:F-G:G-H:H -> 820 | J20: =I20/F20 -> 0.27333333 | K20: =F20*0.01 -> 30
A21: 46044 | B21: 1627 | C21: D7A | D21: Ikot | F21: 16400 | G21: 10290 | I21: =F:F-G:G-H:H -> 6110 | J21: =I21/F21 -> 0.37256098 | K21: =F21*0.01 -> 164 | L21: DR lacking in computation
A22: 46044 | B22: 1628 | C22: Drench | D22: Ikot | F22: 5000 | G22: 3500 | I22: =F:F-G:G-H:H -> 1500 | J22: =I22/F22 -> 0.3 | K22: =F22*0.01 -> 50
A23: 46045 | B23: 1629 | C23: Auto Aire | D23: Ikot | F23: 3600 | G23: 2450 | I23: =F:F-G:G-H:H -> 1150 | J23: =I23/F23 -> 0.31944444 | K23: =F23*0.01 -> 36
A24: 46048 | B24: 1630 | C24: Buenafe | D24: Ikot | F24: 1500 | G24: 1050 | I24: =F:F-G:G-H:H -> 450 | J24: =I24/F24 -> 0.3 | K24: =F24*0.01 -> 15
A25: 46048 | B25: 1631 | C25: Mervin Hilotin | D25: Ikot | F25: 7600 | G25: 5360 | I25: =F:F-G:G-H:H -> 2240 | J25: =I25/F25 -> 0.29473684 | K25: =F25*0.01 -> 76
A26: 46046 | B26: 1632 | C26: Vhong | D26: Ikot | F26: 8900 | G26: 6600 | I26: =F:F-G:G-H:H -> 2300 | J26: =I26/F26 -> 0.25842697 | K26: =F26*0.01 -> 89
A27: 46051 | B27: 1633 | C27: Auto Aire | D27: Ikot | F27: 1600 | G27: 1150 | I27: =F:F-G:G-H:H -> 450 | J27: =I27/F27 -> 0.28125 | K27: =F27*0.01 -> 16
A28: 46051 | B28: 1634 | C28: Auto Aire | D28: Ikot | F28: 1900 | G28: 1350 | I28: =F:F-G:G-H:H -> 550 | J28: =I28/F28 -> 0.28947368 | K28: =F28*0.01 -> 19
A29: 46051 | B29: 1635 | C29: D7A | D29: Ikot | F29: 8000 | G29: 4850 | I29: =F:F-G:G-H:H -> 3150 | J29: =I29/F29 -> 0.39375 | K29: =F29*0.01 -> 80
A30: 46051 | B30: 1636 | C30: Drench | D30: Ikot | F30: 18000 | G30: 16400 | I30: =F:F-G:G-H:H -> 1600 | J30: =I30/F30 -> 0.088888889 | K30: =F30*0.01 -> 180
A31: 46051 | B31: 1637 | C31: RAJ | D31: Ikot | F31: 7100 | G31: 5000 | I31: =F:F-G:G-H:H -> 2100 | J31: =I31/F31 -> 0.29577465 | K31: =F31*0.01 -> 71
A32: 46051 | B32: 1638 | C32: Darla | D32: Ikot | F32: 6860 | G32: 4850 | I32: =F:F-G:G-H:H -> 2010 | J32: =I32/F32 -> 0.29300292 | K32: =F32*0.01 -> 68.6
B33: 1655 | C33: cancelled | I33: =F:F-G:G-H:H -> 0 | J33: =I33/F33 -> #DIV/0!
B34: 1656 | C34: cancelled | I34: =F:F-G:G-H:H -> 0 | J34: =I34/F34 -> #DIV/0!
A35: 46036 | B35: 1657 | C35: Matthew Tan | D35: Rocky | E35: Gcash | F35: 4200 | G35: 2142.4 | I35: =F:F-G:G-H:H -> 2057.6 | J35: =I35/F35 -> 0.48990476 | K35: =I35*0.2 -> 411.52
A36: 46036 | B36: 1658 | C36: Subic GS Auto | D36: Store | E36: Check | F36: 3999.97 | G36: 1200 | I36: =F:F-G:G-H:H -> 2799.97 | J36: =I36/F36 -> 0.69999775
A37: 46036 | B37: 1659 | C37: Subic GS Auto | D37: Store | E37: Check | F37: 36786 | G37: 26928 | I37: =F:F-G:G-H:H -> 9858 | J37: =I37/F37 -> 0.26798238
A38: 46041 | B38: 1660 | C38: Vi N Vi | D38: Rocky | E38: Cash | F38: 12700 | G38: 7500 | I38: =F:F-G:G-H:H -> 5200 | J38: =I38/F38 -> 0.40944882 | K38: =I38*0.2 -> 1040
B39: 1661 | C39: cancelled | I39: =F:F-G:G-H:H -> 0 | J39: =I39/F39 -> #DIV/0!
A40: 46045 | B40: 1662 | C40: Marelco | D40: Rocky | E40: Cash | F40: 60000 | G40: 45000 | I40: =F:F-G:G-H:H -> 15000 | J40: =I40/F40 -> 0.25 | K40: =I40*0.2 -> 3000
A41: 46045 | B41: 1663 | C41: Brian Bosa | D41: Store | E41: Bank Transfer | F41: 1800 | G41: 1050 | I41: =F:F-G:G-H:H -> 750 | J41: =I41/F41 -> 0.41666667
A42: 46050 | B42: 1664 | C42: Jobs Wright | D42: Rocky | E42: Gcash | F42: 9400 | G42: 5570 | I42: =F:F-G:G-H:H -> 3830 | J42: =I42/F42 -> 0.40744681 | K42: =I42*0.2 -> 766
A44: For the month of February 2026 | C44: FEBRUARY | F44: =sum(F45:F102) -> 314994.6 | G44: =sum(G45:G102) -> 206326.08 | H44: =sum(H45:H80) -> 0 | I44: =sum(I45:I102) -> 108668.52 | J44: =I44/F44 -> 0.34498534 | K44: =sum(K45:K102) -> 8046.984 | M44: =sum(F46,F47,F49,F64,F73,F79,F86,F88,F90,F96) -> 61850 | N44: =M44*0.03 -> 1855.5
A45: 46056 | B45: 1639 | C45: Auto Aire | D45: Ikot | E45: Cash | F45: 1800 | G45: 1300 | I45: =F:F-G:G-H:H -> 500 | J45: =I45/F45 -> 0.27777778 | K45: =F45*0.01 -> 18
A46: 46056 | B46: 1640 | C46: Auto Aire | D46: Ikot | E46: Cash | F46: 2800 | G46: 1650 | I46: =F:F-G:G-H:H -> 1150 | J46: =I46/F46 -> 0.41071429 | K46: =F46*0.01 -> 28
A47: 46058 | B47: 1641 | C47: Auto Aire | D47: Ikot | E47: Cash | F47: 3800 | G47: 1250 | I47: =F:F-G:G-H:H -> 2550 | J47: =I47/F47 -> 0.67105263 | K47: =F47*0.01 -> 38
A48: 46058 | B48: 1642 | C48: Auto Aire | D48: Ikot | E48: Cash | F48: 3900 | G48: 3000 | I48: =F:F-G:G-H:H -> 900 | J48: =I48/F48 -> 0.23076923 | K48: =F48*0.01 -> 39
A49: 46058 | B49: 1643 | C49: Drench | D49: Ikot | F49: 8000 | G49: =1600+1700+780 -> 4080 | I49: =F:F-G:G-H:H -> 3920 | J49: =I49/F49 -> 0.49 | K49: =F49*0.01 -> 80
A50: 46058 | B50: 1644 | C50: RAJ | D50: Ikot | F50: 4400 | G50: 3200 | I50: =F:F-G:G-H:H -> 1200 | J50: =I50/F50 -> 0.27272727 | K50: =F50*0.01 -> 44
A51: 46058 | B51: 1645 | C51: Vhong | D51: Ikot | F51: 2500 | G51: 1700 | I51: =F:F-G:G-H:H -> 800 | J51: =I51/F51 -> 0.32 | K51: =F51*0.01 -> 25
B52: 1646 | C52: blank | I52: =F:F-G:G-H:H -> 0 | J52: =I52/F52 -> #DIV/0!
B53: 1647 | C53: blank | I53: =F:F-G:G-H:H -> 0 | J53: =I53/F53 -> #DIV/0!
B54: 1648 | C54: blank | I54: =F:F-G:G-H:H -> 0 | J54: =I54/F54 -> #DIV/0!
B55: 1649 | C55: blank | I55: =F:F-G:G-H:H -> 0 | J55: =I55/F55 -> #DIV/0!
B56: 1650 | C56: blank | I56: =F:F-G:G-H:H -> 0 | J56: =I56/F56 -> #DIV/0!
A57: 46055 | B57: 1665 | C57: JS Electronomical | D57: Arnold | E57: Cash | F57: 40246 | G57: 26078 | I57: =F:F-G:G-H:H -> 14168 | J57: =I57/F57 -> 0.35203498 | K57: =I57*0.2 -> 2833.6 | L57: with DP 10,000+20000
A58: 46055 | B58: 1666 | C58: JS Electronomical | D58: Arnold | E58: Cash | F58: 7100 | G58: 5518 | I58: =F:F-G:G-H:H -> 1582 | J58: =I58/F58 -> 0.2228169 | K58: =I58*0.2 -> 316.4
A59: 46055 | B59: 1667 | C59: Jobs Wright | D59: Rocky | E59: Gcash | F59: 4800 | G59: 2785 | I59: =F:F-G:G-H:H -> 2015 | J59: =I59/F59 -> 0.41979167 | K59: =I59*0.2 -> 403
A60: 46056 | B60: 1668 | C60: JS Electronomical | D60: Arnold | E60: Cash | F60: 8835 | G60: 5645 | I60: =F:F-G:G-H:H -> 3190 | J60: =I60/F60 -> 0.36106395 | K60: =I60*0.2 -> 638
A61: 46056 | B61: 1669 | C61: Subic GS Auto | D61: Store | E61: Check | F61: 4000 | G61: 1700 | I61: =F:F-G:G-H:H -> 2300 | J61: =I61/F61 -> 0.575
A62: 46056 | B62: 1670 | C62: Chrstian Erick | D62: Rocky | E62: Gcash | F62: 2400 | G62: 1500 | I62: =F:F-G:G-H:H -> 900 | J62: =I62/F62 -> 0.375 | K62: =I62*0.2 -> 180
A63: 46058 | B63: 1671 | C63: Subic GS Auto | D63: Store | E63: Check | F63: 3201 | G63: 1299 | I63: =F:F-G:G-H:H -> 1902 | J63: =I63/F63 -> 0.59418932
A64: 46059 | B64: 1672 | C64: 2011 | D64: Store | E64: Cash | F64: 1950 | G64: 1150 | I64: =F:F-G:G-H:H -> 800 | J64: =I64/F64 -> 0.41025641
A65: 46062 | B65: 1673 | C65: Subic GS Auto | D65: Store | E65: Check | F65: 5370 | G65: 3340 | I65: =F:F-G:G-H:H -> 2030 | J65: =I65/F65 -> 0.37802607
A66: 46065 | B66: 1701 | C66: RAJ | D66: Ikot | F66: 6150 | G66: 3820 | I66: =F:F-G:G-H:H -> 2330 | J66: =I66/F66 -> 0.37886179 | K66: =F66*0.01 -> 61.5
A67: 46065 | B67: 1702 | C67: Vhong | D67: Ikot | F67: 8090 | G67: 5606 | I67: =F:F-G:G-H:H -> 2484 | J67: =I67/F67 -> 0.30704574 | K67: =F67*0.01 -> 80.9
A68: 46065 | B68: 1703 | C68: Darla | D68: Ikot | F68: 1900 | G68: 1250 | I68: =F:F-G:G-H:H -> 650 | J68: =I68/F68 -> 0.34210526 | K68: =F68*0.01 -> 19
A69: 46069 | B69: 1674 | C69: BLB KING REYES | D69: Rocky | E69: Gcash | F69: 474 | G69: 168.28 | I69: =F:F-G:G-H:H -> 305.72 | J69: =I69/F69 -> 0.6449789 | K69: =I69*0.2 -> 61.144
A70: 46070 | B70: 1675 | C70: 2011 | D70: Rocky | E70: Gcash | F70: 8980 | G70: 5640 | I70: =F:F-G:G-H:H -> 3340 | J70: =I70/F70 -> 0.37193764 | K70: =I70*0.2 -> 668
A71: 46066 | B71: 1704 | C71: Auto Aire | D71: Ikot | F71: 6150 | G71: 3820 | I71: =F:F-G:G-H:H -> 2330 | J71: =I71/F71 -> 0.37886179 | K71: =F71*0.01 -> 61.5
B72: 1705 | C72: RAJ | D72: Ikot | F72: 8090 | G72: 5606 | I72: =F:F-G:G-H:H -> 2484 | J72: =I72/F72 -> 0.30704574 | K72: =F72*0.01 -> 80.9
B73: 1706 | C73: Drench | D73: Ikot | F73: 1900 | G73: 1250 | I73: =F:F-G:G-H:H -> 650 | J73: =I73/F73 -> 0.34210526 | K73: =F73*0.01 -> 19
B74: 1707 | C74: Auto Aire | D74: Ikot | F74: 760 | G74: 520 | I74: =F:F-G:G-H:H -> 240 | J74: =I74/F74 -> 0.31578947 | K74: =F74*0.01 -> 7.6
B75: 1708 | C75: Auto Aire | D75: Ikot | F75: 5000 | G75: 4000 | I75: =F:F-G:G-H:H -> 1000 | J75: =I75/F75 -> 0.2 | K75: =F75*0.01 -> 50
B76: 1709 | C76: D7A | D76: Ikot | F76: 8500 | G76: 5450 | I76: =F:F-G:G-H:H -> 3050 | J76: =I76/F76 -> 0.35882353 | K76: =F76*0.01 -> 85
B77: 1710 | C77: Mervin Hilotin | D77: Ikot | F77: 2660 | G77: 1820 | I77: =F:F-G:G-H:H -> 840 | J77: =I77/F77 -> 0.31578947 | K77: =F77*0.01 -> 26.6
B78: 1711 | C78: D7A | D78: Ikot | F78: 4650 | G78: 3150 | I78: =F:F-G:G-H:H -> 1500 | J78: =I78/F78 -> 0.32258065 | K78: =F78*0.01 -> 46.5
B79: 1712 | C79: RAJ | D79: Ikot | F79: 8300 | G79: 5450 | I79: =F:F-G:G-H:H -> 2850 | J79: =I79/F79 -> 0.34337349 | K79: =F79*0.01 -> 83
B80: 1713 | C80: Auto Aire | D80: Ikot | F80: 5600 | G80: 4000 | I80: =F:F-G:G-H:H -> 1600 | J80: =I80/F80 -> 0.28571429 | K80: =F80*0.01 -> 56
A81: 46072 | B81: 1714 | C81: Mervin Hilotin | D81: Ikot | F81: 4800 | G81: 2820 | I81: =F:F-G:G-H:H -> 1980 | J81: =I81/F81 -> 0.4125 | K81: =F81*0.01 -> 48
A82: 46077 | B82: 1676 | C82: REC AC | D82: Rocky | F82: 4950 | G82: 2637.4 | I82: =F:F-G:G-H:H -> 2312.6 | J82: =I82/F82 -> 0.46719192 | K82: =I82*0.2 -> 462.52
A83: 46079 | B83: 1677 | C83: Subic GS Auto | D83: Store | E83: Check | F83: 4000.6 | G83: 1700 | I83: =F:F-G:G-H:H -> 2300.6 | J83: =I83/F83 -> 0.57506374
B84: 1678 | C84: Subic GS Auto | D84: Store | E84: Check | F84: 18144 | G84: 14144 | I84: =F:F-G:G-H:H -> 4000 | J84: =I84/F84 -> 0.22045855
A85: 46079 | B85: 1679 | C85: REC AC | D85: Rocky | F85: 4761 | G85: 3975 | I85: =F:F-G:G-H:H -> 786 | J85: =I85/F85 -> 0.16509137 | K85: =I85*0.2 -> 157.2
A86: 46073 | B86: 1715 | C86: DRENCH | D86: Ikot | F86: 26500 | G86: 23672 | I86: =F:F-G:G-H:H -> 2828 | J86: =I86/F86 -> 0.10671698 | K86: =F86*0.01 -> 265
B87: 1716 | C87: RAJ | D87: Ikot | F87: 1800 | G87: 850 | I87: =F:F-G:G-H:H -> 950 | J87: =I87/F87 -> 0.52777778 | K87: =F87*0.01 -> 18
A88: 46077 | B88: 1717 | C88: Auto Aire | D88: Ikot | F88: 2560 | G88: 1560 | I88: =F:F-G:G-H:H -> 1000 | J88: =I88/F88 -> 0.390625 | K88: =F88*0.01 -> 25.6
B89: 1718 | C89: Auto Aire | D89: Ikot | F89: 500 | G89: 240 | I89: =F:F-G:G-H:H -> 260 | J89: =I89/F89 -> 0.52 | K89: =F89*0.01 -> 5
B90: 1719 | C90: Auto Aire | D90: Ikot | F90: 1800 | G90: 1300 | I90: =F:F-G:G-H:H -> 500 | J90: =I90/F90 -> 0.27777778 | K90: =F90*0.01 -> 18
A91: 46079 | B91: 1720 | C91: 2011 | D91: Ikot | F91: 5900 | G91: 4180 | I91: =F:F-G:G-H:H -> 1720 | J91: =I91/F91 -> 0.29152542 | K91: =F91*0.01 -> 59
B92: 1721 | C92: D7A | D92: Ikot | F92: 12100 | G92: 7850 | I92: =F:F-G:G-H:H -> 4250 | J92: =I92/F92 -> 0.35123967 | K92: =F92*0.01 -> 121
B93: 1722 | C93: RAJ | D93: Ikot | F93: 9420 | G93: 5960 | I93: =F:F-G:G-H:H -> 3460 | J93: =I93/F93 -> 0.36730361 | K93: =F93*0.01 -> 94.2
B94: 1723 | C94: VHONG | D94: Ikot | F94: 10600 | G94: 5795 | I94: =F:F-G:G-H:H -> 4805 | J94: =I94/F94 -> 0.45330189 | K94: =F94*0.01 -> 106
B95: 1724 | C95: DARLA | D95: Ikot | F95: 9600 | G95: 3100 | I95: =F:F-G:G-H:H -> 6500 | J95: =I95/F95 -> 0.67708333 | K95: =F95*0.01 -> 96
A96: 46080 | B96: 1680 | C96: 2011 | D96: Store | F96: 4240 | G96: 3000 | I96: =F:F-G:G-H:H -> 1240 | J96: =I96/F96 -> 0.29245283
A97: 46081 | B97: 1681 | C97: REC AC | D97: Rocky | F97: 4943 | G97: 2637.4 | I97: =F:F-G:G-H:H -> 2305.6 | J97: =I97/F97 -> 0.46643739 | K97: =I97*0.2 -> 461.12
A98: 46080 | B98: 1725 | C98: Auto Air | D98: Ikot | F98: 1400 | G98: 780 | I98: =F:F-G:G-H:H -> 620 | J98: =I98/F98 -> 0.44285714 | K98: =F98*0.01 -> 14
B99: 1726 | C99: Auto Air | D99: Ikot | F99: 760 | G99: 460 | I99: =F:F-G:G-H:H -> 300 | J99: =I99/F99 -> 0.39473684 | K99: =F99*0.01 -> 7.6
B100: 1727 | C100: RAJ | D100: Ikot | F100: 1400 | G100: 1100 | I100: =F:F-G:G-H:H -> 300 | J100: =I100/F100 -> 0.21428571 | K100: =F100*0.01 -> 14
B101: 1728 | C101: HILARIO | D101: Ikot | F101: 760 | G101: 520 | I101: =F:F-G:G-H:H -> 240 | J101: =I101/F101 -> 0.31578947 | K101: =F101*0.01 -> 7.6
...

Sheet 2026 Ikot
A1: 2025 Ikot Summary
A3: Sales: | F3: Collection
A4: DR # | B4: Customer Name | C4: Amount | D4: Mode | F4: CR # | G4: Customer Name | H4: Amount | I4: Mode | J4: Remarks
B5: Jan 8 2026 | C5: =SUM(C6:C17) -> 88100 | G5: Mervin Hilotin | H5: 3000 | I5: Gcash
A6: 1613 | B6: Drench | C6: 17600 | G6: June Tibayan | H6: 2000 | I6: Cash | J6: Rocky Expense 1400
A7: 1614 | B7: RAJ | C7: 6600 | G7: D7A | H7: 5000 | I7: Gcash
A8: 1615 | B8: D7A | C8: 17900 | D8: Gcash | G8: MHM | H8: 2000 | I8: Gcash
A9: 1616 | B9: Vhong | C9: 7500 | D9: Cash | G9: RAJ | H9: 6600 | I9: Cash | J9: expense 1300 gas & meal
A10: 1617 | B10: Vhong | C10: 12100
A11: 1618 | B11: RAJ | C11: 1500
A12: 1619 | B12: Buenafe | C12: 4500
A13: 1620 | B13: 2011 | C13: 800
A14: 1621 | B14: D7A | C14: 16200 | G14: 46058
A15: 1622 | F15: 664 | G15: D7A | H15: 13300
A16: 1623 | B16: RAJ | C16: 1700 | F16: 665 | G16: Drench | H16: 17839.29
A17: 1624 | B17: Vhong | C17: 1700 | F17: 666 | G17: VHONG | H17: 5000
G19: 46065
A20: 1625 | B20: Auto Aire | C20: 5000 | D20: Gcash | F20: 667 | G20: MESAR | H20: 1000
A21: 1626 | B21: Buenafe | C21: 3000 | D21: Gcash | F21: 668 | G21: D7A | H21: 9000
A22: 1627 | B22: Buenafe | C22: 1500 | F22: 669 | G22: Drench | H22: 8000
A23: 1628 | B23: Mervin Hilotin | C23: 7600 | F23: 670 | G23: VHONG | H23: 5000
A24: 1629 | B24: Vhong | C24: 8900 | F24: 671 | G24: Darla | H24: 5000
A25: 1630 | B25: Buenafe | C25: 1500
A26: 1631 | G26: 46072
A27: 1632 | F27: 672 | G27: D7A | H27: 9000
A28: 1633 | F28: 673 | G28: MHM | H28: 2000
A29: 1634 | F29: 674 | G29: VHONG | H29: 5000
G31: 46079
A32: 1635 | F32: 675 | G32: D7A | H32: 14050
A33: 1636 | F33: 676 | G33: VHONG | H33: 5000
A34: 1637 | F34: 677 | G34: Darla | H34: 5000
G36: 46083
F37: 682 | G37: Subic GS Auto | H37: 17982
G39: 46085
A40: 1638 | F40: 678 | G40: Subic GS Auto | H40: 5328
B41: February 03, 2026
A42: 1639 | B42: Auto Aire | C42: 1800 | G42: 46086
A43: 1640 | B43: Auto Aire | C43: 2800 | F43: 679 | G43: D7A | H43: 18000
F44: 680 | G44: Drench | H44: 18500
B45: 46058 | F45: 681 | G45: MHM | H45: 1500
A46: 1641 | B46: Auto Aire | C46: 3800 | F46: 683 | G46: Subic GS Auto | H46: 3964.88
A47: 1642 | B47: Auto Aire | C47: 3900
A48: 1643 | B48: Drench | C48: 8000 | G48: 46093
A49: 1644 | B49: RAJ | C49: 4400 | F49: 684 | G49: D7A | H49: 20000
A50: 1645 | B50: Vhong | C50: 2500 | F50: 685 | G50: Drench | H50: 17400
F51: 686 | G51: VHONG | H51: 5000
G53: 46100
B54: 46065 | F54: 687 | G54: D7A | H54: 16700
A55: 1701 | B55: RAJ | C55: 6150 | F55: 688 | G55: Drench | H55: 25173.21
A56: 1702 | B56: Vhong | C56: 8090 | F56: 689 | G56: VHONG | H56: 5000
A57: 1703 | B57: Darla | C57: 1900 | F57: 690 | G57: Darla | H57: 5000
B59: 46066 | G59: 46107
A60: 1704 | B60: Auto Aire | C60: 6150 | F60: 691 | G60: Blank
A61: 1705 | B61: RAJ | C61: 8090 | F61: 692 | G61: D7A | H61: 10000
A62: 1706 | B62: Drench | C62: 1900 | F62: 693 | G62: Drench | H62: 6400
A63: 1707 | B63: Auto Aire | C63: 760 | F63: 694 | G63: Vhong | H63: 5000
A64: 1708 | B64: Auto Aire | C64: 5000 | F64: 695 | G64: Darla | H64: 5000
A65: 1709 | B65: D7A | C65: 8500
A66: 1710 | B66: Mervin Hilotin | C66: 2660 | G66: 46113
A67: 1711 | B67: D7A | C67: 4650 | F67: 696 | G67: D7A | H67: 10000
A68: 1712 | B68: RAJ | C68: 8300
A69: 1713 | B69: Auto Aire | C69: 5600 | G69: 46120
F70: 700 | G70: Subic GS Auto | H70: 37549.97
B71: 46072
A72: 1714 | B72: Mervin Hilotin | C72: 4800
B74: 46073 | G74: 46121
A75: 1715 | B75: DRENCH | C75: 26500 | F75: 697 | G75: D7A | H75: 10000
A76: 1716 | B76: RAJ | C76: 1800 | F76: 698 | G76: Vhong | H76: 5000
F77: 699 | G77: Darla | H77: 5000
B78: 46077
A79: 1717 | B79: Auto Aire | C79: 2560 | G79: 46128
A80: 1718 | B80: Auto Aire | C80: 500 | F80: 701 | G80: D7A | H80: 25000
A81: 1719 | B81: Auto Aire | C81: 1800 | F81: 702 | G81: Drench | H81: 9100
F82: 703 | G82: Vhong | H82: 5000
B83: 46079 | F83: 704 | G83: Darla | H83: 5000
A84: 1720 | B84: 2011 | C84: 5900
A85: 1721 | B85: D7A | C85: 12100 | G85: 46135
A86: 1722 | B86: RAJ | C86: 9420 | F86: 705 | G86: D7A | H86: 20000
A87: 1723 | B87: VHONG | C87: 10600 | F87: 706 | G87: Vhong | H87: 5000
A88: 1724 | B88: DARLA | C88: 9600
G89: 46139
B90: 46080 | F90: 707 | G90: Subic GS Auto | H90: 43929.29
A91: 1725 | B91: Auto Air | C91: 1400
A92: 1726 | B92: Auto Air | C92: 760 | G92: 46142
A93: 1727 | B93: RAJ | C93: 1400 | F93: 708 | G93: Drench | H93: 7900
A94: 1728 | B94: HILARIO | C94: 760
A95: 1729 | B95: Auto Air | C95: 1750
B98: 46085
A99: 1730 | B99: MED | C99: 380
A100: 1731 | B100: Auto Air | C100: 3700
A101: 1732 | B101: D7A | C101: 9400
A102: 1733 | B102: Auto Air | C102: 1400
A103: 1734 | B103: Buenafe | C103: 1500
A104: 1735 | B104: Cancelled | C104: -----------------
B106: 46086
A107: 1736 | B107: William | C107: 9400
A108: 1737 | B108: DRENCH | C108: 17900
A109: 1738 | B109: William | C109: 1300
A110: 1739 | B110: D7A | C110: 11200
A111: 1740 | B111: RAJ | C111: 9490
...

Sheet 2026 Purch
A1: Date | B1: Ref # | C1: Suppliers Name | D1: Term | E1: Amount | F1: Payment | G1: Date | H1: Total Purchases Monthly | I1: Cost of Sales | J1: Inventory Balance | K1: End Balance Dec 31 2025
D2: Days | E2: =sum(E4:E1035) -> 3540492.6 | F2: =sum(F4:F1035) -> 0 | H2: =sum(H4:H1035) -> 2104151 | I2: =sum(I4:I1035) -> 2051023.4 | J2: =K2+H2-I2 -> 635649.14 | K2: 582521.5 | M2: Due Date | N2: Check #
A3: 45995 | B3: DR#191 | C3: STAL | D3: 90 | E3: 4750 | L3: issued check
A4: 45994 | B4: DR#189 | C4: STAL | D4: 90 | E4: 31350 | L4: issued check
A5: 46009 | B5: DR#197 | C5: STAL | D5: 90 | E5: 5100 | L5: issued check
A6: 46029 | B6: DR#94218 | C6: JYQL | D6: 30 | E6: 10290 | L6: issued check
A7: 46030 | B7: DR#002 | C7: ENTALPIA | D7: 15 | E7: 44145 | L7: paid
A8: 46035 | B8: DR#70746 | C8: JYQL | D8: 30 | E8: 9400 | L8: issued check
A9: 46036 | C9: UNIWESTECH | D9: 7 | E9: 16000 | L9: paid
A10: 46036 | B10: DR#108 | C10: STAL | D10: 90 | E10: 14550 | L10: issued check
A11: 46037 | B11: DR#001 | C11: ENTALPIA | D11: 15 | E11: 26928 | L11: paid
A12: 46038 | B12: DR#91780 | C12: JYQL | D12: 30 | E12: 19240 | L12: issued check
A13: 46041 | B13: DR#14429 | C13: JYQL | D13: 30 | E13: 9200 | L13: issued check
A14: 46042 | B14: DR#44561 | C14: JYQL | D14: 30 | E14: 45000 | L14: issued check
A15: 46043 | B15: DR#110 | C15: STAL | D15: 90 | E15: 6750 | L15: issued check
A16: 46044 | B16: DR#111 | C16: STAL | D16: 90 | E16: 5650 | L16: issued check
A17: 46044 | B17: DR#85619 | C17: JYQL | D17: 30 | E17: 6385 | L17: issued check
A18: 46049 | B18: DR#95150 | C18: JYQL | D18: 30 | E18: 20730 | L18: issued check
A19: 46049 | B19: DR#116 | C19: STAL | D19: 90 | E19: 10800 | L19: issued check
A20: 46051 | C20: UNIWESTECH | D20: 7 | E20: 16400 | H20: =sum(E6:E20) -> 261468 | I20: ='2026 DS'!G3 -> 280718.4 | J20: =K2+H20-I20 -> 563271.1 | L20: issued check
A21: 46051 | B21: DR#119 | C21: STAL | D21: 90 | E21: 8500 | L21: issued check | M21: =A21+D21 -> 46141
A22: 46056 | B22: DR#126 | C22: STAL | D22: 90 | E22: 10500 | L22: issued check | M22: =A22+D22 -> 46146 | N22: 943019
A23: 46056 | C23: ISHABELLA | D23: 0 | E23: =9854.8 -> 9854.8 | L23: paid
A24: 46057 | B24: DR#51328 | C24: JYQL | D24: 30 | E24: 2780 | L24: issued check | M24: =A24+D24+15 -> 46102
A25: 46057 | B25: DR#92794 | C25: JYQL | D25: 30 | E25: 4750 | L25: issued check | M25: =A25+D25+15 -> 46102
A26: 46058 | B26: DR#127 | C26: STAL | D26: 90 | E26: 15550 | L26: issued check | M26: =A26+D26 -> 46148
A27: 46065 | B27: DR#21733 | C27: JYQL | D27: 30 | E27: 17050 | L27: issued check | M27: =A27+D27+15 -> 46110
A28: 46071 | B28: DR#52984 | C28: JYQL | D28: 30 | E28: 18090 | L28: issued check | M28: =A28+D28+15 -> 46116
A29: 46071 | B29: DR#130 | C29: STAL | D29: 90 | E29: 11750 | L29: issued check | M29: =A29+D29 -> 46161
A30: 46073 | C30: UNIWESTECH | D30: 0 | E30: 16600 | L30: paid
A31: 46077 | B31: DR# 45034 | C31: JYQL | D31: 30 | E31: 7840 | L31: issued check | M31: =A31+D31+15 -> 46122
A32: 46076 | B32: DR# 0132 | C32: STAL | D32: 90 | E32: 43850 | L32: issued check | M32: =A32+D32 -> 46166 | O32: 46178 | P32: 20000/23850
A33: 46078 | C33: ISHABELLA | D33: 30 | E33: =9854.8+7072 -> 16926.8 | L33: paid | Q33: 2pcs DP 8m | R33: 5570
A34: 46078 | C34: ENTALPIA | D34: 10 | E34: =5*7072 -> 35360 | H34: =sum(E21:E34) -> 219401.6 | I34: ='2026 DS'!G44 -> 206326.08 | J34: =J20+H34-I34 -> 576346.62 | L34: c/o Ishabella | M34: =A34 -> 46078 | Q34: 1 tank 134A | R34: 7072
A35: 46084 | B35: DR# 93049 | C35: JYQL | D35: 38 | E35: 15095 | L35: issued check | M35: =A35+D35 -> 46122 | N35: 943020 | Q35: Total | R35: =SUM(P37:P42) -> 4284.8
A36: 46085 | B36: DR# 74013 | C36: JYQL | D36: 37 | E36: 5600 | L36: issued check | M36: =A36+D36 -> 46122 | O36: Ishabella | Q36: 2/18/2026 deposit | R36: -3964.29
A37: 46086 | B37: DR# 139 | C37: STAL | D37: 90 | E37: 20000 | L37: issued check | M37: =A37+D37 -> 46176 | N37: 943021 | O37: 2pcs DP 6m | P37: 4284.8 | Q37: 2/25/2026 deposit | R37: -3172.42
A38: 46092 | B38: DR# 61845 | C38: JYQL | D38: 37 | E38: 38530 | L38: issued check | M38: =A38+D38 -> 46129 | N38: 943022 | Q38: 03/02/2026 deposit | R38: -5328
A39: 46092 | B39: DR# 143 | C39: STAL | D39: 90 | E39: 20680 | L39: issued check | M39: =A39+D39 -> 46182 | N39: 943023 | Q39: 03/02/2026 full payment | R39: =-sum(R35:R38) -> 8179.91
A40: 46097 | B40: DR# 0117 | C40: HYSIS | D40: 10 | E40: 191644.12 | L40: issued check | M40: =A40+D40 -> 46107 | O40: 2 checks | Q40: Balance | R40: =sum(R35:R39) -> 0
A41: 46098 | B41: DR# 02137 | C41: JYQL | D41: 38 | E41: 20380 | L41: issued check | M41: =A41+D41 -> 46136 | N41: 943024
A42: 46099 | B42: DR# 148 | C42: STAL | D42: 90 | E42: 14300 | L42: issued check | M42: =A42+D42 -> 46189 | N42: 943025
A43: 46102 | B43: DR#212162 | C43: WINTERPINE | D43: 45 | E43: 86031 | L43: issued check | M43: =A43+D43 -> 46147 | N43: 943026 / 943027 / 943028
A44: 46106 | B44: DR#75401 | C44: JYQL | D44: 44 | E44: 42170 | L44: issued check | M44: =A44+D44 -> 46150 | O44: 42129
A45: 46106 | B45: DR# 53181 | C45: JYQL | D45: 40 | E45: 9200 | L45: issued check | M45: =A45+D45 -> 46146
B46: Return | C46: JYQL | E46: -1550 | L46: applied to DR#35765 | N46: for deduction next check (April)
A47: 46106 | B47: DR# 153 | C47: STAL | D47: 90 | E47: 5250 | L47: issued check | M47: =A47+D47 -> 46196
A48: 46107 | B48: DR#212394 | C48: WINTERPINE | D48: 92 | E48: 16780 | L48: issued check | M48: =A48+D48 -> 46199 | N48: 943045
A49: 46109 | B49: DR#212516 | C49: WINTERPINE | D49: 97 | E49: 28330 | L49: issued check | M49: =A49+D49 -> 46206 | N49: 943046
A50: 46107 | C50: ISHABELLA | E50: 3500 | L50: paid 05/01/26 | M50: =A50+D50 -> 46107 | N50: 2 ROLLS HOSE
A51: 46084 | C51: ISHABELLA | E51: 1100 | L51: paid 05/01/26 | M51: =A51+D51 -> 46084 | N51: VIOS BLOWER MOTOR
A52: 46112 | B52: DR# 155 | C52: STAL | D52: 90 | E52: 26500 | L52: issued check | M52: =A52+D52 -> 46202
A53: 46112 | B53: DR# 30724 | C53: JYQL | D53: 45 | E53: 4800 | H53: =sum(E35:E53) -> 548340.12 | I53: ='2026 DS'!G103 -> 521692.8 | J53: =J34+H53-I53 -> 602993.94 | L53: issued check | M53: =A53+D53 -> 46157
A54: 46119 | C54: ISHABELLA | E54: 720 | L54: paid 05/01/26 | M54: =A54+D54 -> 46119 | N54: 8 ND OIL
A55: 46119 | C55: 3BMA | E55: 46200 | L55: paid 04/14/26 | M55: =A55+D55 -> 46119 | N55: 6 R134A
A56: 46120 | B56: DR#43432 | C56: JYQL | D56: 30 | E56: 9500 | L56: issued check | M56: =A56+D56 -> 46150
A57: 46126 | B57: DR#655588 | C57: JYQL | D57: 40 | E57: 28200 | L57: issued check | M57: =A57+D57 -> 46166
A58: 46126 | B58: DR#2885 | C58: 3BMA | D58: 7 | E58: 23100 | L58: issued check | M58: =A58+D58 -> 46133
A59: 46118 | B59: DR#212730 | C59: WINTERPINE | D59: 60 | E59: 108810 | L59: issued check | M59: =A59+D59 -> 46178 | O59: June 5,12,19,26 | Q59: =E59/4 -> 27202.5
A60: 46129 | B60: DR#213350 | C60: WINTERPINE | D60: 60 | E60: 59463.12 | L60: issued check | M60: =A60+D60 -> 46189 | O60: June 19, July 3, 10
A61: 46127 | B61: DR# 158 | C61: STAL | D61: 90 | E61: 14550 | L61: issued check | M61: =A61+D61 -> 46217
A62: 46134 | B62: DR#61962 | C62: JYQL | D62: 49 | E62: 5325 | L62: issued check | M62: =A62+D62 -> 46183 | N62: 943047
A63: 46134 | B63: DR#35765 | C63: JYQL | D63: 37 | E63: =27470-1550 -> 25920 | L63: issued check | M63: =A63+D63 -> 46171 | N63: 943048
A64: 46134 | B64: DR#0159 | C64: KM AIRE (HYSIS) | D64: PAID | E64: 14389 | L64: Cash payment
A65: 46132 | B65: DR#3039 | C65: 3BMA | D65: 7 | E65: 46200 | L65: paid 04/29/26 | M65: =A65+D65 -> 46139
A66: 46138 | B66: DR#3124 | C66: 3BMA | D66: 8 | E66: 30800 | L66: issued check | M66: =A66+D66 -> 46146
A67: 46140 | B67: DR#0169 | C67: STAL | D67: 90 | E67: 34720 | L67: issued check | M67: =A67+D67 -> 46230 | N67: 943049
A68: 46140 | B68: DR#42282 | C68: JYQL | D68: 38 | E68: 17225 | L68: issued check | M68: =A68+D68 -> 46178 | N68: 943050
A69: 46140 | B69: DR#73165 | C69: JYQL | D69: 45 | E69: 24760 | L69: issued check | M69: =A69+D69 -> 46185 | N69: 956451
A70: 46132 | B70: DR#213490 | C70: WINTERPINE | D70: 90 | E70: 7360 | H70: =sum(E54:E70) -> 497242.12 | I70: ='2026 DS'!G170 -> 500048.32 | J70: =J53+H70-I70 -> 600187.74 | L70: issued check | M70: =A70+D70 -> 46222 | N70: 956452
A71: 46147 | B71: DR#40309 | C71: JYQL | D71: 52 | E71: 15170 | L71: issued check | M71: =A71+D71 -> 46199 | N71: 956453
A72: 46149 | B72: DR#80939 | C72: JYQL | D72: 45 | E72: 5200 | L72: issued check | M72: =A72+D72 -> 46194 | N72: 956454
A73: 46149 | B73: DR#0172 | C73: STAL | D73: 90 | E73: 7500 | L73: issued check | M73: =A73+D73 -> 46239 | O73: ok
A74: 46155 | B74: DR#02529 | C74: JYQL | D74: 44 | E74: 36595 | L74: issued check | M74: =A74+D74 -> 46199 | N74: 956455 / 956456 | O74: June 26 (16,595) July 10 (20,000)
A75: 46162 | B75: DR#62933 | C75: JYQL | D75: 45 | E75: 48685 | L75: issued check | M75: =A75+D75 -> 46207 | N75: 956457 / 956458 / 956459 | O75: July 8 (15,000) July 15 (15,000) July 20 (18,685)
A76: 46155 | B76: DR#0173 | C76: STAL | D76: 90 | E76: 53890 | L76: issued check | M76: =A76+D76 -> 46245 | N76: 956460 / 956461 / 956462 | O76: Aug 7 (20,000) 14 (20,000) 21 (13,890)
A77: 46102 | B77: DR#212162 | C77: WINTERPINE (Adjustment) | D77: 0 | E77: 675 | L77: fund transfer 5/27/26 | M77: =A77+D77 -> 46102
A78: 46095 | B78: RE-ISSUE | C78: STAL | D78: 0 | E78: 4750 | L78: issued check | M78: =A78+D78 -> 46095 | N78: 956463 | O78: May 28
A79: 46164 | B79: DR#0086 | C79: KM AIRE (HYSIS) | D79: 0 | E79: 15675 | L79: Cash payment | M79: =A79+D79 -> 46164
A80: 46170 | B80: DR#183 | C80: STAL | D80: 99 | E80: 12000 | L80: issued check | M80: =A80+D80 -> 46269 | N80: 956476
A81: 46170 | B81: DR#63073 | C81: JYQL | D81: 50 | E81: 22580 | H81: =sum(E71:E81) -> 222720 | I81: ='2026 DS'!G239 -> 222972 | J81: =J70+H81-I81 -> 599935.74 | L81: issued check | M81: =A81+D81 -> 46220 | N81: 956477
A82: 46174 | B82: DR#22586 | C82: JYQL | D82: 60 | E82: 34950 | L82: issued check | M82: =A82+D82 -> 46234 | O82: ok
A83: 46174 | B83: DR#90569 | C83: JYQL | D83: 53 | E83: 4150 | L83: issued check | M83: =A83+D83 -> 46227 | O83: ok
A84: 46175 | B84: DR#0185 | C84: STAL | D84: 90 | E84: 17260 | L84: issued check | M84: =A84+D84 -> 46265 | O84: ok
A85: 46179 | B85: DR#04263 | C85: JYQL | D85: 48 | E85: 17350 | L85: issued check | M85: =A85+D85 -> 46227 | N85: 956478
A86: 46182 | B86: DR#0188 | C86: STAL | D86: 90 | E86: 7950 | L86: issued check | M86: =A86+D86 -> 46272
A87: 46182 | B87: DR#92228 | C87: JYQL | D87: 59 | E87: 29350 | L87: issued check | M87: =A87+D87 -> 46241 | O87: ok
A88: 46190 | B88: DR#0002 | C88: STAL | D88: 90 | E88: 12840 | L88: issued check | M88: =A88+D88 -> 46280 | N88: 956479 | O88: ok
A89: 46190 | B89: DR#0006 | C89: STAL | D89: 90 | E89: 3600 | L89: issued check | M89: =A89+D89 -> 46280 | O89: ok
A90: 46190 | B90: DR# | C90: ISHABELLA | D90: 30 | E90: 5570 | M90: =A90+D90 -> 46220
A91: 46190 | C91: ISHABELLA | D91: 30 | E91: 4284.8 | M91: =A91+D91 -> 46220
A92: 46192 | B92: DR#21329 | C92: 3BMA | D92: 0 | E92: 63200 | L92: fund transfer | M92: =A92+D92 -> 46192
A93: 45831 | B93: DR#72846 | C93: JYQL | D93: 52 | E93: 28360 | L93: issued check | M93: =A93+D93 -> 45883 | O93: ok
A94: 46197 | B94: DR#0004 | C94: STAL | D94: 90 | E94: 8500 | L94: issued check | M94: =A94+D94 -> 46287 | O94: ok
A95: 46197 | B95: DR#0002 | C95: STAL | D95: 90 | E95: 8500 | L95: issued check | M95: =A95+D95 -> 46287 | O95: ok
A96: 46197 | C96: ISHABELLA | D96: 30 | E96: 65154.8 | L96: paid 55300 direct to 3BMA (July 30 - 50k, Aug 1 - 5300
A97: 46198 | B97: DR#03094 | C97: JYQL | D97: 57 | E97: 17500 | L97: issued check | M97: =A97+D97 -> 46255 | O97: ok
A98: 46198 | B98: DR#03094 | C98: JYQL (additional) | E98: 1500 | M98: 46251 | N98: 956505
A99: 46198 | B99: DR#0218 | C99: KM AIRE (HYSIS) | D99: 0 | E99: 13354.8 | L99: cash payment
A100: 46203 | B100: DR#118 | C100: KM AIRE (HYSIS) | D100: 0 | E100: 11604.8 | H100: =sum(E82:E100) -> 354979.2 | I100: ='2026 DS'!G291 -> 319265.8 | J100: =J81+H100-I100 -> 635649.14 | L100: cash payment
...

Sheet 2026 AP
A1: Aton Aire Trading Corporation | G1: Summary | H1: Payment | I1: Purchases | J1: Balance
A2: 2026 Payable | G2: Ishabella | H2: =K12 -> 182141.6 | I2: =L12 -> 142471.2 | J2: =M12 -> -134107.4
A3: =TODAY() -> 46311 | G3: JYQL | H3: =N12 -> 594175 | I3: =O12 -> 675800 | J3: =P12 -> 284235
G4: STAL | H4: =Q12 -> 282470 | I4: =R12 -> 395940 | J4: =S12 -> 382490
G5: Winterpine | H5: =T12 -> 271260.32 | I5: =U12 -> 307449.12 | J5: =V12 -> 112396
G6: Hisys | H6: =W12 -> 246667.72 | I6: =X12 -> 246667.72 | J6: =Y12 -> 0
G7: Uniwestech | H7: =Z12 -> 129600 | I7: =AA12 -> 49000 | J7: =AB12 -> 0
G8: Entalpia | H8: =AC12 -> 71073 | I8: =AD12 -> 71073 | J8: =AE12 -> 0
G9: 3BMA | H9: =AF12 -> 69300 | I9: =AG12 -> 209500 | J9: =AH12 -> 140200
H11: =sum(H2:H10) -> 1846687.6 | I11: =sum(I2:I10) -> 2097901 | J11: =sum(J2:J10) -> 785213.6
H12: =SUM(H16:H1048583) -> 1846687.6 | I12: =SUM(I16:#REF!) -> 2097901 | J12: =J15+I12-H12 -> 785213.6 | K12: =SUM(K16:K1048583) -> 182141.6 | L12: =SUM(L16:#REF!) -> 142471.2 | M12: =M15+L12-K12 -> -134107.4 | N12: =SUM(N16:N1048583) -> 594175 | O12: =SUM(O16:#REF!) -> 675800 | P12: =P15+O12-N12 -> 284235 | Q12: =SUM(Q16:Q1048583) -> 282470 | R12: =SUM(R16:#REF!) -> 395940 | S12: =S15+R12-Q12 -> 382490 | T12: =SUM(T16:T1048583) -> 271260.32 | U12: =SUM(U16:#REF!) -> 307449.12 | V12: =V15+U12-T12 -> 112396 | W12: =SUM(W16:W1048583) -> 246667.72 | X12: =SUM(X16:#REF!) -> 246667.72 | Y12: =Y15+X12-W12 -> 0 | Z12: =SUM(Z16:Z1048583) -> 129600 | AA12: =SUM(AA16:#REF!) -> 49000 | AB12: =AB15+AA12-Z12 -> 0 | AC12: =SUM(AC16:AC1048583) -> 71073 | AD12: =SUM(AD16:#REF!) -> 71073 | AE12: =AE15+AD12-AC12 -> 0 | AF12: =SUM(AF16:AF1048583) -> 69300 | AG12: =SUM(AG16:#REF!) -> 209500 | AH12: =AH15+AG12-AF12 -> 140200 | AI12: =SUM(AI16:AI1048583) -> 0 | AJ12: =SUM(AJ16:#REF!) -> 0 | AK12: =AK15+AJ12-AI12 -> 0 | AL12: =SUM(AL16:AL1048583) -> 0 | AM12: =SUM(AM16:#REF!) -> 0 | AN12: =AN15+AM12-AL12 -> 0
I13: OverAll | K13: ISHABELLA | N13: JYQL AIRCON PARTS TRADING | Q13: STAL | T13: WINTERPINE AIR CONDITIONING CORP | W13: HISYS / KM AIRE ALLIANCE CORP | Z13: UNIWESTECH | AC13: ENTALPIA | AF13: 3BMA
A14: Term | B14: Date | C14: Due Date | D14: Particulars | E14: Supplier | F14: DR # | G14: Check # | H14: Debit | I14: Credit | J14: Balance | K14: Debit | L14: Credit | M14: Balance | N14: Debit | O14: Credit | P14: Balance | Q14: Debit | R14: Credit | S14: Balance | T14: Debit | U14: Credit | V14: Balance | W14: Debit | X14: Credit | Y14: Balance | Z14: Debit | AA14: Credit | AB14: Balance | AC14: Debit | AD14: Credit | AE14: Balance | AF14: Debit | AG14: Credit | AH14: Balance | AI14: Debit | AJ14: Credit | AK14: Balance | AL14: Debit | AM14: Credit | AN14: Balance
A15: Days | B15: 46024 | D15: Beg Bal | J15: =sum(M15,P15,S15,V15,Y15,AB15,AE15,AH15,AK15,AN15) -> 534000.2 | M15: -94437 | P15: 202610 | S15: 269020 | V15: =50976.4+25230.8 -> 76207.2 | Y15: 0 | AB15: 80600 | AE15: 0 | AH15: 0 | AK15: 0 | AN15: 0
A16: 30 | B16: 46029 | C16: =B16+A16 -> 46059 | D16: Purchases | F16: 94218 JYQL | H16: =sum(K16,N16,Q16,T16,W16,Z16,AC16,AF16,AI16,AL16) -> 0 | I16: =sum(L16,O16,R16,U16,X16,AA16,AD16,AG16,AJ16,AM16) -> 10290 | J16: =sum(M16,P16,S16,V16,Y16,AB16,AE16,AH16,AK16,AN16) -> 544290.2 | M16: =M15+L16-K16 -> -94437 | O16: 10290 | P16: =P15+O16-N16 -> 212900 | S16: =S15+R16-Q16 -> 269020 | V16: =V15+U16-T16 -> 76207.2 | Y16: =Y15+X16-W16 -> 0 | AB16: =AB15+AA16-Z16 -> 80600 | AE16: =AE15+AD16-AC16 -> 0 | AH16: =AH15+AG16-AF16 -> 0 | AK16: =AK15+AJ16-AI16 -> 0 | AN16: =AN15+AM16-AL16 -> 0
A17: 30 | B17: 46035 | C17: =B17+A17 -> 46065 | D17: Purchases | F17: 70746 JYQL | H17: =sum(K17,N17,Q17,T17,W17,Z17,AC17,AF17,AI17,AL17) -> 0 | I17: =sum(L17,O17,R17,U17,X17,AA17,AD17,AG17,AJ17,AM17) -> 9400 | J17: =sum(M17,P17,S17,V17,Y17,AB17,AE17,AH17,AK17,AN17) -> 553690.2 | M17: =M16+L17-K17 -> -94437 | O17: 9400 | P17: =P16+O17-N17 -> 222300 | S17: =S16+R17-Q17 -> 269020 | V17: =V16+U17-T17 -> 76207.2 | Y17: =Y16+X17-W17 -> 0 | AB17: =AB16+AA17-Z17 -> 80600 | AE17: =AE16+AD17-AC17 -> 0 | AH17: =AH16+AG17-AF17 -> 0 | AK17: =AK16+AJ17-AI17 -> 0 | AN17: =AN16+AM17-AL17 -> 0
A18: 30 | B18: 46038 | C18: =B18+A18 -> 46068 | D18: Purchases | F18: 91780 JYQL | H18: =sum(K18,N18,Q18,T18,W18,Z18,AC18,AF18,AI18,AL18) -> 0 | I18: =sum(L18,O18,R18,U18,X18,AA18,AD18,AG18,AJ18,AM18) -> 19240 | J18: =sum(M18,P18,S18,V18,Y18,AB18,AE18,AH18,AK18,AN18) -> 572930.2 | M18: =M17+L18-K18 -> -94437 | O18: 19240 | P18: =P17+O18-N18 -> 241540 | S18: =S17+R18-Q18 -> 269020 | V18: =V17+U18-T18 -> 76207.2 | Y18: =Y17+X18-W18 -> 0 | AB18: =AB17+AA18-Z18 -> 80600 | AE18: =AE17+AD18-AC18 -> 0 | AH18: =AH17+AG18-AF18 -> 0 | AK18: =AK17+AJ18-AI18 -> 0 | AN18: =AN17+AM18-AL18 -> 0
A19: 30 | B19: 46041 | C19: =B19+A19 -> 46071 | D19: Purchases | F19: 14429 JYQL | H19: =sum(K19,N19,Q19,T19,W19,Z19,AC19,AF19,AI19,AL19) -> 0 | I19: =sum(L19,O19,R19,U19,X19,AA19,AD19,AG19,AJ19,AM19) -> 9200 | J19: =sum(M19,P19,S19,V19,Y19,AB19,AE19,AH19,AK19,AN19) -> 582130.2 | M19: =M18+L19-K19 -> -94437 | O19: 9200 | P19: =P18+O19-N19 -> 250740 | S19: =S18+R19-Q19 -> 269020 | V19: =V18+U19-T19 -> 76207.2 | Y19: =Y18+X19-W19 -> 0 | AB19: =AB18+AA19-Z19 -> 80600 | AE19: =AE18+AD19-AC19 -> 0 | AH19: =AH18+AG19-AF19 -> 0 | AK19: =AK18+AJ19-AI19 -> 0 | AN19: =AN18+AM19-AL19 -> 0
A20: 30 | B20: 46042 | C20: =B20+A20 -> 46072 | D20: Purchases | F20: 44561 JYQL | H20: =sum(K20,N20,Q20,T20,W20,Z20,AC20,AF20,AI20,AL20) -> 0 | I20: =sum(L20,O20,R20,U20,X20,AA20,AD20,AG20,AJ20,AM20) -> 22500 | J20: =sum(M20,P20,S20,V20,Y20,AB20,AE20,AH20,AK20,AN20) -> 604630.2 | M20: =M19+L20-K20 -> -94437 | O20: 22500 | P20: =P19+O20-N20 -> 273240 | S20: =S19+R20-Q20 -> 269020 | V20: =V19+U20-T20 -> 76207.2 | Y20: =Y19+X20-W20 -> 0 | AB20: =AB19+AA20-Z20 -> 80600 | AE20: =AE19+AD20-AC20 -> 0 | AH20: =AH19+AG20-AF20 -> 0 | AK20: =AK19+AJ20-AI20 -> 0 | AN20: =AN19+AM20-AL20 -> 0
A21: 30 | B21: 46042 | C21: =B21+A21 -> 46072 | D21: Purchases | F21: 44561 JYQL | H21: =sum(K21,N21,Q21,T21,W21,Z21,AC21,AF21,AI21,AL21) -> 0 | I21: =sum(L21,O21,R21,U21,X21,AA21,AD21,AG21,AJ21,AM21) -> 22500 | J21: =sum(M21,P21,S21,V21,Y21,AB21,AE21,AH21,AK21,AN21) -> 627130.2 | M21: =M20+L21-K21 -> -94437 | O21: 22500 | P21: =P20+O21-N21 -> 295740 | S21: =S20+R21-Q21 -> 269020 | V21: =V20+U21-T21 -> 76207.2 | Y21: =Y20+X21-W21 -> 0 | AB21: =AB20+AA21-Z21 -> 80600 | AE21: =AE20+AD21-AC21 -> 0 | AH21: =AH20+AG21-AF21 -> 0 | AK21: =AK20+AJ21-AI21 -> 0 | AN21: =AN20+AM21-AL21 -> 0
A22: 30 | B22: 46044 | C22: =B22+A22 -> 46074 | D22: Purchases | F22: 85619 JYQL | H22: =sum(K22,N22,Q22,T22,W22,Z22,AC22,AF22,AI22,AL22) -> 0 | I22: =sum(L22,O22,R22,U22,X22,AA22,AD22,AG22,AJ22,AM22) -> 6385 | J22: =sum(M22,P22,S22,V22,Y22,AB22,AE22,AH22,AK22,AN22) -> 633515.2 | M22: =M21+L22-K22 -> -94437 | O22: 6385 | P22: =P21+O22-N22 -> 302125 | S22: =S21+R22-Q22 -> 269020 | V22: =V21+U22-T22 -> 76207.2 | Y22: =Y21+X22-W22 -> 0 | AB22: =AB21+AA22-Z22 -> 80600 | AE22: =AE21+AD22-AC22 -> 0 | AH22: =AH21+AG22-AF22 -> 0 | AK22: =AK21+AJ22-AI22 -> 0 | AN22: =AN21+AM22-AL22 -> 0
A23: 30 | B23: 46049 | C23: =B23+A23 -> 46079 | D23: Purchases | F23: 95150 JYQL | H23: =sum(K23,N23,Q23,T23,W23,Z23,AC23,AF23,AI23,AL23) -> 0 | I23: =sum(L23,O23,R23,U23,X23,AA23,AD23,AG23,AJ23,AM23) -> 20730 | J23: =sum(M23,P23,S23,V23,Y23,AB23,AE23,AH23,AK23,AN23) -> 654245.2 | M23: =M22+L23-K23 -> -94437 | O23: 20730 | P23: =P22+O23-N23 -> 322855 | S23: =S22+R23-Q23 -> 269020 | V23: =V22+U23-T23 -> 76207.2 | Y23: =Y22+X23-W23 -> 0 | AB23: =AB22+AA23-Z23 -> 80600 | AE23: =AE22+AD23-AC23 -> 0 | AH23: =AH22+AG23-AF23 -> 0 | AK23: =AK22+AJ23-AI23 -> 0 | AN23: =AN22+AM23-AL23 -> 0
B24: 46042 | D24: Payment | E24: Centralworld | G24: 938017 | H24: =sum(K24,N24,Q24,T24,W24,Z24,AC24,AF24,AI24,AL24) -> 20000 | I24: =sum(L24,O24,R24,U24,X24,AA24,AD24,AG24,AJ24,AM24) -> 0 | J24: =sum(M24,P24,S24,V24,Y24,AB24,AE24,AH24,AK24,AN24) -> 622445.2 | K24: 20000 | M24: =M23+L24-K24 -> -114437 | P24: =P23+O24-N25 -> 311055 | S24: =S23+R24-Q24 -> 269020 | V24: =V23+U24-T24 -> 76207.2 | Y24: =Y23+X24-W24 -> 0 | AB24: =AB23+AA24-Z24 -> 80600 | AE24: =AE23+AD24-AC24 -> 0 | AH24: =AH23+AG24-AF24 -> 0 | AK24: =AK23+AJ24-AI24 -> 0 | AN24: =AN23+AM24-AL24 -> 0
B25: 45669 | D25: Payment | E25: JYQL | G25: 938046 | H25: =sum(K25,N25,Q25,T25,W25,Z25,AC25,AF25,AI25,AL25) -> 11800 | I25: =sum(L25,O25,R25,U25,X25,AA25,AD25,AG25,AJ25,AM25) -> 0 | J25: =sum(M25,P25,S25,V25,Y25,AB25,AE25,AH25,AK25,AN25) -> 608645.2 | M25: =M24+L25-K25 -> -114437 | N25: 11800 | P25: =P24+O25-N26 -> 297255 | S25: =S24+R25-Q25 -> 269020 | V25: =V24+U25-T25 -> 76207.2 | Y25: =Y24+X25-W25 -> 0 | AB25: =AB24+AA25-Z25 -> 80600 | AE25: =AE24+AD25-AC25 -> 0 | AH25: =AH24+AG25-AF25 -> 0 | AK25: =AK24+AJ25-AI25 -> 0 | AN25: =AN24+AM25-AL25 -> 0
B26: 45670 | D26: Payment | E26: JYQL | G26: 942956 | H26: =sum(K26,N26,Q26,T26,W26,Z26,AC26,AF26,AI26,AL26) -> 13800 | I26: =sum(L26,O26,R26,U26,X26,AA26,AD26,AG26,AJ26,AM26) -> 0 | J26: =sum(M26,P26,S26,V26,Y26,AB26,AE26,AH26,AK26,AN26) -> 592345.2 | M26: =M25+L26-K26 -> -114437 | N26: 13800 | P26: =P25+O26-N27 -> 280955 | S26: =S25+R26-Q26 -> 269020 | V26: =V25+U26-T26 -> 76207.2 | Y26: =Y25+X26-W26 -> 0 | AB26: =AB25+AA26-Z26 -> 80600 | AE26: =AE25+AD26-AC26 -> 0 | AH26: =AH25+AG26-AF26 -> 0 | AK26: =AK25+AJ26-AI26 -> 0 | AN26: =AN25+AM26-AL26 -> 0
B27: 45670 | D27: Payment | E27: JYQL | G27: 942957 | H27: =sum(K27,N27,Q27,T27,W27,Z27,AC27,AF27,AI27,AL27) -> 16300 | I27: =sum(L27,O27,R27,U27,X27,AA27,AD27,AG27,AJ27,AM27) -> 0 | J27: =sum(M27,P27,S27,V27,Y27,AB27,AE27,AH27,AK27,AN27) -> 592345.2 | M27: =M26+L27-K27 -> -114437 | N27: 16300 | P27: =P26+O27-N28 -> 280955 | S27: =S26+R27-Q27 -> 269020 | V27: =V26+U27-T27 -> 76207.2 | Y27: =Y26+X27-W27 -> 0 | AB27: =AB26+AA27-Z27 -> 80600 | AE27: =AE26+AD27-AC27 -> 0 | AH27: =AH26+AG27-AF27 -> 0 | AK27: =AK26+AJ27-AI27 -> 0 | AN27: =AN26+AM27-AL27 -> 0
B28: 46041 | D28: Payment | E28: STAL | G28: 917636 | H28: =sum(K28,N28,Q28,T28,W28,Z28,AC28,AF28,AI28,AL28) -> 5310 | I28: =sum(L28,O28,R28,U28,X28,AA28,AD28,AG28,AJ28,AM28) -> 0 | J28: =sum(M28,P28,S28,V28,Y28,AB28,AE28,AH28,AK28,AN28) -> 587035.2 | M28: =M27+L28-K28 -> -114437 | P28: =P27+O28-N29 -> 280955 | Q28: 5310 | S28: =S27+R28-Q28 -> 263710 | V28: =V27+U28-T28 -> 76207.2 | Y28: =Y27+X28-W28 -> 0 | AB28: =AB27+AA28-Z28 -> 80600 | AE28: =AE27+AD28-AC28 -> 0 | AH28: =AH27+AG28-AF28 -> 0 | AK28: =AK27+AJ28-AI28 -> 0 | AN28: =AN27+AM28-AL28 -> 0
B29: 46041 | D29: Payment | E29: STAL | G29: 917637 | H29: =sum(K29,N29,Q29,T29,W29,Z29,AC29,AF29,AI29,AL29) -> 18760 | I29: =sum(L29,O29,R29,U29,X29,AA29,AD29,AG29,AJ29,AM29) -> 0 | J29: =sum(M29,P29,S29,V29,Y29,AB29,AE29,AH29,AK29,AN29) -> 568275.2 | M29: =M28+L29-K29 -> -114437 | P29: =P28+O29-N30 -> 280955 | Q29: 18760 | S29: =S28+R29-Q29 -> 244950 | V29: =V28+U29-T29 -> 76207.2 | Y29: =Y28+X29-W29 -> 0 | AB29: =AB28+AA29-Z29 -> 80600 | AE29: =AE28+AD29-AC29 -> 0 | AH29: =AH28+AG29-AF29 -> 0 | AK29: =AK28+AJ29-AI29 -> 0 | AN29: =AN28+AM29-AL29 -> 0
B30: 46041 | D30: Payment | E30: STAL | G30: 917646 | H30: =sum(K30,N30,Q30,T30,W30,Z30,AC30,AF30,AI30,AL30) -> 10020 | I30: =sum(L30,O30,R30,U30,X30,AA30,AD30,AG30,AJ30,AM30) -> 0 | J30: =sum(M30,P30,S30,V30,Y30,AB30,AE30,AH30,AK30,AN30) -> 558255.2 | M30: =M29+L30-K30 -> -114437 | P30: =P29+O30-N30 -> 280955 | Q30: 10020 | S30: =S29+R30-Q30 -> 234930 | V30: =V29+U30-T30 -> 76207.2 | Y30: =Y29+X30-W30 -> 0 | AB30: =AB29+AA30-Z30 -> 80600 | AE30: =AE29+AD30-AC30 -> 0 | AH30: =AH29+AG30-AF30 -> 0 | AK30: =AK29+AJ30-AI30 -> 0 | AN30: =AN29+AM30-AL30 -> 0
B31: 46036 | D31: Payment | E31: Winterpine | G31: 942953 | H31: =sum(K31,N31,Q31,T31,W31,Z31,AC31,AF31,AI31,AL31) -> 32118 | I31: =sum(L31,O31,R31,U31,X31,AA31,AD31,AG31,AJ31,AM31) -> 0 | J31: =sum(M31,P31,S31,V31,Y31,AB31,AE31,AH31,AK31,AN31) -> 526137.2 | M31: =M30+L31-K31 -> -114437 | P31: =P30+O31-N31 -> 280955 | S31: =S30+R31-Q31 -> 234930 | T31: 32118 | V31: =V30+U31-T31 -> 44089.2 | Y31: =Y30+X31-W31 -> 0 | AB31: =AB30+AA31-Z31 -> 80600 | AE31: =AE30+AD31-AC31 -> 0 | AH31: =AH30+AG31-AF31 -> 0 | AK31: =AK30+AJ31-AI31 -> 0 | AN31: =AN30+AM31-AL31 -> 0
A32: 10 | B32: 46030 | C32: =B32+A32 -> 46040 | D32: Purchases | E32: Entalpia | H32: =sum(K32,N32,Q32,T32,W32,Z32,AC32,AF32,AI32,AL32) -> 0 | I32: =sum(L32,O32,R32,U32,X32,AA32,AD32,AG32,AJ32,AM32) -> 44145 | J32: =sum(M32,P32,S32,V32,Y32,AB32,AE32,AH32,AK32,AN32) -> 570282.2 | M32: =M31+L32-K32 -> -114437 | P32: =P31+O32-N32 -> 280955 | S32: =S31+R32-Q32 -> 234930 | V32: =V31+U32-T32 -> 44089.2 | Y32: =Y31+X32-W32 -> 0 | AB32: =AB31+AA32-Z32 -> 80600 | AD32: 44145 | AE32: =AE31+AD32-AC32 -> 44145 | AH32: =AH31+AG32-AF32 -> 0 | AK32: =AK31+AJ32-AI32 -> 0 | AN32: =AN31+AM32-AL32 -> 0
A33: 10 | B33: 46037 | C33: =B33+A33 -> 46047 | D33: Purchases | E33: Entalpia | H33: =sum(K33,N33,Q33,T33,W33,Z33,AC33,AF33,AI33,AL33) -> 0 | I33: =sum(L33,O33,R33,U33,X33,AA33,AD33,AG33,AJ33,AM33) -> 26928 | J33: =sum(M33,P33,S33,V33,Y33,AB33,AE33,AH33,AK33,AN33) -> 597210.2 | M33: =M32+L33-K33 -> -114437 | P33: =P32+O33-N33 -> 280955 | S33: =S32+R33-Q33 -> 234930 | V33: =V32+U33-T33 -> 44089.2 | Y33: =Y32+X33-W33 -> 0 | AB33: =AB32+AA33-Z33 -> 80600 | AD33: 26928 | AE33: =AE32+AD33-AC33 -> 71073 | AH33: =AH32+AG33-AF33 -> 0 | AK33: =AK32+AJ33-AI33 -> 0 | AN33: =AN32+AM33-AL33 -> 0
B34: 46044 | D34: Payment | E34: Entalpia | G34: 942970 | H34: =sum(K34,N34,Q34,T34,W34,Z34,AC34,AF34,AI34,AL34) -> 44145 | I34: =sum(L34,O34,R34,U34,X34,AA34,AD34,AG34,AJ34,AM34) -> 0 | J34: =sum(M34,P34,S34,V34,Y34,AB34,AE34,AH34,AK34,AN34) -> 553065.2 | M34: =M33+L34-K34 -> -114437 | P34: =P33+O34-N34 -> 280955 | S34: =S33+R34-Q34 -> 234930 | V34: =V33+U34-T34 -> 44089.2 | Y34: =Y33+X34-W34 -> 0 | AB34: =AB33+AA34-Z34 -> 80600 | AC34: 44145 | AE34: =AE33+AD34-AC34 -> 26928 | AH34: =AH33+AG34-AF34 -> 0 | AK34: =AK33+AJ34-AI34 -> 0 | AN34: =AN33+AM34-AL34 -> 0
B35: 46044 | D35: Payment | E35: Entalpia | G35: 942972 | H35: =sum(K35,N35,Q35,T35,W35,Z35,AC35,AF35,AI35,AL35) -> 26928 | I35: =sum(L35,O35,R35,U35,X35,AA35,AD35,AG35,AJ35,AM35) -> 0 | J35: =sum(M35,P35,S35,V35,Y35,AB35,AE35,AH35,AK35,AN35) -> 526137.2 | M35: =M34+L35-K35 -> -114437 | P35: =P34+O35-N35 -> 280955 | S35: =S34+R35-Q35 -> 234930 | V35: =V34+U35-T35 -> 44089.2 | Y35: =Y34+X35-W35 -> 0 | AB35: =AB34+AA35-Z35 -> 80600 | AC35: 26928 | AE35: =AE34+AD35-AC35 -> 0 | AH35: =AH34+AG35-AF35 -> 0 | AK35: =AK34+AJ35-AI35 -> 0 | AN35: =AN34+AM35-AL35 -> 0
B36: 46037 | D36: Payment | E36: Uniwestech | G36: 938035 | H36: =sum(K36,N36,Q36,T36,W36,Z36,AC36,AF36,AI36,AL36) -> 20000 | I36: =sum(L36,O36,R36,U36,X36,AA36,AD36,AG36,AJ36,AM36) -> 0 | J36: =sum(M36,P36,S36,V36,Y36,AB36,AE36,AH36,AK36,AN36) -> 506137.2 | M36: =M35+L36-K36 -> -114437 | P36: =P35+O36-N36 -> 280955 | S36: =S35+R36-Q36 -> 234930 | V36: =V35+U36-T36 -> 44089.2 | Y36: =Y35+X36-W36 -> 0 | Z36: 20000 | AB36: =AB35+AA36-Z36 -> 60600 | AE36: =AE35+AD36-AC36 -> 0 | AH36: =AH35+AG36-AF36 -> 0 | AK36: =AK35+AJ36-AI36 -> 0 | AN36: =AN35+AM36-AL36 -> 0
B37: 46038 | D37: Payment | E37: JYQL | G37: 938045 | H37: =sum(K37,N37,Q37,T37,W37,Z37,AC37,AF37,AI37,AL37) -> 27260 | I37: =sum(L37,O37,R37,U37,X37,AA37,AD37,AG37,AJ37,AM37) -> 0 | J37: =sum(M37,P37,S37,V37,Y37,AB37,AE37,AH37,AK37,AN37) -> 478877.2 | M37: =M36+L37-K37 -> -114437 | N37: 27260 | P37: =P36+O37-N37 -> 253695 | S37: =S36+R37-Q37 -> 234930 | V37: =V36+U37-T37 -> 44089.2 | Y37: =Y36+X37-W37 -> 0 | AB37: =AB36+AA37-Z37 -> 60600 | AE37: =AE36+AD37-AC37 -> 0 | AH37: =AH36+AG37-AF37 -> 0 | AK37: =AK36+AJ37-AI37 -> 0 | AN37: =AN36+AM37-AL37 -> 0
B38: 46038 | D38: Payment | E38: JYQL | G38: 942958 | H38: =sum(K38,N38,Q38,T38,W38,Z38,AC38,AF38,AI38,AL38) -> 12000 | I38: =sum(L38,O38,R38,U38,X38,AA38,AD38,AG38,AJ38,AM38) -> 0 | J38: =sum(M38,P38,S38,V38,Y38,AB38,AE38,AH38,AK38,AN38) -> 466877.2 | M38: =M37+L38-K38 -> -114437 | N38: 12000 | P38: =P37+O38-N38 -> 241695 | S38: =S37+R38-Q38 -> 234930 | V38: =V37+U38-T38 -> 44089.2 | Y38: =Y37+X38-W38 -> 0 | AB38: =AB37+AA38-Z38 -> 60600 | AE38: =AE37+AD38-AC38 -> 0 | AH38: =AH37+AG38-AF38 -> 0 | AK38: =AK37+AJ38-AI38 -> 0 | AN38: =AN37+AM38-AL38 -> 0
B39: 46038 | D39: Payment | E39: JYQL | G39: 942959 | H39: =sum(K39,N39,Q39,T39,W39,Z39,AC39,AF39,AI39,AL39) -> 10800 | I39: =sum(L39,O39,R39,U39,X39,AA39,AD39,AG39,AJ39,AM39) -> 0 | J39: =sum(M39,P39,S39,V39,Y39,AB39,AE39,AH39,AK39,AN39) -> 456077.2 | M39: =M38+L39-K39 -> -114437 | N39: 10800 | P39: =P38+O39-N39 -> 230895 | S39: =S38+R39-Q39 -> 234930 | V39: =V38+U39-T39 -> 44089.2 | Y39: =Y38+X39-W39 -> 0 | AB39: =AB38+AA39-Z39 -> 60600 | AE39: =AE38+AD39-AC39 -> 0 | AH39: =AH38+AG39-AF39 -> 0 | AK39: =AK38+AJ39-AI39 -> 0 | AN39: =AN38+AM39-AL39 -> 0
B40: 46044 | D40: Payment | E40: JYQL | G40: 942960 | H40: =sum(K40,N40,Q40,T40,W40,Z40,AC40,AF40,AI40,AL40) -> 8550 | I40: =sum(L40,O40,R40,U40,X40,AA40,AD40,AG40,AJ40,AM40) -> 0 | J40: =sum(M40,P40,S40,V40,Y40,AB40,AE40,AH40,AK40,AN40) -> 447527.2 | M40: =M39+L40-K40 -> -114437 | N40: 8550 | P40: =P39+O40-N40 -> 222345 | S40: =S39+R40-Q40 -> 234930 | V40: =V39+U40-T40 -> 44089.2 | Y40: =Y39+X40-W40 -> 0 | AB40: =AB39+AA40-Z40 -> 60600 | AE40: =AE39+AD40-AC40 -> 0 | AH40: =AH39+AG40-AF40 -> 0 | AK40: =AK39+AJ40-AI40 -> 0 | AN40: =AN39+AM40-AL40 -> 0
B41: 46045 | D41: Payment | E41: Winterpine | G41: 942955 | H41: =sum(K41,N41,Q41,T41,W41,Z41,AC41,AF41,AI41,AL41) -> 18858.4 | I41: =sum(L41,O41,R41,U41,X41,AA41,AD41,AG41,AJ41,AM41) -> 0 | J41: =sum(M41,P41,S41,V41,Y41,AB41,AE41,AH41,AK41,AN41) -> 428668.8 | M41: =M40+L41-K41 -> -114437 | P41: =P40+O41-N41 -> 222345 | S41: =S40+R41-Q41 -> 234930 | T41: 18858.4 | V41: =V40+U41-T41 -> 25230.8 | Y41: =Y40+X41-W41 -> 0 | AB41: =AB40+AA41-Z41 -> 60600 | AE41: =AE40+AD41-AC41 -> 0 | AH41: =AH40+AG41-AF41 -> 0 | AK41: =AK40+AJ41-AI41 -> 0 | AN41: =AN40+AM41-AL41 -> 0
B42: 46045 | D42: Payment | E42: STAL | G42: 917650 | H42: =sum(K42,N42,Q42,T42,W42,Z42,AC42,AF42,AI42,AL42) -> 3650 | I42: =sum(L42,O42,R42,U42,X42,AA42,AD42,AG42,AJ42,AM42) -> 0 | J42: =sum(M42,P42,S42,V42,Y42,AB42,AE42,AH42,AK42,AN42) -> 425018.8 | M42: =M41+L42-K42 -> -114437 | P42: =P41+O42-N42 -> 222345 | Q42: 3650 | S42: =S41+R42-Q42 -> 231280 | V42: =V41+U42-T42 -> 25230.8 | Y42: =Y41+X42-W42 -> 0 | AB42: =AB41+AA42-Z42 -> 60600 | AE42: =AE41+AD42-AC42 -> 0 | AH42: =AH41+AG42-AF42 -> 0 | AK42: =AK41+AJ42-AI42 -> 0 | AN42: =AN41+AM42-AL42 -> 0
B43: 46045 | D43: Payment | E43: STAL | G43: 938001 | H43: =sum(K43,N43,Q43,T43,W43,Z43,AC43,AF43,AI43,AL43) -> 7470 | I43: =sum(L43,O43,R43,U43,X43,AA43,AD43,AG43,AJ43,AM43) -> 0 | J43: =sum(M43,P43,S43,V43,Y43,AB43,AE43,AH43,AK43,AN43) -> 417548.8 | M43: =M42+L43-K43 -> -114437 | P43: =P42+O43-N43 -> 222345 | Q43: 7470 | S43: =S42+R43-Q43 -> 223810 | V43: =V42+U43-T43 -> 25230.8 | Y43: =Y42+X43-W43 -> 0 | AB43: =AB42+AA43-Z43 -> 60600 | AE43: =AE42+AD43-AC43 -> 0 | AH43: =AH42+AG43-AF43 -> 0 | AK43: =AK42+AJ43-AI43 -> 0 | AN43: =AN42+AM43-AL43 -> 0
B44: 46048 | D44: Payment | E44: Uniwestech | G44: 938036 | H44: =sum(K44,N44,Q44,T44,W44,Z44,AC44,AF44,AI44,AL44) -> 25600 | I44: =sum(L44,O44,R44,U44,X44,AA44,AD44,AG44,AJ44,AM44) -> 0 | J44: =sum(M44,P44,S44,V44,Y44,AB44,AE44,AH44,AK44,AN44) -> 391948.8 | M44: =M43+L44-K44 -> -114437 | P44: =P43+O44-N44 -> 222345 | S44: =S43+R44-Q44 -> 223810 | V44: =V43+U44-T44 -> 25230.8 | Y44: =Y43+X44-W44 -> 0 | Z44: 25600 | AB44: =AB43+AA44-Z44 -> 35000 | AE44: =AE43+AD44-AC44 -> 0 | AH44: =AH43+AG44-AF44 -> 0 | AK44: =AK43+AJ44-AI44 -> 0 | AN44: =AN43+AM44-AL44 -> 0
B45: 46036 | D45: Purchases | E45: Uniwestech | H45: =sum(K45,N45,Q45,T45,W45,Z45,AC45,AF45,AI45,AL45) -> 0 | I45: =sum(L45,O45,R45,U45,X45,AA45,AD45,AG45,AJ45,AM45) -> 16000 | J45: =sum(M45,P45,S45,V45,Y45,AB45,AE45,AH45,AK45,AN45) -> 407948.8 | M45: =M44+L45-K45 -> -114437 | P45: =P44+O45-N45 -> 222345 | S45: =S44+R45-Q45 -> 223810 | V45: =V44+U45-T45 -> 25230.8 | Y45: =Y44+X45-W45 -> 0 | AA45: 16000 | AB45: =AB44+AA45-Z45 -> 51000 | AE45: =AE44+AD45-AC45 -> 0 | AH45: =AH44+AG45-AF45 -> 0 | AK45: =AK44+AJ45-AI45 -> 0 | AN45: =AN44+AM45-AL45 -> 0
B46: 46036 | D46: Purchases | E46: STAL | F46: DR#108 | H46: =sum(K46,N46,Q46,T46,W46,Z46,AC46,AF46,AI46,AL46) -> 0 | I46: =sum(L46,O46,R46,U46,X46,AA46,AD46,AG46,AJ46,AM46) -> 14550 | J46: =sum(M46,P46,S46,V46,Y46,AB46,AE46,AH46,AK46,AN46) -> 422498.8 | M46: =M45+L46-K46 -> -114437 | P46: =P45+O46-N46 -> 222345 | R46: 14550 | S46: =S45+R46-Q46 -> 238360 | V46: =V45+U46-T46 -> 25230.8 | Y46: =Y45+X46-W46 -> 0 | AB46: =AB45+AA46-Z46 -> 51000 | AE46: =AE45+AD46-AC46 -> 0 | AH46: =AH45+AG46-AF46 -> 0 | AK46: =AK45+AJ46-AI46 -> 0 | AN46: =AN45+AM46-AL46 -> 0
B47: 46043 | D47: Purchases | E47: STAL | F47: DR#110 | H47: =sum(K47,N47,Q47,T47,W47,Z47,AC47,AF47,AI47,AL47) -> 0 | I47: =sum(L47,O47,R47,U47,X47,AA47,AD47,AG47,AJ47,AM47) -> 6750 | J47: =sum(M47,P47,S47,V47,Y47,AB47,AE47,AH47,AK47,AN47) -> 429248.8 | M47: =M46+L47-K47 -> -114437 | P47: =P46+O47-N47 -> 222345 | R47: 6750 | S47: =S46+R47-Q47 -> 245110 | V47: =V46+U47-T47 -> 25230.8 | Y47: =Y46+X47-W47 -> 0 | AB47: =AB46+AA47-Z47 -> 51000 | AE47: =AE46+AD47-AC47 -> 0 | AH47: =AH46+AG47-AF47 -> 0 | AK47: =AK46+AJ47-AI47 -> 0 | AN47: =AN46+AM47-AL47 -> 0
B48: 46044 | D48: Purchases | E48: STAL | F48: DR#111 | H48: =sum(K48,N48,Q48,T48,W48,Z48,AC48,AF48,AI48,AL48) -> 0 | I48: =sum(L48,O48,R48,U48,X48,AA48,AD48,AG48,AJ48,AM48) -> 5650 | J48: =sum(M48,P48,S48,V48,Y48,AB48,AE48,AH48,AK48,AN48) -> 434898.8 | M48: =M47+L48-K48 -> -114437 | P48: =P47+O48-N48 -> 222345 | R48: 5650 | S48: =S47+R48-Q48 -> 250760 | V48: =V47+U48-T48 -> 25230.8 | Y48: =Y47+X48-W48 -> 0 | AB48: =AB47+AA48-Z48 -> 51000 | AE48: =AE47+AD48-AC48 -> 0 | AH48: =AH47+AG48-AF48 -> 0 | AK48: =AK47+AJ48-AI48 -> 0 | AN48: =AN47+AM48-AL48 -> 0
B49: 46049 | D49: Purchases | E49: STAL | F49: DR#116 | H49: =sum(K49,N49,Q49,T49,W49,Z49,AC49,AF49,AI49,AL49) -> 0 | I49: =sum(L49,O49,R49,U49,X49,AA49,AD49,AG49,AJ49,AM49) -> 10800 | J49: =sum(M49,P49,S49,V49,Y49,AB49,AE49,AH49,AK49,AN49) -> 445698.8 | M49: =M48+L49-K49 -> -114437 | P49: =P48+O49-N49 -> 222345 | R49: 10800 | S49: =S48+R49-Q49 -> 261560 | V49: =V48+U49-T49 -> 25230.8 | Y49: =Y48+X49-W49 -> 0 | AB49: =AB48+AA49-Z49 -> 51000 | AE49: =AE48+AD49-AC49 -> 0 | AH49: =AH48+AG49-AF49 -> 0 | AK49: =AK48+AJ49-AI49 -> 0 | AN49: =AN48+AM49-AL49 -> 0
B50: 46051 | D50: Purchases | E50: Uniwestech | H50: =sum(K50,N50,Q50,T50,W50,Z50,AC50,AF50,AI50,AL50) -> 0 | I50: =sum(L50,O50,R50,U50,X50,AA50,AD50,AG50,AJ50,AM50) -> 16400 | J50: =sum(M50,P50,S50,V50,Y50,AB50,AE50,AH50,AK50,AN50) -> 462098.8 | M50: =M49+L50-K50 -> -114437 | P50: =P49+O50-N50 -> 222345 | S50: =S49+R50-Q50 -> 261560 | V50: =V49+U50-T50 -> 25230.8 | Y50: =Y49+X50-W50 -> 0 | AA50: 16400 | AB50: =AB49+AA50-Z50 -> 67400 | AE50: =AE49+AD50-AC50 -> 0 | AH50: =AH49+AG50-AF50 -> 0 | AK50: =AK49+AJ50-AI50 -> 0 | AN50: =AN49+AM50-AL50 -> 0
B51: 46051 | D51: Purchases | E51: STAL | F51: DR#119 | H51: =sum(K51,N51,Q51,T51,W51,Z51,AC51,AF51,AI51,AL51) -> 0 | I51: =sum(L51,O51,R51,U51,X51,AA51,AD51,AG51,AJ51,AM51) -> 8500 | J51: =sum(M51,P51,S51,V51,Y51,AB51,AE51,AH51,AK51,AN51) -> 470598.8 | M51: =M50+L51-K51 -> -114437 | P51: =P50+O51-N51 -> 222345 | R51: 8500 | S51: =S50+R51-Q51 -> 270060 | V51: =V50+U51-T51 -> 25230.8 | Y51: =Y50+X51-W51 -> 0 | AB51: =AB50+AA51-Z51 -> 67400 | AE51: =AE50+AD51-AC51 -> 0 | AH51: =AH50+AG51-AF51 -> 0 | AK51: =AK50+AJ51-AI51 -> 0 | AN51: =AN50+AM51-AL51 -> 0
B52: 46056 | C52: cash | D52: Purchases | E52: Ishabella | G52: transfer | H52: =sum(K52,N52,Q52,T52,W52,Z52,AC52,AF52,AI52,AL52) -> 9854.8 | I52: =sum(L52,O52,R52,U52,X52,AA52,AD52,AG52,AJ52,AM52) -> 9854.8 | J52: =sum(M52,P52,S52,V52,Y52,AB52,AE52,AH52,AK52,AN52) -> 470598.8 | K52: 9854.8 | L52: =9854.8 -> 9854.8 | M52: =M51+L52-K52 -> -114437 | P52: =P51+O52-N52 -> 222345 | S52: =S51+R52-Q52 -> 270060 | V52: =V51+U52-T52 -> 25230.8 | Y52: =Y51+X52-W52 -> 0 | AB52: =AB51+AA52-Z52 -> 67400 | AE52: =AE51+AD52-AC52 -> 0 | AH52: =AH51+AG52-AF52 -> 0 | AK52: =AK51+AJ52-AI52 -> 0 | AN52: =AN51+AM52-AL52 -> 0
B53: 46057 | D53: Purchases | E53: JYQL | F53: DR#51328 | H53: =sum(K53,N53,Q53,T53,W53,Z53,AC53,AF53,AI53,AL53) -> 0 | I53: =sum(L53,O53,R53,U53,X53,AA53,AD53,AG53,AJ53,AM53) -> 2780 | J53: =sum(M53,P53,S53,V53,Y53,AB53,AE53,AH53,AK53,AN53) -> 473378.8 | M53: =M52+L53-K53 -> -114437 | O53: 2780 | P53: =P52+O53-N53 -> 225125 | S53: =S52+R53-Q53 -> 270060 | V53: =V52+U53-T53 -> 25230.8 | Y53: =Y52+X53-W53 -> 0 | AB53: =AB52+AA53-Z53 -> 67400 | AE53: =AE52+AD53-AC53 -> 0 | AH53: =AH52+AG53-AF53 -> 0 | AK53: =AK52+AJ53-AI53 -> 0 | AN53: =AN52+AM53-AL53 -> 0
B54: 46057 | D54: Purchases | E54: JYQL | F54: DR#92794 | H54: =sum(K54,N54,Q54,T54,W54,Z54,AC54,AF54,AI54,AL54) -> 0 | I54: =sum(L54,O54,R54,U54,X54,AA54,AD54,AG54,AJ54,AM54) -> 4750 | J54: =sum(M54,P54,S54,V54,Y54,AB54,AE54,AH54,AK54,AN54) -> 478128.8 | M54: =M53+L54-K54 -> -114437 | O54: 4750 | P54: =P53+O54-N54 -> 229875 | S54: =S53+R54-Q54 -> 270060 | V54: =V53+U54-T54 -> 25230.8 | Y54: =Y53+X54-W54 -> 0 | AB54: =AB53+AA54-Z54 -> 67400 | AE54: =AE53+AD54-AC54 -> 0 | AH54: =AH53+AG54-AF54 -> 0 | AK54: =AK53+AJ54-AI54 -> 0 | AN54: =AN53+AM54-AL54 -> 0
B55: 46058 | D55: Payment | E55: JYQL | G55: 942965 | H55: =sum(K55,N55,Q55,T55,W55,Z55,AC55,AF55,AI55,AL55) -> 27450 | I55: =sum(L55,O55,R55,U55,X55,AA55,AD55,AG55,AJ55,AM55) -> 0 | J55: =sum(M55,P55,S55,V55,Y55,AB55,AE55,AH55,AK55,AN55) -> 450678.8 | M55: =M54+L55-K55 -> -114437 | N55: 27450 | P55: =P54+O55-N55 -> 202425 | S55: =S54+R55-Q55 -> 270060 | V55: =V54+U55-T55 -> 25230.8 | AB55: =AB54+AA55-Z55 -> 67400
B56: 46058 | D56: Payment | E56: JYQL | G56: 942961 | H56: =sum(K56,N56,Q56,T56,W56,Z56,AC56,AF56,AI56,AL56) -> 18610 | I56: =sum(L56,O56,R56,U56,X56,AA56,AD56,AG56,AJ56,AM56) -> 0 | J56: =sum(M56,P56,S56,V56,Y56,AB56,AE56,AH56,AK56,AN56) -> 432068.8 | M56: =M55+L56-K56 -> -114437 | N56: 18610 | P56: =P55+O56-N56 -> 183815 | S56: =S55+R56-Q56 -> 270060 | V56: =V55+U56-T56 -> 25230.8 | AB56: =AB55+AA56-Z56 -> 67400
B57: 46058 | D57: Purchases | E57: STAL | F57: DR#127 | H57: =sum(K57,N57,Q57,T57,W57,Z57,AC57,AF57,AI57,AL57) -> 0 | I57: =sum(L57,O57,R57,U57,X57,AA57,AD57,AG57,AJ57,AM57) -> 15550 | J57: =sum(M57,P57,S57,V57,Y57,AB57,AE57,AH57,AK57,AN57) -> 447618.8 | M57: =M54+L57-K57 -> -114437 | P57: =P56+O57-N57 -> 183815 | R57: 15550 | S57: =S56+R57-Q57 -> 285610 | V57: =V56+U57-T57 -> 25230.8 | Y57: =Y54+X57-W57 -> 0 | AB57: =AB56+AA57-Z57 -> 67400 | AE57: =AE54+AD57-AC57 -> 0 | AH57: =AH54+AG57-AF57 -> 0 | AK57: =AK54+AJ57-AI57 -> 0 | AN57: =AN54+AM57-AL57 -> 0
B58: 46059 | D58: Payment | E58: Uniwestech | G58: 942952 | H58: =sum(K58,N58,Q58,T58,W58,Z58,AC58,AF58,AI58,AL58) -> 35000 | I58: =sum(L58,O58,R58,U58,X58,AA58,AD58,AG58,AJ58,AM58) -> 0 | J58: =sum(M58,P58,S58,V58,Y58,AB58,AE58,AH58,AK58,AN58) -> 412618.8 | M58: =M55+L58-K58 -> -114437 | P58: =P57+O58-N58 -> 183815 | S58: =S57+R58-Q58 -> 285610 | V58: =V57+U58-T58 -> 25230.8 | Z58: 35000 | AB58: =AB57+AA58-Z58 -> 32400
B59: 46060 | D59: Payment | E59: JYQL | G59: 942982 | H59: =sum(K59,N59,Q59,T59,W59,Z59,AC59,AF59,AI59,AL59) -> 12850 | I59: =sum(L59,O59,R59,U59,X59,AA59,AD59,AG59,AJ59,AM59) -> 0 | J59: =sum(M59,P59,S59,V59,Y59,AB59,AE59,AH59,AK59,AN59) -> 399768.8 | M59: =M56+L59-K59 -> -114437 | N59: 12850 | P59: =P58+O59-N59 -> 170965 | S59: =S58+R59-Q59 -> 285610 | V59: =V58+U59-T59 -> 25230.8 | AB59: =AB58+AA59-Z59 -> 32400
B60: 46065 | D60: Purchases | E60: JYQL | F60: DR#21733 | H60: =sum(K60,N60,Q60,T60,W60,Z60,AC60,AF60,AI60,AL60) -> 0 | I60: =sum(L60,O60,R60,U60,X60,AA60,AD60,AG60,AJ60,AM60) -> 17050 | J60: =sum(M60,P60,S60,V60,Y60,AB60,AE60,AH60,AK60,AN60) -> 416818.8 | M60: =M57+L60-K60 -> -114437 | O60: 17050 | P60: =P59+O60-N60 -> 188015 | S60: =S59+R60-Q60 -> 285610 | V60: =V59+U60-T60 -> 25230.8 | Y60: =Y57+X60-W60 -> 0 | AB60: =AB59+AA60-Z60 -> 32400 | AE60: =AE57+AD60-AC60 -> 0 | AH60: =AH57+AG60-AF60 -> 0 | AK60: =AK57+AJ60-AI60 -> 0 | AN60: =AN57+AM60-AL60 -> 0
B61: 46065 | D61: Payment | E61: JYQL | G61: 942974 | H61: =sum(K61,N61,Q61,T61,W61,Z61,AC61,AF61,AI61,AL61) -> 23500 | I61: =sum(L61,O61,R61,U61,X61,AA61,AD61,AG61,AJ61,AM61) -> 0 | J61: =sum(M61,P61,S61,V61,Y61,AB61,AE61,AH61,AK61,AN61) -> 393318.8 | M61: =M58+L61-K61 -> -114437 | N61: 23500 | P61: =P60+O61-N61 -> 164515 | S61: =S60+R61-Q61 -> 285610 | V61: =V60+U61-T61 -> 25230.8 | AB61: =AB60+AA61-Z61 -> 32400
B62: 46066 | D62: Payment | E62: JYQL | G62: 942975 | H62: =sum(K62,N62,Q62,T62,W62,Z62,AC62,AF62,AI62,AL62) -> 10290 | I62: =sum(L62,O62,R62,U62,X62,AA62,AD62,AG62,AJ62,AM62) -> 0 | J62: =sum(M62,P62,S62,V62,Y62,AB62,AE62,AH62,AK62,AN62) -> 383028.8 | M62: =M59+L62-K62 -> -114437 | N62: 10290 | P62: =P61+O62-N62 -> 154225 | S62: =S61+R62-Q62 -> 285610 | V62: =V61+U62-T62 -> 25230.8 | AB62: =AB61+AA62-Z62 -> 32400
B63: 46066 | D63: Payment | E63: JYQL | G63: 942976 | H63: =sum(K63,N63,Q63,T63,W63,Z63,AC63,AF63,AI63,AL63) -> 9400 | I63: =sum(L63,O63,R63,U63,X63,AA63,AD63,AG63,AJ63,AM63) -> 0 | J63: =sum(M63,P63,S63,V63,Y63,AB63,AE63,AH63,AK63,AN63) -> 373628.8 | M63: =M60+L63-K63 -> -114437 | N63: 9400 | P63: =P62+O63-N63 -> 144825 | S63: =S62+R63-Q63 -> 285610 | V63: =V62+U63-T63 -> 25230.8 | AB63: =AB62+AA63-Z63 -> 32400
B64: 46071 | D64: Purchases | E64: JYQL | F64: DR#52984 | H64: =sum(K64,N64,Q64,T64,W64,Z64,AC64,AF64,AI64,AL64) -> 0 | I64: =sum(L64,O64,R64,U64,X64,AA64,AD64,AG64,AJ64,AM64) -> 18090 | J64: =sum(M64,P64,S64,V64,Y64,AB64,AE64,AH64,AK64,AN64) -> 391718.8 | M64: =M61+L64-K64 -> -114437 | O64: 18090 | P64: =P63+O64-N64 -> 162915 | S64: =S63+R64-Q64 -> 285610 | V64: =V63+U64-T64 -> 25230.8 | Y64: =Y60+X64-W64 -> 0 | AB64: =AB63+AA64-Z64 -> 32400 | AE64: =AE60+AD64-AC64 -> 0 | AH64: =AH60+AG64-AF64 -> 0 | AK64: =AK60+AJ64-AI64 -> 0 | AN64: =AN60+AM64-AL64 -> 0
B65: 46071 | D65: Purchases | E65: STAL | F65: DR#130 | H65: =sum(K65,N65,Q65,T65,W65,Z65,AC65,AF65,AI65,AL65) -> 0 | I65: =sum(L65,O65,R65,U65,X65,AA65,AD65,AG65,AJ65,AM65) -> 11750 | J65: =sum(M65,P65,S65,V65,Y65,AB65,AE65,AH65,AK65,AN65) -> 403468.8 | M65: =M62+L65-K65 -> -114437 | P65: =P64+O65-N65 -> 162915 | R65: 11750 | S65: =S64+R65-Q65 -> 297360 | V65: =V64+U65-T65 -> 25230.8 | Y65: =Y64+X65-W65 -> 0 | AB65: =AB64+AA65-Z65 -> 32400 | AE65: =AE64+AD65-AC65 -> 0 | AH65: =AH64+AG65-AF65 -> 0 | AK65: =AK64+AJ65-AI65 -> 0 | AN65: =AN64+AM65-AL65 -> 0
B66: 46073 | C66: cash | D66: Purchases | E66: Uniwestech | H66: =sum(K66,N66,Q66,T66,W66,Z66,AC66,AF66,AI66,AL66) -> 16600 | I66: =sum(L66,O66,R66,U66,X66,AA66,AD66,AG66,AJ66,AM66) -> 16600 | J66: =sum(M66,P66,S66,V66,Y66,AB66,AE66,AH66,AK66,AN66) -> 403468.8 | M66: =M63+L66-K66 -> -114437 | P66: =P65+O66-N66 -> 162915 | S66: =S65+R66-Q66 -> 297360 | V66: =V65+U66-T66 -> 25230.8 | Y66: =Y65+X66-W66 -> 0 | Z66: 16600 | AA66: 16600 | AB66: =AB65+AA66-Z66 -> 32400 | AE66: =AE65+AD66-AC66 -> 0 | AH66: =AH65+AG66-AF66 -> 0 | AK66: =AK65+AJ66-AI66 -> 0 | AN66: =AN65+AM66-AL66 -> 0
B67: 46077 | D67: Purchases | E67: JYQL | F67: DR# 45034 | H67: =sum(K67,N67,Q67,T67,W67,Z67,AC67,AF67,AI67,AL67) -> 0 | I67: =sum(L67,O67,R67,U67,X67,AA67,AD67,AG67,AJ67,AM67) -> 7840 | J67: =sum(M67,P67,S67,V67,Y67,AB67,AE67,AH67,AK67,AN67) -> 411308.8 | M67: =M64+L67-K67 -> -114437 | O67: 7840 | P67: =P66+O67-N67 -> 170755 | S67: =S66+R67-Q67 -> 297360 | V67: =V66+U67-T67 -> 25230.8 | Y67: =Y66+X67-W67 -> 0 | AB67: =AB66+AA67-Z67 -> 32400 | AE67: =AE66+AD67-AC67 -> 0 | AH67: =AH66+AG67-AF67 -> 0 | AK67: =AK66+AJ67-AI67 -> 0 | AN67: =AN66+AM67-AL67 -> 0
B68: 46076 | D68: Purchases | E68: STAL | F68: DR# 0132 | H68: =sum(K68,N68,Q68,T68,W68,Z68,AC68,AF68,AI68,AL68) -> 0 | I68: =sum(L68,O68,R68,U68,X68,AA68,AD68,AG68,AJ68,AM68) -> 43850 | J68: =sum(M68,P68,S68,V68,Y68,AB68,AE68,AH68,AK68,AN68) -> 455158.8 | M68: =M65+L68-K68 -> -114437 | P68: =P67+O68-N68 -> 170755 | R68: 43850 | S68: =S67+R68-Q68 -> 341210 | V68: =V67+U68-T68 -> 25230.8 | Y68: =Y67+X68-W68 -> 0 | AB68: =AB67+AA68-Z68 -> 32400 | AE68: =AE67+AD68-AC68 -> 0 | AH68: =AH67+AG68-AF68 -> 0 | AK68: =AK67+AJ68-AI68 -> 0 | AN68: =AN67+AM68-AL68 -> 0
B69: 46078 | D69: Purchases | E69: Ishabella | H69: =sum(K69,N69,Q69,T69,W69,Z69,AC69,AF69,AI69,AL69) -> 0 | I69: =sum(L69,O69,R69,U69,X69,AA69,AD69,AG69,AJ69,AM69) -> 16926.8 | J69: =sum(M69,P69,S69,V69,Y69,AB69,AE69,AH69,AK69,AN69) -> 472085.6 | L69: =9854.8+7072 -> 16926.8 | M69: =M68+L69-K69 -> -97510.2 | P69: =P68+O69-N69 -> 170755 | S69: =S68+R69-Q69 -> 341210 | V69: =V68+U69-T69 -> 25230.8 | Y69: =Y68+X69-W69 -> 0 | AB69: =AB68+AA69-Z69 -> 32400 | AE69: =AE68+AD69-AC69 -> 0 | AH69: =AH68+AG69-AF69 -> 0 | AK69: =AK68+AJ69-AI69 -> 0 | AN69: =AN68+AM69-AL69 -> 0
B70: 46078 | D70: Purchases | E70: Entalpia c/o Ishabella | H70: =sum(K70,N70,Q70,T70,W70,Z70,AC70,AF70,AI70,AL70) -> 0 | I70: =sum(L70,O70,R70,U70,X70,AA70,AD70,AG70,AJ70,AM70) -> 35360 | J70: =sum(M70,P70,S70,V70,Y70,AB70,AE70,AH70,AK70,AN70) -> 507445.6 | L70: =5*7072 -> 35360 | M70: =M69+L70-K70 -> -62150.2 | P70: =P69+O70-N70 -> 170755 | S70: =S69+R70-Q70 -> 341210 | V70: =V69+U70-T70 -> 25230.8 | Y70: =Y69+X70-W70 -> 0 | AB70: =AB69+AA70-Z70 -> 32400 | AE70: =AE69+AD70-AC70 -> 0 | AH70: =AH69+AG70-AF70 -> 0 | AK70: =AK69+AJ70-AI70 -> 0 | AN70: =AN69+AM70-AL70 -> 0
B71: 46078 | D71: Payment | E71: JYQL | G71: 943001 | H71: =sum(K71,N71,Q71,T71,W71,Z71,AC71,AF71,AI71,AL71) -> 19240 | I71: =sum(L71,O71,R71,U71,X71,AA71,AD71,AG71,AJ71,AM71) -> 0 | J71: =sum(M71,P71,S71,V71,Y71,AB71,AE71,AH71,AK71,AN71) -> 488205.6 | M71: =M70+L71-K71 -> -62150.2 | N71: 19240 | P71: =P70+O71-N71 -> 151515 | S71: =S70+R71-Q71 -> 341210 | V71: =V70+U71-T71 -> 25230.8 | Y71: =Y70+X71-W71 -> 0 | AB71: =AB70+AA71-Z71 -> 32400 | AE71: =AE70+AD71-AC71 -> 0 | AH71: =AH70+AG71-AF71 -> 0 | AK71: =AK70+AJ71-AI71 -> 0 | AN71: =AN70+AM71-AL71 -> 0
B72: 46080 | D72: Payment | E72: Uniwestech | G72: 942973 | H72: =sum(K72,N72,Q72,T72,W72,Z72,AC72,AF72,AI72,AL72) -> 16000 | I72: =sum(L72,O72,R72,U72,X72,AA72,AD72,AG72,AJ72,AM72) -> 0 | J72: =sum(M72,P72,S72,V72,Y72,AB72,AE72,AH72,AK72,AN72) -> 472205.6 | M72: =M71+L72-K72 -> -62150.2 | P72: =P71+O72-N72 -> 151515 | S72: =S71+R72-Q72 -> 341210 | V72: =V71+U72-T72 -> 25230.8 | Y72: =Y71+X72-W72 -> 0 | Z72: 16000 | AB72: =AB71+AA72-Z72 -> 16400 | AE72: =AE71+AD72-AC72 -> 0 | AH72: =AH71+AG72-AF72 -> 0 | AK72: =AK71+AJ72-AI72 -> 0 | AN72: =AN71+AM72-AL72 -> 0
B73: 46056 | D73: Purchases | E73: STAL | F73: DR#126 | H73: =sum(K73,N73,Q73,T73,W73,Z73,AC73,AF73,AI73,AL73) -> 0 | I73: =sum(L73,O73,R73,U73,X73,AA73,AD73,AG73,AJ73,AM73) -> 10500 | J73: =sum(M73,P73,S73,V73,Y73,AB73,AE73,AH73,AK73,AN73) -> 482705.6 | M73: =M72+L73-K73 -> -62150.2 | P73: =P72+O73-N73 -> 151515 | R73: 10500 | S73: =S72+R73-Q73 -> 351710 | V73: =V72+U73-T73 -> 25230.8 | Y73: =Y72+X73-W73 -> 0 | AB73: =AB72+AA73-Z73 -> 16400 | AE73: =AE72+AD73-AC73 -> 0 | AH73: =AH72+AG73-AF73 -> 0 | AK73: =AK72+AJ73-AI73 -> 0 | AN73: =AN72+AM73-AL73 -> 0
B74: 46080 | D74: Payment | E74: Centralworld | H74: =sum(K74,N74,Q74,T74,W74,Z74,AC74,AF74,AI74,AL74) -> 20000 | I74: =sum(L74,O74,R74,U74,X74,AA74,AD74,AG74,AJ74,AM74) -> 0 | J74: =sum(M74,P74,S74,V74,Y74,AB74,AE74,AH74,AK74,AN74) -> 462705.6 | K74: 20000 | M74: =M73+L74-K74 -> -82150.2 | P74: =P73+O74-N74 -> 151515 | S74: =S73+R74-Q74 -> 351710 | V74: =V73+U74-T74 -> 25230.8 | Y74: =Y73+X74-W74 -> 0 | AB74: =AB73+AA74-Z74 -> 16400 | AE74: =AE73+AD74-AC74 -> 0 | AH74: =AH73+AG74-AF74 -> 0 | AK74: =AK73+AJ74-AI74 -> 0 | AN74: =AN73+AM74-AL74 -> 0
B75: 46083 | D75: Payment | E75: Ishabella | G75: transfer | H75: =sum(K75,N75,Q75,T75,W75,Z75,AC75,AF75,AI75,AL75) -> 16926.8 | I75: =sum(L75,O75,R75,U75,X75,AA75,AD75,AG75,AJ75,AM75) -> 0 | J75: =sum(M75,P75,S75,V75,Y75,AB75,AE75,AH75,AK75,AN75) -> 445778.8 | K75: 16926.8 | M75: =M74+L75-K75 -> -99077 | P75: =P74+O75-N75 -> 151515 | S75: =S74+R75-Q75 -> 351710 | V75: =V74+U75-T75 -> 25230.8 | Y75: =Y74+X75-W75 -> 0 | AB75: =AB74+AA75-Z75 -> 16400 | AE75: =AE74+AD75-AC75 -> 0 | AH75: =AH74+AG75-AF75 -> 0 | AK75: =AK74+AJ75-AI75 -> 0 | AN75: =AN74+AM75-AL75 -> 0
B76: 46083 | D76: Payment | E76: JYQL | G76: 943002 | H76: =sum(K76,N76,Q76,T76,W76,Z76,AC76,AF76,AI76,AL76) -> 9200 | I76: =sum(L76,O76,R76,U76,X76,AA76,AD76,AG76,AJ76,AM76) -> 0 | J76: =sum(M76,P76,S76,V76,Y76,AB76,AE76,AH76,AK76,AN76) -> 436578.8 | M76: =M75+L76-K76 -> -99077 | N76: 9200 | P76: =P75+O76-N76 -> 142315 | S76: =S75+R76-Q76 -> 351710 | V76: =V75+U76-T76 -> 25230.8 | Y76: =Y75+X76-W76 -> 0 | AB76: =AB75+AA76-Z76 -> 16400 | AE76: =AE75+AD76-AC76 -> 0 | AH76: =AH75+AG76-AF76 -> 0 | AK76: =AK75+AJ76-AI76 -> 0 | AN76: =AN75+AM76-AL76 -> 0
B77: 46085 | D77: Payment | E77: STAL | G77: 938002 | H77: =sum(K77,N77,Q77,T77,W77,Z77,AC77,AF77,AI77,AL77) -> 12150 | I77: =sum(L77,O77,R77,U77,X77,AA77,AD77,AG77,AJ77,AM77) -> 0 | J77: =sum(M77,P77,S77,V77,Y77,AB77,AE77,AH77,AK77,AN77) -> 424428.8 | M77: =M76+L77-K77 -> -99077 | P77: =P76+O77-N77 -> 142315 | Q77: 12150 | S77: =S76+R77-Q77 -> 339560 | V77: =V76+U77-T77 -> 25230.8 | Y77: =Y76+X77-W77 -> 0 | AB77: =AB76+AA77-Z77 -> 16400 | AE77: =AE76+AD77-AC77 -> 0 | AH77: =AH76+AG77-AF77 -> 0 | AK77: =AK76+AJ77-AI77 -> 0 | AN77: =AN76+AM77-AL77 -> 0
B78: 46087 | D78: Payment | E78: JYQL | G78: 943003 | H78: =sum(K78,N78,Q78,T78,W78,Z78,AC78,AF78,AI78,AL78) -> 22500 | I78: =sum(L78,O78,R78,U78,X78,AA78,AD78,AG78,AJ78,AM78) -> 0 | J78: =sum(M78,P78,S78,V78,Y78,AB78,AE78,AH78,AK78,AN78) -> 401928.8 | M78: =M77+L78-K78 -> -99077 | N78: 22500 | P78: =P77+O78-N78 -> 119815 | S78: =S77+R78-Q78 -> 339560 | V78: =V77+U78-T78 -> 25230.8 | Y78: =Y77+X78-W78 -> 0 | AB78: =AB77+AA78-Z78 -> 16400 | AE78: =AE77+AD78-AC78 -> 0 | AH78: =AH77+AG78-AF78 -> 0 | AK78: =AK77+AJ78-AI78 -> 0 | AN78: =AN77+AM78-AL78 -> 0
B79: 46087 | D79: Payment | E79: JYQL | G79: 943005 | H79: =sum(K79,N79,Q79,T79,W79,Z79,AC79,AF79,AI79,AL79) -> 6385 | I79: =sum(L79,O79,R79,U79,X79,AA79,AD79,AG79,AJ79,AM79) -> 0 | J79: =sum(M79,P79,S79,V79,Y79,AB79,AE79,AH79,AK79,AN79) -> 395543.8 | M79: =M78+L79-K79 -> -99077 | N79: 6385 | P79: =P78+O79-N79 -> 113430 | S79: =S78+R79-Q79 -> 339560 | V79: =V78+U79-T79 -> 25230.8 | Y79: =Y78+X79-W79 -> 0 | AB79: =AB78+AA79-Z79 -> 16400 | AE79: =AE78+AD79-AC79 -> 0 | AH79: =AH78+AG79-AF79 -> 0 | AK79: =AK78+AJ79-AI79 -> 0 | AN79: =AN78+AM79-AL79 -> 0
B80: 46091 | D80: Payment | E80: Ishabella | G80: transfer | H80: =sum(K80,N80,Q80,T80,W80,Z80,AC80,AF80,AI80,AL80) -> 35360 | I80: =sum(L80,O80,R80,U80,X80,AA80,AD80,AG80,AJ80,AM80) -> 0 | J80: =sum(M80,P80,S80,V80,Y80,AB80,AE80,AH80,AK80,AN80) -> 360183.8 | K80: 35360 | M80: =M79+L80-K80 -> -134437 | P80: =P79+O80-N80 -> 113430 | S80: =S79+R80-Q80 -> 339560 | V80: =V79+U80-T80 -> 25230.8 | Y80: =Y79+X80-W80 -> 0 | AB80: =AB79+AA80-Z80 -> 16400 | AE80: =AE79+AD80-AC80 -> 0 | AH80: =AH79+AG80-AF80 -> 0 | AK80: =AK79+AJ80-AI80 -> 0 | AN80: =AN79+AM80-AL80 -> 0
B81: 45728 | D81: Payment | E81: Winterpine | G81: transfer | H81: =sum(K81,N81,Q81,T81,W81,Z81,AC81,AF81,AI81,AL81) -> 25230.8 | I81: =sum(L81,O81,R81,U81,X81,AA81,AD81,AG81,AJ81,AM81) -> 0 | J81: =sum(M81,P81,S81,V81,Y81,AB81,AE81,AH81,AK81,AN81) -> 334953 | M81: =M80+L81-K81 -> -134437 | P81: =P80+O81-N81 -> 113430 | S81: =S80+R81-Q81 -> 339560 | T81: 25230.8 | V81: =V80+U81-T81 -> 0 | Y81: =Y80+X81-W81 -> 0 | AB81: =AB80+AA81-Z81 -> 16400 | AE81: =AE80+AD81-AC81 -> 0 | AH81: =AH80+AG81-AF81 -> 0 | AK81: =AK80+AJ81-AI81 -> 0 | AN81: =AN80+AM81-AL81 -> 0
B82: 46099 | D82: Payment | E82: STAL | G82: 917639 | H82: =sum(K82,N82,Q82,T82,W82,Z82,AC82,AF82,AI82,AL82) -> 20660 | I82: =sum(L82,O82,R82,U82,X82,AA82,AD82,AG82,AJ82,AM82) -> 0 | J82: =sum(M82,P82,S82,V82,Y82,AB82,AE82,AH82,AK82,AN82) -> 314293 | M82: =M81+L82-K82 -> -134437 | P82: =P81+O82-N82 -> 113430 | Q82: 20660 | S82: =S81+R82-Q82 -> 318900 | V82: =V81+U82-T82 -> 0 | Y82: =Y81+X82-W82 -> 0 | AB82: =AB81+AA82-Z82 -> 16400 | AE82: =AE81+AD82-AC82 -> 0 | AH82: =AH81+AG82-AF82 -> 0 | AK82: =AK81+AJ82-AI82 -> 0 | AN82: =AN81+AM82-AL82 -> 0
B83: 46099 | D83: Payment | E83: JYQL | G83: 943006 | H83: =sum(K83,N83,Q83,T83,W83,Z83,AC83,AF83,AI83,AL83) -> 20730 | I83: =sum(L83,O83,R83,U83,X83,AA83,AD83,AG83,AJ83,AM83) -> 0 | J83: =sum(M83,P83,S83,V83,Y83,AB83,AE83,AH83,AK83,AN83) -> 293563 | M83: =M82+L83-K83 -> -134437 | N83: 20730 | P83: =P82+O83-N83 -> 92700 | S83: =S82+R83-Q83 -> 318900 | V83: =V82+U83-T83 -> 0 | Y83: =Y82+X83-W83 -> 0 | AB83: =AB82+AA83-Z83 -> 16400 | AE83: =AE82+AD83-AC83 -> 0 | AH83: =AH82+AG83-AF83 -> 0 | AK83: =AK82+AJ83-AI83 -> 0 | AN83: =AN82+AM83-AL83 -> 0
B84: 46099 | D84: Payment | E84: STAL | G84: 938003 | H84: =sum(K84,N84,Q84,T84,W84,Z84,AC84,AF84,AI84,AL84) -> 19680 | I84: =sum(L84,O84,R84,U84,X84,AA84,AD84,AG84,AJ84,AM84) -> 0 | J84: =sum(M84,P84,S84,V84,Y84,AB84,AE84,AH84,AK84,AN84) -> 273883 | M84: =M83+L84-K84 -> -134437 | P84: =P83+O84-N84 -> 92700 | Q84: 19680 | S84: =S83+R84-Q84 -> 299220 | V84: =V83+U84-T84 -> 0 | Y84: =Y83+X84-W84 -> 0 | AB84: =AB83+AA84-Z84 -> 16400 | AE84: =AE83+AD84-AC84 -> 0 | AH84: =AH83+AG84-AF84 -> 0 | AK84: =AK83+AJ84-AI84 -> 0 | AN84: =AN83+AM84-AL84 -> 0
B85: 46102 | D85: Payment | E85: JYQL | G85: 943008 | H85: =sum(K85,N85,Q85,T85,W85,Z85,AC85,AF85,AI85,AL85) -> 7530 | I85: =sum(L85,O85,R85,U85,X85,AA85,AD85,AG85,AJ85,AM85) -> 0 | J85: =sum(M85,P85,S85,V85,Y85,AB85,AE85,AH85,AK85,AN85) -> 266353 | M85: =M84+L85-K85 -> -134437 | N85: 7530 | P85: =P84+O85-N85 -> 85170 | S85: =S84+R85-Q85 -> 299220 | V85: =V84+U85-T85 -> 0 | Y85: =Y84+X85-W85 -> 0 | AB85: =AB84+AA85-Z85 -> 16400 | AE85: =AE84+AD85-AC85 -> 0 | AH85: =AH84+AG85-AF85 -> 0 | AK85: =AK84+AJ85-AI85 -> 0 | AN85: =AN84+AM85-AL85 -> 0
B86: 46099 | D86: Payment | E86: KM Aire / HISYS | G86: 943017 | H86: =sum(K86,N86,Q86,T86,W86,Z86,AC86,AF86,AI86,AL86) -> 60000 | I86: =sum(L86,O86,R86,U86,X86,AA86,AD86,AG86,AJ86,AM86) -> 0 | J86: =sum(M86,P86,S86,V86,Y86,AB86,AE86,AH86,AK86,AN86) -> 206353 | M86: =M85+L86-K86 -> -134437 | P86: =P85+O86-N86 -> 85170 | S86: =S85+R86-Q86 -> 299220 | V86: =V85+U86-T86 -> 0 | W86: 60000 | Y86: =Y85+X86-W86 -> -60000 | AB86: =AB85+AA86-Z86 -> 16400 | AE86: =AE85+AD86-AC86 -> 0 | AH86: =AH85+AG86-AF86 -> 0 | AK86: =AK85+AJ86-AI86 -> 0 | AN86: =AN85+AM86-AL86 -> 0
B87: 46100 | D87: Payment | E87: Uniwestech | G87: transfer | H87: =sum(K87,N87,Q87,T87,W87,Z87,AC87,AF87,AI87,AL87) -> 16400 | I87: =sum(L87,O87,R87,U87,X87,AA87,AD87,AG87,AJ87,AM87) -> 0 | J87: =sum(M87,P87,S87,V87,Y87,AB87,AE87,AH87,AK87,AN87) -> 189953 | M87: =M86+L87-K87 -> -134437 | P87: =P86+O87-N87 -> 85170 | S87: =S86+R87-Q87 -> 299220 | V87: =V86+U87-T87 -> 0 | Y87: =Y86+X87-W87 -> -60000 | Z87: 16400 | AB87: =AB86+AA87-Z87 -> 0 | AE87: =AE86+AD87-AC87 -> 0 | AH87: =AH86+AG87-AF87 -> 0 | AK87: =AK86+AJ87-AI87 -> 0 | AN87: =AN86+AM87-AL87 -> 0
B88: 46105 | D88: Payment | E88: Centralworld | G88: 938019 | H88: =sum(K88,N88,Q88,T88,W88,Z88,AC88,AF88,AI88,AL88) -> 20000 | I88: =sum(L88,O88,R88,U88,X88,AA88,AD88,AG88,AJ88,AM88) -> 0 | J88: =sum(M88,P88,S88,V88,Y88,AB88,AE88,AH88,AK88,AN88) -> 169953 | K88: 20000 | M88: =M86+L88-K88 -> -154437 | P88: =P86+O88-N88 -> 85170 | S88: =S86+R88-Q88 -> 299220 | V88: =V86+U88-T88 -> 0 | Y88: =Y87+X88-W88 -> -60000 | AB88: =AB87+AA88-Z88 -> 0 | AE88: =AE86+AD88-AC88 -> 0 | AH88: =AH86+AG88-AF88 -> 0 | AK88: =AK86+AJ88-AI88 -> 0 | AN88: =AN86+AM88-AL88 -> 0
B89: 46108 | D89: Payment | E89: JYQL | G89: 943004 | H89: =sum(K89,N89,Q89,T89,W89,Z89,AC89,AF89,AI89,AL89) -> 22500 | I89: =sum(L89,O89,R89,U89,X89,AA89,AD89,AG89,AJ89,AM89) -> 0 | J89: =sum(M89,P89,S89,V89,Y89,AB89,AE89,AH89,AK89,AN89) -> 147453 | M89: =M88+L89-K89 -> -154437 | N89: 22500 | P89: =P88+O89-N89 -> 62670 | S89: =S88+R89-Q89 -> 299220 | V89: =V88+U89-T89 -> 0 | Y89: =Y88+X89-W89 -> -60000 | AB89: =AB88+AA89-Z89 -> 0 | AE89: =AE88+AD89-AC89 -> 0 | AH89: =AH88+AG89-AF89 -> 0 | AK89: =AK88+AJ89-AI89 -> 0 | AN89: =AN88+AM89-AL89 -> 0
B90: 46108 | D90: Payment | E90: STAL | G90: 938047 | H90: =sum(K90,N90,Q90,T90,W90,Z90,AC90,AF90,AI90,AL90) -> 19070 | I90: =sum(L90,O90,R90,U90,X90,AA90,AD90,AG90,AJ90,AM90) -> 0 | J90: =sum(M90,P90,S90,V90,Y90,AB90,AE90,AH90,AK90,AN90) -> 128383 | M90: =M89+L90-K90 -> -154437 | P90: =P89+O90-N90 -> 62670 | Q90: 19070 | S90: =S89+R90-Q90 -> 280150 | V90: =V89+U90-T90 -> 0 | Y90: =Y89+X90-W90 -> -60000 | AB90: =AB89+AA90-Z90 -> 0 | AE90: =AE89+AD90-AC90 -> 0 | AH90: =AH89+AG90-AF90 -> 0 | AK90: =AK89+AJ90-AI90 -> 0 | AN90: =AN89+AM90-AL90 -> 0
B91: 46108 | D91: Payment | E91: STAL | G91: 938048 | H91: =sum(K91,N91,Q91,T91,W91,Z91,AC91,AF91,AI91,AL91) -> 21250 | I91: =sum(L91,O91,R91,U91,X91,AA91,AD91,AG91,AJ91,AM91) -> 0 | J91: =sum(M91,P91,S91,V91,Y91,AB91,AE91,AH91,AK91,AN91) -> 107133 | M91: =M90+L91-K91 -> -154437 | P91: =P90+O91-N91 -> 62670 | Q91: 21250 | S91: =S90+R91-Q91 -> 258900 | V91: =V90+U91-T91 -> 0 | Y91: =Y90+X91-W91 -> -60000 | AB91: =AB90+AA91-Z91 -> 0 | AE91: =AE90+AD91-AC91 -> 0 | AH91: =AH90+AG91-AF91 -> 0 | AK91: =AK90+AJ91-AI91 -> 0 | AN91: =AN90+AM91-AL91 -> 0
B92: 46110 | D92: Payment | E92: JYQL | G92: 943009 | H92: =sum(K92,N92,Q92,T92,W92,Z92,AC92,AF92,AI92,AL92) -> 17050 | I92: =sum(L92,O92,R92,U92,X92,AA92,AD92,AG92,AJ92,AM92) -> 0 | J92: =sum(M92,P92,S92,V92,Y92,AB92,AE92,AH92,AK92,AN92) -> 90083 | M92: =M91+L92-K92 -> -154437 | N92: 17050 | P92: =P91+O92-N92 -> 45620 | S92: =S91+R92-Q92 -> 258900 | V92: =V91+U92-T92 -> 0 | Y92: =Y91+X92-W92 -> -60000 | AB92: =AB91+AA92-Z92 -> 0 | AE92: =AE91+AD92-AC92 -> 0 | AH92: =AH91+AG92-AF92 -> 0 | AK92: =AK91+AJ92-AI92 -> 0 | AN92: =AN91+AM92-AL92 -> 0
B93: 46112 | D93: Payment | E93: KM Aire / HISYS | G93: 943018 | H93: =sum(K93,N93,Q93,T93,W93,Z93,AC93,AF93,AI93,AL93) -> 131644.12 | I93: =sum(L93,O93,R93,U93,X93,AA93,AD93,AG93,AJ93,AM93) -> 0 | J93: =sum(M93,P93,S93,V93,Y93,AB93,AE93,AH93,AK93,AN93) -> -41561.12 | M93: =M92+L93-K93 -> -154437 | P93: =P92+O93-N93 -> 45620 | S93: =S92+R93-Q93 -> 258900 | V93: =V92+U93-T93 -> 0 | W93: 131644.12 | Y93: =Y92+X93-W93 -> -191644.12 | AB93: =AB92+AA93-Z93 -> 0 | AE93: =AE92+AD93-AC93 -> 0 | AH93: =AH92+AG93-AF93 -> 0 | AK93: =AK92+AJ93-AI93 -> 0 | AN93: =AN92+AM93-AL93 -> 0
B94: 46084 | D94: Purchases | E94: JYQL | F94: DR# 93049 | H94: =sum(K94,N94,Q94,T94,W94,Z94,AC94,AF94,AI94,AL94) -> 0 | I94: =sum(L94,O94,R94,U94,X94,AA94,AD94,AG94,AJ94,AM94) -> 15095 | J94: =sum(M94,P94,S94,V94,Y94,AB94,AE94,AH94,AK94,AN94) -> -26466.12 | M94: =M93+L94-K94 -> -154437 | O94: 15095 | P94: =P93+O94-N94 -> 60715 | S94: =S93+R94-Q94 -> 258900 | V94: =V93+U94-T94 -> 0 | Y94: =Y93+X94-W94 -> -191644.12 | AB94: =AB93+AA94-Z94 -> 0 | AE94: =AE93+AD94-AC94 -> 0 | AH94: =AH93+AG94-AF94 -> 0 | AK94: =AK93+AJ94-AI94 -> 0 | AN94: =AN93+AM94-AL94 -> 0
B95: 46085 | D95: Purchases | E95: JYQL | F95: DR# 74013 | H95: =sum(K95,N95,Q95,T95,W95,Z95,AC95,AF95,AI95,AL95) -> 0 | I95: =sum(L95,O95,R95,U95,X95,AA95,AD95,AG95,AJ95,AM95) -> 5600 | J95: =sum(M95,P95,S95,V95,Y95,AB95,AE95,AH95,AK95,AN95) -> -20866.12 | M95: =M94+L95-K95 -> -154437 | O95: 5600 | P95: =P94+O95-N95 -> 66315 | S95: =S94+R95-Q95 -> 258900 | V95: =V94+U95-T95 -> 0 | Y95: =Y94+X95-W95 -> -191644.12 | AB95: =AB94+AA95-Z95 -> 0 | AE95: =AE94+AD95-AC95 -> 0 | AH95: =AH94+AG95-AF95 -> 0 | AK95: =AK94+AJ95-AI95 -> 0 | AN95: =AN94+AM95-AL95 -> 0
B96: 46086 | D96: Purchases | E96: STAL | F96: DR# 139 | H96: =sum(K96,N96,Q96,T96,W96,Z96,AC96,AF96,AI96,AL96) -> 0 | I96: =sum(L96,O96,R96,U96,X96,AA96,AD96,AG96,AJ96,AM96) -> 20000 | J96: =sum(M96,P96,S96,V96,Y96,AB96,AE96,AH96,AK96,AN96) -> -866.12 | M96: =M95+L96-K96 -> -154437 | P96: =P95+O96-N96 -> 66315 | R96: 20000 | S96: =S95+R96-Q96 -> 278900 | V96: =V95+U96-T96 -> 0 | Y96: =Y95+X96-W96 -> -191644.12 | AB96: =AB95+AA96-Z96 -> 0 | AE96: =AE95+AD96-AC96 -> 0 | AH96: =AH95+AG96-AF96 -> 0 | AK96: =AK95+AJ96-AI96 -> 0 | AN96: =AN95+AM96-AL96 -> 0
B97: 46092 | D97: Purchases | E97: JYQL | F97: DR# 61845 | H97: =sum(K97,N97,Q97,T97,W97,Z97,AC97,AF97,AI97,AL97) -> 0 | I97: =sum(L97,O97,R97,U97,X97,AA97,AD97,AG97,AJ97,AM97) -> 38530 | J97: =sum(M97,P97,S97,V97,Y97,AB97,AE97,AH97,AK97,AN97) -> 37663.88 | M97: =M96+L97-K97 -> -154437 | O97: 38530 | P97: =P96+O97-N97 -> 104845 | S97: =S96+R97-Q97 -> 278900 | V97: =V96+U97-T97 -> 0 | Y97: =Y96+X97-W97 -> -191644.12 | AB97: =AB96+AA97-Z97 -> 0 | AE97: =AE96+AD97-AC97 -> 0 | AH97: =AH96+AG97-AF97 -> 0 | AK97: =AK96+AJ97-AI97 -> 0 | AN97: =AN96+AM97-AL97 -> 0
B98: 46092 | D98: Purchases | E98: STAL | F98: DR# 143 | H98: =sum(K98,N98,Q98,T98,W98,Z98,AC98,AF98,AI98,AL98) -> 0 | I98: =sum(L98,O98,R98,U98,X98,AA98,AD98,AG98,AJ98,AM98) -> 20680 | J98: =sum(M98,P98,S98,V98,Y98,AB98,AE98,AH98,AK98,AN98) -> 58343.88 | M98: =M97+L98-K98 -> -154437 | P98: =P97+O98-N98 -> 104845 | R98: 20680 | S98: =S97+R98-Q98 -> 299580 | V98: =V97+U98-T98 -> 0 | Y98: =Y97+X98-W98 -> -191644.12 | AB98: =AB97+AA98-Z98 -> 0 | AE98: =AE97+AD98-AC98 -> 0 | AH98: =AH97+AG98-AF98 -> 0 | AK98: =AK97+AJ98-AI98 -> 0 | AN98: =AN97+AM98-AL98 -> 0
B99: 46097 | D99: Purchases | E99: HYSIS | F99: DR# 0117 | H99: =sum(K99,N99,Q99,T99,W99,Z99,AC99,AF99,AI99,AL99) -> 0 | I99: =sum(L99,O99,R99,U99,X99,AA99,AD99,AG99,AJ99,AM99) -> 191644.12 | J99: =sum(M99,P99,S99,V99,Y99,AB99,AE99,AH99,AK99,AN99) -> 249988 | M99: =M98+L99-K99 -> -154437 | P99: =P98+O99-N99 -> 104845 | S99: =S98+R99-Q99 -> 299580 | V99: =V98+U99-T99 -> 0 | X99: 191644.12 | Y99: =Y98+X99-W99 -> 0 | AB99: =AB98+AA99-Z99 -> 0 | AE99: =AE98+AD99-AC99 -> 0 | AH99: =AH98+AG99-AF99 -> 0 | AK99: =AK98+AJ99-AI99 -> 0 | AN99: =AN98+AM99-AL99 -> 0
B100: 46098 | D100: Purchases | E100: JYQL | F100: DR# 02137 | H100: =sum(K100,N100,Q100,T100,W100,Z100,AC100,AF100,AI100,AL100) -> 0 | I100: =sum(L100,O100,R100,U100,X100,AA100,AD100,AG100,AJ100,AM100) -> 20380 | J100: =sum(M100,P100,S100,V100,Y100,AB100,AE100,AH100,AK100,AN100) -> 270368 | M100: =M99+L100-K100 -> -154437 | O100: 20380 | P100: =P99+O100-N100 -> 125225 | S100: =S99+R100-Q100 -> 299580 | V100: =V99+U100-T100 -> 0 | Y100: =Y99+X100-W100 -> 0 | AB100: =AB99+AA100-Z100 -> 0 | AE100: =AE99+AD100-AC100 -> 0 | AH100: =AH99+AG100-AF100 -> 0 | AK100: =AK99+AJ100-AI100 -> 0 | AN100: =AN99+AM100-AL100 -> 0
B101: 46099 | D101: Purchases | E101: STAL | F101: DR# 148 | H101: =sum(K101,N101,Q101,T101,W101,Z101,AC101,AF101,AI101,AL101) -> 0 | I101: =sum(L101,O101,R101,U101,X101,AA101,AD101,AG101,AJ101,AM101) -> 14300 | J101: =sum(M101,P101,S101,V101,Y101,AB101,AE101,AH101,AK101,AN101) -> 284668 | M101: =M100+L101-K101 -> -154437 | P101: =P100+O101-N101 -> 125225 | R101: 14300 | S101: =S100+R101-Q101 -> 313880 | V101: =V100+U101-T101 -> 0 | Y101: =Y100+X101-W101 -> 0 | AB101: =AB100+AA101-Z101 -> 0 | AE101: =AE100+AD101-AC101 -> 0 | AH101: =AH100+AG101-AF101 -> 0 | AK101: =AK100+AJ101-AI101 -> 0 | AN101: =AN100+AM101-AL101 -> 0
...

Sheet 2026 issuances
A1: 46060
A2: Date of Issuance | B2: Check Date | C2: Deposit Date | D2: Check # | E2: Amount | F2: Payee | G2: Reference | H2: Remarks
A3: 45908 | B3: 46011 | C3: 46011 | D3: 938016 | E3: 20000 | F3: Centralworld Enterprises
C4: 46017 | E4: 18000 | F4: salaries
B5: 46017 | D5: 942969 | E5: 13800 | F5: 2BMA
A7: 45978 | B7: 46003 | C7: 45669 | D7: 938046 | E7: 11800 | F7: JYQL | G7: 034534 & 180294 JYQL (6350+5450) | H7: HOLD, deposit Jan 12, 2026
B8: 46035 | C8: 45670 | D8: 942956 | E8: 13800 | F8: 65045 JYQL | G8: 45945
B9: 46035 | C9: 45670 | D9: 942957 | E9: 16300 | F9: 91741 JYQL | G9: 45959
A10: 45845 | B10: 45924 | C10: 46010 | D10: 917636 | E10: 5310 | F10: Jambon / Cash | G10: DR#0108 | H10: HOLD, deposit Dec 19
A11: 45845 | B11: 45952 | C11: 46010 | D11: 917637 | E11: 18760 | F11: Jambon / Cash | G11: DR#0116 | H11: HOLD, deposit Dec 19
A12: 45845 | B12: 45961 | C12: 46010 | D12: 917646 | E12: 10020 | F12: Jambon / Cash | G12: DR#0123 | H12: HOLD, deposit Dec 19
B13: 46036 | C13: 45671 | D13: 942953 | E13: 32118 | F13: 204688 Winterpine (JS)
C14: 46037 | E14: 15600 | F14: Salaries
A15: 45940 | B15: 45966 | C15: 46037 | D15: 938035 | E15: 20000 | F15: UNIWESTECH | G15: for 8 cylender freon | H15: deposit Jan 15 2026
A16: 45978 | B16: 46000 | C16: 46038 | D16: 938045 | E16: 27260 | F16: JYQL | G16: 401581 JYQL | H16: HOLD, deposit Jan 16, 2026
B17: 46038 | C17: 46038 | D17: 942958 | E17: 12000 | F17: 72620 JYQL | G17: 45972
B18: 46038 | C18: 46038 | D18: 942959 | E18: 10800 | F18: 20202 JYQL | G18: 45973
A20: 45908 | B20: 46042 | C20: 46042 | D20: 938017 | E20: 20000 | F20: Centralworld Enterprises
B21: 46030 | C21: 46044 | D21: 942970 | E21: 44145 | F21: Entalpia | H21: 10 cyls 404, deposit date Jan 22
A22: 46036 | B22: 45672 | C22: 46044 | D22: 942972 | E22: 26928 | F22: Entalpia | G22: 4 cyls R314A | H22: Entalpia Europe (Philippines) Inc
B23: 46044 | C23: 46044 | D23: 942960 | E23: 8550 | F23: 50116 JYQL | G23: 45980
B24: 46041 | C24: 46045 | D24: 942955 | E24: 18858.4 | F24: 208141 Winterpine | G24: 45996
A25: 45905 | B25: 45965 | C25: 45314 | D25: 917650 | E25: 3650 | F25: Jambon / Cash | G25: DR#0126 additional, less overpayment DR#108 | H25: HOLD, deposit Jan 24, 2026
A26: 45905 | B26: 45970 | C26: 45314 | D26: 938001 | E26: 7470 | F26: Jambon / Cash | G26: DR#0130 | H26: HOLD, deposit Jan 24, 2026
A28: 45940 | B28: 45971 | C28: 46048 | D28: 938036 | E28: 25600 | F28: UNIWESTECH | G28: for 8 cylender freon | H28: deposit Jan 26, 2026
C29: 46052 | E29: 18000 | F29: Salaries
B31: 46045 | C31: 46058 | D31: 942965 | E31: 27450 | F31: 30652 JYQL | G31: 45989 | H31: moved to Feb 5 2026
B32: 46044 | C32: 46058 | D32: 942961 | E32: 18610 | F32: 65427 JYQL | G32: 45980 | H32: moved to Feb 5 2026
A33: 45981 | B33: 46008 | C33: 46047 | D33: 942952 | E33: 35000 | F33: UNIWESTECH | G33: replacement check # 917648 | H33: bounced, redep Feb 13, cleared Feb 6 2026
B34: 46059 | C34: 45694 | D34: 942962 | E34: 12850 | F34: 63426 JYQL | G34: 45994 | H34: paid thru bank transfer Feb 7 2026
A36: 46037 | B36: 46065 | C36: 46065 | D36: 942974 | E36: 23500 | F36: 65820 JYQL
A37: 46037 | B37: 46066 | C37: 46066 | D37: 942975 | E37: 10290 | F37: 94218 JYQL
A38: 46037 | B38: 46066 | C38: 46066 | D38: 942976 | E38: 9400 | F38: 70746JYQL
C39: 46066 | E39: 18000 | F39: Salaries
B41: 46069 | C41: 46069 | D41: 942999 | E41: 10290 | F41: 94218 JYQL | G41: DR# 94218
B43: 46075 | C43: 46075 | D43: 943000 | E43: 9400 | F43: 70746 JYQL | G43: DR# 70746
B44: 46078 | C44: 46078 | D44: 943001 | E44: 19240 | F44: 91780 JYQL | G44: DR# 91780 | H44: Good
A46: 45908 | B46: 46073 | C46: 46073 | D46: 938018 | E46: 20000 | F46: Centralworld Enterprises | H46: cleared Feb 27
A47: 46036 | B47: 46043 | C47: 46080 | D47: 942973 | E47: 16000 | F47: Uniwestech | G47: 2 tanks Gaz | H47: Uniwestech Philippines Inc
C48: 46081 | E48: 18000 | F48: Salaries
C49: 46052 | E49: 10000 | F49: Ishabella | G49: Suzuki
C50: 46081 | E50: 10000 | F50: Ishabella | G50: Suzuki
C51: 46096 | E51: 30000 | F51: commissions
B60: 46081 | C60: 46081 | D60: 943002 | E60: 9200 | F60: 14429 JYQL | G60: DR# 14429 | J60: =VLOOKUP(D60, '2026 AP'!$G$75:$H$93, 2, FALSE) -> 9200 | K60: =J60-E60 -> 0
C61: 46083 | E61: 16926.8 | F61: ISHABELLA | H61: TRANSFER
A62: 45905 | B62: 45974 | C62: 46084 | D62: 938002 | E62: 12150 | F62: STAL / Cash | G62: DR#0137 | H62: deposit March 3 2026, Tuesday | J62: =VLOOKUP(D62, '2026 AP'!$G$75:$H$93, 2, FALSE) -> 12150 | K62: =J62-E62 -> 0
B63: 46051 | C63: 46086 | D63: 942954 | E63: 25230.8 | F63: 204958 Winterpine | G63: 45922 | H63: bank transfer March 12 2026 | J63: =VLOOKUP(D63, '2026 AP'!$G$75:$H$93, 2, FALSE) -> #N/A | K63: =J63-E63 -> #N/A
B64: 46078 | C64: 46093 | D64: 943007 | E64: 35360 | F64: Entalpia | G64: c/o Ishabella | H64: 5 tanks R134A | J64: =VLOOKUP(D64, '2026 AP'!$G$75:$H$93, 2, FALSE) -> #N/A | K64: =J64-E64 -> #N/A
B65: 46087 | C65: 46087 | D65: 943003 | E65: 22500 | F65: 44561 JYQL | G65: DR# 44561a | H65: deposit March 13 2026 | J65: =VLOOKUP(D65, '2026 AP'!$G$75:$H$93, 2, FALSE) -> 22500 | K65: =J65-E65 -> 0
B66: 46089 | C66: 46089 | D66: 943005 | E66: 6385 | F66: 85619 JYQL | G66: DR# 85619 | J66: =VLOOKUP(D66, '2026 AP'!$G$75:$H$93, 2, FALSE) -> 6385 | K66: =J66-E66 -> 0
A67: 46051 | B67: 46059 | C67: 46100 | D67: 942979 | E67: 16400 | F67: Uniwestech | G67: 2 tanks Gaz | J67: =VLOOKUP(D67, '2026 AP'!$G$75:$H$93, 2, FALSE) -> #N/A | K67: =J67-E67 -> #N/A
A68: 45845 | B68: 45965 | C68: 46087 | D68: 917639 | E68: 20660 | F68: STAL / Cash | G68: DR#0126 | H68: deposit March 18 | J68: =VLOOKUP(D68, '2026 AP'!$G$75:$H$93, 2, FALSE) -> 20660 | K68: =J68-E68 -> 0
B69: 46099 | C69: 46099 | D69: 943006 | E69: 20730 | F69: 95150 JYQL | G69: DR# 95150 | J69: =VLOOKUP(D69, '2026 AP'!$G$75:$H$93, 2, FALSE) -> 20730 | K69: =J69-E69 -> 0
A70: 45905 | B70: 45982 | C70: 46052 | D70: 938003 | E70: 19680 | F70: Jambon / Cash | G70: DR#0140 | H70: deposit March 19 | J70: =VLOOKUP(D70, '2026 AP'!$G$75:$H$93, 2, FALSE) -> 19680 | K70: =J70-E70 -> 0
B71: 46102 | C71: 46102 | D71: 943008 | E71: 7530 | F71: JYQL | G71: DR#51328 & DR#92794 | J71: =VLOOKUP(D71, '2026 AP'!$G$75:$H$93, 2, FALSE) -> 7530 | K71: =J71-E71 -> 0
B72: 46099 | C72: 46099 | D72: 943017 | E72: 60000 | F72: KM Aire Alliance Corporation | H72: cleared March 24 | J72: =VLOOKUP(D72, '2026 AP'!$G$75:$H$93, 2, FALSE) -> 60000 | K72: =J72-E72 -> 0
A73: 45908 | B73: 46101 | C73: 46105 | D73: 938019 | E73: 20000 | F73: Centralworld Enterprises | H73: deposit March 24 2026, Tuesday | J73: =VLOOKUP(D73, '2026 AP'!$G$75:$H$93, 2, FALSE) -> 20000 | K73: =J73-E73 -> 0
B74: 46102 | C74: 46108 | D74: 943004 | E74: 22500 | F74: 44561 JYQL | G74: DR# 44561b | H74: deposit March 27 2026, Friday | J74: =VLOOKUP(D74, '2026 AP'!$G$75:$H$93, 2, FALSE) -> 22500 | K74: =J74-E74 -> 0
A75: 45978 | B75: 46007 | C75: 46108 | D75: 938047 | E75: 19070 | F75: Jambon / Cash | G75: DR#148 | H75: deposit March 27 2026, Friday | J75: =VLOOKUP(D75, '2026 AP'!$G$75:$H$93, 2, FALSE) -> 19070 | K75: =J75-E75 -> 0
A76: 45978 | B76: 46034 | C76: 46108 | D76: 938048 | E76: 21250 | F76: Jambon / Cash | G76: DR#150 | H76: deposit March 27, Today | J76: =VLOOKUP(D76, '2026 AP'!$G$75:$H$93, 2, FALSE) -> 21250 | K76: =J76-E76 -> 0
B77: 46110 | C77: 46110 | D77: 943009 | E77: 17050 | F77: JYQL | G77: DR#21733 | J77: =VLOOKUP(D77, '2026 AP'!$G$75:$H$93, 2, FALSE) -> 17050 | K77: =J77-E77 -> 0
B78: 46107 | C78: 46112 | D78: 943018 | E78: 131644.12 | F78: KM Aire Alliance Corporation | H78: deposit March 31 2026, Tuesday | J78: =VLOOKUP(D78, '2026 AP'!$G$75:$H$93, 2, FALSE) -> 131644.12 | K78: =J78-E78 -> 0
B80: 46116 | C80: 46116 | D80: 943010 | E80: 18090 | F80: JYQL | G80: DR#52984
B81: 46122 | C81: 46122 | D81: 943011 | E81: 7840 | F81: JYQL | G81: DR#45034
B82: 46062 | C82: 46122 | D82: 942966 | E82: 20250 | F82: 172 Cash/Stal | G82: 45972 | H82: deposit April 10 2026
B83: 46064 | C83: 46122 | D83: 942967 | E83: 3900 | F83: 174 Cash/Stal | G83: 45974 | H83: deposit April 10 2026
B84: 46127 | C84: 46127 | D84: FT | E84: 46200 | F84: 3BMA | G84: 6 tanks R134a
A85: 45978 | B85: 46044 | C85: 46129 | D85: 938049 | E85: 25400 | F85: 160 Jambon / Cash | G85: DR#160 | H85: deposit April 17
B86: 46070 | C86: 46129 | D86: 942968 | E86: 12600 | F86: 184 Jambon/Stal | G86: 45980 | H86: deposit April 17
B87: 46133 | C87: 46133 | E87: 23100 | F87: 3BMA | H87: paid April 21, 2026 (bank transfer)
C88: 46132 | E88: 5500 | F88: Q2 business permit | H88: paid April 20 2026
A89: 45908 | B89: 46132 | C89: 46132 | D89: 938021 | E89: 20000 | F89: Centralworld Enterprises
A90: 46102 | B90: 46122 | C90: 46129 | D90: 943020 | E90: 20695 | F90: JYQL | G90: DR# 93049/74013 | H90: deposit April 17 2026
A91: 46102 | B91: 46129 | C91: 46129 | D91: 943022 | E91: 38530 | F91: JYQL | G91: DR#61845
C92: 46134 | E92: 13600 | F92: Q1 percentage tax
A93: 45978 | B93: 46071 | C93: 46136 | D93: 938050 | E93: 31300 | F93: CASH/STAL | G93: DR#170 | H93: deposit April 24
A94: 46102 | B94: 46136 | C94: 46136 | D94: 943024 | E94: 18080 | F94: JYQL | G94: DR#02137
A95: 46102 | B95: 46136 | C95: 46136 | D95: 943027 | E95: 25000 | F95: Winterpine | G95: DR#212162 (2/3)
B96: 46139 | E96: 46200 | F96: 3BMA | G96: 6 tanks R134a
B97: 46142 | E97: 20000 | F97: Salary
A99: 46130 | B99: 46146 | D99: 943031 | E99: 9200 | F99: JYQL | G99: DR# 53181
A100: 46130 | B100: 46147 | D100: 943029 | E100: 22170 | F100: JYQL | G100: DR# 75401 (1/2) | H100: transferred May 11 2026
B101: 46142 | E101: =7700*4 -> 30800 | F101: 3BMA | G101: 4 tanks R134a
E102: 9500 | F102: Audit Fee 2025
B103: 46095 | C103: 46136 | D103: 942994 | E103: 4750 | F103: CASH/STAL | G103: DR# 191 | H103: re deposit May 8
B104: 46084 | D104: 942993 | E104: 31350 | F104: CASH/STAL | G104: DR# 189 | H104: deposit May 8
B105: 46104 | D105: 942995 | E105: 5100 | F105: CASH/STAL | G105: DR# 197 | H105: deposit May 8
A106: 46130 | B106: 46150 | D106: 943033 | E106: 9500 | F106: JYQL | G106: DR# 43432
A108: 46102 | B108: 46150 | D108: 943028 | E108: 25000 | F108: Winterpine | G108: DR#212162 (3/3)
A109: 46130 | B109: 46157 | D109: 943030 | E109: 20000 | F109: JYQL | G109: DR# 75401 (2/2)
A110: 46130 | B110: 46157 | D110: 943032 | E110: 4800 | F110: JYQL | G110: DR# 30724
A111: 45908 | B111: 46162 | D111: 938022 | E111: 20000 | F111: Centralworld Enterprises
A112: 46130 | B112: 46166 | D112: 943034 | E112: 28200 | F112: JYQL | G112: DR# 55588
A113: 46143 | B113: 46171 | D113: 943048 | E113: =27470-1550 -> 25920 | F113: JYQL | G113: DR#35765
B114: 46171 | E114: 20000 | F114: salaries
B115: 46171 | E115: 10000 | F115: suzuki
A117: 46130 | B117: 46178 | D117: 943038 | E117: 27202.5 | F117: WINTERPINE | G117: DR# 212730 (1/4)
A118: 46143 | B118: 46178 | D118: 943050 | E118: 17225 | F118: JYQL | G118: DR#42282
A119: 46143 | B119: 46183 | D119: 943047 | E119: 5325 | F119: JYQL | G119: DR#61962
A120: 46143 | B120: 46185 | D120: 956451 | E120: 24760 | F120: JYQL | G120: DR#73165
...

Sheet 2026 AR
A1: Aton Aire Trading Corporation
A2: 2026 Receivable | E2: =SUM(E3:E10) -> 0
A3: =TODAY() -> 46311 | D3: ISHABELLA | E3: =H11 -> 0
D4: JYQL | E4: =K11 -> 0
D5: JAMBON | E5: =N11 -> 0
D6: WINTERPINE | E6: =Q11 -> 0
D7: COOP | E7: =T11 -> 0
D8: UNIWESTECH | E8: =W11 -> 0
D9: HISYS | E9: =Z11 -> 0
D10: NBO
F11: =SUM(F15:F1048576) -> 0 | G11: =SUM(G15:G1048576) -> 0 | H11: =H14+G11-F11 -> 0 | I11: =SUM(I15:I1048576) -> 0 | J11: =SUM(J15:J1048576) -> 0 | K11: =K14+J11-I11 -> 0 | L11: =SUM(L15:L1048576) -> 0 | M11: =SUM(M15:M1048576) -> 0 | N11: =N14+M11-L11 -> 0 | O11: =SUM(O15:O1048576) -> 0 | P11: =SUM(P15:P1048576) -> 0 | Q11: =Q14+P11-O11 -> 0 | R11: =SUM(R15:R1048576) -> 0 | S11: =SUM(S15:S1048576) -> 0 | T11: =T14+S11-R11 -> 0 | U11: =SUM(U15:U1048576) -> 0 | V11: =SUM(V15:V1048576) -> 0 | W11: =W14+V11-U11 -> 0 | X11: =SUM(X15:X1048576) -> 0 | Y11: =SUM(Y15:Y1048576) -> 0 | Z11: =Z14+Y11-X11 -> 0 | AA11: =SUM(AA15:AA1048576) -> 0 | AB11: =SUM(AB15:AB1048576) -> 0 | AC11: =AC14+AB11-AA11 -> 0
F12: ISHABELLA | I12: JYQL AIRCON PARTS TRADING | L12: JAMBON/STAL | O12: WINTERPINE AIR CONDITIONING CORP | R12: COOP | U12: UNIWESTECH | X12: HISYS | AA12: LUFT
B13: Date | C13: Due Date | D13: Particulars | E13: References | F13: Debit | G13: Credit | H13: Balance | I13: Debit | J13: Credit | K13: Balance | L13: Debit | M13: Credit | N13: Balance | O13: Debit | P13: Credit | Q13: Balance | R13: Debit | S13: Credit | T13: Balance | U13: Debit | V13: Credit | W13: Balance | X13: Debit | Y13: Credit | Z13: Balance | AA13: Debit | AB13: Credit | AC13: Balance
Q14: 0 | T14: 0 | W14: 0 | Z14: 0 | AC14: 0
H15: =H14+G15-F15 -> 0 | K15: =K14+J15-I15 -> 0 | N15: =N14+M15-L15 -> 0 | Q15: =Q14+P15-O15 -> 0 | T15: =T14+S15-R15 -> 0 | W15: =W14+V15-U15 -> 0 | Z15: =Z14+Y15-X15 -> 0 | AC15: =AC14+AB15-AA15 -> 0
H16: =H15+G16-F16 -> 0 | K16: =K15+J16-I16 -> 0 | N16: =N15+M16-L16 -> 0 | Q16: =Q15+P16-O16 -> 0 | T16: =T15+S16-R16 -> 0 | W16: =W15+V16-U16 -> 0 | Z16: =Z15+Y16-X16 -> 0 | AC16: =AC15+AB16-AA16 -> 0
H17: =H16+G17-F17 -> 0 | K17: =K16+J17-I17 -> 0 | N17: =N16+M17-L17 -> 0 | Q17: =Q16+P17-O17 -> 0 | T17: =T16+S17-R17 -> 0 | W17: =W16+V17-U17 -> 0 | Z17: =Z16+Y17-X17 -> 0 | AC17: =AC16+AB17-AA17 -> 0
H18: =H17+G18-F18 -> 0 | K18: =K17+J18-I18 -> 0 | N18: =N17+M18-L18 -> 0 | Q18: =Q17+P18-O18 -> 0 | T18: =T17+S18-R18 -> 0 | W18: =W17+V18-U18 -> 0 | Z18: =Z17+Y18-X18 -> 0 | AC18: =AC17+AB18-AA18 -> 0
H19: =H18+G19-F19 -> 0 | K19: =K18+J19-I19 -> 0 | N19: =N18+M19-L19 -> 0 | Q19: =Q18+P19-O19 -> 0 | T19: =T18+S19-R19 -> 0 | W19: =W18+V19-U19 -> 0 | Z19: =Z18+Y19-X19 -> 0 | AC19: =AC18+AB19-AA19 -> 0
H20: =H18+G20-F20 -> 0 | K20: =K19+J20-I20 -> 0 | N20: =N19+M20-L20 -> 0 | Q20: =Q19+P20-O20 -> 0 | T20: =T19+S20-R20 -> 0 | W20: =W19+V20-U20 -> 0 | Z20: =Z19+Y20-X20 -> 0 | AC20: =AC19+AB20-AA20 -> 0
H21: =H19+G21-F21 -> 0 | K21: =K20+J21-I21 -> 0 | N21: =N20+M21-L21 -> 0 | Q21: =Q20+P21-O21 -> 0 | T21: =T20+S21-R21 -> 0 | W21: =W20+V21-U21 -> 0 | Z21: =Z20+Y21-X21 -> 0 | AC21: =AC20+AB21-AA21 -> 0
H22: =H20+G22-F22 -> 0 | K22: =K21+J22-I22 -> 0 | N22: =N21+M22-L22 -> 0 | Q22: =Q21+P22-O22 -> 0 | T22: =T21+S22-R22 -> 0 | W22: =W21+V22-U22 -> 0 | Z22: =Z21+Y22-X22 -> 0 | AC22: =AC21+AB22-AA22 -> 0
H23: =H21+G23-F23 -> 0 | K23: =K22+J23-I23 -> 0 | N23: =N22+M23-L23 -> 0 | Q23: =Q22+P23-O23 -> 0 | T23: =T22+S23-R23 -> 0 | W23: =W22+V23-U23 -> 0 | Z23: =Z22+Y23-X23 -> 0 | AC23: =AC22+AB23-AA23 -> 0
H24: =H22+G24-F24 -> 0 | K24: =K23+J24-I24 -> 0 | N24: =N23+M24-L24 -> 0 | Q24: =Q23+P24-O24 -> 0 | T24: =T23+S24-R24 -> 0 | W24: =W23+V24-U24 -> 0 | Z24: =Z23+Y24-X24 -> 0 | AC24: =AC23+AB24-AA24 -> 0
H25: =H24+G25-F25 -> 0 | K25: =K24+J25-I25 -> 0 | N25: =N24+M25-L25 -> 0 | Q25: =Q24+P25-O25 -> 0 | T25: =T24+S25-R25 -> 0 | W25: =W24+V25-U25 -> 0 | Z25: =Z24+Y25-X25 -> 0 | AC25: =AC24+AB25-AA25 -> 0
H26: =H25+G26-F26 -> 0 | K26: =K25+J26-I26 -> 0 | N26: =N25+M26-L26 -> 0 | Q26: =Q25+P26-O26 -> 0 | T26: =T25+S26-R26 -> 0 | W26: =W25+V26-U26 -> 0 | Z26: =Z25+Y26-X26 -> 0 | AC26: =AC25+AB26-AA26 -> 0
H27: =H26+G27-F27 -> 0 | K27: =K26+J27-I27 -> 0 | N27: =N26+M27-L27 -> 0 | Q27: =Q26+P27-O27 -> 0 | T27: =T26+S27-R27 -> 0 | W27: =W26+V27-U27 -> 0 | Z27: =Z26+Y27-X27 -> 0 | AC27: =AC26+AB27-AA27 -> 0
H28: =H27+G28-F28 -> 0 | K28: =K27+J28-I28 -> 0 | N28: =N27+M28-L28 -> 0 | Q28: =Q27+P28-O28 -> 0 | T28: =T27+S28-R28 -> 0 | W28: =W27+V28-U28 -> 0 | Z28: =Z27+Y28-X28 -> 0 | AC28: =AC27+AB28-AA28 -> 0
H29: =H28+G29-F29 -> 0 | K29: =K28+J29-I29 -> 0 | N29: =N28+M29-L29 -> 0 | Q29: =Q28+P29-O29 -> 0 | T29: =T28+S29-R29 -> 0 | W29: =W28+V29-U29 -> 0 | Z29: =Z28+Y29-X29 -> 0 | AC29: =AC28+AB29-AA29 -> 0
H30: =H29+G30-F30 -> 0 | K30: =K29+J30-I30 -> 0 | N30: =N29+M30-L30 -> 0 | Q30: =Q29+P30-O30 -> 0 | T30: =T29+S30-R30 -> 0 | W30: =W29+V30-U30 -> 0 | Z30: =Z29+Y30-X30 -> 0 | AC30: =AC29+AB30-AA30 -> 0
H31: =H30+G31-F31 -> 0 | K31: =K30+J31-I31 -> 0 | N31: =N30+M31-L31 -> 0 | Q31: =Q30+P31-O31 -> 0 | T31: =T30+S31-R31 -> 0 | W31: =W30+V31-U31 -> 0 | Z31: =Z30+Y31-X31 -> 0 | AC31: =AC30+AB31-AA31 -> 0
H32: =H31+G32-F32 -> 0 | K32: =K31+J32-I32 -> 0 | N32: =N31+M32-L32 -> 0 | Q32: =Q31+P32-O32 -> 0 | T32: =T31+S32-R32 -> 0 | W32: =W31+V32-U32 -> 0 | Z32: =Z31+Y32-X32 -> 0 | AC32: =AC31+AB32-AA32 -> 0
H33: =H32+G33-F33 -> 0 | K33: =K32+J33-I33 -> 0 | N33: =N32+M33-L33 -> 0 | Q33: =Q32+P33-O33 -> 0 | T33: =T32+S33-R33 -> 0 | W33: =W32+V33-U33 -> 0 | Z33: =Z32+Y33-X33 -> 0 | AC33: =AC32+AB33-AA33 -> 0
H34: =H33+G34-F34 -> 0 | K34: =K33+J34-I34 -> 0 | N34: =N33+M34-L34 -> 0 | Q34: =Q33+P34-O34 -> 0 | T34: =T33+S34-R34 -> 0 | W34: =W33+V34-U34 -> 0 | Z34: =Z33+Y34-X34 -> 0 | AC34: =AC33+AB34-AA34 -> 0
H35: =H34+G35-F35 -> 0 | K35: =K34+J35-I35 -> 0 | N35: =N34+M35-L35 -> 0 | Q35: =Q34+P35-O35 -> 0 | T35: =T34+S35-R35 -> 0 | W35: =W34+V35-U35 -> 0 | Z35: =Z34+Y35-X35 -> 0 | AC35: =AC34+AB35-AA35 -> 0
H36: =H35+G36-F36 -> 0 | K36: =K35+J36-I36 -> 0 | N36: =N35+M36-L36 -> 0 | Q36: =Q35+P36-O36 -> 0 | T36: =T35+S36-R36 -> 0 | W36: =W35+V36-U36 -> 0 | Z36: =Z35+Y36-X36 -> 0 | AC36: =AC35+AB36-AA36 -> 0
... H300: =H299+G300-F300 -> 0 | K300: =K299+J300-I300 -> 0 | N300: =N299+M300-L300 -> 0 | Q300: =Q299+P300-O300 -> 0 | T300: =T299+S300-R300 -> 0 | W300: =W299+V300-U300 -> 0 | Z300: =Z299+Y300-X300 -> 0 | AC300: =AC299+AB300-AA300 -> 0

Sheet Template
C2: 0 5 0 5 2 0 2 6
B5: JYQL AIRCON PARTS TRADING | C5: 22170
B6: TWENTY TWO THOUSAND ONE HUNDRED SEVENTY PESOS ONLY

Sheet 2026 Comm
A1: Aton Aire Trading Corporation | I1: Drench
A2: 2026 Commissions | C2: =C3-C4 -> 0 | D2: =D3-D4 -> 0 | E2: =E3-E4 -> 0 | F2: =F3-F4 -> 0 | G2: =G3-G4 -> 0 | H2: =H3-H4 -> 0 | I2: =I3-I4 -> 2000
C3: ='2026 DS'!K3 -> 7449.12 | D3: ='2026 IS'!D32 -> 8046.984 | E3: ='2026 IS'!E32 -> 3061.1 | F3: ='2026 IS'!F32 -> 6234.4 | G3: ='2026 IS'!G32 -> 6360.22 | H3: ='2026 IS'!H32 -> 11371.94 | I3: ='2026 IS'!I32 -> 11635.78
C4: =SUM(C6:C25) -> 7449.12 | D4: =SUM(D6:D25) -> 8046.984 | E4: =SUM(E6:E25) -> 3061.1 | F4: =SUM(F6:F25) -> 6234.4 | G4: =SUM(G6:G25) -> 6360.22 | H4: =SUM(H6:H25) -> 11371.94 | I4: =SUM(I6:I25) -> 9635.78 | J4: =SUM(J6:J25) -> 0 | ... O4: =SUM(O6:O25) -> 52159.544
A5: Names | B5: Gcash # | C5: January | D5: February | E5: March | F5: April | G5: May | H5: June | I5: July | J5: August | K5: September | L5: October | M5: November | N5: December | O5: Total
A6: Store | C6: =sumif('2026 DS'!$D$4:$D$42,$A$6,'2026 DS'!$K$4:$K$42) -> 0 | D6: =sumif('2026 DS'!$D$45:$D$102,$A6,'2026 DS'!$K$45:$K$102) -> 0 | E6: =sumif('2026 DS'!$D$104:$D$169,$A6,'2026 DS'!$K$104:$K$169) -> 0 | F6: =sumif('2026 DS'!$D$171:$D$238,$A6,'2026 DS'!$K$171:$K$238) -> 0 | G6: =sumif('2026 DS'!$D$240:$D$290,$A6,'2026 DS'!$K$240:$K$290) -> 44 | H6: =sumif('2026 DS'!$D$292:$D$357,A6,'2026 DS'!$K$292:$K$357) -> 0 | I6: =sumif('2026 DS'!$D$359:$D$435,A6,'2026 DS'!$K$359:$K$435) -> 0 | O6: =SUM(C6:N6) -> 44
A7: Rocky | C7: =sumif('2026 DS'!D$4:D$42,A7,'2026 DS'!K$4:K$42) -> 5397.52 | D7: =sumif('2026 DS'!$D$45:$D$102,$A7,'2026 DS'!$K$45:$K$102) -> 2392.984 | E7: =sumif('2026 DS'!$D$104:$D$169,$A7,'2026 DS'!$K$104:$K$169) -> 593 | F7: =sumif('2026 DS'!$D$171:$D$238,$A7,'2026 DS'!$K$171:$K$238) -> 3131.2 | G7: =sumif('2026 DS'!$D$240:$D$290,$A7,'2026 DS'!$K$240:$K$290) -> 3654.32 | H7: =sumif('2026 DS'!$D$292:$D$357,A7,'2026 DS'!$K$292:$K$357) -> 8659.44 | I7: =sumif('2026 DS'!$D$359:$D$435,A7,'2026 DS'!$K$359:$K$435) -> 3758.08 | O7: =SUM(C7:N7) -> 27586.544
A8: Arnold | C8: =sumif('2026 DS'!D$4:D$42,A8,'2026 DS'!K$4:K$42) -> 0 | D8: =sumif('2026 DS'!$D$45:$D$102,$A8,'2026 DS'!$K$45:$K$102) -> 3788 | E8: =sumif('2026 DS'!$D$104:$D$169,$A8,'2026 DS'!$K$104:$K$169) -> 0 | F8: =sumif('2026 DS'!$D$171:$D$238,$A8,'2026 DS'!$K$171:$K$238) -> 0 | G8: =sumif('2026 DS'!$D$240:$D$290,$A8,'2026 DS'!$K$240:$K$290) -> 0 | H8: =sumif('2026 DS'!$D$292:$D$357,A8,'2026 DS'!$K$292:$K$357) -> 0 | I8: =sumif('2026 DS'!$D$359:$D$435,A8,'2026 DS'!$K$359:$K$435) -> 0 | O8: =SUM(C8:N8) -> 3788
A9: Ikot | C9: =sumif('2026 DS'!D$4:D$42,A9,'2026 DS'!K$4:K$42) -> 2051.6 | D9: =sumif('2026 DS'!$D$45:$D$102,$A9,'2026 DS'!$K$45:$K$102) -> 1866 | E9: =sumif('2026 DS'!$D$104:$D$169,$A9,'2026 DS'!$K$104:$K$169) -> 2468.1 | F9: =sumif('2026 DS'!$D$171:$D$238,$A9,'2026 DS'!$K$171:$K$238) -> 3103.2 | G9: =sumif('2026 DS'!$D$240:$D$290,$A9,'2026 DS'!$K$240:$K$290) -> 2661.9 | H9: =sumif('2026 DS'!$D$292:$D$357,A9,'2026 DS'!$K$292:$K$357) -> 2712.5 | I9: =sumif('2026 DS'!$D$359:$D$435,A9,'2026 DS'!$K$359:$K$435) -> 5877.7 | O9: =SUM(C9:N9) -> 20741
A10: Jun Villanueva | C10: =sumif('2026 DS'!D$4:D$42,A10,'2026 DS'!K$4:K$42) -> 0 | E10: =sumif('2026 DS'!$D$104:$D$169,$A10,'2026 DS'!$K$104:$K$169) -> 0 | F10: =sumif('2026 DS'!$D$171:$D$238,$A10,'2026 DS'!$K$171:$K$238) -> 0 | G10: =sumif('2026 DS'!$D$240:$D$290,$A10,'2026 DS'!$K$240:$K$290) -> 0 | H10: =sumif('2026 DS'!$D$292:$D$357,A10,'2026 DS'!$K$292:$K$357) -> 0 | I10: =sumif('2026 DS'!$D$359:$D$435,A10,'2026 DS'!$K$359:$K$435) -> 0
O13: =SUM(C13:N13) -> 0

Sheet check summ
B2: Reference | E2: Amount | F2: Check # | G2: Check Date
A3: 46198 | B3: DR#03094 | C3: JYQL (additional) | E3: 1500 | F3: 956505 | G3: 46251
A4: 46224 | B4: DR#32742 | C4: JYQL | D4: 52 | E4: 18500 | F4: 956506 | G4: 46276
A5: 46225 | B5: DR#04781 | C5: JYQL | D5: 58 | E5: 16625 | F5: 956507 | G5: 46283
A6: 46225 | B6: DR#0004 | C6: STAL | D6: 90 | E6: 25150 | F6: 956508 | G6: 46315
A7: 46230 | B7: DR#218650 | C7: WINTERPINE | D7: 90 | E7: 23000 | F7: 956509 | G7: 46311
A8: 46230 | B8: DR#218650 | C8: WINTERPINE | D8: 90 | E8: 23000 | F8: 956510 | G8: 46318
A9: 46230 | B9: DR#218650 | C9: WINTERPINE | D9: 90 | E9: 22976 | F9: 956511 | G9: 46332
A10: 46232 | B10: DR#25897 | C10: JYQL | D10: 30 | E10: 700 | F10: 956513 | G10: 46283 | H10: correct amount is 7100
A11: 46232 | B11: DR#61221 | C11: JYQL | D11: 51 | E11: 16000 | H11: returned | I11: cancelled for replacement (wrong amount)
A12: 46232 | B12: DR#61221 | C12: JYQL | D12: 51 | E12: 16400 | F12: 956514 | G12: 46290 | H12: returned
A13: 46232 | B13: DR#0004 | C13: STAL | D13: 90 | E13: 23100 | F13: 956515 | G13: 46322
A14: 46238 | B14: DR#0005 | C14: STAL | D14: 90 | E14: 14250 | F14: 956516 | G14: 46328
A15: 46239 | B15: DR#62058 | C15: JYQL | D15: 45 | E15: 2600 | F15: 956517 | G15: 46284
A16: 46239 | B16: DR#21413 | C16: JYQL | D16: 45 | E16: 20800 | F16: 956518 | G16: 46293
A17: 46239 | B17: DR#21413 | C17: JYQL | D17: 45 | E17: 25000 | F17: 956519 | G17: 46297
A18: 46247 | B18: DR#84293 | C18: JYQL | D18: 57 | E18: 17980 | F18: 956520 | G18: 46304
A20: 46232 | B20: DR#61221 | C20: JYQL | D20: 51 | E20: 16400 | F20: 956514 | G20: 46290 | H20: (1/2) | I20: good check
A21: 46271 | B21: DR#61221 | C21: JYQL | D21: 51 | E21: 16000 | F21: 956521 | G21: 46283 | H21: (2/2)
A22: 46271 | B22: DR#25897 | C22: JYQL | D22: 30 | E22: 7100 | F22: 956522 | G22: 46290
A23: 46271 | B23: DR#0169 | C23: STAL | E23: =34720-24220 -> 10500 | F23: 956523 | G23: 46297 | H23: DR#0169 34,720 less return 24,220
A24: 46271 | B24: DR#21435 | C24: JYQL | E24: =35015-15015 -> 20000 | F24: 956524 | G24: 46304 | H24: (1/2)
A25: 46271 | B25: DR#21435 | C25: JYQL | E25: =35015-20000 -> 15015 | F25: 956525 | G25: 46311 | H25: (2/2)
A26: 46271 | B26: DR#0010 | C26: STAL | E26: 17500 | F26: 956528 | G26: 46350
A27: 46271 | B27: DR#0005 | C27: STAL | E27: 6000 | F27: 956526 | G27: 46343
A28: 46271 | B28: DR#62788 | C28: JYQL | E28: 11100 | F28: 956527 | G28: 46318
A29: 46271 | B29: DR#05088 | C29: JYQL | E29: 14400 | F29: 956529 | G29: 46325
A33: 46295 | B33: deposit to Ishabella | E33: 112343.1
B34: payment to Ishabella | E34: -2500 | F34: JC allowance Sept 2026
B35: payment to Ishabella | E35: =-7900*2 -> -15800 | F35: 2 tanks 134A
B36: payment to 3BMA | E36: -29000 | F36: full payment DR#9977
B37: payment to 3BMA | E37: -47400 | F37: full payment DR#7011
B38: payment to 3BMA | E38: -12000 | F38: full payment DR#7238
B39: payment to 3BMA | E39: -5000 | F39: partial payment DR#7473
B40: remaining balance | E40: =sum(E33:E39) -> 643.1 | F40: snacks Shiena
A42: 46301 | C42: Winterpine | D42: 93 | E42: 10660 | F42: 956530 | G42: 46360
A43: 46301 | B43: DR#72094 | C43: JYQL | D43: 58 | E43: 5650 | F43: 956531 | G43: 46332
A44: 46301 | B44: DR#03425 | C44: JYQL | D44: 59 | E44: 24950 | F44: 956532 | G44: 46339
A45: 46301 | B45: DR#85456 | C45: JYQL | D45: 51 | E45: 7700 | F45: 956533 | G45: 46339
A46: 46301 | B46: DR#00441 | C46: JYQL | D46: 58 | E46: 27900 | F46: 956534 | G46: 46346
A47: 46301 | B47: DR#0012 | C47: STAL | D47: 90 | E47: 22750 | F47: 956535 | G47: 46409
A48: 46301 | B48: DR#91555 | C48: JYQL | D48: 63 | E48: 15450 | F48: 956536 | G48: 46353 | H48: cancelled
A49: 46301 | B49: DR#0001 | C49: STAL | D49: 99 | E49: 27550 | F49: 956537 | G49: 46416
A50: 46301 | B50: DR#91555 | C50: JYQL | D50: 63 | E50: 15450 | F50: 956538 | G50: 46353
