Workbook
Name DashboardMonths: [1]Summary!$AE$131:$AE$142
Name DashboardMonths: [1]Summary!$AE$131:$AE$142
Name DashboardMonths: Summary!$AE$131:$AE$142
Name DashboardMonths: #REF!
Name InventoryCodes: [1]!LIST[CODE]
Name InventoryCodes: [1]!LIST[CODE]
Name InventoryCodes: #REF!
Name InventoryCodes: #REF!
Name Phase2_ApprovedAgents: '[1]Workbook Map'!$H$91:$H$103
Name Phase2_ApprovedAgents: '[1]Workbook Map'!$H$91:$H$103
Name Phase2_ApprovedAgents: 'Workbook Map'!$H$91:$H$103
Name Phase2_ClientCategories: '[1]Workbook Map'!$I$91:$I$93
Name Phase2_ClientCategories: '[1]Workbook Map'!$I$91:$I$93
Name Phase2_ClientCategories: 'Workbook Map'!$I$91:$I$93
Name Phase2_ProductCategories: '[1]Workbook Map'!$G$91:$G$94
Name Phase2_ProductCategories: '[1]Workbook Map'!$G$91:$G$94
Name Phase2_ProductCategories: 'Workbook Map'!$G$91:$G$94

Sheet Operating Guide
A1: OPERATING GUIDE — 2026
A2: Quick-start controls and approved entry locations for daily workbook operation
A4: Use only the entry locations listed below. Sales, cost, commission, reporting and dashboard outputs recalculate automatically. Inventory movement formulas are stable, but 364 products still have unsupported negative stock; do not create purchases or adjustments without source evidence or owner approval.
A7: WHERE TO WORK
A8: Workflow | B8: Sheet | C8: Entry point | D8: Required inputs | E8: Automatic results | F8: Primary check | G8: Stop condition | H8: Current state
A9: Enter sales | B9: Daily Sales | C9: sales[Month] to sales[Price] | D9: Month, date, agent, client, item, qty, price | E9: Sales, cost, capital, markup, commission | F9: Audit sales difference | G9: Any nonzero difference | H9: READY
A10: Add products | B10: Inventory | C10: LIST[ITEM] to LIST[UNIT COST] | D10: Description, code, category, unit cost | E10: Price and stock calculations | F10: Duplicate/missing codes | G10: Duplicate code or blank cost | H10: CONTROLLED
A11: Add clients | B11: Client List01 | C11: Table28 | D11: Client name, initials, agent | E11: Sales client lookups | F11: Unknown client / blank agent | G11: Any unresolved client | H11: READY
A12: Enter expenses | B12: Expenses | C12: Monthly expense columns | D12: Category, date, item, amount | E12: Summary expense and profit rows | F12: Summary annual expenses | G12: Unexpected annual change | H12: READY
A13: Enter purchases | B13: Purchase Log | C13: PurchaseLog | D13: ID, date, supplier, invoice, code, qty, cost | E13: Item/category/amount and stock purchased | F13: Validation Status = READY | G13: Duplicate ID or invalid code | H13: READY FOR ENTRY
A14: Review results | B14: INDEX / Audit | C14: KPI dashboard and controls | D14: No manual edits to formulas | E14: 2026 KPIs, charts and control statuses | F14: Audit PASS/FAIL controls | G14: Any FAIL without approval | H14: REVIEW
A16: LIVE CONTROL CHECK — REVIEW BEFORE AND AFTER ENTRY
A17: Control | B17: Current value | C17: Status | D17: Operator response | F17: HANDOVER LIMITATION
A18: Sales difference | B18: =Audit!D17 -> #REF! | C18: =Audit!E17 -> #REF! | D18: Must remain ₱0.00 | F18: Inventory exceptions are fully traced in Stock Exceptions, but remain open because Purchase Log contains no validated historical purchases. Continue normal sales and reporting operations only under the documented override; do not treat current running stock as fully reconciled.
A19: Cost difference | B19: =Audit!D18 -> #REF! | C19: =Audit!E18 -> #REF! | D19: Must remain ₱0.00
A20: Commission difference | B20: =Audit!D19 -> #REF! | C20: =Audit!E19 -> #REF! | D20: Must remain ₱0.00
A21: Movement exceptions | B21: =Audit!B20 -> #REF! | C21: =Audit!E20 -> #REF! | D21: Must remain zero
A22: Negative running stock | B22: =Audit!B24 -> #REF! | C22: =Audit!E24 -> #REF! | D22: Source support required
A23: Missing unit cost | B23: =Audit!B25 -> #REF! | C23: =Audit!E25 -> #REF! | D23: Complete product cost | F23: AFTER EVERY ENTRY BATCH
A24: Sales exceeding stock | B24: =Audit!B26 -> #REF! | C24: =Audit!E26 -> #REF! | D24: Source support required | F24: 1. Recalculate. 2. Confirm sales, cost and commission differences remain zero. 3. Review new validation or stock exceptions. 4. Save a new workbook version. 5. Stop immediately if a financial difference appears.

Sheet Summary
B1: DR SALES SUMMARY | C1: 3 | D1: 46298
B2: Progress | D2: 0.36944833 | F2: 0.46434267 | H2: 0.47125637 | J2: 0.573418 | L2: 0.64928867 | N2: 0.67444333 | P2: 0.570506 | R2: 0.369747 | T2: 0.433837 | V2: 0.023076667 | X2: 0 | Z2: 0 | AB2: Annual target/progress | AD2: BALANCE
B3: Mo. Sales | D3: 554172.5 | F3: 696514 | H3: 706884.55 | J3: 860127 | L3: 973933 | N3: 1011665 | P3: 855759 | R3: 554620.5 | T3: 650755.5 | V3: 34615 | X3: 0 | Z3: 0 | AB3: 6899046 | AC3: 0.38328034 | AD3: -11100954
B4: 46298 | C4: Day | D4: 46023 | F4: 46055 | H4: 46083 | J4: 46114 | L4: 46144 | N4: 46175 | P4: 46205 | R4: 46236 | T4: 46267 | V4: 46297 | X4: 46328 | Z4: 46358
D5: Daily | E5: Cummulative | F5: Daily | G5: Cummulative | H5: Daily | I5: Cummulative | J5: Daily | K5: Cummulative | L5: Daily | M5: Cummulative | N5: Daily | O5: Cummulative | P5: Daily | Q5: Cummulative | R5: Daily | S5: Cummulative | T5: Daily | U5: Cummulative | V5: Daily | W5: Cummulative | X5: Daily | Y5: Cummulative | Z5: Daily | AA5: Cummulative | AB5: 18000000
B6: Target | D6: 75000 | E6: 1500000 | F6: 75000 | G6: 1500000 | H6: 75000 | I6: 1500000 | J6: 75000 | K6: 1500000 | L6: 75000 | M6: 1500000 | N6: 75000 | O6: 1500000 | P6: 75000 | Q6: 1500000 | R6: 75000 | S6: 1500000 | T6: 75000 | U6: 1500000 | V6: 75000 | W6: 1500000 | X6: 75000 | Y6: 1500000 | Z6: 75000 | AA6: 1500000
B7: 45566 | C7: 1 | D7: 0 | E7: 0 | F7: 0 | G7: 0 | H7: 0 | I7: 0 | J7: 51239 | K7: 51239 | L7: 0 | M7: 0 | N7: 56723 | O7: 56723 | P7: 22046 | Q7: 22046 | R7: 23680 | S7: 23680 | T7: 18288 | U7: 18288 | V7: 34615 | W7: 34615 | X7: 0 | Y7: 0 | Z7: 0 | AA7: 0 | AE7: 1500000 | AF7: 75000 | AG7: 27605.129
B8: 45567 | C8: 2 | D8: 18062 | E8: 18062 | F8: 35345 | G8: 35345 | H8: 36375 | I8: 36375 | J8: 0 | K8: 51239 | L8: 31324 | M8: 31324 | N8: 44632 | O8: 101355 | P8: 30014 | Q8: 52060 | R8: 0 | S8: 23680 | T8: 31870 | U8: 50158 | V8: 0 | W8: 34615 | X8: 0 | Y8: 0 | Z8: 0 | AA8: 0 | AE8: 1500000 | AF8: 75000 | AG8: 27605.129
B9: 45568 | C9: 3 | D9: 23348 | E9: 41410 | F9: 27093 | G9: 62438 | H9: 31114 | I9: 67489 | J9: 0 | K9: 51239 | L9: 0 | M9: 31324 | N9: 39515 | O9: 140870 | P9: 38931 | Q9: 90991 | R9: 10568 | S9: 34248 | T9: 31088.5 | U9: 81246.5 | V9: 0 | W9: 34615 | X9: 0 | Y9: 0 | Z9: 0 | AA9: 0 | AC9: CATEGORY | AD9: ADD ON | AE9: 1500000 | AF9: 75000 | AG9: 27605.129
B10: 45569 | C10: 4 | D10: 0 | E10: 41410 | F10: 31455 | G10: 93893 | H10: 57986 | I10: 125475 | J10: 24657 | K10: 75896 | L10: 38209 | M10: 69533 | N10: 24707 | O10: 165577 | P10: 46195 | Q10: 137186 | R10: 30710 | S10: 64958 | T10: 42401 | U10: 123647.5 | V10: 0 | W10: 34615 | X10: 0 | Y10: 0 | Z10: 0 | AA10: 0 | AC10: GENERAL | AD10: 0.05 | AE10: 1500000 | AF10: 75000 | AG10: 27605.129
B11: 45570 | C11: 5 | D11: 27160 | E11: 68570 | F11: 5010 | G11: 98903 | H11: 27506 | I11: 152981 | J11: 0 | K11: 75896 | L11: 21276 | M11: 90809 | N11: 27135 | O11: 192712 | P11: 0 | Q11: 137186 | R11: 10707.5 | S11: 75665.5 | T11: 58371 | U11: 182018.5 | V11: 0 | W11: 34615 | X11: 0 | Y11: 0 | Z11: 0 | AA11: 0 | AC11: TOOLS | AD11: 0.05 | AE11: 1500000 | AF11: 75000 | AG11: 27605.129
B12: 45571 | C12: 6 | D12: 27471 | E12: 96041 | F12: 6300 | G12: 105203 | H12: 37701.55 | I12: 190682.55 | J12: 30785 | K12: 106681 | L12: 40219 | M12: 131028 | N12: 31718 | O12: 224430 | P12: 30413 | Q12: 167599 | R12: 45960 | S12: 121625.5 | T12: 0 | U12: 182018.5 | V12: 0 | W12: 34615 | X12: 0 | Y12: 0 | Z12: 0 | AA12: 0 | AC12: INSTALLATION MATERIALS | AD12: 0.03 | AE12: 1500000 | AF12: 75000 | AG12: 27605.129
B13: 45572 | C13: 7 | D13: 46280 | E13: 142321 | F13: 29488 | G13: 134691 | H13: 48158 | I13: 238840.55 | J13: 69658 | K13: 176339 | L13: 16814 | M13: 147842 | N13: 0 | O13: 224430 | P13: 42315 | Q13: 209914 | R13: 28094 | S13: 149719.5 | T13: 14198 | U13: 196216.5 | V13: 0 | W13: 34615 | X13: 0 | Y13: 0 | Z13: 0 | AA13: 0 | AC13: CAR AIRCON | AD13: 0.05 | AE13: 1500000 | AF13: 75000 | AG13: 27605.129
B14: 45573 | C14: 8 | D14: 8450 | E14: 150771 | F14: 0 | G14: 134691 | H14: 0 | I14: 238840.55 | J14: 23263 | K14: 199602 | L14: 24832 | M14: 172674 | N14: 19084 | O14: 243514 | P14: 32335 | Q14: 242249 | R14: 30986 | S14: 180705.5 | T14: 15763 | U14: 211979.5 | V14: 0 | W14: 34615 | X14: 0 | Y14: 0 | Z14: 0 | AA14: 0 | AE14: 1500000 | AF14: 75000 | AG14: 27605.129
B15: 45574 | C15: 9 | D15: 18931 | E15: 169702 | F15: 17255 | G15: 151946 | H15: 37221 | I15: 276061.55 | J15: 41275 | K15: 240877 | L15: 64342 | M15: 237016 | N15: 45256 | O15: 288770 | P15: 37365 | Q15: 279614 | R15: 0 | S15: 180705.5 | T15: 14255 | U15: 226234.5 | V15: 0 | W15: 34615 | X15: 0 | Y15: 0 | Z15: 0 | AA15: 0 | AE15: 1500000 | AF15: 75000 | AG15: 27605.129
B16: 45575 | C16: 10 | D16: 36175 | E16: 205877 | F16: 39549 | G16: 191495 | H16: 7630 | I16: 283691.55 | J16: 48177 | K16: 289054 | L16: 0 | M16: 237016 | N16: 28085 | O16: 316855 | P16: 38598 | Q16: 318212 | R16: 4600 | S16: 185305.5 | T16: 16450 | U16: 242684.5 | V16: 0 | W16: 34615 | X16: 0 | Y16: 0 | Z16: 0 | AA16: 0 | AE16: 1500000 | AF16: 75000 | AG16: 27605.129
B17: 45576 | C17: 11 | D17: 0 | E17: 205877 | F17: 44230 | G17: 235725 | H17: 17065 | I17: 300756.55 | J17: 28101 | K17: 317155 | L17: 56942 | M17: 293958 | N17: 24278 | O17: 341133 | P17: 36566 | Q17: 354778 | R17: 15898 | S17: 201203.5 | T17: 15380 | U17: 258064.5 | V17: 0 | W17: 34615 | X17: 0 | Y17: 0 | Z17: 0 | AA17: 0 | AE17: 1500000 | AF17: 75000 | AG17: 27605.129
B18: 45577 | C18: 12 | D18: 20225 | E18: 226102 | F18: 14930 | G18: 250655 | H18: 28850 | I18: 329606.55 | J18: 0 | K18: 317155 | L18: 32610 | M18: 326568 | N18: 37523 | O18: 378656 | P18: 0 | Q18: 354778 | R18: 16665 | S18: 217868.5 | T18: 29862 | U18: 287926.5 | V18: 0 | W18: 34615 | X18: 0 | Y18: 0 | Z18: 0 | AA18: 0 | AE18: 1500000 | AF18: 75000 | AG18: 27605.129
B19: 45578 | C19: 13 | D19: 11540 | E19: 237642 | F19: 31030 | G19: 281685 | H19: 40688 | I19: 370294.55 | J19: 15400 | K19: 332555 | L19: 0 | M19: 326568 | N19: 57994 | O19: 436650 | P19: 28229 | Q19: 383007 | R19: 33572 | S19: 251440.5 | T19: 0 | U19: 287926.5 | V19: 0 | W19: 34615 | X19: 0 | Y19: 0 | Z19: 0 | AA19: 0 | AE19: 1500000 | AF19: 75000 | AG19: 27605.129
B20: 45579 | C20: 14 | D20: 28621 | E20: 266263 | F20: 20320 | G20: 302005 | H20: 23767 | I20: 394061.55 | J20: 27855 | K20: 360410 | L20: 23260 | M20: 349828 | N20: 0 | O20: 436650 | P20: 12981 | Q20: 395988 | R20: 3510 | S20: 254950.5 | T20: 14021 | U20: 301947.5 | V20: 0 | W20: 34615 | X20: 0 | Y20: 0 | Z20: 0 | AA20: 0 | AE20: 1500000 | AF20: 75000 | AG20: 27605.129
B21: 45580 | C21: 15 | D21: 13336 | E21: 279599 | F21: 0 | G21: 302005 | H21: 0 | I21: 394061.55 | J21: 121659 | K21: 482069 | L21: 56305 | M21: 406133 | N21: 35586 | O21: 472236 | P21: 36189 | Q21: 432177 | R21: 26827 | S21: 281777.5 | T21: 15895 | U21: 317842.5 | V21: 0 | W21: 34615 | X21: 0 | Y21: 0 | Z21: 0 | AA21: 0 | AE21: 1500000 | AF21: 75000 | AG21: 27605.129
B22: 45581 | C22: 16 | D22: 18185 | E22: 297784 | F22: 27675 | G22: 329680 | H22: 21100 | I22: 415161.55 | J22: 13285 | K22: 495354 | L22: 28127 | M22: 434260 | N22: 33260 | O22: 505496 | P22: 23965 | Q22: 456142 | R22: 200 | S22: 281977.5 | T22: 30340 | U22: 348182.5 | V22: 0 | W22: 34615 | X22: 0 | Y22: 0 | Z22: 0 | AA22: 0 | AE22: 1500000 | AF22: 75000 | AG22: 27605.129
B23: 45582 | C23: 17 | D23: 18420 | E23: 316204 | F23: 21570 | G23: 351250 | H23: 17962 | I23: 433123.55 | J23: 20528 | K23: 515882 | L23: 0 | M23: 434260 | N23: 54565 | O23: 560061 | P23: 41128 | Q23: 497270 | R23: 9290 | S23: 291267.5 | T23: 11545 | U23: 359727.5 | V23: 0 | W23: 34615 | X23: 0 | Y23: 0 | Z23: 0 | AA23: 0 | AE23: 1500000 | AF23: 75000 | AG23: 27605.129
B24: 45583 | C24: 18 | D24: 0 | E24: 316204 | F24: 20232 | G24: 371482 | H24: 21290 | I24: 454413.55 | J24: 21273 | K24: 537155 | L24: 44081 | M24: 478341 | N24: 54396 | O24: 614457 | P24: 21621 | Q24: 518891 | R24: 19816 | S24: 311083.5 | T24: 4777 | U24: 364504.5 | V24: 0 | W24: 34615 | X24: 0 | Y24: 0 | Z24: 0 | AA24: 0 | AE24: 1500000 | AF24: 75000 | AG24: 27605.129
B25: 45584 | C25: 19 | D25: 9625 | E25: 325829 | F25: 27060 | G25: 398542 | H25: 29104 | I25: 483517.55 | J25: 350 | K25: 537505 | L25: 24697 | M25: 503038 | N25: 31954 | O25: 646411 | P25: 500 | Q25: 519391 | R25: 7970 | S25: 319053.5 | T25: 24774 | U25: 389278.5 | V25: 0 | W25: 34615 | X25: 0 | Y25: 0 | Z25: 0 | AA25: 0 | AE25: 1500000 | AF25: 75000 | AG25: 27605.129
... B37: 45596 | C37: 31 | D37: 17220 | E37: 554172.5 | F37: 0 | G37: 696514 | H37: 13120 | I37: 706884.55 | J37: 0 | K37: 860127 | L37: 0 | M37: 973933 | N37: 0 | O37: 1011665 | P37: 20960 | Q37: 855759 | R37: 18005 | S37: 554620.5 | T37: 0 | U37: 650755.5 | V37: 0 | W37: 34615 | X37: 0 | Y37: 0 | Z37: 0 | AA37: 0 | AE37: 1500000 | AF37: 75000 | AG37: 27605.129
B38: 0.03
B39: MONTH | C39: ANNUAL | D39: 1 | F39: 2 | H39: 3 | J39: 4 | L39: 5 | N39: 6 | P39: 7 | R39: 8 | T39: 9 | V39: 10 | X39: 46328 | Z39: 46358
B40: [1]T-SALES | C40: 6899046 | D40: 554172.5 | F40: 696514 | H40: 706884.55 | J40: 860127 | L40: 973933 | N40: 1011665 | P40: 855759 | R40: 554620.5 | T40: 650755.5 | V40: 34615 | X40: 0 | Z40: 0
B41: [2]T-CAPITAL | C41: 4343170 | D41: 372521.97 | F41: 519477.67 | H41: 490787.68 | J41: 477023.89 | L41: 423396.4 | N41: 564360.89 | P41: 619192.51 | R41: 398804.1 | T41: 451575.4 | V41: 26029.49 | X41: 0 | Z41: 0
B42: [3]T-COST | C42: 4151287.6 | D42: 355356.11 | F42: 496195.63 | H42: 468391.97 | J42: 455238.36 | L42: 405464.07 | N42: 540599.88 | P42: 591909.29 | R42: 381300.7 | T42: 431631.04 | V42: 25200.6 | X42: 0 | Z42: 0
B43: [4]T-AGENT | C43: 266326.26 | D43: 21344.085 | F43: 19634.272 | H43: 18376.849 | J43: 39320.199 | L43: 54781.184 | N43: 47228.378 | P43: 26748.582 | R43: 18690.388 | T43: 20009.425 | V43: 192.9 | X43: 0 | Z43: 0
B44: [5-1]T-MANAGER (1.0%) | C44: 68990.46 | D44: 5541.725 | F44: 6965.14 | H44: 7068.8455 | J44: 8601.27 | L44: 9739.33 | N44: 10116.65 | P44: 8557.59 | R44: 5546.205 | T44: 6507.555 | V44: 346.15 | X44: 0 | Z44: 0
B45: [5-2]STORE MANAGER (0.5%) | C45: 34495.23 | D45: 2770.8625 | F45: 3482.57 | H45: 3534.4228 | J45: 4300.635 | L45: 4869.665 | N45: 5058.325 | P45: 4278.795 | R45: 2773.1025 | T45: 3253.7775 | V45: 173.075 | X45: 0 | Z45: 0
B46: [5-3]ISHABELLA SALES (1%) | C46: 8831.47 | D46: 1109.45 | F46: 863.98 | H46: 895.87 | J46: 1100.16 | L46: 1277.01 | N46: 774.44 | P46: 1127.2 | R46: 758.43 | T46: 914.93 | V46: 10 | X46: 0 | Z46: 0
B47: [5-4]OWNER'S ALLOWANCE | C47: 85405.051 | D47: 8312.5875 | F47: 10447.71 | H47: 10603.268 | J47: 12901.905 | L47: 14608.995 | N47: 15174.975 | P47: 12836.385 | R47: 0 | T47: 0 | V47: 519.225 | X47: 0 | Z47: 0
B48: [7-1]T-EXPENSES | C48: 1381162.7 | D48: 141564 | F48: 168083.6 | H48: 149703.3 | J48: 160227.3 | L48: 150531.3 | N48: 157646.3 | P48: 152727.33 | R48: 142974.3 | T48: 157705.3 | V48: 0 | X48: 0 | Z48: 0
B49: [8] GROSS INCOME [1]-[2]-[4] | C49: 2289549.8 | D49: 160306.44 | F49: 157402.06 | H49: 197720.02 | J49: 343782.91 | L49: 495755.42 | N49: 400075.73 | P49: 209817.9 | R49: 137126.01 | T49: 179170.68 | V49: 8392.61 | X49: 0 | Z49: 0 | AC49: CAPITAL = | AD49: COST x 105%
B50: [9]NET INCOME | C50: 804901.37 | D50: 10429.856 | F50: -21129.249 | H50: 37413.455 | J50: 170653.7 | L50: 330615.12 | N50: 227254.46 | P50: 44254.189 | R50: -14167.595 | T50: 11704.045 | V50: 7873.385 | X50: 0 | Z50: 0 | AC50: - MANAGER INCT. = | AD50: 1% x 2
B51: [10] ADD ON CAPITAL [2]-[3] | C51: 106477.3 | D51: 8853.2738 | F51: 12834.327 | H51: 11792.439 | J51: 8883.6286 | L51: 3323.3341 | N51: 8586.0334 | P51: 14446.839 | R51: 17503.4 | T51: 19944.358 | V51: 309.665 | X51: 0 | Z51: 0
B52: [11]OVERALL | C52: 911378.67 | D52: 19283.13 | F52: -8294.9225 | H52: 49205.894 | J52: 179537.33 | L52: 333938.46 | N52: 235840.49 | P52: 58701.028 | R52: 3335.805 | T52: 31648.403 | V52: 8183.05 | X52: 0 | Z52: 0 | AC52: - TAX = | AD52: 1%
AD53: - ADD ON CAPITAL = | AE53: 2%
B54: [12] GROSS INCOME/SALES [8]/[1] | C54: 0.39828092 | D54: 0.35876264 | F54: 0.28760135 | H54: 0.33738548 | J54: 0.47073123 | L54: 0.58368382 | N54: 0.46563351 | P54: 0.30832245 | R54: 0.31250161 | T54: 0.33672318 | V54: 0.27197458 | X54: 0.27197458 | Z54: 0.27197458 | AD54: - TOTAL ADD ON = | AE54: 5%
B55: [13] BREAK-EVEN SALES [7]/[12] | C55: 3467810.4 | D55: 394589.58 | F55: 584432.57 | H55: 443715.9 | J55: 340379.58 | L55: 257898.7 | N55: 338563.05 | P55: 495349.37 | R55: 488724.94 | T55: 453569.4 | V55: 561550.02 | X55: 561550.02 | Z55: 561550.02
B56: [14] SALES VARIANCE [1]-[13] | C56: 4417172.9 | D56: 159582.92 | F56: 112081.43 | H56: 263168.65 | J56: 519747.42 | L56: 716034.3 | N56: 673101.95 | P56: 360409.63 | R56: 65895.564 | T56: 197186.1 | V56: -526935.02 | X56: 938449.98 | Z56: 938449.98 | AD56: GROSS INCOME = | AE56: TOTAL SALES - CAPITAL - AGENT COMM.
B58: [18] BOTTOMLINE | C58: 911378.67 | D58: 19283.13 | F58: -8294.9225 | H58: 49205.894 | J58: 179537.33 | L58: 333938.46 | N58: 235840.49 | P58: 58701.028 | R58: 3335.805 | T58: 31648.403 | V58: 8183.05 | X58: 0 | Z58: 0
AB59: …................................
B65: SELECTED MONTH | C65: 46266
B66: Month No. | C66: 9
B67: Method | C67: (All)
B68: Date | C68: (All)
B69: AGENT'S SELECTED-MONTH PERFORMANCE
B70: AGENT | C70: T-Sales | D70: T-Agent Comm.
B71: Bro. Rhoge | C71: 20058 | D71: 1433.76
B72: Bro. Jovy | C72: 0 | D72: 0
B73: Bro. Manuel | C73: 7700 | D73: 782.25
B74: Bro. Mel | C74: 0 | D74: 0
B75: Bro. Rocky | C75: 0 | D75: 0
B76: Ptr. Rod | C76: 91493 | D76: 7605.3
B77: Sis. Jackie | C77: 15694 | D77: 1384.95
B78: Sis. Mhai | C78: 0 | D78: 0
B79: Bro. Jr | C79: 0 | D79: 0
B80: Sis. Lorie | C80: 0 | D80: 0
B81: Bro. Vin | C81: 22070 | D81: 919.83
B82: Bro. Roxie | C82: 10451 | D82: 1130.745
... B86: Grand Total | C86: 576356.5 | D86: 13256.835
B88: 0.5
B89: 46266 | C89: Total Sales | D89: 46023 | E89: 46055 | F89: 46083 | G89: 46114 | H89: 46144 | I89: 46175 | J89: 46205 | K89: 46236 | L89: 46267 | M89: 46297 | N89: 46328 | O89: 46358 | Q89: Cummulative
C90: September 01 - September 30 | D90: 46055 | E90: 46083 | F90: 46114 | G90: 46144 | H90: 46175 | I90: 46205 | J90: 46236 | K90: 46267 | L90: 46297 | M90: 45598 | N90: 46358 | O90: 0 | Q90: Total
B91: Bro. Rhoge | C91: 20058 | D91: 0 | E91: 70.65 | F91: 0 | G91: 1433.76 | H91: 1433.76 | I91: 1433.76 | J91: 1433.76 | K91: 1433.76 | L91: 1433.76 | M91: 1433.76 | N91: 1433.76 | O91: 1433.76 | Q91: 1433.76
B92: Bro. Jovy | C92: 0 | D92: 0 | E92: 0 | F92: 0 | G92: 0 | H92: 0 | I92: 0 | J92: 0 | K92: 0 | L92: 0 | M92: 0 | N92: 0 | O92: 0 | Q92: 0
B93: Bro. Manuel | C93: 7700 | D93: 162 | E93: 162 | F93: 248.25 | G93: 782.25 | H93: 782.25 | I93: 782.25 | J93: 782.25 | K93: 782.25 | L93: 782.25 | M93: 782.25 | N93: 782.25 | O93: 782.25 | Q93: 782.25
B94: Bro. Mel | C94: 0 | D94: 141.435 | E94: 141.435 | F94: 370.35 | G94: 0 | H94: 0 | I94: 0 | J94: 0 | K94: 0 | L94: 0 | M94: 0 | N94: 0 | O94: 0 | Q94: 0
B95: Bro. Rocky | C95: 0 | D95: 0 | E95: 0 | F95: 0 | G95: 0 | H95: 0 | I95: 0 | J95: 0 | K95: 0 | L95: 0 | M95: 0 | N95: 0 | O95: 0 | Q95: 0
B96: Ptr. Rod | C96: 91493 | D96: 11289.45 | E96: 11462.7 | F96: 8009.595 | G96: 7605.3 | H96: 7605.3 | I96: 7605.3 | J96: 7605.3 | K96: 7605.3 | L96: 7605.3 | M96: 7605.3 | N96: 7605.3 | O96: 7605.3 | Q96: 7605.3
B97: Sis. Jackie | C97: 15694 | D97: 1315.35 | E97: 1315.35 | F97: 2171.925 | G97: 1384.95 | H97: 1384.95 | I97: 1384.95 | J97: 1384.95 | K97: 1384.95 | L97: 1384.95 | M97: 1384.95 | N97: 1384.95 | O97: 1384.95 | Q97: 1384.95
B98: Sis. Mhai | C98: 0 | D98: 0 | E98: 0 | F98: 0 | G98: 0 | H98: 0 | I98: 0 | J98: 0 | K98: 0 | L98: 0 | M98: 0 | N98: 0 | O98: 0 | Q98: 0
B99: Bro. Jr | C99: 0 | D99: 1503 | E99: 1503 | F99: 0 | G99: 0 | H99: 0 | I99: 0 | J99: 0 | K99: 0 | L99: 0 | M99: 0 | N99: 0 | O99: 0 | Q99: 0
B100: Sis. Lorie | C100: 0 | D100: 0 | E100: 0 | F100: 0 | G100: 0 | H100: 0 | I100: 0 | J100: 0 | K100: 0 | L100: 0 | M100: 0 | N100: 0 | O100: 0 | Q100: 0
B101: Bro. Vin | C101: 22070 | D101: 4715.28 | E101: 4715.28 | F101: 4527.765 | G101: 919.83 | H101: 919.83 | I101: 919.83 | J101: 919.83 | K101: 919.83 | L101: 919.83 | M101: 919.83 | N101: 919.83 | O101: 919.83 | Q101: 919.83
B102: Bro. Roxie | C102: 10451 | D102: 1813.875 | E102: 1813.875 | F102: 2855.925 | G102: 1130.745 | H102: 1130.745 | I102: 1130.745 | J102: 1130.745 | K102: 1130.745 | L102: 1130.745 | M102: 1130.745 | N102: 1130.745 | O102: 1130.745 | Q102: 1130.745
... B105: Store | C105: 408890.5 | D105: 0 | E105: 0 | F105: 0 | G105: 0 | H105: 0 | I105: 0 | J105: 0 | K105: 0 | L105: 0 | M105: 0 | N105: 0 | O105: 0 | Q105: 0
B106: Total | C106: 576356.5 | D106: 20940.39 | E106: 21184.29 | F106: 18183.81 | G106: 13256.835 | H106: 13256.835 | I106: 13256.835 | J106: 13256.835 | K106: 13256.835 | L106: 13256.835 | M106: 13256.835 | N106: 13256.835 | O106: 13256.835 | P106: 0 | Q106: 13256.835
C110: Expenses | D110: 46023 | E110: 46055 | F110: 46083 | G110: 46114 | H110: 46144 | I110: 46175 | J110: 46205 | K110: 46236 | L110: 46267 | M110: 46297 | N110: 46328 | O110: 46358
D111: 0 | E111: 0 | F111: 0 | G111: 0 | H111: 0 | I111: 0 | J111: 0 | K111: 0 | L111: 0 | M111: 0 | N111: 0 | O111: 0
B112: Bro. Rhoge
B113: Bro. Jovy
B114: Bro. Manuel
B115: Bro. Mel
B116: Bro. Rocky
B117: Ptr. Rod
B118: Sis. Jackie
B119: Sis. Mhai
B120: Bro. Jr
B121: Sis. Lorie
B122: Bro. Daniel
B123: Bro. Vin
... B129: Bro. Jay
B130: Store | AE130: Month | AF130: Break-even | AG130: Expenses | AH130: Net Income | AI130: Target Sales | AJ130: Monthly Sales
AE131: 46023 | AF131: 394589.58 | AG131: 141564 | AH131: 10429.856 | AI131: 1500000 | AJ131: 554172.5
...

Sheet Sales Record
A1: DR SALES RECORD — 2026
A2: One consolidated record per delivery receipt, grouped by transaction date and client
A4: TOTAL DR | B4: 2153 | C4: TOTAL SALES | D4: 6899046 | E4: TOTAL COST | F4: 4151287.7 | G4: GROSS PROFIT | H4: 2747758.4 | I4: AGENT COMM. | J4: 266326.26 | K4: AVG. DR SALE | L4: 3204.3874
A6: DR Number | B6: Date | C6: Agent | D6: Client | E6: Line Items | F6: Total Qty | G6: Delivery | H6: Sales | I6: Total Cost | J6: Capital | K6: Markup | L6: Agent Commission | M6: Gross Profit | N6: Gross Margin
A7: 0102-01 | B7: 46024 | C7: Store | D7: DODOY | E7: 1 | F7: 1 | G7: 0 | H7: 1800 | I7: 1150 | J7: 1207.5 | K7: 592.5 | L7: 0 | M7: 650 | N7: 0.36111111
A8: 0102-02 | B8: 46024 | C8: Store | D8: EDWARD NAILGAS | E8: 5 | F8: 55 | G8: 0 | H8: 1667 | I8: 865.6 | J8: 896.018 | K8: 770.982 | L8: 0 | M8: 801.4 | N8: 0.48074385
A9: 0102-03 | B9: 46024 | C9: Ptr. Rod | D9: GIE | E9: 1 | F9: 1 | G9: 0 | H9: 1625 | I9: 800 | J9: 840 | K9: 785 | L9: 235.5 | M9: 825 | N9: 0.50769231
A10: 0102-04 | B10: 46024 | C10: Store | D10: JAY STA ROSA | E10: 1 | F10: 1 | G10: 0 | H10: 7800 | I10: 6732 | J10: 7068.6 | K10: 731.4 | L10: 0 | M10: 1068 | N10: 0.13692308
A11: 0102-05 | B11: 46024 | C11: Store | D11: JHUN M / MC MC | E11: 1 | F11: 1 | G11: 0 | H11: 300 | I11: 100 | J11: 105 | K11: 195 | L11: 0 | M11: 200 | N11: 0.66666667
A12: 0102-06 | B12: 46024 | C12: Store | D12: RHAYMAR CARBUNGCO | E12: 1 | F12: 1 | G12: 0 | H12: 2100 | I12: 1100 | J12: 1155 | K12: 945 | L12: 0 | M12: 1000 | N12: 0.47619048
A13: 0102-07 | B13: 46024 | C13: Bro. Vin | D13: SPTC | E13: 1 | F13: 2 | G13: 0 | H13: 900 | I13: 360 | J13: 378 | K13: 522 | L13: 156.6 | M13: 540 | N13: 0.6
A14: 0102-08 | B14: 46024 | C14: Store | D14: WALK IN | E14: 2 | F14: 2 | G14: 0 | H14: 1870 | I14: 990 | J14: 1039.5 | K14: 830.5 | L14: 0 | M14: 880 | N14: 0.47058824
A15: 0103-01 | B15: 46025 | D15: AirCooled / Yohanan Saul | E15: 2 | F15: 2 | G15: 0 | H15: 175 | I15: 105 | J15: 108.75 | K15: 66.25 | L15: 19.875 | M15: 70 | N15: 0.4
A16: 0103-02 | B16: 46025 | C16: Bro. Rhoge | D16: BERNABE DE VERA CONSTRUCTION | E16: 1 | F16: 30 | G16: 0 | H16: 1338 | I16: 1050 | J16: 1102.5 | K16: 235.5 | L16: 70.65 | M16: 288 | N16: 0.21524664
A17: 0103-03 | B17: 46025 | D17: BIB / BOB | E17: 2 | F17: 3 | G17: 0 | H17: 860 | I17: 452 | J17: 474.6 | K17: 385.4 | L17: 115.62 | M17: 408 | N17: 0.4744186
A18: 0103-04 | B18: 46025 | C18: Ptr. Rod | D18: EDLAN | E18: 2 | F18: 2 | G18: 0 | H18: 3975 | I18: 2550 | J18: 2677.5 | K18: 1297.5 | L18: 389.25 | M18: 1425 | N18: 0.35849057
A19: 0103-05 | B19: 46025 | C19: Store | D19: EDWARD NAILGAS | E19: 4 | F19: 5.8 | G19: 0 | H19: 3410 | I19: 1488.6 | J19: 1533.258 | K19: 1876.742 | L19: 0 | M19: 1921.4 | N19: 0.56346041
A20: 0103-06 | B20: 46025 | C20: Ptr. Rod | D20: GIE | E20: 16 | F20: 22 | G20: 0 | H20: 8205 | I20: 5005 | J20: 5248.65 | K20: 2956.35 | L20: 886.905 | M20: 3200 | N20: 0.39000609
A21: 0103-07 | B21: 46025 | C21: Store | D21: JOVI TECH | E21: 5 | F21: 11 | G21: 0 | H21: 855 | I21: 515 | J21: 534.23 | K21: 320.77 | L21: 0 | M21: 340 | N21: 0.39766082
A22: 0103-08 | B22: 46025 | C22: Store | D22: LAGUNA AIR BINAN | E22: 1 | F22: 1 | G22: 0 | H22: 2100 | I22: 1075 | J22: 1128.75 | K22: 971.25 | L22: 0 | M22: 1025 | N22: 0.48809524
A23: 0103-09 | B23: 46025 | C23: Bro. Mel | D23: ROSIPITO | E23: 2 | F23: 12 | G23: 0 | H23: 1050 | I23: 551 | J23: 578.55 | K23: 471.45 | L23: 141.435 | M23: 499 | N23: 0.4752381
A24: 0103-10 | B24: 46025 | C24: Store | D24: WALK IN | E24: 3 | F24: 3 | G24: 0 | H24: 1380 | I24: 410 | J24: 430.5 | K24: 949.5 | L24: 0 | M24: 970 | N24: 0.70289855
A25: 0105-01 | B25: 46027 | C25: Store | D25: CEMTRANS | E25: 1 | F25: 2 | G25: 0 | H25: 900 | I25: 360 | J25: 378 | K25: 522 | L25: 0 | M25: 540 | N25: 0.6
A26: 0105-02 | B26: 46027 | C26: Ptr. Rod | D26: CRISJAP | E26: 2 | F26: 2 | G26: 0 | H26: 2475 | I26: 1210 | J26: 1270.5 | K26: 1204.5 | L26: 361.35 | M26: 1265 | N26: 0.51111111
A27: 0105-03 | B27: 46027 | C27: Store | D27: DODOY | E27: 7 | F27: 67 | G27: 0 | H27: 4940 | I27: 2482 | J27: 2606.1 | K27: 2333.9 | L27: 0 | M27: 2458 | N27: 0.49757085
A28: 0105-04 | B28: 46027 | C28: Sis. Jackie | D28: DXB KING JEFF | E28: 1 | F28: 1 | G28: 0 | H28: 2300 | I28: 1500 | J28: 1575 | K28: 725 | L28: 217.5 | M28: 800 | N28: 0.34782609
A29: 0105-05 | B29: 46027 | C29: Ptr. Rod | D29: GIE | E29: 1 | F29: 1 | G29: 0 | H29: 1700 | I29: 1200 | J29: 1260 | K29: 440 | L29: 132 | M29: 500 | N29: 0.29411765
... A33: 0105-09 | B33: 46027 | C33: Store | D33: WALK IN | E33: 1 | F33: 1 | G33: 0 | H33: 585 | I33: 480 | J33: 504 | K33: 81 | L33: 0 | M33: 105 | N33: 0.17948718
A34: 0106-01 | B34: 46028 | D34: BIB / BOB | E34: 2 | F34: 2 | G34: 0 | H34: 3400 | I34: 2250 | J34: 2362.5 | K34: 1037.5 | L34: 311.25 | M34: 1150 | N34: 0.33823529
A35: 0106-02 | B35: 46028 | C35: Store | D35: CJ PANTHER/SEVILLA | E35: 2 | F35: 4 | G35: 0 | H35: 2055 | I35: 1565 | J35: 1643.25 | K35: 411.75 | L35: 0 | M35: 490 | N35: 0.23844282
A36: 0106-03 | B36: 46028 | C36: Store | D36: DEMY | E36: 1 | F36: 1 | G36: 0 | H36: 2000 | I36: 1100 | J36: 1155 | K36: 845 | L36: 0 | M36: 900 | N36: 0.45
A37: 0106-04 | B37: 46028 | C37: Sis. Jackie | D37: DXB KING JEFF | E37: 1 | F37: 1 | G37: 0 | H37: 2000 | I37: 1300 | J37: 1365 | K37: 635 | L37: 190.5 | M37: 700 | N37: 0.35
A38: 0106-05 | B38: 46028 | C38: Bro. Roxie | D38: ENTENG CAR AIRCON | E38: 2 | F38: 2 | G38: 0 | H38: 3800 | I38: 2200 | J38: 2310 | K38: 1490 | L38: 447 | M38: 1600 | N38: 0.42105263
A39: 0106-06 | B39: 46028 | C39: Store | D39: LAGUNA AIR PACITA | E39: 2 | F39: 2 | G39: 0 | H39: 9700 | I39: 7632 | J39: 8013.6 | K39: 1686.4 | L39: 0 | M39: 2068 | N39: 0.21319588
A40: 0106-07 | B40: 46028 | C40: Store | D40: WALK IN | E40: 14 | F40: 48.8 | G40: 0 | H40: 4516 | I40: 2825.8 | J40: 2941.214 | K40: 1574.786 | L40: 0 | M40: 1690.2 | N40: 0.37426926
A41: 0107-01 | B41: 46029 | C41: Ptr. Rod | D41: CRISJAP | E41: 2 | F41: 2 | G41: 0 | H41: 9900 | I41: 8132 | J41: 8538.6 | K41: 1361.4 | L41: 408.42 | M41: 1768 | N41: 0.17858586
A42: 0107-02 | B42: 46029 | C42: Store | D42: DODOY | E42: 2 | F42: 3 | G42: 0 | H42: 17700 | I42: 14964 | J42: 15712.2 | K42: 1987.8 | L42: 0 | M42: 2736 | N42: 0.15457627
A43: 0107-03 | B43: 46029 | D43: HELBERT ARIETE / MHM AUTOSHOP | E43: 2 | F43: 2 | G43: 0 | H43: 2230 | I43: 1230 | J43: 1291.5 | K43: 938.5 | L43: 281.55 | M43: 1000 | N43: 0.44843049
A44: 0107-04 | B44: 46029 | C44: Store | D44: JHUN M / MC MC | E44: 5 | F44: 5 | G44: 0 | H44: 5390 | I44: 3200 | J44: 3360 | K44: 2030 | L44: 0 | M44: 2190 | N44: 0.40630798
A45: 0107-05 | B45: 46029 | C45: Store | D45: LAGUNA AIR PACITA | E45: 1 | F45: 1 | G45: 0 | H45: 2000 | I45: 1400 | J45: 1470 | K45: 530 | L45: 0 | M45: 600 | N45: 0.3
A46: 0107-06 | B46: 46029 | C46: Store | D46: OGIE LORICA | E46: 11 | F46: 34 | G46: 0 | H46: 5930 | I46: 1059.15 | J46: 1093.5445 | K46: 4836.4555 | L46: 0 | M46: 4870.85 | N46: 0.82139123
A47: 0107-07 | B47: 46029 | C47: Store | D47: WALK IN | E47: 5 | F47: 7 | G47: 0 | H47: 3130 | I47: 2165 | J47: 2268.55 | K47: 861.45 | L47: 0 | M47: 965 | N47: 0.30830671
A48: 0108-01 | B48: 46030 | D48: BIB / BOB | E48: 1 | F48: 1 | G48: 0 | H48: 2100 | I48: 1100 | J48: 1155 | K48: 945 | L48: 283.5 | M48: 1000 | N48: 0.47619048
A49: 0108-02 | B49: 46030 | C49: Ptr. Rod | D49: EDLAN | E49: 1 | F49: 1 | G49: 0 | H49: 1780 | I49: 1380 | J49: 1449 | K49: 331 | L49: 99.3 | M49: 400 | N49: 0.2247191
A50: 0108-03 | B50: 46030 | C50: Store | D50: JEFFREY DALIT | E50: 3 | F50: 6 | G50: 0 | H50: 540 | I50: 354 | J50: 365.18 | K50: 174.82 | L50: 0 | M50: 186 | N50: 0.34444444
A51: 0108-04 | B51: 46030 | C51: Store | D51: JMT AUTO PARTS | E51: 1 | F51: 1 | G51: 0 | H51: 2000 | I51: 780 | J51: 819 | K51: 1181 | L51: 0 | M51: 1220 | N51: 0.61
A52: 0108-05 | B52: 46030 | C52: Bro. Manuel | D52: LOTZKI CAR AIRCON/GRSV | E52: 1 | F52: 1 | G52: 0 | H52: 1800 | I52: 1200 | J52: 1260 | K52: 540 | L52: 162 | M52: 600 | N52: 0.33333333
A53: 0108-06 | B53: 46030 | C53: Store | D53: WALK IN | E53: 2 | F53: 2 | G53: 0 | H53: 230 | I53: 91 | J53: 95.55 | K53: 134.45 | L53: 0 | M53: 139 | N53: 0.60434783
A54: 0109-01 | B54: 46031 | C54: Store | D54: DODOY | E54: 6 | F54: 6 | G54: 0 | H54: 7650 | I54: 3720 | J54: 3906 | K54: 3744 | L54: 0 | M54: 3930 | N54: 0.51372549
A55: 0109-02 | B55: 46031 | C55: Ptr. Rod | D55: EDLAN | E55: 2 | F55: 2 | G55: 0 | H55: 3675 | I55: 2250 | J55: 2362.5 | K55: 1312.5 | L55: 393.75 | M55: 1425 | N55: 0.3877551
A56: 0109-03 | B56: 46031 | C56: Ptr. Rod | D56: GIE | E56: 3 | F56: 46 | G56: 0 | H56: 1600 | I56: 746 | J56: 783.3 | K56: 816.7 | L56: 245.01 | M56: 854 | N56: 0.53375
A57: 0109-04 | B57: 46031 | C57: Store | D57: WALK IN | E57: 10 | F57: 37.8 | G57: 0 | H57: 6006 | I57: 2979.2 | J57: 3089.6 | K57: 2916.4 | L57: 0 | M57: 3026.8 | N57: 0.5039627
A58: 0110-01 | B58: 46032 | D58: BIB / BOB | E58: 2 | F58: 2 | G58: 0 | H58: 2350 | I58: 1385 | J58: 1454.25 | K58: 895.75 | L58: 268.725 | M58: 965 | N58: 0.4106383
A59: 0110-02 | B59: 46032 | C59: Store | D59: CHROME EDGE | E59: 3 | F59: 3 | G59: 0 | H59: 10115 | I59: 8302 | J59: 8717.1 | K59: 1397.9 | L59: 0 | M59: 1813 | N59: 0.17923875
A60: 0110-03 | B60: 46032 | C60: Ptr. Rod | D60: CRISJAP | E60: 2 | F60: 2 | G60: 0 | H60: 990 | I60: 500 | J60: 525 | K60: 465 | L60: 139.5 | M60: 490 | N60: 0.49494949
A61: 0110-04 | B61: 46032 | C61: Store | D61: EUGENE | E61: 1 | F61: 1 | G61: 0 | H61: 450 | I61: 180 | J61: 189 | K61: 261 | L61: 0 | M61: 270 | N61: 0.6
A62: 0110-05 | B62: 46032 | C62: Ptr. Rod | D62: GIE | E62: 5 | F62: 9 | G62: 0 | H62: 3805 | I62: 2120 | J62: 2226 | K62: 1579 | L62: 473.7 | M62: 1685 | N62: 0.44283837
A63: 0110-06 | B63: 46032 | C63: Store | D63: JHUN M / MC MC | E63: 4 | F63: 4 | G63: 0 | H63: 2650 | I63: 1410 | J63: 1480.5 | K63: 1169.5 | L63: 0 | M63: 1240 | N63: 0.46792453
A64: 0110-07 | B64: 46032 | C64: Store | D64: LAGUNA AIR PACITA | E64: 1 | F64: 1 | G64: 0 | H64: 2100 | I64: 1100 | J64: 1155 | K64: 945 | L64: 0 | M64: 1000 | N64: 0.47619048
A65: 0110-08 | B65: 46032 | C65: Store | D65: OGIE LORICA | E65: 4 | F65: 4.8 | G65: 0 | H65: 2490 | I65: 247.8 | J65: 255.234 | K65: 2234.766 | L65: 0 | M65: 2242.2 | N65: 0.90048193
A66: 0110-09 | B66: 46032 | C66: Store | D66: PHILVENT | E66: 1 | F66: 20 | G66: 0 | H66: 500 | I66: 380 | J66: 391.4 | K66: 108.6 | L66: 0 | M66: 120 | N66: 0.24
A67: 0110-10 | B67: 46032 | C67: Store | D67: RHAYMAR CARBUNGCO | E67: 2 | F67: 2 | G67: 0 | H67: 1100 | I67: 420 | J67: 441 | K67: 659 | L67: 0 | M67: 680 | N67: 0.61818182
A68: 0110-11 | B68: 46032 | C68: Bro. Vin | D68: SPTC | E68: 2 | F68: 2 | G68: 0 | H68: 8250 | I68: 6912 | J68: 7257.6 | K68: 992.4 | L68: 297.72 | M68: 1338 | N68: 0.16218182
A69: 0110-12 | B69: 46032 | C69: Store | D69: WALK IN | E69: 5 | F69: 5.4 | G69: 0 | H69: 1375 | I69: 212.7 | J69: 219.081 | K69: 1155.919 | L69: 0 | M69: 1162.3 | N69: 0.84530909
A70: 0112-01 | B70: 46034 | D70: BIB / BOB | E70: 2 | F70: 2 | G70: 0 | H70: 9800 | I70: 7582 | J70: 7961.1 | K70: 1838.9 | L70: 551.67 | M70: 2218 | N70: 0.22632653
A71: 0112-02 | B71: 46034 | C71: Store | D71: JHUN M / MC MC | E71: 1 | F71: 1 | G71: 0 | H71: 2000 | I71: 1350 | J71: 1417.5 | K71: 582.5 | L71: 0 | M71: 650 | N71: 0.325
A72: 0112-03 | B72: 46034 | C72: Store | D72: SOUTHBOYZ AUTOCARE | E72: 3 | F72: 4 | G72: 0 | H72: 970 | I72: 460 | J72: 483 | K72: 487 | L72: 0 | M72: 510 | N72: 0.5257732
A73: 0112-04 | B73: 46034 | C73: Store | D73: WALK IN | E73: 12 | F73: 51 | G73: 0 | H73: 7455 | I73: 4476.02 | J73: 4636.6646 | K73: 2818.3354 | L73: 0 | M73: 2978.98 | N73: 0.3995949
A74: 0113-01 | B74: 46035 | C74: Ptr. Rod | D74: EDLAN | E74: 5 | F74: 61 | G74: 0 | H74: 4300 | I74: 2260 | J74: 2373 | K74: 1927 | L74: 578.1 | M74: 2040 | N74: 0.4744186
A75: 0113-02 | B75: 46035 | C75: Bro. Roxie | D75: ENTENG CAR AIRCON | E75: 3 | F75: 4 | G75: 0 | H75: 2655 | I75: 1550 | J75: 1627.5 | K75: 1027.5 | L75: 308.25 | M75: 1105 | N75: 0.41619586
A76: 0113-03 | B76: 46035 | C76: Ptr. Rod | D76: GIE | E76: 1 | F76: 1 | G76: 0 | H76: 1800 | I76: 1000 | J76: 1050 | K76: 750 | L76: 225 | M76: 800 | N76: 0.44444444
A77: 0113-04 | B77: 46035 | C77: Store | D77: MANTECH / KULOT | E77: 1 | F77: 1 | G77: 0 | H77: 2200 | I77: 1450 | J77: 1522.5 | K77: 677.5 | L77: 0 | M77: 750 | N77: 0.34090909
A78: 0113-05 | B78: 46035 | C78: Store | D78: WALK IN | E78: 1 | F78: 1 | G78: 0 | H78: 585 | I78: 480 | J78: 504 | K78: 81 | L78: 0 | M78: 105 | N78: 0.17948718
A79: 0114-01 | B79: 46036 | C79: Store | D79: AXM RESTOWORKZ | E79: 1 | F79: 1 | G79: 0 | H79: 900 | I79: 350 | J79: 367.5 | K79: 532.5 | L79: 0 | M79: 550 | N79: 0.61111111
A80: 0114-02 | B80: 46036 | D80: BIB / BOB | E80: 3 | F80: 3 | G80: 0 | H80: 4550 | I80: 1940 | J80: 2037 | K80: 2513 | L80: 753.9 | M80: 2610 | N80: 0.57362637
A81: 0114-03 | B81: 46036 | D81: COOL TIME / JM DIAMAT | E81: 3 | F81: 3 | G81: 0 | H81: 4150 | I81: 2390 | J81: 2509.5 | K81: 1640.5 | L81: 492.15 | M81: 1760 | N81: 0.42409639
A82: 0114-04 | B82: 46036 | C82: Store | D82: DEMY | E82: 1 | F82: 1 | G82: 0 | H82: 4200 | I82: 2400 | J82: 2520 | K82: 1680 | L82: 0 | M82: 1800 | N82: 0.42857143
A83: 0114-05 | B83: 46036 | C83: Sis. Jackie | D83: DXB KING JEFF | E83: 1 | F83: 1 | G83: 0 | H83: 1700 | I83: 1100 | J83: 1155 | K83: 545 | L83: 163.5 | M83: 600 | N83: 0.35294118
A84: 0114-06 | B84: 46036 | C84: Store | D84: JEFFREY DALIT | E84: 8 | F84: 17 | G84: 0 | H84: 1856 | I84: 1152.42 | J84: 1201.2526 | K84: 654.7474 | L84: 0 | M84: 703.58 | N84: 0.37908405
A85: 0114-07 | B85: 46036 | C85: Store | D85: LAGUNA AIR BINAN | E85: 1 | F85: 1 | G85: 0 | H85: 600 | I85: 340 | J85: 357 | K85: 243 | L85: 0 | M85: 260 | N85: 0.43333333
A86: 0114-08 | B86: 46036 | C86: Store | D86: LAGUNA AIR PACITA | E86: 1 | F86: 1 | G86: 0 | H86: 7800 | I86: 6732 | J86: 7068.6 | K86: 731.4 | L86: 0 | M86: 1068 | N86: 0.13692308
A87: 0114-09 | B87: 46036 | C87: Store | D87: MULTITECH ELECTRO MECHANICAL | E87: 1 | F87: 1 | G87: 0 | H87: 415 | I87: 170 | J87: 178.5 | K87: 236.5 | L87: 0 | M87: 245 | N87: 0.59036145
A88: 0114-10 | B88: 46036 | C88: Store | D88: RHAYMAR CARBUNGCO | E88: 1 | F88: 1 | G88: 0 | H88: 1900 | I88: 800 | J88: 840 | K88: 1060 | L88: 0 | M88: 1100 | N88: 0.57894737
A89: 0114-11 | B89: 46036 | C89: Store | D89: SOUTHBOYZ AUTOCARE | E89: 1 | F89: 1 | G89: 0 | H89: 550 | I89: 255 | J89: 267.75 | K89: 282.25 | L89: 0 | M89: 295 | N89: 0.53636364
A90: 0115-01 | B90: 46037 | D90: AirCooled / Yohanan Saul | E90: 2 | F90: 2 | G90: 0 | H90: 340 | I90: 159 | J90: 164.45 | K90: 175.55 | L90: 52.665 | M90: 181 | N90: 0.53235294
A91: 0115-02 | B91: 46037 | C91: Ptr. Rod | D91: EDLAN | E91: 2 | F91: 2 | G91: 0 | H91: 2650 | I91: 1660 | J91: 1743 | K91: 907 | L91: 272.1 | M91: 990 | N91: 0.37358491
A92: 0115-03 | B92: 46037 | C92: Store | D92: EUGENE | E92: 1 | F92: 1 | G92: 0 | H92: 2000 | I92: 1400 | J92: 1470 | K92: 530 | L92: 0 | M92: 600 | N92: 0.3
A93: 0115-04 | B93: 46037 | C93: Ptr. Rod | D93: GIE | E93: 1 | F93: 1 | G93: 0 | H93: 2100 | I93: 1650 | J93: 1732.5 | K93: 367.5 | L93: 110.25 | M93: 450 | N93: 0.21428571
A94: 0115-05 | B94: 46037 | C94: Store | D94: JHUN M / MC MC | E94: 4 | F94: 4 | G94: 0 | H94: 4140 | I94: 2560 | J94: 2688 | K94: 1452 | L94: 0 | M94: 1580 | N94: 0.38164251
A95: 0115-06 | B95: 46037 | C95: Store | D95: LAGUNA AIR PACITA | E95: 1 | F95: 1 | G95: 0 | H95: 1700 | I95: 1100 | J95: 1155 | K95: 545 | L95: 0 | M95: 600 | N95: 0.35294118
A96: 0115-07 | B96: 46037 | C96: Store | D96: WALK IN | E96: 2 | F96: 5 | G96: 0 | H96: 406 | I96: 226.72 | J96: 233.5216 | K96: 172.4784 | L96: 0 | M96: 179.28 | N96: 0.44157635
A97: 0116-01 | B97: 46038 | D97: BIB / BOB | E97: 1 | F97: 1 | G97: 0 | H97: 600 | I97: 340 | J97: 357 | K97: 243 | L97: 72.9 | M97: 260 | N97: 0.43333333
A98: 0116-02 | B98: 46038 | C98: Store | D98: JHUN M / MC MC | E98: 1 | F98: 1 | G98: 0 | H98: 7800 | I98: 6732 | J98: 7068.6 | K98: 731.4 | L98: 0 | M98: 1068 | N98: 0.13692308
A99: 0116-03 | B99: 46038 | C99: Store | D99: LAZADA | E99: 1 | F99: 1 | G99: 0 | H99: 260 | I99: 130 | J99: 136.5 | K99: 123.5 | L99: 0 | M99: 130 | N99: 0.5
A100: 0116-04 | B100: 46038 | C100: Store | D100: MIGUEL LADERA | E100: 4 | F100: 6 | G100: 0 | H100: 695 | I100: 542.7 | J100: 558.981 | K100: 136.019 | L100: 0 | M100: 152.3 | N100: 0.21913669
A101: 0116-05 | B101: 46038 | C101: Bro. Vin | D101: TGM | E101: 1 | F101: 1 | G101: 0 | H101: 7800 | I101: 6732 | J101: 7068.6 | K101: 731.4 | L101: 219.42 | M101: 1068 | N101: 0.13692308
A102: 0116-06 | B102: 46038 | C102: Store | D102: TNS | E102: 2 | F102: 2 | G102: 0 | H102: 630 | I102: 455 | J102: 468.65 | K102: 161.35 | L102: 0 | M102: 175 | N102: 0.27777778
A103: 0116-07 | B103: 46038 | C103: Store | D103: WALK IN | E103: 4 | F103: 6 | G103: 0 | H103: 400 | I103: 253 | J103: 262.45 | K103: 137.55 | L103: 0 | M103: 147 | N103: 0.3675
A104: 0117-01 | B104: 46039 | D104: BIB / BOB | E104: 1 | F104: 1 | G104: 0 | H104: 550 | I104: 260 | J104: 273 | K104: 277 | L104: 83.1 | M104: 290 | N104: 0.52727273
A105: 0117-02 | B105: 46039 | C105: Ptr. Rod | D105: GIE | E105: 13 | F105: 74 | G105: 0 | H105: 9700 | I105: 4810 | J105: 5050.5 | K105: 4649.5 | L105: 1394.85 | M105: 4890 | N105: 0.50412371
...

Sheet Expense List
A1: EXPENSE LIST — 2026
A2: Live summary of expense items and monthly amounts from the Expenses sheet
A4: Category | B4: Expense Item | C4: January | D4: February | E4: March | F4: April | G4: May | H4: June | I4: July | J4: August | K4: September | L4: October | M4: November | N4: December | O4: YTD Total
A5: Fixed | B5: Globe | C5: 599 | D5: 599 | E5: 605 | F5: 605 | G5: 605 | H5: 605 | I5: 605 | J5: 605 | K5: 605 | L5: 0 | M5: 0 | N5: 0 | O5: 5433
A6: Fixed | B6: PLDT | C6: 1907 | D6: 1907 | E6: 1907 | F6: 1907 | G6: 1907 | H6: 1907 | I6: 1907 | J6: 1907 | K6: 1907 | L6: 0 | M6: 0 | N6: 0 | O6: 17163
A7: Fixed | B7: Rental | C7: 9000 | D7: 9000 | E7: 9000 | F7: 9000 | G7: 9000 | H7: 9000 | I7: 9000 | J7: 9000 | K7: 9000 | L7: 0 | M7: 0 | N7: 0 | O7: 81000
A8: Fixed | B8: Bookkeeping | C8: 5000 | D8: 5000 | E8: 5000 | F8: 5000 | G8: 5000 | H8: 5000 | I8: 5000 | J8: 5000 | K8: 5000 | L8: 0 | M8: 0 | N8: 0 | O8: 45000
A9: Fixed | B9: Avanza | C9: 17365 | D9: 17365 | E9: 17365 | F9: 17365 | G9: 17365 | H9: 17365 | I9: 17365 | J9: 17365 | K9: 17365 | L9: 0 | M9: 0 | N9: 0 | O9: 156285
A10: Fixed | B10: Insurance | C10: 2000 | D10: 2000 | E10: 2000 | F10: 2000 | G10: 2000 | H10: 2000 | I10: 2000 | J10: 2000 | K10: 2000 | L10: 0 | M10: 0 | N10: 0 | O10: 18000
A11: Fixed | B11: Meralco | C11: 6306 | D11: 7104 | E11: 8413 | F11: 9632 | G11: 11203 | H11: 11637 | I11: 8815.03 | J11: 5766 | K11: 8135 | L11: 0 | M11: 0 | N11: 0 | O11: 77011.03
A12: Fixed | B12: Water | C12: 505 | D12: 502 | E12: 502 | F12: 497 | G12: 502 | H12: 497 | I12: 503 | J12: 503 | K12: 551 | L12: 0 | M12: 0 | N12: 0 | O12: 4562
A13: 0 | B13: Laptop | C13: 1500 | D13: 1500 | E13: 1500 | F13: 1500 | G13: 1500 | H13: 1500 | I13: 1500 | J13: 1500 | K13: 1500 | L13: 0 | M13: , | N13: 0 | O13: 13500
A14: 0 | B14: BIR | C14: 470 | D14: 470 | E14: 470 | F14: 470 | G14: 470 | H14: 470 | I14: 470 | J14: 470 | K14: 470 | L14: 0 | M14: 0 | N14: 0 | O14: 4230
A15: 0 | B15: Salary 15th | C15: 30951 | D15: 28750 | E15: 29850 | F15: 26963 | G15: 27743 | H15: 28785 | I15: 28935 | J15: 29177 | K15: 35935 | L15: 0 | M15: 0 | N15: 0 | O15: 267089
A16: 0 | B16: Salary 30th | C16: 31630 | D16: 30400 | E16: 30962 | F16: 28343 | G16: 28985 | H16: 29692 | I16: 30435 | J16: 28985 | K16: 35242 | L16: 0 | M16: 0 | N16: 0 | O16: 274674
A17: 0 | B17: Mandatories | C17: 14130 | D17: 14130 | E17: 14130 | F17: 12025 | G17: 12025 | H17: 12025 | I17: 12025 | J17: 12025 | K17: 12025 | L17: 0 | M17: 0 | N17: 0 | O17: 114540
A18: 0 | B18: Gas Avanza | C18: 3000 | D18: 3000 | E18: 3000 | F18: 3000 | G18: 3000 | H18: 3000 | I18: 3000 | J18: 3000 | K18: 3000 | L18: 0 | M18: 0 | N18: 0 | O18: 27000
A19: 0 | B19: Food and water | C19: 3842 | D19: 3683 | E19: 4149 | F19: 3907 | G19: 3668 | H19: 4720 | I19: 4370 | J19: 3940 | K19: 3742 | L19: 0 | M19: 0 | N19: 0 | O19: 36021
A20: 0 | B20: lalamove/ Delivery | C20: 6340 | D20: 4058 | E20: 2595 | F20: 7480 | G20: 7565 | H20: 10190 | I20: 5330 | J20: 2900 | K20: 2775 | L20: 0 | M20: 0 | N20: 0 | O20: 49233
A21: 0 | B21: Grocery | C21: 3974 | D21: 1749 | E21: 2062 | F21: 1415 | G21: 1800 | H21: 2230 | I21: 1764 | J21: 919 | K21: 920 | L21: 0 | M21: 0 | N21: 0 | O21: 16833
A22: 0 | B22: Ishabella ADMIN | C22: 2500 | D22: 2500 | E22: 2500 | F22: 2500 | G22: 2500 | H22: 2500 | I22: 2500 | J22: 2500 | K22: 2500 | L22: 0 | M22: 0 | N22: 0 | O22: 22500
A23: 0 | B23: return item | C23: 545 | D23: 0 | E23: 260 | F23: 570 | G23: 260 | H23: 1090 | I23: 2070 | J23: 880 | K23: 0 | L23: 0 | M23: 0 | N23: 0 | O23: 5675
A24: 0 | B24: Acct. Firm | C24: 0 | D24: 0 | E24: 0 | F24: 7500 | G24: 0 | H24: 0 | I24: 0 | J24: 0 | K24: 0 | L24: 0 | M24: 0 | N24: 0 | O24: 7500
A25: 0 | B25: DR Reciept | C25: 0 | D25: 7500 | E25: 0 | F25: 0 | G25: 0 | H25: 0 | I25: 0 | J25: 0 | K25: 0 | L25: 0 | M25: 0 | N25: 0 | O25: 7500
... A29: 0 | B29: paypal | C29: 0 | D29: 0 | E29: 0 | F29: 0 | G29: 0 | H29: 0 | I29: 0 | J29: 1099 | K29: 0 | L29: 0 | M29: 0 | N29: 0 | O29: 1099
A30: Annual Expenses | B30: 161200 | C30: 13433.333 | D30: 13433.3 | E30: 13433.3 | F30: 13433.3 | G30: 13433.3 | H30: 13433.3 | I30: 13433.3 | J30: 13433.3 | K30: 13433.3 | L30: 0 | M30: 0 | N30: 0 | O30: 120899.73
A31: 13th Month | B31: 77000 | C31: 6416.6667 | D31: 6416.6667 | E31: 6416.6667 | F31: 6416.6667 | G31: 6416.6667 | H31: 6416.6667 | I31: 6416.6667 | J31: 6416.6667 | K31: 6416.6667 | L31: 0 | M31: 0 | N31: 0 | O31: 57750
A32: Business Permit | B32: 72200 | C32: 6016.6667 | D32: 6016.6667 | E32: 6016.6667 | F32: 6016.6667 | G32: 6016.6667 | H32: 6016.6667 | I32: 6016.6667 | J32: 6016.6667 | K32: 6016.6667 | L32: 0 | M32: 0 | N32: 0 | O32: 54150
A33: Give away / Calendar | B33: 12000 | C33: 1000 | D33: 1000 | E33: 1000 | F33: 1000 | G33: 1000 | H33: 1000 | I33: 1000 | J33: 1000 | K33: 1000 | L33: 0 | M33: 0 | N33: 0 | O33: 9000

Sheet Report
P15: Car Aircon parts | Q15: =D65 -> #REF! | R15: =D67 -> #REF! | U15: =D68 -> #REF!
P16: TOOLS | Q16: =H65 -> #REF! | R16: =H67 -> #REF! | U16: =H68 -> #REF!
P17: GENERAL | Q17: =D76 -> #REF! | R17: =D78 -> #REF! | U17: =D79 -> #REF!
P18: INSTALLATION MATERIALS | Q18: =H76 -> #REF! | R18: =H83 -> 513430 | U18: =H79 -> #REF!
Q19: =SUM(Q15:Q18) -> #REF!
A31: I. | B31: Total Annual
B32: Sales | F32: Expenses | G32: = | H32: =SUM(H33:H37) -> #REF!
B33: Gross Sales | C33: = | D33: =#REF! -> #REF! | F33: Agent Comm | G33: = | H33: =#REF! -> #REF!
B34: Cost of material | C34: = | D34: =#REF! -> #REF! | F34: Manager Incentive | G34: = | H34: =#REF! -> #REF!
B35: Declared Capital | C35: = | D35: =#REF! -> #REF! | F35: Owners Allowance | G35: = | H35: =#REF! -> #REF!
B36: Add on Capital | C36: = | D36: =#REF! -> #REF! | F36: Store Opex | G36: = | H36: =#REF! -> #REF!
F37: Store Manager Incentive | G37: = | H37: =#REF! -> #REF!
B39: Capitalization & Assets | D39: =SUM(D40:D44) -> 433300 | F39: Income
B40: Capitalization | C40: = | D40: =298000-18000 -> 280000 | F40: Net Income | G40: = | H40: =#REF! -> #REF!
B41: Motorcycle | C41: = | D41: 76000 | F41: Bottom Line | G41: = | H41: =#REF! -> #REF!
B42: CCTV | C42: = | D42: 15600 | F42: After Capitalization@1/3 | G42: = | H42: =H41-(D39*1/3) -> #REF!
B43: Receipts | C43: = | D43: 12800
B44: Store Improvement | C44: = | D44: 48900
B46: Sharing@50% | D46: =H42/2 -> #REF!
B47: Rod@60% | C47: = | D47: =$D$46*0.6 -> #REF!
B48: Vin@30% | C48: = | D48: =$D$46*0.3 -> #REF!
B49: Fred@10% | C49: = | D49: =$D$46*0.1 -> #REF!
A51: II. | B51: Collectibles | D51: =SUM(D52:D61) -> 897309
B52: Envirocool | C52: = | D52: 630839 | F52: For client visit, payment negotiation
B53: Janus | C53: = | D53: 0 | F53: For collection
B54: Anna | C54: = | D54: 0 | F54: For collection - January 22
B55: James | C55: = | D55: 0 | F55: OK
B56: ALB | C56: = | D56: 199090 | F56: For update
B57: ABG | C57: = | D57: 3115 | F57: OK
B58: Bobby | C58: = | D58: 5655 | F58: OK
B59: Ghie | C59: = | D59: 9350 | F59: OK
B60: Edlan | C60: = | D60: 25560 | F60: OK
B61: Benjie | C61: = | D61: =18400+5300 -> 23700 | F61: OK
A63: III. | B63: Categories Monthly
B64: Car Aircon parts | F64: TOOLS
B65: Sales | C65: = | D65: =SUMIFS(#REF!,#REF!,"CAR AIRCON") -> #REF! | F65: Sales | G65: = | H65: =SUMIFS(#REF!,#REF!,"TOOLS") -> #REF!
B66: Capital | C66: = | D66: =SUMIFS(#REF!,#REF!,"CAR AIRCON") -> #REF! | F66: Capital | G66: = | H66: =SUMIFS(#REF!,#REF!,"TOOLS") -> #REF!
B67: Mark up | C67: = | D67: =D65-D66 -> #REF! | F67: Mark up | G67: = | H67: =H65-H66 -> #REF!
B68: Mark up % | C68: = | D68: =IF(D65=0,0,D67/D65) -> #REF! | F68: Mark up % | H68: =IF(H65=0,0,H67/H65) -> #REF!
B69: - Max | C69: = | D69: 456300 | F69: - Max | G69: = | H69: 140223
B70: - Min | C70: = | D70: 285418 | F70: - Min | G70: = | H70: 40690
B71: - Mean | C71: = | D71: 374033.5 | F71: - Mean | G71: = | H71: 69825.167
B72: New Target | C72: = | D72: =D71*1.2 -> 448840.2 | F72: New Target | G72: = | H72: =H71*1.2 -> 83790.2 | Q72: SRP | R72: Discount
B73: No. of Clients | C73: = | D73: 14 clients @55.7% | Q73: 39295
Q74: 38998
B75: GENERAL | F75: INSTALLATION MATERIALS | Q75: 45998
B76: Sales | C76: = | D76: =SUMIFS(#REF!,#REF!,"GENERAL") -> #REF! | F76: Sales | G76: = | H76: =SUMIFS(#REF!,#REF!,"INSTALLATION MATERIALS") -> #REF!
B77: Capital | C77: = | D77: =SUMIFS(#REF!,#REF!,"GENERAL") -> #REF! | F77: Capital | G77: = | H77: =SUMIFS(#REF!,#REF!,"INSTALLATION MATERIALS") -> #REF!
B78: Mark up | C78: = | D78: =D76-D77 -> #REF! | F78: Mark up | G78: = | H78: =H76-H77 -> #REF!
B79: Mark up % | C79: = | D79: =IF(D76=0,0,D78/D76) -> #REF! | F79: Mark up % | G79: = | H79: =IF(H76=0,0,H78/H76) -> #REF!
B80: - Max | C80: = | D80: 790350.4 | F80: - Max | G80: = | H80: 1258720.5
B81: - Min | C81: = | D81: 201213 | F81: - Min | G81: = | H81: 163865
B82: - Mean | C82: = | D82: 358177.83 | F82: - Mean | G82: = | H82: 427858.34
B83: New Target | D83: =D82*1.2 -> 429813.4 | F83: New Target | H83: =H82*1.2 -> 513430
B84: No. of Clients | C84: = | D84: 20 clients @35.2% | F84: No. of Clients | G84: = | H84: 13 clients @24.2%
B86: Total
B87: - Max | D87: =D69+H69+H80+D80 -> 2645593.9
B88: - Min | D88: =D70+H70+D81+H81 -> 691186
B89: - Mean | D89: =D71+H71+D82+H82 -> 1229894.8
B90: Percent Growth | D90: 0.2
B91: New Target Monthly | D91: =D89*(1+D90) -> 1475873.8
B92: New Target Annual | D92: =D91*12 -> 17710486

Sheet Client Record
B1: INDEX
B5: Sum of Sales | C5: Column Labels
B6: Row Labels | C6: 1 | D6: 2 | E6: 3 | F6: 4 | G6: 5 | H6: 6 | I6: 7 | J6: 8 | K6: 9 | L6: 10 | M6: 11 | N6: 12 | P6: (blank)
B7: AGAPOR AIRCONDITIONING | D7: 900
B8: ALB | F8: 83899
B9: ANAKIN | D9: 7800 | E9: 8550 | F9: 8500 | G9: 8500
B10: ARNEL CAHIGAS | F10: 491 | G10: 780 | H10: 1040 | J10: 430
B11: ARVIN PASCO | G11: 1010 | H11: 464
B12: AXM RESTOWORKZ | C12: 900 | E12: 120 | F12: 2200 | H12: 1300 | I12: 1630
B13: BEMBOL | G13: 9770 | H13: 3855 | I13: 300 | J13: 145 | K13: 2000
B14: BERNABE DE VERA CONSTRUCTION | C14: 1338 | D14: 7750 | F14: 2140 | G14: 1040 | H14: 1555 | J14: 200
B15: BONG CANTILLAN | D15: 23295 | E15: 38700 | F15: 8070 | G15: 34234 | H15: 83760 | I15: 30660 | J15: 11875
B16: BRYAN CAR AIRCON | F16: 8492 | I16: 8800
B17: BUBOY CORONEL | C17: 9225 | D17: 7195 | E17: 4995 | F17: 15582 | G17: 49151 | H17: 5116 | I17: 4776
B18: CAPILI | C18: 5975 | D18: 2100 | E18: 3485 | F18: 1970 | I18: 2000
B19: CHIE ESTRELLA | F19: 8460 | G19: 3340 | J19: 6920
B20: CHROME EDGE | C20: 12815 | D20: 1650 | E20: 5900 | F20: 10300 | G20: 2450 | H20: 20550 | I20: 5100 | J20: 15836
B21: CJ PANTHER/SEVILLA | C21: 2055 | D21: 4626 | E21: 6315 | F21: 6001 | G21: 15395 | H21: 33455 | I21: 2370 | J21: 8750
B22: COOL LEAN | E22: 4400 | H22: 3534 | I22: 7495
B23: COOL TIME / JM DIAMAT | C23: 5650 | D23: 5250 | E23: 4400 | F23: 2800 | G23: 17100 | H23: 5500 | I23: 5550 | J23: 1200
B24: CRISJAP | C24: 30015 | D24: 29306 | E24: 43898 | F24: 42229 | G24: 64198 | H24: 26982 | I24: 56912 | J24: 21563
B25: DEMY | C25: 6940 | D25: 8450 | E25: 531 | F25: 100 | G25: 6786 | I25: 1900
B26: DXB KING JEFF | C26: 13320 | D26: 22436 | E26: 12115 | F26: 12545 | G26: 25092 | H26: 23005 | I26: 16133 | J26: 24682 | K26: 1600
B27: EDLAN | C27: 35400 | D27: 5800 | E27: 4928 | F27: 17580 | G27: 34496 | H27: 16715 | I27: 15640 | J27: 22934
B28: ENTENG CAR AIRCON | C28: 10410 | D28: 21930 | E28: 12575 | F28: 9424 | G28: 18400 | H28: 15252 | I28: 5956 | J28: 6722
B29: EUGENE | C29: 8700 | D29: 34398 | E29: 46700 | F29: 34370 | G29: 38482 | H29: 35380 | I29: 38680 | J29: 19230
B30: EVANGELISTA HOSPITAL | D30: 2290 | G30: 13601 | H30: 16506 | I30: 7471
B31: EXPLORER | J31: 700
B32: FLEXTRAC | H32: 3710 | I32: 1800
B33: GEORGE AUTOCARE | D33: 8100 | H33: 8900 | J33: 9000
B34: GIE | C34: 39555 | D34: 49192 | E34: 35276 | F34: 45469 | G34: 27222 | H34: 33747 | I34: 36018 | J34: 27346
B35: JAIMAX AUTOMOTIVE/COOLMAX | I35: 180
B36: JANSON | D36: 1900
B37: JAY ALVIN OCAMPO | D37: 3700 | G37: 4275
B38: JAY STA ROSA | C38: 7800 | D38: 7800
B39: JDS | E39: 19960 | F39: 23360 | G39: 860 | H39: 24720 | I39: 8350 | J39: 33055
B40: JEFFREY DALIT | C40: 2806 | E40: 5330 | F40: 568 | G40: 2808 | I40: 2988
B41: JHONVER AUTO AIRCON | F41: 1900 | I41: 5100 | J41: 7250
B42: JHUN M / MC MC | C42: 43955 | D42: 39496 | E42: 37625 | F42: 46746 | G42: 64300 | H42: 42152 | I42: 52865 | J42: 22841.5 | K42: 2200
B43: JHUN SPORTSMAN | D43: 6550 | E43: 3700 | F43: 7700 | G43: 2000 | H43: 5100 | I43: 3970 | J43: 3600 | K43: 2000
B44: JMT AUTO PARTS | C44: 2000 | E44: 5100 | G44: 2367
B45: LAB AIRCONDITIONING | E45: 200 | F45: 1721 | I45: 385
B46: LAGUNA AIR BINAN | C46: 12570 | D46: 25050 | E46: 24325 | F46: 46278 | G46: 33640 | H46: 34400 | I46: 14100 | J46: 3897
B47: LAGUNA AIR PACITA | C47: 40880 | D47: 42776 | E47: 49315 | F47: 28585 | G47: 60360 | H47: 51080 | I47: 57796 | J47: 19751
B48: LAZADA | C48: 6767.5 | D48: 5200 | E48: 8260 | F48: 7318 | G48: 14730 | H48: 6680 | I48: 10900
B49: LEON RIVERA | E49: 9150
B50: LOTZKI CAR AIRCON | C50: 1800 | D50: 1800 | E50: 3400 | G50: 4823 | H50: 2000 | I50: 1900 | J50: 1900
B51: MANTECH / KULOT | C51: 6700 | E51: 28017 | F51: 25307 | G51: 30485 | H51: 28133 | I51: 35730 | J51: 15575 | K51: 2200
B52: MARK HAO | G52: 2550
B53: MARTIN ESCALANTE | D53: 2250 | E53: 8815 | F53: 4365 | G53: 1526 | H53: 19607 | I53: 4175 | J53: 9650
B54: MHM AUTOSHOP | I54: 11366
B55: MIGUEL LADERA | C55: 695 | D55: 3163 | E55: 2000 | F55: 9621 | G55: 11120 | H55: 8210 | J55: 6375
B56: MULTITECH ELECTRO MECHANICAL | C56: 415 | D56: 440 | E56: 430 | I56: 2275
B57: NALDO'S CAR AIRCON | H57: 8700 | I57: 8800
B58: OGIE LORICA | C58: 9835 | D58: 4785 | E58: 2890 | F58: 11143 | G58: 6006 | H58: 5635 | I58: 5040 | J58: 2115
B59: PHILVENT | C59: 870 | D59: 500 | H59: 430
B60: POLARWIND | C60: 200
B61: PRSC | I61: 5060
B62: PSYCHRO | C62: 6700 | E62: 1090 | F62: 627 | J62: 950
B63: PUREGOLD | G63: 660
B64: RAFFY LP | E64: 2000 | F64: 2768 | G64: 1785 | I64: 2150 | J64: 4000
B65: RICHARD | H65: 3295
B66: RONALD REYES | C66: 13200
B67: ROSIPITO | C67: 1050 | E67: 2610 | F67: 30807 | H67: 758
B68: RQUINT TRADING | I68: 3880
B69: SAINT ROSE TRANSIT | H69: 100
B70: SGP | F70: 6700
B71: SPTC | C71: 18300 | D71: 24000 | E71: 31895 | F71: 25650 | G71: 36350 | H71: 59190 | I71: 29131 | J71: 19350
B72: SPVC | I72: 714
B73: TGM | C73: 7800 | G73: 550 | H73: 8700 | I73: 550 | J73: 2000
B74: TNS | C74: 630 | D74: 540 | F74: 8530 | G74: 3500 | H74: 3500
B75: TOTAL MECHANICS | I75: 738
B76: TRUE COOL | F76: 6755 | G76: 7630 | I76: 2061
B77: VI N VI | D77: 8160 | F77: 5250 | I77: 6620
B78: WALK IN | C78: 58900 | D78: 57184 | E78: 51495 | F78: 39274 | G78: 53126 | H78: 57934 | I78: 69694 | J78: 24280
B79: WORK COOL | H79: 485 | I79: 225 | J79: 750
B80: (blank) | C80: 0 | D80: 0 | E80: 0 | F80: 0 | G80: 0 | H80: 0 | I80: 0 | J80: 0 | K80: 0 | L80: 0 | M80: 0 | N80: 0 | O80: 0 | P80: 0
B81: SOUTHBOYZ AUTOCARE | C81: 1520 | D81: 2890 | E81: 1550 | F81: 2200 | H81: 2000
B82: JOVI TECH | C82: 1959 | D82: 1405 | F82: 2455 | G82: 12256 | I82: 1270 | J82: 250
B83: P A ALVAREZ PROPERTY | D83: 2500 | E83: 3342 | F83: 2677 | H83: 350
B84: DODOY | C84: 36290 | D84: 26000 | E84: 16020 | F84: 35961 | G84: 39050 | H84: 35530 | I84: 22500 | J84: 29316
B85: HELBERT ARIETE / MHM AUTOSHOP | C85: 6425 | D85: 14250 | E85: 15094 | F85: 17519 | G85: 21290 | H85: 35206 | I85: 1964
B86: JOEMANS /BOYET GONZALES | J86: 3486
B87: JHUN GATS | F87: 9949 | G87: 600 | H87: 3600 | J87: 7686
B88: BOBBY ARCABOS | H88: 39500 | I88: 31600
B89: SACHO SON | C89: 1700 | D89: 3400 | E89: 4100
B90: JAYSON REGACHUELO | G90: 2026
B91: YNGEN DATACOM CORP | D91: 47460
B92: AirCooled / Yohanan Saul | C92: 515 | D92: 265 | E92: 2921 | F92: 1336 | G92: 3558 | H92: 4880 | I92: 12553 | J92: 10686
B93: MARLON PEREZ | G93: 1685
B94: 2RK AIRCON SERVICES | I94: 470
B95: GLORIKAR ENGINEERING/ ORVEN GUTIERREZ | F95: 1828
B96: RHAYMAR CARBUNGCO | C96: 27850 | D96: 39250 | E96: 31018 | F96: 37405 | G96: 19479 | H96: 28881 | I96: 22730 | J96: 13664
B97: BARTOLINI | E97: 1900
B98: RAM COOL | G98: 1015
B99: MCMB INDUSTRIAL | H99: 1696
B100: GT TRADES CORP | J100: 200
B101: EJ MERCADO | D101: 500
B102: NIC | E102: 405
B103: COLD ZONE | I103: 800
...

Sheet Workbook Map
A1: WORKBOOK REFURBISHMENT MAP
A2: Phase 1 — architecture, dependencies, current business rules and confirmation register
A3: Documentation only: no operational formulas or source data were changed. Original empty Cash sheet was reused.
A5: WORKBOOK INVENTORY — ORIGINAL 20 SHEETS
A6: # | B6: Original Sheet | C6: Classification | D6: Purpose | E6: Objects and data flow | F6: Status / notes
A7: 1 | B7: Report | C7: Report / legacy | D7: Annual management report with sales, costs, expenses, income and a monthly chart. | E7: Objects: Chart 1; formula report Upstream: Summary Downstream: Management output | F7: REVIEW — Hidden; stale 2021 chart title and broken report references.
A8: 2 | B8: Client Record | C8: Pivot / report | D8: Client-by-month sales matrix used to review purchasing history. | E8: Objects: PivotTable1 Upstream: Daily Sales Downstream: Client review | F8: SUPPORT — Hidden; one stale pivot item displays #REF!.
A9: 3 | B9: INDEX | C9: Dashboard / report | D9: Primary management dashboard for targets, running sales, bottom line and category charts. | E9: Objects: 8 charts; KPI formulas Upstream: Summary; Sales Summary Downstream: Management decisions | F9: CORE — Current visual front end; some chart labels and titles are stale.
A10: 4 | B10: Cash | C10: Empty / obsolete | D10: Original sheet was empty and hidden; repurposed in Phase 1 as Workbook Map. | E10: Objects: None Upstream: None Downstream: None | F10: REPURPOSED — No operational data was removed.
A11: 5 | B11: Summary | C11: Calculation / pivot / report | D11: Central monthly and annual financial model: sales, capital, cost, incentives, expenses, profit and bottom line. | E11: Objects: ADD_ON table; PivotTable1; 2 charts Upstream: Sales Summary; Expenses; Sales; INDEX Downstream: INDEX; Report | F11: CORE — Financial control center; contains inconsistent copied formulas that need confirmation.
A12: 6 | B12: Sales Summary | C12: Pivot / calculation | D12: Five PivotTables summarizing sales, capital, costs, categories and agents by month. | E12: Objects: PivotTables 1–5 Upstream: Daily Sales Downstream: Summary; INDEX | F12: CORE — Main aggregation layer between transactions and reports.
A13: 7 | B13: Inventory | C13: Master input / calculation | D13: Product master, codes, category, unit cost, selling price, stock start and running quantity. | E13: Objects: LIST table: 2,220 products Upstream: Code; Purchase Log; Daily Sales Downstream: Daily Sales; management controls | F13: CORE — Movement formulas rebuilt; 364 source-supported stock deficits remain open.
A14: 8 | B14: Daily Sales | C14: Transaction input / calculation | D14: Detailed sales-entry ledger with clients, products, quantity, price, cost, capital, markup and commission. | E14: Objects: sales table: 8,100 rows Upstream: Client List01; Inventory; ADD_ON Downstream: Sales Summary; client and stock pivots | F14: CORE — Transaction product/client keys and calculation engine repaired. 4,742 positive-sale rows calculate with stable table references; Sales ₱5,682,935.05, Total Cost ₱4,012,118.84, Agent Commission ₱150,211.23.
A15: 9 | B15: Expenses | C15: Input / calculation | D15: Monthly operating-expense schedule by category and item with annual totals. | E15: Objects: Monthly expense grid Upstream: Manual entries Downstream: Summary | F15: CORE — Totals are intact; structure is manual and month columns are irregular.
A16: 10 | B16: Client List01 | C16: Master input | D16: Client master with contact, company, address, category and assigned agent. | E16: Objects: Table28: 382 rows Upstream: Manual entries Downstream: Daily Sales; client pivots | F16: CORE — Initial column contains broken references; client name is the practical key.
A17: 11 | B17: Input Slicer | C17: Pivot support | D17: Distinct product and client lists used as PivotTable/slicer support. | E17: Objects: PivotTables 1–2 Upstream: Daily Sales / masters Downstream: Filtering support | F17: SUPPORT — Helper sheet; not intended for direct editing.
A18: 12 | B18: Sales | C18: Pivot / calculation support | D18: Wide historical pivot workspace supporting monthly and analytical sales outputs. | E18: Objects: PivotTable1 only; 1,102 columns × 92 rows Upstream: Daily Sales Downstream: Summary daily grid | F18: SUPPORT — Redundant lower pivots retired; live Summary anchor preserved.
... A26: 20 | B26: FREDSAN | C26: Support / uncertain | D26: Small two-column helper calculation; operational purpose is not evident from labels. | E26: Objects: 2 formulas Upstream: Unknown Downstream: Unknown | F26: CONFIRM — Confirm whether this sheet is active, legacy or experimental.
A29: CORE DEPENDENCY MAP
A30: Source | B30: Destination | C30: Data / logic transferred | D30: Mechanism | E30: State | F30: Risk / operating note
A31: Client List01 | B31: Daily Sales | C31: Client name lookup assigns agent and related client information. | D31: VLOOKUP to Table28 | E31: ACTIVE | F31: Client name spelling must match exactly.
A32: Inventory | B32: Daily Sales | C32: Product description/code lookup supplies item, category, store price and unit cost. | D32: 9,813 direct formula references | E32: PARTLY BROKEN | F32: Some rows use deleted or external lookup ranges.
A33: Summary.ADD_ON | B33: Daily Sales | C33: Category percentage converts Total Cost into declared Capital. | D33: GENERAL 5%; TOOLS 5%; INSTALLATION MATERIALS 3%; CAR AIRCON 5% | E33: ACTIVE | F33: Confirm whether rates are tax/add-on policy or temporary assumptions.
A34: Daily Sales | B34: Sales Summary | C34: Transaction table feeds monthly PivotTables for sales, capital, cost, category and agent totals. | D34: Pivot cache dependency | E34: ACTIVE | F34: Pivot refresh timing is operationally important.
A35: Daily Sales | B35: Daily Inventory | C35: Transaction quantities are summarized by product code. | D35: PivotTable1 | E35: ACTIVE | F35: Inventory Qty Sold depends on this pivot being refreshed.
A36: Daily Inventory | B36: Inventory | C36: Qty Sold is retrieved by product code into the stock equation. | D36: 2,209 direct formula references | E36: ACTIVE | F36: Returns zero if a code is absent.
A37: Purchased | B37: Inventory | C37: Purchased quantity should be retrieved by product code into stock movement. | D37: New Purchase Log table lookup/aggregation by product code | E37: RETIRED / REPLACEMENT PLANNED | F37: Owner confirmed the deleted Purchased sheet will not be restored; create a controlled Purchase Log from scratch before rebuilding Inventory[Purchased].
A38: Inventory | B38: STORE PRICE | C38: Product data, cost, capital, store price and stock feed discount pricing. | D38: 1,648 direct formula references | E38: RETIRED | F38: RETIRED — STORE PRICE sheet permanently deleted; this dependency will not be rebuilt.
A39: Expenses | B39: Summary | C39: Monthly expense totals feed the financial model. | D39: 12 direct month links | E39: ACTIVE | F39: August onward remain zero until entered.
A40: Sales Summary | B40: Summary | C40: Monthly sales capital and cost aggregates feed financial calculations. | D40: 39 direct references / GETPIVOTDATA | E40: ACTIVE WITH ISSUE | F40: Cost uses Unit Cost for Jan–Oct but Total Cost for Nov–Dec.
A41: Summary | B41: INDEX | C41: Targets, sales, progress and bottom line feed the dashboard. | D41: 52 direct formula references | E41: ACTIVE | F41: Dashboard accuracy depends entirely on Summary.
... A43: Summary | B43: Report | C43: Annual financial totals feed the hidden legacy report. | D43: 9 direct formula references | E43: ACTIVE WITH ERRORS | F43: Report also references deleted internal cells.
A46: CURRENT BUSINESS-RULE REGISTER — DOCUMENTED, NOT YET CORRECTED
A47: ID | B47: Rule | C47: Current workbook logic | D47: Primary location | E47: State / interpretation | F47: Confirmation required
A48: R01 | B48: Sales | C48: Quantity × Price + Delivery | D48: Daily Sales[Sales] | E48: ACTIVE — Delivery is added to revenue. | F48: Confirm whether Delivery is always billable revenue.
A49: R02 | B49: Unit cost | C49: Lookup product Unit Cost from Inventory | D49: Daily Sales[Unit Cost] | E49: ACTIVE — Cost per unit comes from product master. | F49: Some sales with missing product code resolve to zero.
A50: R03 | B50: Total cost | C50: Unit Cost × Quantity | D50: Daily Sales[Total Cost] | E50: ACTIVE — Extended transaction cost. | F50: Summary currently does not consistently use this measure.
A51: R04 | B51: Declared capital | C51: Total Cost × (1 + category add-on) | D51: Daily Sales[Capital] / Summary.ADD_ON | E51: ACTIVE — Add-on: General 5%, Tools 5%, Installation Materials 3%, Car Aircon 5%. | F51: Confirm meaning and ownership of the add-on percentage.
A52: R05 | B52: Transaction markup | C52: Sales − Capital − Delivery | D52: Daily Sales[Mark up] | E52: ACTIVE — Margin after declared capital and delivery. | F52: Confirm whether delivery should be removed after already being included in Sales.
A53: R06 | B53: Agent commission | C53: Store = 0; otherwise 30% of transaction markup | D53: Daily Sales[Agent Comm.] | E53: ACTIVE — Commission is margin-based, not sales-based. | F53: Confirm that every non-Store agent receives the same 30%.
A54: R07 | B54: Manager incentive | C54: 1% of monthly sales | D54: Summary row 44 | E54: ACTIVE — Monthly manager incentive. | F54: Net-income formulas deduct it once Jan–Apr, twice May–Aug.
A55: R08 | B55: Store manager | C55: Mixed: threshold formula, 0.5% sales, or linked allowance | D55: Summary row 45 | E55: INCONSISTENT — Current intent appears to be 0.5%, sometimes multiplied by three. | F55: Confirm one rule, threshold and eligible base for all months.
A56: R09 | B56: Ishabella sales | C56: 1% of Ptr. Rod sales or selected INDEX cells | D56: Summary row 46 | E56: INCONSISTENT — Separate 1% sales allocation. | F56: Confirm recipient, applicable agent and why the dashboard is a source.
A57: R10 | B57: Owner allowance / tax | C57: 0.5% × 3 under threshold logic, later 3 × store-manager value | D57: Summary row 47; Report H35 | E57: UNCERTAIN — Summary calls this Owner's Allowance; Report calls same total Tax Withheld. | F57: Confirm whether this is allowance, withholding tax, or two separate items.
A58: R11 | B58: Gross income | C58: Sales − Capital − Agent commission, plus a 50% helper adjustment in current formulas | D58: Summary row 49 | E58: INCONSISTENT — Core gross-income concept is visible in notes. | F58: Confirm purpose of row 115 and the 50% factor in B92.
... A69: R22 | B69: Invoice price | C69: If invoice number exists, Price × 1.12 | D69: Daily Sales[SI PRICE] | E69: ACTIVE — Adds 12% to selling price for invoiced transactions. | F69: Confirm whether this is VAT and whether Sales should also use SI PRICE.
A72: OWNER CONFIRMATION REGISTER — RESOLVE BEFORE FORMULA REBUILD
A73: ID | B73: Topic | C73: Question | D73: Priority / location | E73: Why it matters | F73: Decision / status
A74: U01 | B74: Cost basis | C74: Should monthly T-COST be Total Cost (quantity-extended) rather than Unit Cost? | D74: HIGH — Summary row 42 | E74: Blocks reliable profit and add-on capital. | F74: APPLIED — Total Cost = Unit Cost × Quantity for every month
A75: U02 | B75: Agent commission period | C75: Should the commission pivot always follow each report month automatically? | D75: HIGH — Summary B70:D85 and row 43 | E75: Current pivot is filtered to Month 6. | F75: APPLIED — Commission calculated automatically by report month
A76: U03 | B76: Manager incentive | C76: Deduct 1% once or twice, and from sales or another base? | D76: HIGH — Summary rows 44 and 50 | E76: Material effect on net income. | F76: APPLIED — Manager incentive is 1% of pre-incentive net income, deducted once
A77: U04 | B77: Store-manager rule | C77: Choose one consistent percentage, threshold, multiplier and base. | D77: HIGH — Summary row 45 | E77: Current formulas change by month. | F77: APPLIED — Manager incentive is 1% and Store Manager incentive is 0.5% of gross sales for every month.
A78: U05 | B78: Owner allowance versus tax | C78: Are these one item or two separate obligations? | D78: HIGH — Summary row 47 / Report H35 | E78: Same amount carries two labels. | F78: APPLIED — Three owners receive 0.5% each; 1.5% total gross sales
A79: U06 | B79: Gross-income adjustment | C79: What are row 115 and the 50% control in B92 intended to represent? | D79: HIGH — Summary row 49 | E79: Hidden adjustment changes reported gross income. | F79: APPLIED — Deleted obsolete gross-income adjustment
A80: U07 | B80: Tithes and offering | C80: Confirm rates, bases, special months and whether negatives are allowed. | D80: HIGH — Summary rows 57:60 | E80: Copied formulas are not uniform. | F80: APPLIED — Removed tithes/offering rows and bottom-line deduction
A81: U08 | B81: Break-even | C81: Confirm standard formula should apply identically to all months. | D81: MEDIUM — Summary rows 54:56 | E81: Several month formulas reference mismatched cells. | F81: APPLIED — Gross margin uses (Sales − Total Cost) ÷ Sales. Break-even uses Expenses ÷ Gross Margin. Zero-sales future months carry the latest actual margin and monthly expense; Sales Variance uses the ₱1.5m monthly target for future months.
A82: U09 | B82: Inventory adjustment sign | C82: Does a positive adjustment add stock or remove stock? | D82: MEDIUM — Inventory[Running] | E82: Current formula subtracts Adjustment. | F82: OPEN
A83: U10 | B83: Pricing multiplier | C83: Define when store price is 2× versus 2.75× floor capital. | D83: MEDIUM — Inventory[STORE PRICE] | E83: No explicit rule field controls the choice. | F83: OPEN
A84: U11 | B84: Discount eligibility | C84: Define Column4 and who receives Discount1/2/3 tiers. | D84: MEDIUM — STORE PRICE LIST53 | E84: Labels are technical rather than operational. | F84: OPEN
A85: U12 | B85: Legacy sheets | C85: Confirm whether Report, Sales wide history, In Store and FREDSAN are still required. | D85: LOW — Multiple sheets | E85: Determines later archive and simplification work. | F85: CONFIRMED — Deleted legacy sheets will not be restored.
A88: PHASE 1 CHECKPOINT: all 20 original sheets are classified; core dependencies and 22 business rules are mapped; 12 owner decisions remain open before any formula changes.
A90: PHASE 2 — MASTER RECORD STABILIZATION | G90: Product Categories | H90: Approved Agents | I90: Client Categories
A91: Area | B91: Change | C91: Affected records | D91: Control added | E91: Result | F91: Status | G91: GENERAL | H91: Store | I91: Retail
A92: Product variants | B92: Separated Ford Ranger Type A / Type B | C92: Inventory 1461–1462; Code 687 and 1392 | D92: Unique descriptions with existing codes | E92: CA-000752 / CA-001514 | F92: COMPLETE | G92: TOOLS | H92: Bro. Bryan | I92: Trade
A93: Product variants | B93: Separated Isuzu Crosswind Type A / Type B | C93: Inventory 1495 and 1499; Code 719 and 723 | D93: Unique descriptions with existing codes | E93: CA-000784 / CA-000788 | F93: COMPLETE | G93: INSTALLATION MATERIALS | H93: Bro. Jay | I93: Corporate
A94: Missing product code | B94: Added Hyundai RV evaporator | C94: Inventory 909; Code table new row | D94: New unique Car Aircon code | E94: CA-001866 | F94: COMPLETE | G94: CAR AIRCON | H94: Bro. Jr
A95: Client initials | B95: Rebuilt from Client Name | C95: 378 active clients; 4 reserved rows | D95: Live calculated-column formula | E95: All active initials calculate; no current errors | F95: COMPLETE | H95: Bro. Manuel
A96: Product categories | B96: Controlled Inventory and Code inputs | C96: All 2,209 Inventory product rows | D96: Approved-list validation | E96: 4 categories | F96: COMPLETE — All 2,209 Inventory products map uniquely to Code; no missing or duplicate codes. | H96: Bro. Mel
A97: Client classification | B97: Added Retail / Trade / Corporate | C97: 378 active clients awaiting owner classification | D97: Approved-list validation | E97: Ready for owner classification | F97: OWNER INPUT — Add six historical clients; NIC maps to Store. Assign approved agents to five other new clients before repairing transaction agents. | H97: Bro. Rhoge
A98: Master uniqueness | B98: Protected clients, item descriptions and codes | C98: Client and Code masters | D98: Stop-alert uniqueness validation | E98: Prevents new duplicates | F98: COMPLETE | H98: Bro. Rocky
A99: Legacy duplicate codes | B99: Retired 10 unused duplicate mappings | C99: Code master only | D99: Verified absent from sales, purchases, pricing and inventory | E99: Inactive rows cleared without shifting layout | F99: COMPLETE | H99: Bro. Roxie
A100: PHASE 2 CHECKPOINT: product and client keys are unique; code errors are cleared; master inputs are controlled; client classification remains for owner entry. | H100: Bro. Vin
H101: Ptr. Rod
H102: Sis. Jackie
H103: Sis. Mhai

Sheet Audit
A1: MODEL AUDIT & PHASE 0 BASELINE
A2: Baseline captured 2026-08-01 22:00 GMT+08 | Operational formulas and source data unchanged
A4: STORY IN BRIEF
A5: The transaction ledger still totals ₱5.683m and reconciles exactly to Summary for sales, total cost, and agent commission. The baseline scan found 21,156 visible errors, led by STORE PRICE, Daily Sales, and Inventory. Inventory has 23 movement-equation exceptions, one negative-stock item, and 412 positive-sales rows without a product code. The workbook text expected 4,942 active transactions; the measurable positive-sales count is 4,742, so the active-row definition needs confirmation before Phase 3.
A7: BASELINE KPI | B7: Value | C7: Source / definition | D7: Status
A8: Original sheets | B8: 20 | C8: Pre-Phase 0 workbook inventory | D8: BASELINE
A9: Positive-sales transactions | B9: 4742 | C9: Daily Sales rows where Sales > 0 | D9: REVIEW
A10: Transaction sales | B10: 5682935 | C10: SUM(sales[Sales]) | D10: PASS
A11: Transaction total cost | B11: 2952627.4 | C11: SUM(sales[Total Cost]) | D11: PASS
A12: Transaction agent commission | B12: 256529.59 | C12: SUM(sales[Agent Comm.]) | D12: PASS
A13: Inventory master rows | B13: 2209 | C13: Inventory rows with an item description | D13: BASELINE
A14: Visible formula errors | B14: 21156 | C14: Full 20-sheet baseline scan | D14: FAIL
A16: LIVE CONTROL | B16: Workbook source | C16: Control target | D16: Difference / count | E16: Status | F16: Owner action | G16: Phase | H16: Priority
A17: Sales-to-Summary reconciliation | B17: =SUM(#REF!) -> #REF! | C17: =#REF! -> #REF! | D17: =B17-C17 -> #REF! | E17: =IF(ABS(D17)<0.01,"PASS","FAIL") -> #REF! | F17: No action while difference is zero | G17: 6 | H17: HIGH
A18: Cost reconciliation | B18: =_xlfn.AGGREGATE(9,6,#REF!) -> #REF! | C18: =#REF! -> #REF! | D18: =B18-C18 -> #REF! | E18: =IF(ABS(D18)<0.01,"PASS","FAIL") -> #REF! | F18: No action while difference is zero | G18: 6 | H18: HIGH
A19: Commission reconciliation | B19: =_xlfn.AGGREGATE(9,6,#REF!) -> #REF! | C19: =#REF! -> #REF! | D19: =B19-C19 -> #REF! | E19: =IF(ABS(D19)<0.01,"PASS","FAIL") -> #REF! | F19: No action while difference is zero | G19: 6 | H19: HIGH
A20: Inventory equation exceptions | B20: {=SUMPRODUCT(--(ABS(#REF!-(#REF!+#REF!+#REF!-#REF!))>0.0001))} -> #REF! | D20: =B20 -> #REF! | E20: =IF(B20=0,"PASS","FAIL") -> #REF! | F20: Repair Running / movement formulas | G20: 4 | H20: HIGH
A21: Duplicate product-code rows | B21: {=SUMPRODUCT((#REF!<>"")*(COUNTIF(#REF!,#REF!)>1))} -> #REF! | D21: =B21 -> #REF! | E21: =IF(D21=0,"PASS","FAIL") -> #REF! | F21: Keep at zero | G21: 2 | H21: HIGH
A22: Missing client on positive-sales rows | B22: =COUNTIFS(#REF!,">0",#REF!,"") -> #REF! | D22: =B22 -> #REF! | E22: =IF(D22=0,"PASS","FAIL") -> #REF! | F22: Complete client reference | G22: 3 | H22: HIGH
A23: Missing item code on positive-sales rows | B23: =COUNTIFS(#REF!,">0",#REF!,"") -> #REF! | D23: =B23 -> #REF! | E23: =IF(D23=0,"PASS","FAIL") -> #REF! | F23: Repair product lookup / code | G23: 3 | H23: HIGH
A24: Negative running stock | B24: =COUNTIF(#REF!,"<0") -> #REF! | D24: =B24 -> #REF! | E24: =IF(B24=0,"PASS","FAIL") -> #REF! | F24: Trace purchases, sales and adjustments | G24: 4 | H24: HIGH
A25: Missing unit cost | B25: =COUNTIFS(#REF!,"<>",#REF!,0) -> #REF! | D25: =B25 -> #REF! | E25: =IF(D25=0,"PASS","FAIL") -> #REF! | F25: Complete product master cost | G25: 2 | H25: HIGH
A26: Sales exceeding available stock | B26: {=SUMPRODUCT(--(#REF!>(#REF!+#REF!+#REF!)))} -> #REF! | D26: =B26 -> #REF! | E26: =IF(B26=0,"PASS","FAIL") -> #REF! | F26: Trace stock movement | G26: 4 | H26: HIGH
A28: PRIORITY ISSUE LOG | B28: Sheet | C28: Range / object | D28: Severity | E28: Category | F28: Baseline finding | G28: Next phase | H28: Status
A29: 1 | B29: STORE PRICE | C29: LIST53 | D29: CRITICAL | E29: Formula | F29: Worksheet permanently deleted by owner instruction; Phase 0 figures retained as historical baseline | G29: 5 | H29: DELETED
A30: 2 | B30: Daily Sales | C30: sales | D30: CRITICAL | E30: Formula | F30: 6,493 #REF! errors; 412 positive-sales rows lack item code | G30: 3 | H30: OPEN
A31: 3 | B31: Inventory | C31: LIST | D31: CRITICAL | E31: Formula / stock | F31: 2,300 errors; 23 movement exceptions; 1 negative stock | G31: 4 | H31: OPEN
A32: 4 | B32: Summary | C32: B40:AA62 | D32: WARNING | E32: Financial logic | F32: 20 visible errors; break-even rules remain open | G32: 6 | H32: OPEN
A33: 5 | B33: Sales Summary | C33: PivotTables | D33: WARNING | E33: Pivot | F33: 17 visible errors including stale #REF! items | G33: 7 | H33: OPEN
A34: 6 | B34: INDEX | C34: Charts / KPI links | D34: WARNING | E34: Report | F34: 7 visible errors; dashboard depends on Summary | G34: 8 | H34: OPEN
A35: 7 | B35: Workbook Map | C35: U08:U12 | D35: WARNING | E35: Business rules | F35: Five owner decisions remain open | G35: 46028 | H35: CONFIRM
A36: 8 | B36: Phase 0 | C36: External file copy | D36: INFO | E36: Archival | F36: Workbook baseline captured; external archival copy cannot be created from the live sheet session | G36: 0 | H36: MANUAL COPY
A38: 20-SHEET ERROR BASELINE | B38: Visibility | C38: Used range | D38: Formula cells | E38: Reference errors | F38: #DIV/0! / other | G38: Total errors | H38: Phase
A39: Report | B39: Hidden | C39: A15:U92 | D39: 114 | E39: 28 | F39: 0 | G39: 28 | H39: 7
A40: Client Record | B40: Hidden | C40: B1:P184 | D40: 0 | E40: 1 | F40: 0 | G40: 1 | H40: 7
A41: Workbook Map | B41: Visible | C41: A1:I103 | D41: 0 | E41: 0 | F41: 0 | G41: 0 | H41: 0
A42: INDEX | B42: Visible | C42: B2:AV122 | D42: 227 | E42: 7 | F42: 0 | G42: 7 | H42: 8
A43: Summary | B43: Visible | C43: B1:AG174 | D43: 1414 | E43: 8 | F43: 12 | G43: 20 | H43: 6
A44: Sales Summary | B44: Visible | C44: B1:AG88 | D44: 4 | E44: 16 | F44: 1 | G44: 17 | H44: 7
A45: Inventory | B45: Visible | C45: A1:AA2213 | D45: 34334 | E45: 2299 | F45: 1 | G45: 2300 | H45: 4
A46: Daily Sales | B46: Visible | C46: B1:Z8134 | D46: 74561 | E46: 6493 | F46: 0 | G46: 6493 | H46: 3
A47: Expenses | B47: Visible | C47: B3:Z241 | D47: 36 | E47: 0 | F47: 0 | G47: 0 | H47: 6
A48: Client List01 | B48: Visible | C48: C6:K388 | D48: 382 | E48: 0 | F48: 0 | G48: 0 | H48: 2
A49: Input Slicer | B49: Visible | C49: A3:G382 | D49: 0 | E49: 0 | F49: 0 | G49: 0 | H49: 10
A50: Sales | B50: Visible | C50: B2:APK1035 | D50: 16 | E50: 11 | F50: 0 | G50: 11 | H50: 46213
... A58: FREDSAN | B58: Visible | C58: B5:C8 | D58: 2 | E58: 0 | F58: 0 | G58: 0 | H58: 10
A59: TOTAL BASELINE ERRORS | G59: =SUM(G39:G58) -> 21156 | H59: 21156
A61: TIERED REPAIR PLAN — LOW-LOAD WORK PACKETS
A62: Work one packet at a time. Each packet must capture a before-state, change only its stated range, recalculate, compare the control totals, log the result, save a new version, and stop. Do not refresh every PivotTable or rewrite whole tables in the same session.
A64: Tier / packet | B64: Objective | C64: Primary scope | D64: Batch ceiling | E64: Entry gate | F64: Required verification | G64: Stop / rollback trigger | H64: Status
A65: 0A | B65: Create archival checkpoint | C65: Whole workbook | D65: One manual Save As | E65: Current file opens; Audit baseline visible | F65: Manual Save As confirmed by owner on 2026-08-01 | G65: No archival copy available | H65: COMPLETE
A66: 0B | B66: Lock packet controls | C66: Audit!A17:E26 | D66: One control review | E66: 0A complete | F66: Locked: sales ₱5,682,935.05; cost ₱2,952,627.44; commission ₱256,529.59 | G66: Any baseline total changes before repair | H66: COMPLETE
A67: 1A | B67: Confirm surviving architecture | C67: 15 remaining sheets | D67: One dependency review | E67: 0B complete | F67: Confirmed: five deleted sheets are permanently retired; dependencies must not reference them | G67: Required source is missing | H67: COMPLETE
A68: 1B | B68: Stabilize product keys | C68: Code[CODE] and Inventory!LIST[CODE] | D68: 500 master rows | E68: 1A complete | F68: COMPLETE: all 2,209 Inventory products checked in five low-load batches. 0 missing codes, 0 duplicates, 0 unmapped codes, and 0 description mismatches. Repaired Code!E2592:F2592 and Inventory!E938. | G68: New duplicate or changed description | H68: COMPLETE
A69: 1C | B69: Stabilize client keys | C69: Client List01!Table28 | D69: All 382 rows | E69: 1A complete | F69: Passed: 378 active clients; 4 validated blank rows reserved. 0 duplicate names, 0 missing initials, 0 invalid/blank agents. All active categories remain blank for owner classification; Retail/Trade/Corporate validation is active. | G69: Any sales/client mismatch increases | H69: COMPLETE
A70: 2A | B70: Audit core sales inputs | C70: sales[Month] through sales[Price] | D70: 500 table rows | E70: Tier 1 passed | F70: COMPLETE — 4,742 positive-sales rows assessed. Month, date, item description, quantity and price are complete and valid. Invoice/DR and receipt type are owner-confirmed optional. Exceptions handed off: 412 missing product codes to 2B; 117 rows across 6 absent clients and 113 blank agents to 2C. No transaction values changed. | G70: Sales total changes | H70: COMPLETE
A71: 2B | B71: Repair product lookups | C71: sales code, SRP, cost, capital, item/category fields | D71: 3 columns × 500 rows | E71: 2A complete | F71: COMPLETE — Restored 412 transaction product codes: 383 deterministic Inventory matches, 28 exact historical Code mappings, and 1 validated product variant. Added 11 inactive historical Inventory records with zero cost/stock by owner policy. Repaired 54 dormant product formulas; product columns I/O/P/U/V contain no visible errors or #REF formulas. | G71: New #REF! or valid lookup changes unexpectedly | H71: COMPLETE
A72: 2C | B72: Repair client lookups | C72: sales client-derived address/pricing fields | D72: 2 columns × 500 rows | E72: 2A and 2B complete | F72: COMPLETE — Added six historical clients, assigned all six to Store by owner instruction, and normalized 5 trailing-space client entries. All 4,742 positive-sale rows now resolve to a master client and approved agent; 0 unknown clients and 0 blank agents. | G72: Client/agent assignment changes unexpectedly | H72: COMPLETE
A73: 2D | B73: Repair sales calculations | C73: sales Sales, Total Cost, Capital, Mark up, Commission | D73: 3 columns × 500 rows | E73: 2B and 2C batch passed | F73: COMPLETE — Rebuilt code-based product lookups and Sales/Total Cost/Capital/Markup/Commission calculations across all 8,100 table rows in 17 controlled packets. Preserved three documented discounted Sales overrides. Positive-sale rows: 4,742; calculation errors: 0. | G73: Any reconciliation difference is nonzero | H73: COMPLETE
A74: 2E | B74: Historical regression test | C74: Representative records from each month/category/agent | D74: 25 records | E74: 2D complete | F74: COMPLETE — 25-record regression sample passed across all 8 active months, 4 categories and 10 agents. Three discounted Sales overrides were preserved and explained; annual sales, cost and commission tie to the repaired ledger. | G74: Any historical result cannot be explained | H74: COMPLETE
A75: 3A | B75: Build new purchase source | C75: New Purchase Log sheet and table | D75: Structure first; then maximum 500 purchase rows per packet | E75: Tier 2 passed; owner decision recorded | F75: COMPLETE — Purchase Log and PurchaseLog table created. Unique IDs are checked by row status; Product Code is restricted to 2,220 Inventory master codes; quantity and unit cost require positive values. Product description/category and purchase amount calculate automatically. No purchase transactions loaded. | G75: Any duplicate purchase ID, invalid code, or inventory reconciliation change | H75: COMPLETE
... A84: 6B | B84: Document and hand over | C84: Workbook Map, Audit, operating guide | D84: One documentation section | E84: All prior tiers passed | F84: BLOCKED — Full 17-sheet audit found 11,272 live error-bearing cells: Daily Sales 7,055; Inventory 4,208; Summary 8; Sales Summary 1. Operating Guide, reports, dashboard and financial controls pass, but final handover cannot be signed off until these cells and the 364 source-supported stock deficits are resolved. | G84: Any edit location remains ambiguous | H84: BLOCKED
A86: SYSTEM-LOAD GUARDRAILS
A87: Rule 1 | B87: Touch only one sheet and one formula group per packet
A88: Rule 2 | B88: Maximum 500 table rows or three calculated columns per write
A89: Rule 3 | B89: For PivotTables, refresh and verify one PivotTable at a time
A90: Rule 4 | B90: Run targeted error checks on the changed range; full-workbook scan only at tier gates
A91: Rule 5 | B91: After every packet: recalculate, compare Audit controls, save a new version, then stop
A92: Rule 6 | B92: If sales, cost, or commission differs from baseline, roll back that packet before continuing
A94: PACKET LOG | B94: Completed | C94: Scope | D94: Sales difference | E94: Cost difference | F94: Commission difference | G94: Outcome | H94: Next packet
A95: 0B | B95: 2026-08-01 23:00 GMT+08 | C95: Audit controls only | D95: 0 | E95: 1.0244548e-08 | F95: 2.6193447e-10 | G95: PASS | H95: 1A
A96: ARCHITECTURE DECISION | B96: Decision date | C96: Retired sheets | D96: Purchase replacement | E96: Impact | F96: Control result | G96: Packet | H96: Status
A97: Permanent retirement | B97: 2026-08-01 23:00 GMT+08 | C97: STORE PRICE; Purchased; FREDSAN; Client Sales Records; CLIENT PRICING | D97: Build new Purchase Log from scratch | E97: Do not rebuild dependencies to retired sheets | F97: Sales/cost/commission differences remain ₱0.00 | G97: 1A | H97: COMPLETE
A98: 1B-01 | B98: 2026-08-01 23:00 GMT+08 | C98: Inventory!B5:F504 | D98: 500 products | E98: 0 missing / 0 duplicate / 0 unmapped / 0 mismatched | F98: No master values changed | G98: PASS | H98: 1B-02
A99: 1C | B99: 2026-08-01 23:00 GMT+08 | C99: Client List01!Table28 | D99: 382 table rows / 378 active | E99: 0 duplicate names; 0 invalid agents; validations active | F99: 378 category inputs intentionally left blank | G99: PASS | H99: Resume 1B-02
A101: 2A READINESS | B101: Prerequisite | C101: Rows assessed | D101: Ready fields | E101: Blocking exceptions | F101: Policy question | G101: Financial controls | H101: Verdict
A102: Core sales inputs | B102: 1B IN PROGRESS; 1C COMPLETE | C102: 4,742 positive-sales rows | D102: Month/date/item description/qty/price | E102: 412 missing codes; 117 unknown-client rows (6 names); 113 blank agents | F102: Are invoice and receipt type optional for cash/non-invoiced sales? | G102: Sales/cost/commission differences ₱0.00 | H102: NOT READY
A103: 1B-02 | B103: 2026-08-01 23:00 GMT+08 | C103: Inventory!C505:F1004 | D103: 500 products | E103: Repaired CA-001866 check and Inventory row 938 code lookup | F103: 0 missing / duplicate / unmapped / mismatched after repair | G103: PASS | H103: 1B-03
A104: 1B-03 | B104: 2026-08-01 23:00 GMT+08 | C104: Inventory!C1005:F1504 | D104: 500 products | E104: No changes | F104: 0 missing / duplicate / unmapped / mismatched | G104: PASS | H104: 1B-04
A105: 1B-04 | B105: 2026-08-01 23:00 GMT+08 | C105: Inventory!C1505:F2004 | D105: 500 products | E105: No changes | F105: 0 missing / duplicate / unmapped / mismatched | G105: PASS | H105: 1B-05
A106: 1B-05 | B106: 2026-08-01 23:00 GMT+08 | C106: Inventory!C2005:F2213 | D106: 209 products | E106: Full key-only check: 2,209 products | F106: 0 missing / duplicate / unmapped / mismatched | G106: PASS | H106: 2A exceptions
A107: 2A DECISION | B107: Invoice / receipt rule | C107: Client rule | D107: Agent rule | E107: Product-code finding | F107: Client/agent finding | G107: Transaction changes | H107: Status
A108: Owner rules | B108: Both may remain blank | C108: Add six historical clients | D108: Use client-master agent only | E108: 412 blank codes; no exact full-description match | F108: 117 rows / 6 clients; 113 blanks all belong to 5 new clients | G108: None | H108: COMPLETE
... A111: 2B PACKET | B111: Scope | C111: Codes restored | D111: Exceptions retained | E111: Master action | F111: Formula action | G111: Financial difference | H111: Outcome
A112: 2B-01 | B112: Rows 7:506 | C112: 219 | D112: 20 pending at packet close | E112: None | F112: None | G112: ₱0.00 | H112: PASS
A113: 2B-02:08 | B113: Rows 507:4506 | C113: 164 | D113: 29 historical candidates before Code review | E113: None | F113: None | G113: ₱0.00 | H113: PASS
A114: 2B-HIST | B114: All remaining rows | C114: 29 | D114: 0 | E114: Added 11 inactive historical products | F114: Validated exact Code records / one matching variant | G114: ₱0.00 | H114: PASS
A115: 2B-FORMULA | B115: Product columns I/O/P/U/V | C115: 0 | D115: 0 | E115: All positive-sale codes resolve to Inventory | F115: Repaired 21 code, 18 SRP, 15 unit-cost dormant #REF formulas | G115: ₱0.00 | H115: COMPLETE
A119: 2C CLOSE | B119: Rows normalized | C119: Positive-sale rows | D119: Unknown clients | E119: Blank agents | F119: Commission before cleanup | G119: Commission after cleanup | H119: Status
A120: Client/agent verification | B120: 5 | C120: 4742 | D120: 0 | E120: 0 | F120: 201692.55 | G120: 201327.67 | H120: COMPLETE
A121: 2D FINAL | B121: Rows covered | C121: Positive-sale rows | D121: Sales | E121: Total Cost | F121: Agent Commission | G121: Exceptions | H121: Status
A122: Calculation engine | B122: Rows 7–8106 | C122: 4742 | D122: 5682935 | E122: 4012118.8 | F122: 150211.23 | G122: Three preserved Sales overrides; 11 inactive historical products have zero cost | H122: COMPLETE
A123: Integrity check | B123: 8,100 table rows | C123: 4742 | D123: 0 | E123: 0 | F123: 0 | G123: Visible errors 0; non-formula calculations 0 | H123: PASS
A124: Change vs Phase 0 | B124: Repaired lookup/calculation basis | D124: 0 | E124: 1059491.4 | F124: -106318.35 | G124: Intentional repair deltas; Summary currently reconciles | H124: LOGGED
A125: Next packet | B125: Post-audit remediation — Daily Sales | C125: Daily Sales!W:Z — Address, SI Price and % markup formulas | G125: Repair in controlled formula-column packets; preserve sales, cost and commission totals. Then repair Inventory legacy references and Summary/Sales Summary residual errors. | H125: READY
A127: 2E HISTORICAL REGRESSION TEST
A128: Twenty-five positive-sale records were selected coverage-first: all active months, every sales category, every agent, and the three documented discounted Sales overrides. Each record checks Sales, Total Cost and Agent Commission against its source inputs; the full-ledger controls remain live.
A130: Control | B130: Value | C130: Control | D130: Value | E130: Control | F130: Value | G130: Control | H130: Value
A131: Table rows | B131: =ROWS(#REF!) -> #REF! | C131: Positive-sale rows | D131: =COUNTIF(#REF!,">0") -> #REF! | E131: Annual Sales | F131: =SUM(#REF!) -> #REF! | G131: Annual Total Cost | H131: =SUM(#REF!) -> #REF!
A132: Annual Agent Commission | B132: =SUM(#REF!) -> #REF! | C132: Sample records | D132: =ROWS(A138:A162) -> 25 | E132: Active months covered | F132: =COUNTA(_xlfn.UNIQUE(B138:B162)) -> 1 | G132: Categories covered | H132: =COUNTA(_xlfn.UNIQUE(D138:D162)) -> 1
...

Sheet Client List
A1: CLIENT MASTER & AGENT ASSIGNMENTS — 2026
A2: Aligned to the supplied customer codes; unmatched active names are flagged for review.
A4: TOTAL ACCOUNTS | B4: 195 | C4: MATCHED | D4: 193 | E4: UNMATCHED | F4: 2 | G4: ACTIVE | H4: 195
A6: Code | B6: Customer | C6: Terms | D6: Credit Limit | E6: Status | F6: Action | G6: Assigned Agent | H6: Assignment Status | I6: Agents Found | J6: DR Count | K6: Latest Sale | L6: Total Sales | M6: Agent Commission
A7: CUS-PILI-00001 | B7: 1984 CONSTRUCTIONS SERVICES | C7: — | D7: 0 | E7: Active | F7: Edit / Deactivate | G7: Store | H7: ASSIGNED | I7: Store | J7: 1 | K7: 46126 | L7: 2500 | M7: 0
A8: CUS-PILI-00002 | B8: 2RK AIRCON SERVICES | C8: — | D8: 0 | E8: Active | F8: Edit / Deactivate | G8: Store | H8: ASSIGNED | I8: Store | J8: 1 | K8: 46213 | L8: 470 | M8: 0
A9: CUS-PILI-00003 | B9: 3JE | C9: — | D9: 0 | E9: Active | F9: Edit / Deactivate | G9: Store | H9: ASSIGNED | I9: Store | J9: 1 | K9: 46127 | L9: 900 | M9: 0
A10: CUS-PILI-00004 | B10: 4ER | C10: — | D10: 0 | E10: Active | F10: Edit / Deactivate | G10: Store | H10: ASSIGNED | I10: Store | J10: 2 | K10: 46218 | L10: 5034 | M10: 0
A11: CUS-PILI-00005 | B11: 52ND WIND INC | C11: — | D11: 0 | E11: Active | F11: Edit / Deactivate | G11: Store | H11: ASSIGNED | I11: Store | J11: 3 | K11: 46265 | L11: 12855 | M11: 0
A12: CUS-PILI-00006 | B12: 6 JAM AUTOCARE CENTER/ ADAM ANDEO | C12: — | D12: 0 | E12: Active | F12: Edit / Deactivate | G12: Store | H12: ASSIGNED | I12: Store | J12: 3 | K12: 46240 | L12: 5000 | M12: 532.95
A13: CUS-PILI-00007 | B13: 7 MAJESTIC AC | C13: — | D13: 0 | E13: Active | F13: Edit / Deactivate | G13: Store | H13: ASSIGNED | I13: Store | J13: 1 | K13: 46108 | L13: 2700 | M13: 0
A14: CUS-PILI-00009 | B14: ABEL | C14: — | D14: 0 | E14: Active | F14: Edit / Deactivate | G14: Store | H14: ASSIGNED | I14: Store | J14: 17 | K14: 46265 | L14: 23800 | M14: 0
A15: CUS-PILI-00015 | B15: AGAPOR AIRCONDITIONING | C15: — | D15: 0 | E15: Active | F15: Edit / Deactivate | G15: Bro. Jr | H15: ASSIGNED | I15: Bro. Jr | J15: 1 | K15: 46076 | L15: 900 | M15: 115.5
A16: CUS-PILI-00018 | B16: AIRCOLD SERVE | C16: — | D16: 0 | E16: Active | F16: Edit / Deactivate | G16: Store | H16: ASSIGNED | I16: Store | J16: 1 | K16: 46259 | L16: 3810 | M16: 0
A17: CUS-PILI-00019 | B17: AIRCON BOY | C17: — | D17: 0 | E17: Active | F17: Edit / Deactivate | G17: Store | H17: ASSIGNED | I17: Store | J17: 2 | K17: 46079 | L17: 899 | M17: 0
A18: CUS-PILI-00022 | B18: AirCooled | C18: — | D18: 0 | E18: Active | F18: Edit / Deactivate | G18: Store | H18: ASSIGNED | I18: Store | J18: 23 | K18: 46291 | L18: 38442 | M18: 3370.2533
... A38: CUS-PILI-00057 | B38: BLUE CHIP GAMING | C38: — | D38: 0 | E38: Active | F38: Edit / Deactivate | G38: Store | H38: ASSIGNED | I38: Store | J38: 1 | K38: 46046 | L38: 635 | M38: 0
B39: BOBBY ARCABOS | C39: — | D39: 0 | E39: Active | F39: Edit / Deactivate | G39: Store | H39: ASSIGNED | I39: Store | J39: 2 | K39: 46226 | L39: 71100 | M39: 2871
A40: CUS-PILI-00059 | B40: BONG CANTILLAN | C40: — | D40: 0 | E40: Active | F40: Edit / Deactivate | G40: Store | H40: ASSIGNED | I40: Store | J40: 16 | K40: 46238 | L40: 230594 | M40: 0
A41: CUS-PILI-00061 | B41: BRIGHT AIRE | C41: — | D41: 0 | E41: Active | F41: Edit / Deactivate | G41: Store | H41: ASSIGNED | I41: Store | J41: 1 | K41: 46183 | L41: 50 | M41: 0
A42: CUS-PILI-00062 | B42: BRYAN CAR AIRCON | C42: — | D42: 0 | E42: Active | F42: Edit / Deactivate | G42: Store | H42: ASSIGNED | I42: Store | J42: 3 | K42: 46209 | L42: 17292 | M42: 0
A43: CUS-PILI-00063 | B43: BUBOY CORONEL | C43: — | D43: 0 | E43: Active | F43: Edit / Deactivate | G43: Store | H43: ASSIGNED | I43: Store | J43: 13 | K43: 46269 | L43: 102995 | M43: 0
A44: CUS-PILI-00064 | B44: CAA MECHANICAL ENGINEERING SERVICES | C44: — | D44: 0 | E44: Active | F44: Edit / Deactivate | G44: Store | H44: ASSIGNED | I44: Store | J44: 1 | K44: 46172 | L44: 3000 | M44: 0
A45: CUS-PILI-00065 | B45: CAPILI | C45: — | D45: 0 | E45: Active | F45: Edit / Deactivate | G45: Ptr. Rod | H45: ASSIGNED | I45: Ptr. Rod | J45: 7 | K45: 46211 | L45: 15530 | M45: 1515.3
A46: CUS-PILI-00066 | B46: CAR AIRCON HOME SERVICE | C46: — | D46: 0 | E46: Active | F46: Edit / Deactivate | G46: Store | H46: ASSIGNED | I46: Store | J46: 1 | K46: 46185 | L46: 1220 | M46: 0
A47: CUS-PILI-00067 | B47: CEMTRANS | C47: — | D47: 0 | E47: Active | F47: Edit / Deactivate | G47: Store | H47: ASSIGNED | I47: Store | J47: 2 | K47: 46062 | L47: 1350 | M47: 0
A48: CUS-PILI-00068 | B48: CGM | C48: — | D48: 0 | E48: Active | F48: Edit / Deactivate | G48: Store | H48: ASSIGNED | I48: Store | J48: 1 | K48: 46258 | L48: 2336 | M48: 0
A49: CUS-PILI-00069 | B49: CHIE ESTRELLA | C49: — | D49: 0 | E49: Active | F49: Edit / Deactivate | G49: Store | H49: ASSIGNED | I49: Store | J49: 5 | K49: 46288 | L49: 19950 | M49: 0
A50: CUS-PILI-00071 | B50: CHRISTIAN ESTANISLAO | C50: — | D50: 0 | E50: Active | F50: Edit / Deactivate | G50: Store | H50: ASSIGNED | I50: Store | J50: 1 | K50: 46193 | L50: 600 | M50: 0
A51: CUS-PILI-00072 | B51: CHROME EDGE | C51: — | D51: 0 | E51: Active | F51: Edit / Deactivate | G51: Store | H51: ASSIGNED | I51: Store | J51: 33 | K51: 46295 | L51: 81601 | M51: 0
... A159: CUS-PILI-00255 | B159: PHOMAR CONSTRUCTION SERVICES INC | C159: — | D159: 0 | E159: Active | F159: Edit / Deactivate | G159: STORE | H159: ASSIGNED | I159: STORE | J159: 1 | K159: 46269 | L159: 360 | M159: 0
B160: PRIME TEC | C160: — | D160: 0 | E160: Active | F160: Edit / Deactivate | G160: Store | H160: ASSIGNED | I160: Store | J160: 1 | K160: 46203 | L160: 3000 | M160: 238.5
A161: CUS-PILI-00260 | B161: PRO TECH | C161: — | D161: 0 | E161: Active | F161: Edit / Deactivate | G161: Store | H161: ASSIGNED | I161: Store | J161: 1 | K161: 46192 | L161: 375 | M161: 0
A162: CUS-PILI-00261 | B162: PRSC | C162: — | D162: 0 | E162: Active | F162: Edit / Deactivate | G162: Store | H162: ASSIGNED | I162: Store | J162: 1 | K162: 46223 | L162: 5060 | M162: 0
A163: CUS-PILI-00263 | B163: PSYCHRO | C163: — | D163: 0 | E163: Active | F163: Edit / Deactivate | G163: Store | H163: ASSIGNED | I163: Store | J163: 7 | K163: 46260 | L163: 9367 | M163: 0
A164: CUS-PILI-00264 | B164: PSYCOOL | C164: — | D164: 0 | E164: Active | F164: Edit / Deactivate | G164: Store | H164: ASSIGNED | I164: Store | J164: 1 | K164: 46210 | L164: 350 | M164: 0
A165: CUS-PILI-00265 | B165: PUREGOLD | C165: — | D165: 0 | E165: Active | F165: Edit / Deactivate | G165: Store | H165: ASSIGNED | I165: Store | J165: 1 | K165: 46151 | L165: 660 | M165: 0
A166: CUS-PILI-00269 | B166: R&M CONSTRUCTION INC | C166: — | D166: 0 | E166: Active | F166: Edit / Deactivate | G166: Store | H166: ASSIGNED | I166: Store | J166: 1 | K166: 46254 | L166: 4768 | M166: 0
A167: CUS-PILI-00272 | B167: RAFFY LP | C167: — | D167: 0 | E167: Active | F167: Edit / Deactivate | G167: Ptr. Rod | H167: ASSIGNED | I167: Ptr. Rod | J167: 8 | K167: 46286 | L167: 18203 | M167: 1917.15
A168: CUS-PILI-00274 | B168: RAM COOL | C168: — | D168: 0 | E168: Active | F168: Edit / Deactivate | G168: Store | H168: ASSIGNED | I168: Store | J168: 3 | K168: 46153 | L168: 1015 | M168: 0
A169: CUS-PILI-00276 | B169: RAVXPERT INC | C169: — | D169: 0 | E169: Active | F169: Edit / Deactivate | G169: Store | H169: ASSIGNED | I169: Store | J169: 1 | K169: 46232 | L169: 2411 | M169: 0
A170: CUS-PILI-00278 | B170: RD AC TRADING AND SERVICES | C170: — | D170: 0 | E170: Active | F170: Edit / Deactivate | G170: Store | H170: ASSIGNED | I170: Store | J170: 1 | K170: 46150 | L170: 3375 | M170: 0
A171: CUS-PILI-00281 | B171: RELLEVE FERNAN | C171: — | D171: 0 | E171: Active | F171: Edit / Deactivate | G171: Store | H171: ASSIGNED | I171: Store | J171: 1 | K171: 46291 | L171: 850 | M171: 0
A172: CUS-PILI-00285 | B172: RHAYMAR CARBUNGCO | C172: — | D172: 0 | E172: Active | F172: Edit / Deactivate | G172: Store | H172: ASSIGNED | I172: Store | J172: 67 | K172: 46289 | L172: 247337 | M172: 0
... A201: CUS-PILI-00375 | B201: ZZ CONNECT INC | C201: — | D201: 0 | E201: Active | F201: Edit / Deactivate | G201: Bro. Rhoge | H201: ASSIGNED | I201: Bro. Rhoge | J201: 2 | K201: 46132 | L201: 9000 | M201: 1068.93
