Workbook
Name Agent_Base_Rate: 'Executive Summary'!$C$39
Name Agent_High_Rate: 'Executive Summary'!$C$41
Name Agent_High_Sales_Threshold: 'Executive Summary'!$C$40
Name Agent_Online_Rate: 'Executive Summary'!$C$42
Name Agent_Savings_Rate: 'Executive Summary'!$C$43
Name Back_Office_Rate: 'Executive Summary'!$C$51
Name Back_Office_Threshold: 'Executive Summary'!$C$50
Name Ikot_Commission_Rate: 'Executive Summary'!$C$49
Name Manager_Base_Rate: 'Executive Summary'!$C$45
Name Manager_Category_Rates: '%Comm'!$B$31:$C$42
Name Manager_High_Rate: 'Executive Summary'!$C$46
Name Manager_Sales_Threshold: 'Executive Summary'!$C$44
Name Offering_Multiplier: 'Executive Summary'!$C$53
Name Sales_Staff_Rate: 'Executive Summary'!$C$48
Name Sales_Staff_Threshold: 'Executive Summary'!$C$47
Name Tithes_Rate: 'Executive Summary'!$C$52

Sheet Executive Summary
A1: EXECUTIVE SUMMARY | G1: 📑 NAVIGATION
G2: ➤ Executive Summary
A3: Selected Month: | B3: August | G3: ➤ Commission Summary
A5: KEY FINANCIAL METRICS | D5: COMMISSION SUMMARY | G5: ➤ Instructions
A6: Total Sales (Gross) | B6: ='Back Office Commission'!D27 -> 5363118.7 | D6: Agent Commission | E6: ='Commission Summary'!C33 -> 152734.16
A7: Store Sales | B7: ='Back Office Commission'!D21 -> 2848080.1 | D7: Back Office Commission | E7: ='Commission Summary'!C34 -> 65978.196 | G7: ➤ Monthly Commission
A8: Monthly Expenses | B8: ='Back Office Commission'!D23 -> 753463.83
A9: Net Income | B9: ='Back Office Commission'!D24 -> 438780.36 | D9: TOTAL COMMISSION PAYOUT | E9: =ROUND('Commission Summary'!J17,2)+ROUND('Commission Summary'!C34,2) -> 206115.16 | G9: ➤ Back Office Commission
A10: Bottomline Before BO Commission | B10: ='Back Office Commission'!D28 -> 438780.36
A11: True Bottomline | B11: ='Back Office Commission'!D29 -> 372802.16 | G11: ➤ AgentYearlySales
G13: ➤ ItemReportsCategory
A14: BACK OFFICE BREAKDOWN | D14: AGENT SALES
A15: Manager (Bert) | B15: ='Back Office Commission'!C7 -> 33645.193 | D15: Agent Monthly Sales | E15: ='Commission Summary'!C17 -> 2481318.6 | G15: ➤ %Comm
A16: Sales Staff (Riza) | B16: ='Back Office Commission'!C8 -> 14433.67 | D16: Agent Net Sales | E16: ='Commission Summary'!D17 -> 539544.19
A17: Raymart (Ikot) | B17: ='Back Office Commission'!C10 -> 2542.02 | G17: ➤ Store Expenses
A18: Back Office Staff | B18: =SUM('Back Office Commission'!C11:C15) -> 10969.509
G19: ➤ Ikot Sales
A20: KEY RATIOS | B20: =B3&" performance" -> August performance | C20: Target Range | D20: Status | E20: Definition
A21: Expense Ratio (Expenses/Gross) | B21: =IFERROR('Back Office Commission'!D23/'Back Office Commission'!D27,0) -> 0.14048987 | C21: 10% - 20% | D21: =IF(AND(B21>=0.1,B21<=0.2),"✅ Good",IF(B21<0.1,"⚠️ Low","🔴 High")) -> ✅ Good | E21: Monthly Expenses ÷ Total Gross Sales. Measures operational cost efficiency. | G21: ➤ Payslip 1 - 4
A22: Net Income Margin | B22: =IFERROR('Back Office Commission'!D24/'Back Office Commission'!D27,0) -> 0.081814405 | C22: 5% - 10% | D22: =IF(AND(B22>=0.05,B22<=0.1),"✅ Good",IF(B22<0.05,"⚠️ Low","🔴 High")) -> ✅ Good | E22: Net Income ÷ Total Gross Sales. Shows profitability after all costs. | G22: ➤ Payslip 5 - 8
A23: Commission as % of Gross Sales | B23: =IFERROR('Commission Summary'!C35/'Back Office Commission'!D27,0) -> 0.040780817 | C23: 2% - 5% | D23: =IF(AND(B23>=0.02,B23<=0.05),"✅ Good",IF(B23<0.02,"⚠️ Low","🔴 High")) -> ✅ Good | E23: Total Commissions ÷ Total Gross Sales. Measures sales cost efficiency. | G23: ➤ Payslip 9 - 10
G25: ➤ Agent Expenses
A26: ASSESSMENT GUIDE
A27: Meaning | B27: Symbol | C27: Status | G27: ➤ Agent Savings
A28: Ratio is within healthy range | B28: ✅ | C28: Within Target
A29: Needs attention - below recommended level | B29: ⚠️ | C29: Below Target
A30: Needs review - may indicate inefficiency | B30: 🔴 | C30: Above Target
A32: =IF(COUNTIFS(CategoryMonthlyRecords[Period],">="&DATE(2026,'Back Office Commission'!$K$3,1),CategoryMonthlyRecords[Period],"<"&EDATE(DATE(2026,'Back Office Commission'!$K$3,1),1))>0,"📋 Month drivers aligned: "&B3,"⚠️ No category records for selected month "&B3) -> 📋 Month drivers aligned: August
A34: COMMISSION COMMAND CENTER
A35: ="Single source of truth for commission rules and live "&B3&" qualification checks. Edit yellow cells only." -> Single source of truth for commission rules and live August qualification checks. Edit yellow cells only.
A37: EDITABLE COMMISSION CONTROLS
A38: Category | B38: Control | C38: Edit Value | D38: Trigger / Applies When | E38: Calculation Basis | F38: Used By | G38: Named Reference
A39: Sales Agents | B39: Direct base rate | C39: 0.2 | D39: Paid gross sales is at or below the direct-agent threshold | E39: Net Sales (commission basis) × applicable rate | F39: Monthly Commission | G39: Agent_Base_Rate
A40: Sales Agents | B40: Direct high-sales threshold | C40: 200000 | D40: Direct paid gross sales must be greater than this amount | E40: Selects the base or high direct-agent rate | F40: Monthly Commission | G40: Agent_High_Sales_Threshold
A41: Sales Agents | B41: Direct high rate | C41: 0.3 | D41: Paid gross sales is greater than the direct-agent threshold | E41: Net Sales (commission basis) × applicable rate | F41: Monthly Commission | G41: Agent_High_Rate
A42: Sales Agents | B42: Online rate | C42: 0.2 | D42: Agent mode is online | E42: Net Sales (commission basis) × online rate | F42: Monthly Commission | G42: Agent_Online_Rate
A43: Sales Agents | B43: Savings rate | C43: 0.05 | D43: Applied after agent-specific expenses | E43: (Commission − Agent Expense) × savings rate | F43: Commission Summary | G43: Agent_Savings_Rate
A44: Manager (Bert) | B44: Category rate source | C44: %Comm!B31:C42 | D44: Match each category for the selected month | E44: (Category Gross − allocated expense) × category rate | F44: Back Office Commission | G44: Manager_Category_Rates
A45: Manager (Bert) | B45: Expense allocation | C45: Gross sales ratio | D45: Allocation pool: Monthly Expenses + Total Agent Commission | E45: Pool × Rate-Tier Gross Sales ÷ Total Gross Sales | F45: Back Office Commission
A46: Manager (Bert) | B46: Month driver | C46: Executive Summary!B3 | D46: Uses selected-month category sales and expenses | E46: Sum of category-level net commissions | F46: Back Office Commission
A47: Sales Staff (Riza) | B47: Store gross sales threshold | C47: 1500000 | D47: Store paid gross sales must be greater than this amount | E47: Store Gross − allocated expenses; allocation uses overall gross sales | F47: Back Office Commission | G47: Sales_Staff_Threshold
A48: Sales Staff (Riza) | B48: Commission rate | C48: 0.005 | D48: Only when store gross exceeds the sales-staff threshold | E48: Eligible net store basis × rate | F48: Back Office Commission | G48: Sales_Staff_Rate
A49: Raymart (Ikot) | B49: Commission rate | C49: 0.01 | D49: Applied to positive net Ikot sales | E49: (Ikot Sales − Ikot Expenses) × rate | F49: Back Office Commission | G49: Ikot_Commission_Rate
A50: Back Office Staff | B50: Bottomline threshold | C50: 300000 | D50: Pre-commission bottomline must be greater than this amount | E50: Determines whether each departmental pool is funded | F50: Back Office Commission | G50: Back_Office_Threshold
A51: Back Office Staff | B51: Department pool rate | C51: 0.01 | D51: Applied per eligible department when threshold is exceeded | E51: Pre-commission Bottomline × rate, divided among department staff | F51: Back Office Commission | G51: Back_Office_Rate
A52: Stewardship | B52: Tithes rate | C52: 0.1 | D52: Applied to true bottomline after Back Office commission | E52: True Bottomline × tithes rate | F52: Back Office Commission | G52: Tithes_Rate
A53: Stewardship | B53: Offering multiplier | C53: 1 | D53: Applied to the calculated tithes amount | E53: Tithes × multiplier; 100% means offering equals tithes | F53: Back Office Commission | G53: Offering_Multiplier
A55: LIVE QUALIFICATION & PAYOUT CHECK
A56: Commission Group | B56: Current Basis | C56: Threshold / Floor | D56: Applied Rate | E56: Current Tier / Status | F56: Current Payout | G56: Source
A57: Manager (Bert) | B57: ='Back Office Commission'!D27 -> 5363118.7 | C57: 0 | D57: =TEXT(MIN('%Comm'!C31:C42),"0.0%")&" – "&TEXT(MAX('%Comm'!C31:C42),"0.0%") -> 0.5% – 1.0% | E57: Category-based rates | F57: ='Back Office Commission'!E38 -> 33645.193 | G57: ItemReportsCategory / Store Expenses
A58: Sales Staff (Riza) | B58: ='Back Office Commission'!D21 -> 2848080.1 | C58: {=Sales_Staff_Threshold} -> 1500000 | D58: {=Sales_Staff_Rate} -> 0.005 | E58: =IF(B58>C58,"Qualifies","Does not qualify") -> Qualifies | F58: ='Back Office Commission'!E43 -> 12239.768 | G58: AgentYearlySales / allocated expenses
A59: Raymart (Ikot) | B59: ='Back Office Commission'!D25-'Back Office Commission'!D26 -> 254202 | C59: =0 -> 0 | D59: {=Ikot_Commission_Rate} -> 0.01 | E59: =IF(B59>0,"Applies to positive net sales","No positive net sales") -> Applies to positive net sales | F59: ='Back Office Commission'!E48 -> 2542.02 | G59: Ikot Summary
A60: Back Office Staff | B60: ='Back Office Commission'!D28 -> 438780.36 | C60: {=Back_Office_Threshold} -> 300000 | D60: {=Back_Office_Rate} -> 0.01 | E60: =IF(B60>C60,"Qualifies","Does not qualify") -> Qualifies | F60: ='Back Office Commission'!E56 -> 17551.214 | G60: Operating Net Income
A61: Agent Savings | B61: ='Commission Summary'!H17 -> 147280.16 | C61: =0 -> 0 | D61: {=Agent_Savings_Rate} -> 0.05 | E61: =IF(B61>0,"Applied after expenses","No positive commission") -> Applied after expenses | F61: ='Commission Summary'!I17 -> 7143.1982 | G61: Commission Summary after expenses
A62: Tithes + Offering | B62: ='Back Office Commission'!D29 -> 372802.16 | C62: =0 -> 0 | D62: {=Tithes_Rate} -> 0.1 | E62: {="Tithes "&TEXT(Tithes_Rate,"0.0%")&" + offering "&TEXT(Offering_Multiplier,"0%")&" of tithes"} -> Tithes 10.0% + offering 100% of tithes | F62: ='Back Office Commission'!D30+'Back Office Commission'!D31 -> 74560.433 | G62: True bottomline after BO commission

Sheet Sales Performance
A1: SALES PERFORMANCE & GROWTH DRIVERS
A2: Live scorecard for revenue momentum, category mix, agent productivity, margin, and collections
A3: Selected Month | B3: ='Executive Summary'!B3 -> August | C3: Period | D3: =DATE(2026,MATCH(B3,{"January","February","March","April","May","June","July","August","September","October","November","December"},0),1) -> 46235
A5: Gross Sales | C5: Net Sales | E5: Net Sales Yield | G5: MoM Gross Growth | I5: Expense Ratio | K5: Ikot Collection Rate
A6: =SUMIFS(CategoryMonthlyRecords[Gross Sales],CategoryMonthlyRecords[Period],$D$3) -> 5363118.7 | C6: =SUMIFS(CategoryMonthlyRecords[Net Sales],CategoryMonthlyRecords[Period],$D$3) -> 1192244.2 | E6: =IFERROR(C6/A6,0) -> 0.22230427 | G6: =IFERROR(A6/SUMIFS(CategoryMonthlyRecords[Gross Sales],CategoryMonthlyRecords[Period],EDATE($D$3,-1))-1,0) -> 0.059309786 | I6: =IFERROR('Executive Summary'!B8/A6,0) -> 0.14048987 | K6: =IFERROR(INDEX('Ikot Summary'!$G$11:$G$22,MATCH($B$3,'Ikot Summary'!$A$11:$A$22,0)),0) -> 0.91379998
A8: STORY IN BRIEF
A9: {="In "&B3&", gross sales were "&TEXT(A6,"₱0.00,,")&"M, "&IF(G6>=0,"up ","down ")&TEXT(ABS(G6),"0.0%")&" versus the prior month. Net sales were "&TEXT(C6,"₱0.00,,")&"M ("&TEXT(E6,"0.0%")&" of gross). The top two categories contributed "&TEXT(IFERROR(SUM(LARGE(B16:B27,{1,2}))/A6,0),"0.0%")&", and the leading agent produced "&TEXT(IFERROR(MAX(C32:C41)/SUM(C32:C41),0),"0.0%")&" of agent paid sales. Prioritize collection follow-up, reactivate zero-sales agents, and protect margin in the highest-volume categories."} -> In August, gross sales were ₱5.36M, up 5.9% versus the prior month. Net sales were ₱1.19M (22.2% of gross). The top two categories contributed 62.9%, and the leading agent produced 54.6% of agent paid sales. Prioritize collection follow-up, reactivate zero-sales agents, and protect margin in the highest-volume categories.
A13: CATEGORY PERFORMANCE | H13: GROSS SALES BY CATEGORY
A15: Category | B15: Gross Sales | C15: Sales Mix | D15: Net Sales | E15: Net Yield | F15: Growth Priority
A16: BATTERY | B16: =SUMIFS(CategoryMonthlyRecords[Gross Sales],CategoryMonthlyRecords[Period],$D$3,CategoryMonthlyRecords[Category],$A16) -> 1571000 | C16: =IFERROR(B16/$A$6,0) -> 0.29292658 | D16: =SUMIFS(CategoryMonthlyRecords[Net Sales],CategoryMonthlyRecords[Period],$D$3,CategoryMonthlyRecords[Category],$A16) -> 254356.4 | E16: =IFERROR(D16/B16,0) -> 0.16190732 | F16: =IF(B16=0,"No sales",IF(E16<10%,"Margin risk",IF(C16>=20%,"Protect & grow","Build pipeline"))) -> Protect & grow
A17: CAR AIRCON | B17: =SUMIFS(CategoryMonthlyRecords[Gross Sales],CategoryMonthlyRecords[Period],$D$3,CategoryMonthlyRecords[Category],$A17) -> 447523.27 | C17: =IFERROR(B17/$A$6,0) -> 0.083444596 | D17: =SUMIFS(CategoryMonthlyRecords[Net Sales],CategoryMonthlyRecords[Period],$D$3,CategoryMonthlyRecords[Category],$A17) -> 103451.63 | E17: =IFERROR(D17/B17,0) -> 0.2311648 | F17: =IF(B17=0,"No sales",IF(E17<10%,"Margin risk",IF(C17>=20%,"Protect & grow","Build pipeline"))) -> Build pipeline
A18: INSTALLATION MATERIALS | B18: =SUMIFS(CategoryMonthlyRecords[Gross Sales],CategoryMonthlyRecords[Period],$D$3,CategoryMonthlyRecords[Category],$A18) -> 1801410.4 | C18: =IFERROR(B18/$A$6,0) -> 0.3358886 | D18: =SUMIFS(CategoryMonthlyRecords[Net Sales],CategoryMonthlyRecords[Period],$D$3,CategoryMonthlyRecords[Category],$A18) -> 341325.57 | E18: =IFERROR(D18/B18,0) -> 0.18947685 | F18: =IF(B18=0,"No sales",IF(E18<10%,"Margin risk",IF(C18>=20%,"Protect & grow","Build pipeline"))) -> Protect & grow
A19: REFRIGERANTS | B19: =SUMIFS(CategoryMonthlyRecords[Gross Sales],CategoryMonthlyRecords[Period],$D$3,CategoryMonthlyRecords[Category],$A19) -> 320496.52 | C19: =IFERROR(B19/$A$6,0) -> 0.059759357 | D19: =SUMIFS(CategoryMonthlyRecords[Net Sales],CategoryMonthlyRecords[Period],$D$3,CategoryMonthlyRecords[Category],$A19) -> 110780.37 | E19: =IFERROR(D19/B19,0) -> 0.34565235 | F19: =IF(B19=0,"No sales",IF(E19<10%,"Margin risk",IF(C19>=20%,"Protect & grow","Build pipeline"))) -> Build pipeline
A20: PV PANELS | B20: =SUMIFS(CategoryMonthlyRecords[Gross Sales],CategoryMonthlyRecords[Period],$D$3,CategoryMonthlyRecords[Category],$A20) -> 0 | C20: =IFERROR(B20/$A$6,0) -> 0 | D20: =SUMIFS(CategoryMonthlyRecords[Net Sales],CategoryMonthlyRecords[Period],$D$3,CategoryMonthlyRecords[Category],$A20) -> 0 | E20: =IFERROR(D20/B20,0) -> 0 | F20: =IF(B20=0,"No sales",IF(E20<10%,"Margin risk",IF(C20>=20%,"Protect & grow","Build pipeline"))) -> No sales
A21: GENERAL | B21: =SUMIFS(CategoryMonthlyRecords[Gross Sales],CategoryMonthlyRecords[Period],$D$3,CategoryMonthlyRecords[Category],$A21) -> 64772.01 | C21: =IFERROR(B21/$A$6,0) -> 0.012077303 | D21: =SUMIFS(CategoryMonthlyRecords[Net Sales],CategoryMonthlyRecords[Period],$D$3,CategoryMonthlyRecords[Category],$A21) -> 18650.833 | E21: =IFERROR(D21/B21,0) -> 0.28794587 | F21: =IF(B21=0,"No sales",IF(E21<10%,"Margin risk",IF(C21>=20%,"Protect & grow","Build pipeline"))) -> Build pipeline
A22: AIRCON UNIT | B22: =SUMIFS(CategoryMonthlyRecords[Gross Sales],CategoryMonthlyRecords[Period],$D$3,CategoryMonthlyRecords[Category],$A22) -> 1058025 | C22: =IFERROR(B22/$A$6,0) -> 0.19727794 | D22: =SUMIFS(CategoryMonthlyRecords[Net Sales],CategoryMonthlyRecords[Period],$D$3,CategoryMonthlyRecords[Category],$A22) -> 342596 | E22: =IFERROR(D22/B22,0) -> 0.32380709 | F22: =IF(B22=0,"No sales",IF(E22<10%,"Margin risk",IF(C22>=20%,"Protect & grow","Build pipeline"))) -> Build pipeline
A23: TOOLS | B23: =SUMIFS(CategoryMonthlyRecords[Gross Sales],CategoryMonthlyRecords[Period],$D$3,CategoryMonthlyRecords[Category],$A23) -> 18235.76 | C23: =IFERROR(B23/$A$6,0) -> 0.0034002156 | D23: =SUMIFS(CategoryMonthlyRecords[Net Sales],CategoryMonthlyRecords[Period],$D$3,CategoryMonthlyRecords[Category],$A23) -> 4128.3059 | E23: =IFERROR(D23/B23,0) -> 0.22638519 | F23: =IF(B23=0,"No sales",IF(E23<10%,"Margin risk",IF(C23>=20%,"Protect & grow","Build pipeline"))) -> Build pipeline
A24: ELECTRICAL | B24: =SUMIFS(CategoryMonthlyRecords[Gross Sales],CategoryMonthlyRecords[Period],$D$3,CategoryMonthlyRecords[Category],$A24) -> 59985.68 | C24: =IFERROR(B24/$A$6,0) -> 0.01118485 | D24: =SUMIFS(CategoryMonthlyRecords[Net Sales],CategoryMonthlyRecords[Period],$D$3,CategoryMonthlyRecords[Category],$A24) -> 13161.94 | E24: =IFERROR(D24/B24,0) -> 0.21941803 | F24: =IF(B24=0,"No sales",IF(E24<10%,"Margin risk",IF(C24>=20%,"Protect & grow","Build pipeline"))) -> Build pipeline
A25: AIRCON PARTS | B25: =SUMIFS(CategoryMonthlyRecords[Gross Sales],CategoryMonthlyRecords[Period],$D$3,CategoryMonthlyRecords[Category],$A25) -> 20000 | C25: =IFERROR(B25/$A$6,0) -> 0.0037291735 | D25: =SUMIFS(CategoryMonthlyRecords[Net Sales],CategoryMonthlyRecords[Period],$D$3,CategoryMonthlyRecords[Category],$A25) -> 3387.622 | E25: =IFERROR(D25/B25,0) -> 0.1693811 | F25: =IF(B25=0,"No sales",IF(E25<10%,"Margin risk",IF(C25>=20%,"Protect & grow","Build pipeline"))) -> Build pipeline
A26: INVERTER | B26: =SUMIFS(CategoryMonthlyRecords[Gross Sales],CategoryMonthlyRecords[Period],$D$3,CategoryMonthlyRecords[Category],$A26) -> 0 | C26: =IFERROR(B26/$A$6,0) -> 0 | D26: =SUMIFS(CategoryMonthlyRecords[Net Sales],CategoryMonthlyRecords[Period],$D$3,CategoryMonthlyRecords[Category],$A26) -> 0 | E26: =IFERROR(D26/B26,0) -> 0 | F26: =IF(B26=0,"No sales",IF(E26<10%,"Margin risk",IF(C26>=20%,"Protect & grow","Build pipeline"))) -> No sales
A27: CONSTRUCTION | B27: =SUMIFS(CategoryMonthlyRecords[Gross Sales],CategoryMonthlyRecords[Period],$D$3,CategoryMonthlyRecords[Category],$A27) -> 1670 | C27: =IFERROR(B27/$A$6,0) -> 0.00031138599 | D27: =SUMIFS(CategoryMonthlyRecords[Net Sales],CategoryMonthlyRecords[Period],$D$3,CategoryMonthlyRecords[Category],$A27) -> 405.52101 | E27: =IFERROR(D27/B27,0) -> 0.24282695 | F27: =IF(B27=0,"No sales",IF(E27<10%,"Margin risk",IF(C27>=20%,"Protect & grow","Build pipeline"))) -> Build pipeline
A29: AGENT PRODUCTIVITY | H29: PAID SALES BY AGENT
A31: Agent | B31: Mode | C31: Paid Sales | D31: Net Sales | E31: Net Yield | F31: Coaching Priority
A32: ='Commission Summary'!A7 -> ARNOLD ORTIZ | B32: ='Commission Summary'!B7 -> direct | C32: ='Commission Summary'!C7 -> 113401 | D32: ='Commission Summary'!D7 -> 26067.4 | E32: =IFERROR(D32/C32,0) -> 0.22986923 | F32: =IF(C32=0,"Inactive",IF(E32<10%,"Low margin",IF(C32>=AVERAGEIF($C$32:$C$41,">0"),"Scale","Develop"))) -> Develop
A33: ='Commission Summary'!A8 -> JENNIFER DUM-OGAN - ONLINE | B33: ='Commission Summary'!B8 -> online | C33: ='Commission Summary'!C8 -> 23556.88 | D33: ='Commission Summary'!D8 -> 7491.37 | E33: =IFERROR(D33/C33,0) -> 0.31801198 | F33: =IF(C33=0,"Inactive",IF(E33<10%,"Low margin",IF(C33>=AVERAGEIF($C$32:$C$41,">0"),"Scale","Develop"))) -> Develop
A34: ='Commission Summary'!A9 -> JOVY VILLANUEVA | B34: ='Commission Summary'!B9 -> direct | C34: ='Commission Summary'!C9 -> 33922 | D34: ='Commission Summary'!D9 -> 6104.24 | E34: =IFERROR(D34/C34,0) -> 0.1799493 | F34: =IF(C34=0,"Inactive",IF(E34<10%,"Low margin",IF(C34>=AVERAGEIF($C$32:$C$41,">0"),"Scale","Develop"))) -> Develop
A35: ='Commission Summary'!A10 -> MARIVIC BRILLANTES | B35: ='Commission Summary'!B10 -> direct | C35: ='Commission Summary'!C10 -> 0 | D35: ='Commission Summary'!D10 -> 0 | E35: =IFERROR(D35/C35,0) -> 0 | F35: =IF(C35=0,"Inactive",IF(E35<10%,"Low margin",IF(C35>=AVERAGEIF($C$32:$C$41,">0"),"Scale","Develop"))) -> Inactive
A36: ='Commission Summary'!A11 -> MICHAEL PLAZA | B36: ='Commission Summary'!B11 -> direct | C36: ='Commission Summary'!C11 -> 817590.78 | D36: ='Commission Summary'!D11 -> 223600.76 | E36: =IFERROR(D36/C36,0) -> 0.27348738 | F36: =IF(C36=0,"Inactive",IF(E36<10%,"Low margin",IF(C36>=AVERAGEIF($C$32:$C$41,">0"),"Scale","Develop"))) -> Scale
A37: ='Commission Summary'!A12 -> MODESTO PAG-ARIGON | B37: ='Commission Summary'!B12 -> direct | C37: ='Commission Summary'!C12 -> 0 | D37: ='Commission Summary'!D12 -> 0 | E37: =IFERROR(D37/C37,0) -> 0 | F37: =IF(C37=0,"Inactive",IF(E37<10%,"Low margin",IF(C37>=AVERAGEIF($C$32:$C$41,">0"),"Scale","Develop"))) -> Inactive
A38: ='Commission Summary'!A13 -> MODESTO PAG-ARIGON - ONLINE | B38: ='Commission Summary'!B13 -> online | C38: ='Commission Summary'!C13 -> 48611.93 | D38: ='Commission Summary'!D13 -> 15357.74 | E38: =IFERROR(D38/C38,0) -> 0.31592533 | F38: =IF(C38=0,"Inactive",IF(E38<10%,"Low margin",IF(C38>=AVERAGEIF($C$32:$C$41,">0"),"Scale","Develop"))) -> Develop
A39: ='Commission Summary'!A14 -> RAMONITO VILLANUEVA - ONLINE | B39: ='Commission Summary'!B14 -> online | C39: ='Commission Summary'!C14 -> 44225.99 | D39: ='Commission Summary'!D14 -> 14231.88 | E39: =IFERROR(D39/C39,0) -> 0.32179901 | F39: =IF(C39=0,"Inactive",IF(E39<10%,"Low margin",IF(C39>=AVERAGEIF($C$32:$C$41,">0"),"Scale","Develop"))) -> Develop
A40: ='Commission Summary'!A15 -> ROCKY DELA PENA | B40: ='Commission Summary'!B15 -> direct | C40: ='Commission Summary'!C15 -> 45600 | D40: ='Commission Summary'!D15 -> 22038.31 | E40: =IFERROR(D40/C40,0) -> 0.48329627 | F40: =IF(C40=0,"Inactive",IF(E40<10%,"Low margin",IF(C40>=AVERAGEIF($C$32:$C$41,">0"),"Scale","Develop"))) -> Develop
A41: ='Commission Summary'!A16 -> ROD SANTIAGO | B41: ='Commission Summary'!B16 -> direct | C41: ='Commission Summary'!C16 -> 1354410 | D41: ='Commission Summary'!D16 -> 224652.49 | E41: =IFERROR(D41/C41,0) -> 0.16586742 | F41: =IF(C41=0,"Inactive",IF(E41<10%,"Low margin",IF(C41>=AVERAGEIF($C$32:$C$41,">0"),"Scale","Develop"))) -> Scale
A45: 3-MONTH SALES WINDOW | H45: GROSS VS NET SALES TREND
A47: Period | B47: Gross Sales | C47: Net Sales
A48: =EDATE($D$3,ROW()-49) -> 46204 | B48: =SUMIFS(CategoryMonthlyRecords[Gross Sales],CategoryMonthlyRecords[Period],A48) -> 5062842.5 | C48: =SUMIFS(CategoryMonthlyRecords[Net Sales],CategoryMonthlyRecords[Period],A48) -> 800129.45
A49: =EDATE($D$3,ROW()-49) -> 46235 | B49: =SUMIFS(CategoryMonthlyRecords[Gross Sales],CategoryMonthlyRecords[Period],A49) -> 5363118.7 | C49: =SUMIFS(CategoryMonthlyRecords[Net Sales],CategoryMonthlyRecords[Period],A49) -> 1192244.2
A50: =EDATE($D$3,ROW()-49) -> 46266 | B50: =SUMIFS(CategoryMonthlyRecords[Gross Sales],CategoryMonthlyRecords[Period],A50) -> 0 | C50: =SUMIFS(CategoryMonthlyRecords[Net Sales],CategoryMonthlyRecords[Period],A50) -> 0
A51: The right-hand month reflects records entered to date and may be partial.
A52: SALES ACTIONS
A53: Driver | B53: Signal | D53: Recommended Action
A54: Momentum | B54: =TEXT($G$6,"0.0%")&" vs prior month" -> 5.9% vs prior month | D54: Recover the prior-month gap with weekly category targets and pipeline reviews.
A55: Category mix | B55: {=TEXT(IFERROR(SUM(LARGE($B$16:$B$27,{1,2}))/$A$6,0),"0.0%")&" from top 2 categories"} -> 62.9% from top 2 categories | D55: Defend Refrigerants and Installation Materials while building secondary categories.
A56: Agent coverage | B56: =COUNTIF($C$32:$C$41,0)&" agents with zero sales" -> 2 agents with zero sales | D56: Reallocate leads and coach inactive agents with weekly activity targets.
A57: Collections | B57: =TEXT($K$6,"0.0%")&" Ikot collection rate" -> 91.4% Ikot collection rate | D57: Prioritize overdue follow-up and track collections separately from booked sales.
A58: Margin | B58: =TEXT($E$6,"0.0%")&" net sales yield" -> 22.2% net sales yield | D58: Review low-yield categories and deals before discounting or approving commissions.

Sheet Commission Summary
A1: COMMISSION SUMMARY | D1: ➤ Executive Summary
A3: August | B3: ='Executive Summary'!B3 -> August
A5: AGENT COMMISSION
A6: Agent | B6: Mode | C6: Paid Gross Sales | D6: Net Sales (Commission Basis) | E6: Comm % | F6: Commission | G6: Expense | H6: Commission after Expense | I6: 5% Savings | J6: Final Commission
A7: ='Monthly Commission'!B6 -> ARNOLD ORTIZ | B7: ='Monthly Commission'!C6 -> direct | C7: ='Monthly Commission'!D6 -> 113401 | D7: ='Monthly Commission'!E6 -> 26067.4 | E7: ='Monthly Commission'!F6 -> 0.2 | F7: ='Monthly Commission'!G6 -> 5213.48 | G7: =IFERROR(INDEX('Agent Expense'!$B$5:$M$14,MATCH(A7,'Agent Expense'!$A$5:$A$14,0),MATCH($A$3,'Agent Expense'!$B$4:$M$4,0)),0) -> 2454 | H7: =F7-G7 -> 2759.48 | I7: =H7*Agent_Savings_Rate -> 137.974 | J7: =H7-I7 -> 2621.506
A8: ='Monthly Commission'!B7 -> JENNIFER DUM-OGAN - ONLINE | B8: ='Monthly Commission'!C7 -> online | C8: ='Monthly Commission'!D7 -> 23556.88 | D8: ='Monthly Commission'!E7 -> 7491.37 | E8: ='Monthly Commission'!F7 -> 0.2 | F8: ='Monthly Commission'!G7 -> 1498.274 | G8: =IFERROR(INDEX('Agent Expense'!$B$5:$M$14,MATCH(A8,'Agent Expense'!$A$5:$A$14,0),MATCH($A$3,'Agent Expense'!$B$4:$M$4,0)),0) -> 1000 | H8: =F8-G8 -> 498.274 | J8: =H8-I8 -> 498.274
A9: ='Monthly Commission'!B8 -> JOVY VILLANUEVA | B9: ='Monthly Commission'!C8 -> direct | C9: ='Monthly Commission'!D8 -> 33922 | D9: ='Monthly Commission'!E8 -> 6104.24 | E9: ='Monthly Commission'!F8 -> 0.2 | F9: ='Monthly Commission'!G8 -> 1220.848 | G9: =IFERROR(INDEX('Agent Expense'!$B$5:$M$14,MATCH(A9,'Agent Expense'!$A$5:$A$14,0),MATCH($A$3,'Agent Expense'!$B$4:$M$4,0)),0) -> 0 | H9: =F9-G9 -> 1220.848 | I9: =H9*Agent_Savings_Rate -> 61.0424 | J9: =H9-I9 -> 1159.8056
A10: ='Monthly Commission'!B9 -> MARIVIC BRILLANTES | B10: ='Monthly Commission'!C9 -> direct | C10: ='Monthly Commission'!D9 -> 0 | D10: ='Monthly Commission'!E9 -> 0 | E10: ='Monthly Commission'!F9 | F10: ='Monthly Commission'!G9 -> 0 | G10: =IFERROR(INDEX('Agent Expense'!$B$5:$M$14,MATCH(A10,'Agent Expense'!$A$5:$A$14,0),MATCH($A$3,'Agent Expense'!$B$4:$M$4,0)),0) -> 0 | H10: =F10-G10 -> 0 | I10: =H10*Agent_Savings_Rate -> 0 | J10: =H10-I10 -> 0
A11: ='Monthly Commission'!B10 -> MICHAEL PLAZA | B11: ='Monthly Commission'!C10 -> direct | C11: ='Monthly Commission'!D10 -> 817590.78 | D11: ='Monthly Commission'!E10 -> 223600.76 | E11: ='Monthly Commission'!F10 -> 0.3 | F11: ='Monthly Commission'!G10 -> 67080.228 | G11: =IFERROR(INDEX('Agent Expense'!$B$5:$M$14,MATCH(A11,'Agent Expense'!$A$5:$A$14,0),MATCH($A$3,'Agent Expense'!$B$4:$M$4,0)),0) -> 0 | H11: =F11-G11 -> 67080.228 | I11: =H11*Agent_Savings_Rate -> 3354.0114 | J11: =H11-I11 -> 63726.217
A12: ='Monthly Commission'!B11 -> MODESTO PAG-ARIGON | B12: ='Monthly Commission'!C11 -> direct | C12: ='Monthly Commission'!D11 -> 0 | D12: ='Monthly Commission'!E11 -> 0 | E12: ='Monthly Commission'!F11 | F12: ='Monthly Commission'!G11 -> 0 | G12: =IFERROR(INDEX('Agent Expense'!$B$5:$M$14,MATCH(A12,'Agent Expense'!$A$5:$A$14,0),MATCH($A$3,'Agent Expense'!$B$4:$M$4,0)),0) -> 0 | H12: =F12-G12 -> 0 | I12: =H12*Agent_Savings_Rate -> 0 | J12: =H12-I12 -> 0
A13: ='Monthly Commission'!B12 -> MODESTO PAG-ARIGON - ONLINE | B13: ='Monthly Commission'!C12 -> online | C13: ='Monthly Commission'!D12 -> 48611.93 | D13: ='Monthly Commission'!E12 -> 15357.74 | E13: ='Monthly Commission'!F12 -> 0.2 | F13: ='Monthly Commission'!G12 -> 3071.548 | G13: =IFERROR(INDEX('Agent Expense'!$B$5:$M$14,MATCH(A13,'Agent Expense'!$A$5:$A$14,0),MATCH($A$3,'Agent Expense'!$B$4:$M$4,0)),0) -> 1000 | H13: =F13-G13 -> 2071.548 | J13: =H13-I13 -> 2071.548
A14: ='Monthly Commission'!B13 -> RAMONITO VILLANUEVA - ONLINE | B14: ='Monthly Commission'!C13 -> online | C14: ='Monthly Commission'!D13 -> 44225.99 | D14: ='Monthly Commission'!E13 -> 14231.88 | E14: ='Monthly Commission'!F13 -> 0.2 | F14: ='Monthly Commission'!G13 -> 2846.376 | G14: =IFERROR(INDEX('Agent Expense'!$B$5:$M$14,MATCH(A14,'Agent Expense'!$A$5:$A$14,0),MATCH($A$3,'Agent Expense'!$B$4:$M$4,0)),0) -> 1000 | H14: =F14-G14 -> 1846.376 | J14: =H14-I14 -> 1846.376
A15: ='Monthly Commission'!B14 -> ROCKY DELA PENA | B15: ='Monthly Commission'!C14 -> direct | C15: ='Monthly Commission'!D14 -> 45600 | D15: ='Monthly Commission'!E14 -> 22038.31 | E15: ='Monthly Commission'!F14 -> 0.2 | F15: ='Monthly Commission'!G14 -> 4407.662 | G15: =IFERROR(INDEX('Agent Expense'!$B$5:$M$14,MATCH(A15,'Agent Expense'!$A$5:$A$14,0),MATCH($A$3,'Agent Expense'!$B$4:$M$4,0)),0) -> 0 | H15: =F15-G15 -> 4407.662 | I15: =H15*Agent_Savings_Rate -> 220.3831 | J15: =H15-I15 -> 4187.2789
A16: ='Monthly Commission'!B15 -> ROD SANTIAGO | B16: ='Monthly Commission'!C15 -> direct | C16: ='Monthly Commission'!D15 -> 1354410 | D16: ='Monthly Commission'!E15 -> 224652.49 | E16: ='Monthly Commission'!F15 -> 0.3 | F16: ='Monthly Commission'!G15 -> 67395.747 | G16: =IFERROR(INDEX('Agent Expense'!$B$5:$M$14,MATCH(A16,'Agent Expense'!$A$5:$A$14,0),MATCH($A$3,'Agent Expense'!$B$4:$M$4,0)),0) -> 0 | H16: =F16-G16 -> 67395.747 | I16: =H16*Agent_Savings_Rate -> 3369.7873 | J16: =H16-I16 -> 64025.96
A17: ='Monthly Commission'!B16 -> TOTAL | B17: ='Monthly Commission'!C16 -> 0 | C17: ='Monthly Commission'!D16 -> 2481318.6 | D17: ='Monthly Commission'!E16 -> 539544.19 | E17: ='Monthly Commission'!F16 -> 0.28307999 | F17: ='Monthly Commission'!G16 -> 152734.16 | G17: =SUM(G7:G16) -> 5454 | H17: =SUM(H7:H16) -> 147280.16 | I17: =SUM(I7:I16) -> 7143.1982 | J17: =SUM(J7:J16) -> 140136.96
A19: BACK OFFICE COMMISSION
A20: Recipient(s) | B20: Category | C20: Commission
A21: ='Back Office Commission'!A7 -> Bert | B21: ='Back Office Commission'!B7 -> Manager | C21: ='Back Office Commission'!C7 -> 33645.193
A22: ='Back Office Commission'!A8 -> Riza | B22: ='Back Office Commission'!B8 -> Sales Staff + Admin | C22: ='Back Office Commission'!C8 -> 14433.67
A23: ='Back Office Commission'!A9 -> Shiena | B23: ='Back Office Commission'!B9 -> Purchasing | C23: ='Back Office Commission'!C9 -> 4387.8036
A24: ='Back Office Commission'!A10 -> Raymart | B24: ='Back Office Commission'!B10 -> Raymart (Ikot) | C24: ='Back Office Commission'!C10 -> 2542.02
A25: ='Back Office Commission'!A11 -> Glydal | B25: ='Back Office Commission'!B11 -> Admin | C25: ='Back Office Commission'!C11 -> 2193.9018
A26: ='Back Office Commission'!A12 -> Vincent | B26: ='Back Office Commission'!B12 -> Logistics | C26: ='Back Office Commission'!C12 -> 1462.6012
A27: ='Back Office Commission'!A13 -> Jojo | B27: ='Back Office Commission'!B13 -> Logistics | C27: ='Back Office Commission'!C13 -> 1462.6012
A28: ='Back Office Commission'!A14 -> Mark | B28: ='Back Office Commission'!B14 -> Logistics | C28: ='Back Office Commission'!C14 -> 1462.6012
A29: ='Back Office Commission'!A15 -> Rod | B29: ='Back Office Commission'!B15 -> Marketing | C29: ='Back Office Commission'!C15 -> 4387.8036
A30: ='Back Office Commission'!A16 -> GRAND TOTAL | B30: ='Back Office Commission'!B16 -> 0 | C30: =SUM(C21:C29) -> 65978.196
A32: COMBINED TOTALS
A33: Agent Commission Total | C33: =F17 -> 152734.16
A34: Back Office Commission Total | C34: =C30 -> 65978.196
A35: GRAND TOTAL | C35: =ROUND(C33,2)+ROUND(C34,2) -> 218712.36

Sheet Instructions
A1: COMMISSION SYSTEM - USER GUIDE | B1: ➤ Executive Summary
A3: 1. SYSTEM OVERVIEW
A4: This workbook calculates commissions for ISHABELLA AIRCON AND REFRIGERATION PARTS TRADING.
A5: It covers two types of commissions:
A6: • Sales Agents (field agents who sell products)
A7: • Back Office Staff (manager, admin, logistics, etc.)
A9: 2. HOW TO USE
A11: Step 1: Select the Month
A12: • Go to the Executive Summary sheet (first tab)
A13: • Change cell B3 to the desired month (dropdown: January-December)
A14: • All calculations across all sheets will automatically update
A15: • Note: Monthly Commission and Back Office Commission sheets reference this selection
A17: Step 2: Review Key Metrics
... A29: SALES AGENTS (Monthly Commission sheet)
A30: =" • Direct Agents: "&TEXT(Agent_Base_Rate,"0%")&" when paid gross sales ≤ "&TEXT(Agent_High_Sales_Threshold,"₱#,##0")&"; "&TEXT(Agent_High_Rate,"0%")&" when above it" -> • Direct Agents: 20% when paid gross sales ≤ ₱200,000; 30% when above it
A31: =" • Online Agents: "&TEXT(Agent_Online_Rate,"0%")&" from the Executive Summary command center" -> • Online Agents: 20% from the Executive Summary command center
A32: • Commission amount is calculated from Net Sales × applicable rate
A34: MANAGER (Bert)
A35: • Manager commission uses the category rates in %Comm!B31:C42.
A36: • Monthly expenses and total agent commission are combined into one deduction pool.
A37: • Allocated deduction = (Monthly Expenses + Agent Commission) × Category Gross Sales ÷ Total Gross Sales.
A38: • Manager commission = (Category Gross Sales − Allocated Deduction) × matching category rate, summed across categories.
A39: SALES STAFF (Riza)
A40: =" • "&TEXT(Sales_Staff_Rate,"0.0%")&" if Store gross sales exceed "&TEXT(Sales_Staff_Threshold,"₱#,##0") -> • 0.5% if Store gross sales exceed ₱1,500,000
A41: • Net basis = Store Gross Sales - allocated monthly expenses
A42: • Allocated expenses = Monthly Expenses × Store Gross Sales ÷ Overall Monthly Sales (paid and unpaid from ItemReportsCategory)
A44: RAYMART (Ikot Sales)
A45: =" • "&TEXT(Ikot_Commission_Rate,"0.0%")&" of Net Ikot Sales (Ikot Sales - Ikot Expenses) for the month" -> • 1.0% of Net Ikot Sales (Ikot Sales - Ikot Expenses) for the month
A47: BACK OFFICE STAFF
A48: =" • Each department receives "&TEXT(Back_Office_Rate,"0.0%")&" of pre-commission Bottomline if it exceeds "&TEXT(Back_Office_Threshold,"₱#,##0") -> • Each department receives 1.0% of pre-commission Bottomline if it exceeds ₱300,000
A49: • Applies to: Purchasing (Shiena), Admin (Glydal, Riza), Logistics (Vincent, Jojo, Mark), Marketing (Rod)
A50: =" • If Bottomline before Back Office commission is ≤ "&TEXT(Back_Office_Threshold,"₱#,##0")&", no commission is paid under this category" -> • If Bottomline before Back Office commission is ≤ ₱300,000, no commission is paid under this category
A52: 4. CURRENT WORKBOOK STRUCTURE
A53: Sheet | B53: Purpose | C53: Primary Inputs
A54: Executive Summary | B54: Master month selector and management dashboard | C54: Executive Summary!B3
A55: Commission Summary | B55: Combined agent and Back Office payout report | C55: Monthly Commission; Back Office Commission
A56: Monthly Commission | B56: Agent commission from paid gross sales | C56: AgentYearlySales
A57: Back Office Commission | B57: Manager, Sales Staff, Raymart, and department commissions | C57: ItemReportsCategory; Store Expenses; Ikot Summary
A58: AgentYearlySales | B58: Monthly paid sales and historical agent records | C58: Manual/imported sales records
A59: ItemReportsCategory | B59: Overall paid and unpaid sales by category | C59: Monthly category report
A60: %Comm | B60: Commission-rate reference | C60: Current approved rules
A61: Store Expenses | B61: Monthly operating expenses, including recurring bad-debt repayment | C61: Expense entries; ₱90,000 monthly Bad Debt Repayment
A62: Ikot Sales | B62: Detailed Ikot transactions | C62: Sales and collection entries
A63: Ikot Summary | B63: Ikot monthly and agent summaries | C63: Ikot Sales
A65: 5. STORE EXPENSES & BAD DEBT REPAYMENT
A66: • Bad Debt Repayment is recorded in Store Expenses at ₱90,000 every month (₱1,080,000 annualized).
A67: • It is included in the monthly TOTAL and therefore reduces Operating Net Income and the true Bottomline.
A68: • It also reduces the Manager and Sales Staff commission bases because both formulas use Monthly Expenses.
A69: • Update the Store Expenses row if the scheduled repayment amount changes.
A70: 6. CURRENT CALCULATION FLOW
A71: Agent Commission | B71: Net Sales × applicable agent rate | C71: =TEXT(Agent_Base_Rate,"0%")&"/"&TEXT(Agent_High_Rate,"0%")&" direct tiers; "&TEXT(Agent_Online_Rate,"0%")&" online" -> 20%/30% direct tiers; 20% online
A72: Manager | B72: (Overall ItemReports Gross Sales - Monthly Expenses) × tier rate | C72: ="At least "&TEXT(Manager_Sales_Threshold,"₱#,##0")&": "&TEXT(Manager_High_Rate,"0.0%")&"; otherwise "&TEXT(Manager_Base_Rate,"0.0%") -> At least %Comm!B31:C42: Executive Summary!B3; otherwise Gross sales ratio
A73: Sales Staff | B73: (Store Gross - proportional expense allocation) × rate | C73: ="Only if Store Gross > "&TEXT(Sales_Staff_Threshold,"₱#,##0")&"; rate "&TEXT(Sales_Staff_Rate,"0.0%") -> Only if Store Gross > ₱1,500,000; rate 0.5%
A74: Raymart | B74: (Ikot Sales - Ikot Expenses) × rate | C74: ="Selected month rate: "&TEXT(Ikot_Commission_Rate,"0.0%") -> Selected month rate: 1.0%
A75: Back Office Staff | B75: Departmental pool from pre-commission Bottomline | C75: ="Pool "&TEXT(Back_Office_Rate,"0.0%")&" only if Bottomline > "&TEXT(Back_Office_Threshold,"₱#,##0") -> Pool 1.0% only if Bottomline > ₱300,000
A76: True Bottomline | B76: Operating Net Income - total Back Office commission | C76: Displayed in Executive Summary
A77: Tithes / Offering | B77: True Bottomline × tithes rate; Offering × multiplier | C77: ="Tithes "&TEXT(Tithes_Rate,"0.0%")&"; Offering "&TEXT(Offering_Multiplier,"0%")&" of tithes" -> Tithes 10.0%; Offering 100% of tithes
A79: 7. MONTH-END CHECKLIST
A80: 1 | B80: Select the month in Executive Summary!B3 | C80: All linked month selectors should update
A81: 2 | B81: Confirm ItemReportsCategory report title matches the selected month | C81: This sheet is a single-month imported report
A82: 3 | B82: Confirm AgentYearlySales paid gross sales | C82: Used for agent and Store gross calculations
A83: 4 | B83: Confirm Store Expenses monthly total and the ₱90,000 Bad Debt Repayment | C83: Used in Manager, Sales Staff, operating income, and Bottomline
A84: 5 | B84: Review Ikot Summary sales and expenses | C84: Used for Raymart commission
A85: 6 | B85: Review comparison differences in Monthly Commission | C85: Historical recorded values may use the previous basis
A86: 7 | B86: Review Commission Summary grand total | C86: Final payout control total
A88: 8. IMPORTANT LIMITATION
A89: ItemReportsCategory is currently a single-month report. | B89: Before changing Executive Summary!B3 to another month, replace or refresh ItemReportsCategory with that month’s report. | C89: The Executive Summary footer displays a mismatch warning.

Sheet Monthly Commission
A1: MONTHLY COMMISSION REPORT | J1: HELPER AREA
A3: Select Month: | B3: ='Executive Summary'!B3 -> August | D3: ➤ Executive Summary | J3: Month Index | K3: =MATCH(B3,{"January","February","March","April","May","June","July","August","September","October","November","December"},0) -> 8
A5: # | B5: Agent | C5: Mode | D5: Paid Gross Sales | E5: Net Sales (Commission Basis) | F5: Comm % | G5: Commission | J5: Month# | K5: Sales Col | L5: Capital Col | M5: NetSales Col | N5: Comm Col
A6: 1 | B6: ARNOLD ORTIZ | C6: direct | D6: {=IFERROR(VALUE(INDIRECT("AgentYearlySales!"&VLOOKUP($K$3,$J$6:$N$16,2,FALSE)&11)),0)} -> 113401 | E6: {=IFERROR(VALUE(INDIRECT("AgentYearlySales!"&VLOOKUP($K$3,$J$6:$N$16,4,FALSE)&11)),0)} -> 26067.4 | F6: =IF(D6=0,"",IF(LOWER(C6)="online",Agent_Online_Rate,IF(D6>Agent_High_Sales_Threshold,Agent_High_Rate,Agent_Base_Rate))) -> 0.2 | G6: =IF(E6<=0,0,E6*F6) -> 5213.48 | J6: 1 | K6: C | L6: D | M6: F | N6: H
A7: 2 | B7: JENNIFER DUM-OGAN - ONLINE | C7: online | D7: {=IFERROR(VALUE(INDIRECT("AgentYearlySales!"&VLOOKUP($K$3,$J$6:$N$16,2,FALSE)&12)),0)} -> 23556.88 | E7: {=IFERROR(VALUE(INDIRECT("AgentYearlySales!"&VLOOKUP($K$3,$J$6:$N$16,4,FALSE)&12)),0)} -> 7491.37 | F7: =IF(D7=0,"",IF(LOWER(C7)="online",Agent_Online_Rate,IF(D7>Agent_High_Sales_Threshold,Agent_High_Rate,Agent_Base_Rate))) -> 0.2 | G7: =IF(E7<=0,0,E7*F7) -> 1498.274 | J7: 2 | K7: I | L7: J | M7: L | N7: O
A8: 3 | B8: JOVY VILLANUEVA | C8: direct | D8: {=IFERROR(VALUE(INDIRECT("AgentYearlySales!"&VLOOKUP($K$3,$J$6:$N$16,2,FALSE)&13)),0)} -> 33922 | E8: {=IFERROR(VALUE(INDIRECT("AgentYearlySales!"&VLOOKUP($K$3,$J$6:$N$16,4,FALSE)&13)),0)} -> 6104.24 | F8: 0.2 | G8: =IF(E8<=0,0,E8*F8) -> 1220.848 | J8: 3 | K8: P | L8: Q | M8: S | N8: U
A9: 4 | B9: MARIVIC BRILLANTES | C9: direct | D9: {=IFERROR(VALUE(INDIRECT("AgentYearlySales!"&VLOOKUP($K$3,$J$6:$N$16,2,FALSE)&14)),0)} -> 0 | E9: {=IFERROR(VALUE(INDIRECT("AgentYearlySales!"&VLOOKUP($K$3,$J$6:$N$16,4,FALSE)&14)),0)} -> 0 | F9: =IF(D9=0,"",IF(LOWER(C9)="online",Agent_Online_Rate,IF(D9>Agent_High_Sales_Threshold,Agent_High_Rate,Agent_Base_Rate))) | G9: =IF(E9<=0,0,E9*F9) -> 0 | J9: 4 | K9: V | L9: W | M9: Y | N9: AA
A10: 5 | B10: MICHAEL PLAZA | C10: direct | D10: {=IFERROR(VALUE(INDIRECT("AgentYearlySales!"&VLOOKUP($K$3,$J$6:$N$16,2,FALSE)&15)),0)} -> 817590.78 | E10: {=IFERROR(VALUE(INDIRECT("AgentYearlySales!"&VLOOKUP($K$3,$J$6:$N$16,4,FALSE)&15)),0)} -> 223600.76 | F10: =IF(D10=0,"",IF(LOWER(C10)="online",Agent_Online_Rate,IF(D10>Agent_High_Sales_Threshold,Agent_High_Rate,Agent_Base_Rate))) -> 0.3 | G10: =IF(E10<=0,0,E10*F10) -> 67080.228 | J10: 5 | K10: AB | L10: AC | M10: AE | N10: AG
A11: 6 | B11: MODESTO PAG-ARIGON | C11: direct | D11: {=IFERROR(VALUE(INDIRECT("AgentYearlySales!"&VLOOKUP($K$3,$J$6:$N$16,2,FALSE)&16)),0)} -> 0 | E11: {=IFERROR(VALUE(INDIRECT("AgentYearlySales!"&VLOOKUP($K$3,$J$6:$N$16,4,FALSE)&16)),0)} -> 0 | F11: =IF(D11=0,"",IF(LOWER(C11)="online",Agent_Online_Rate,IF(D11>Agent_High_Sales_Threshold,Agent_High_Rate,Agent_Base_Rate))) | G11: =IF(E11<=0,0,E11*F11) -> 0 | J11: 6 | K11: AH | L11: AI | M11: AK | N11: AM
A12: 7 | B12: MODESTO PAG-ARIGON - ONLINE | C12: online | D12: {=IFERROR(VALUE(INDIRECT("AgentYearlySales!"&VLOOKUP($K$3,$J$6:$N$16,2,FALSE)&17)),0)} -> 48611.93 | E12: {=IFERROR(VALUE(INDIRECT("AgentYearlySales!"&VLOOKUP($K$3,$J$6:$N$16,4,FALSE)&17)),0)} -> 15357.74 | F12: =IF(D12=0,"",IF(LOWER(C12)="online",Agent_Online_Rate,IF(D12>Agent_High_Sales_Threshold,Agent_High_Rate,Agent_Base_Rate))) -> 0.2 | G12: =IF(E12<=0,0,E12*F12) -> 3071.548 | J12: 7 | K12: AN | L12: AO | M12: AQ | N12: AS
A13: 8 | B13: RAMONITO VILLANUEVA - ONLINE | C13: online | D13: {=IFERROR(VALUE(INDIRECT("AgentYearlySales!"&VLOOKUP($K$3,$J$6:$N$16,2,FALSE)&18)),0)} -> 44225.99 | E13: {=IFERROR(VALUE(INDIRECT("AgentYearlySales!"&VLOOKUP($K$3,$J$6:$N$16,4,FALSE)&18)),0)} -> 14231.88 | F13: =IF(D13=0,"",IF(LOWER(C13)="online",Agent_Online_Rate,IF(D13>Agent_High_Sales_Threshold,Agent_High_Rate,Agent_Base_Rate))) -> 0.2 | G13: =IF(E13<=0,0,E13*F13) -> 2846.376 | J13: 8 | K13: AT | L13: AU | M13: AW | N13: AY
A14: 9 | B14: ROCKY DELA PENA | C14: direct | D14: {=IFERROR(VALUE(INDIRECT("AgentYearlySales!"&VLOOKUP($K$3,$J$6:$N$16,2,FALSE)&19)),0)} -> 45600 | E14: {=IFERROR(VALUE(INDIRECT("AgentYearlySales!"&VLOOKUP($K$3,$J$6:$N$16,4,FALSE)&19)),0)} -> 22038.31 | F14: =IF(D14=0,"",IF(LOWER(C14)="online",Agent_Online_Rate,IF(D14>Agent_High_Sales_Threshold,Agent_High_Rate,Agent_Base_Rate))) -> 0.2 | G14: =IF(E14<=0,0,E14*F14) -> 4407.662 | J14: 9 | K14: AZ | L14: BA | M14: BC | N14: BE
A15: 10 | B15: ROD SANTIAGO | C15: direct | D15: {=IFERROR(VALUE(INDIRECT("AgentYearlySales!"&VLOOKUP($K$3,$J$6:$N$16,2,FALSE)&20)),0)} -> 1354410 | E15: {=IFERROR(VALUE(INDIRECT("AgentYearlySales!"&VLOOKUP($K$3,$J$6:$N$16,4,FALSE)&20)),0)} -> 224652.49 | F15: =IF(D15=0,"",IF(LOWER(C15)="online",Agent_Online_Rate,IF(D15>Agent_High_Sales_Threshold,Agent_High_Rate,Agent_Base_Rate))) -> 0.3 | G15: =IF(E15<=0,0,E15*F15) -> 67395.747 | J15: 10 | K15: BF | L15: BG | M15: BI | N15: BK
B16: TOTAL | D16: =SUM(D6:D15) -> 2481318.6 | E16: =SUM(E6:E15) -> 539544.19 | F16: =IFERROR(G16/E16,0) -> 0.28307999 | G16: =SUM(G6:G15) -> 152734.16 | J16: 12 | K16: BR | L16: BS | M16: BU | N16: BW
A18: COMPARISON: Calculated vs Recorded (AgentYearlySales)
A19: # | B19: Agent | C19: Mode | D19: Calculated Comm | E19: Recorded Commission | F19: Difference | G19: Status
A20: 1 | B20: ARNOLD ORTIZ | C20: direct | D20: =G6 -> 5213.48 | E20: {=IFERROR(VALUE(INDIRECT("AgentYearlySales!"&VLOOKUP($K$3,$J$6:$N$16,5,FALSE)&11)),0)} -> 5213.48 | F20: =D20-E20 -> 0 | G20: =IF(ABS(F20)<1,"✓ Match",IF(F20>0,"Underpaid","Overpaid")) -> ✓ Match
A21: 2 | B21: JENNIFER DUM-OGAN - ONLINE | C21: online | D21: =G7 -> 1498.274 | E21: {=IFERROR(VALUE(INDIRECT("AgentYearlySales!"&VLOOKUP($K$3,$J$6:$N$16,5,FALSE)&12)),0)} -> 1498.274 | F21: =D21-E21 -> 0 | G21: =IF(ABS(F21)<1,"✓ Match",IF(F21>0,"Underpaid","Overpaid")) -> ✓ Match
A22: 3 | B22: JOVY VILLANUEVA | C22: direct | D22: =G8 -> 1220.848 | E22: {=IFERROR(VALUE(INDIRECT("AgentYearlySales!"&VLOOKUP($K$3,$J$6:$N$16,5,FALSE)&13)),0)} -> 1220.848 | F22: =D22-E22 -> 0 | G22: =IF(ABS(F22)<1,"✓ Match",IF(F22>0,"Underpaid","Overpaid")) -> ✓ Match
A23: 4 | B23: MARIVIC BRILLANTES | C23: direct | D23: =G9 -> 0 | E23: {=IFERROR(VALUE(INDIRECT("AgentYearlySales!"&VLOOKUP($K$3,$J$6:$N$16,5,FALSE)&14)),0)} -> 0 | F23: =D23-E23 -> 0 | G23: =IF(ABS(F23)<1,"✓ Match",IF(F23>0,"Underpaid","Overpaid")) -> ✓ Match
A24: 5 | B24: MICHAEL PLAZA | C24: direct | D24: =G10 -> 67080.228 | E24: {=IFERROR(VALUE(INDIRECT("AgentYearlySales!"&VLOOKUP($K$3,$J$6:$N$16,5,FALSE)&15)),0)} -> 67080.228 | F24: =D24-E24 -> 0 | G24: =IF(ABS(F24)<1,"✓ Match",IF(F24>0,"Underpaid","Overpaid")) -> ✓ Match
A25: 6 | B25: MODESTO PAG-ARIGON | C25: direct | D25: =G11 -> 0 | E25: {=IFERROR(VALUE(INDIRECT("AgentYearlySales!"&VLOOKUP($K$3,$J$6:$N$16,5,FALSE)&16)),0)} -> 0 | F25: =D25-E25 -> 0 | G25: =IF(ABS(F25)<1,"✓ Match",IF(F25>0,"Underpaid","Overpaid")) -> ✓ Match
A26: 7 | B26: MODESTO PAG-ARIGON - ONLINE | C26: online | D26: =G12 -> 3071.548 | E26: {=IFERROR(VALUE(INDIRECT("AgentYearlySales!"&VLOOKUP($K$3,$J$6:$N$16,5,FALSE)&17)),0)} -> 3071.548 | F26: =D26-E26 -> 0 | G26: =IF(ABS(F26)<1,"✓ Match",IF(F26>0,"Underpaid","Overpaid")) -> ✓ Match
A27: 8 | B27: RAMONITO VILLANUEVA - ONLINE | C27: online | D27: =G13 -> 2846.376 | E27: {=IFERROR(VALUE(INDIRECT("AgentYearlySales!"&VLOOKUP($K$3,$J$6:$N$16,5,FALSE)&18)),0)} -> 2846.376 | F27: =D27-E27 -> 0 | G27: =IF(ABS(F27)<1,"✓ Match",IF(F27>0,"Underpaid","Overpaid")) -> ✓ Match
A28: 9 | B28: ROCKY DELA PENA | C28: direct | D28: =G14 -> 4407.662 | E28: {=IFERROR(VALUE(INDIRECT("AgentYearlySales!"&VLOOKUP($K$3,$J$6:$N$16,5,FALSE)&19)),0)} -> 4407.662 | F28: =D28-E28 -> 0 | G28: =IF(ABS(F28)<1,"✓ Match",IF(F28>0,"Underpaid","Overpaid")) -> ✓ Match
A29: 10 | B29: ROD SANTIAGO | C29: direct | D29: =G15 -> 67395.747 | E29: {=IFERROR(VALUE(INDIRECT("AgentYearlySales!"&VLOOKUP($K$3,$J$6:$N$16,5,FALSE)&20)),0)} -> 67395.747 | F29: =D29-E29 -> 0 | G29: =IF(ABS(F29)<1,"✓ Match",IF(F29>0,"Underpaid","Overpaid")) -> ✓ Match
B30: TOTAL | D30: =SUM(D20:D29) -> 152734.16 | E30: =SUM(E20:E29) -> 152734.16 | F30: =SUM(F20:F29) -> 0 | G30: =IF(ABS(F30)<1,"✓ Match",IF(F30>0,"Underpaid","Overpaid")) -> ✓ Match
A32: 📋 NOTES:
A33: • Agent commission is calculated from net sales using the existing rate per agent
A34: • Direct agents: 20% if monthly sales ≤ ₱199,999 | 30% if > ₱200,000

Sheet Back Office Commission
A1: BACK OFFICE COMMISSION | C1: ➤ Executive Summary
A3: Select Month: | B3: ='Executive Summary'!B3 -> August | J3: Month Index | K3: =MATCH(B3,{"January","February","March","April","May","June","July","August","September","October","November","December"},0) -> 8
A5: BACK OFFICE COMMISSION SUMMARY
A6: Recipient(s) | B6: Category | C6: Commission
A7: Bert | B7: Manager | C7: =E38 -> 33645.193
A8: Riza | B8: Sales Staff + Admin | C8: =E43+F53 -> 14433.67
A9: Shiena | B9: Purchasing | C9: =F52 -> 4387.8036
A10: Raymart | B10: Raymart (Ikot) | C10: =E48 -> 2542.02
A11: Glydal | B11: Admin | C11: =F53 -> 2193.9018
A12: Vincent | B12: Logistics | C12: =F54 -> 1462.6012
A13: Jojo | B13: Logistics | C13: =F54 -> 1462.6012
A14: Mark | B14: Logistics | C14: =F54 -> 1462.6012
A15: Rod | B15: Marketing | C15: =F55 -> 4387.8036
A16: GRAND TOTAL | C16: =SUM(C7:C15) -> 65978.196
A19: KEY METRICS FOR SELECTED MONTH | J19: Month# | K19: Sales Col | L19: Capital Col | M19: NetSales Col | N19: Comm Col
A20: Metric | B20: Source | C20: Formula | D20: Value | J20: 1 | K20: C | L20: D | M20: F | N20: H
A21: Store Gross Sales (Paid) | B21: AgentYearlySales | C21: INDIRECT | D21: {=IFERROR(VALUE(INDIRECT("AgentYearlySales!"&VLOOKUP($K$3,$J$20:$N$37,2,FALSE)&21)),0)} -> 2848080.1 | J21: 2 | K21: I | L21: J | M21: L | N21: O
A22: Overall Net Sales (Paid & Unpaid) | B22: ItemReportsCategory | C22: DIRECT | D22: =SUMIFS(CategoryMonthlyRecords[Net Sales],CategoryMonthlyRecords[Period],">="&DATE(2026,$K$3,1),CategoryMonthlyRecords[Period],"<"&EDATE(DATE(2026,$K$3,1),1)) -> 1192244.2 | J22: 3 | K22: P | L22: Q | M22: S | N22: U
A23: Monthly Expenses | B23: Store Expenses | C23: INDEX | D23: {=INDEX('Store Expenses'!D34:O34,1,K3)} -> 753463.83 | J23: 4 | K23: V | L23: W | M23: Y | N23: AA
A24: Operating Net Income | B24: Calculated | C24: Net Sales - Expenses | D24: =D22-D23 -> 438780.36 | J24: 5 | K24: AB | L24: AC | M24: AE | N24: AG
A25: Raymart Ikot Sales | B25: Ikot Summary | C25: INDEX/MATCH | D25: {=INDEX('Ikot Summary'!$B$27:$M$28,2,K3)} -> 265250 | J25: 6 | K25: AH | L25: AI | M25: AK | N25: AM
A26: Raymart Ikot Expenses | B26: Ikot Sales | C26: SUMIFS | D26: =SUMIFS('Ikot Sales'!I:I,'Ikot Sales'!A:A,"RAYMART",'Ikot Sales'!B:B,">="&DATE(2026,$K$3,1),'Ikot Sales'!B:B,"<"&EDATE(DATE(2026,$K$3,1),1)) -> 11048 | J26: 7 | K26: AN | L26: AO | M26: AQ | N26: AS
A27: Overall Gross Sales (Paid & Unpaid) | B27: ItemReportsCategory | C27: DIRECT | D27: =SUMIFS(CategoryMonthlyRecords[Gross Sales],CategoryMonthlyRecords[Period],">="&DATE(2026,$K$3,1),CategoryMonthlyRecords[Period],"<"&EDATE(DATE(2026,$K$3,1),1)) -> 5363118.7 | J27: 8 | K27: AT | L27: AU | M27: AW | N27: AY
A28: Bottomline Before Back Office Commission | B28: Calculated | C28: Operating Net Income | D28: =D24 -> 438780.36 | J28: 10 | K28: BF | L28: BG | M28: BI | N28: BK
A29: True Bottomline After Back Office Commission | B29: Calculated | C29: Pre-Comm Bottomline - BO Comm | D29: =D28-C16 -> 372802.16
A30: Tithes | B30: Calculated | C30: True Bottomline × command-center rate | D30: =D29*Tithes_Rate -> 37280.216 | J30: 11 | K30: BL | L30: BM | M30: BO | N30: BQ
A31: Offering | B31: Calculated | C31: Tithes × command-center multiplier | D31: =D30*Offering_Multiplier -> 37280.216 | J31: 12 | K31: BR | L31: BS | M31: BU | N31: BW
A34: 1. MANAGER COMMISSION — BREAKDOWN BY RATE
A35: Rate Tier | B35: Category Gross Sales | C35: Allocated Expenses + Agent Comm | D35: Net Commission Basis | E35: Commission
A36: 0.005 | B36: {=SUMPRODUCT((MONTH(CategoryMonthlyRecords[Period])=$K$3)*CategoryMonthlyRecords[Gross Sales]*(SUMIF('%Comm'!$B$31:$B$42,CategoryMonthlyRecords[Category],'%Comm'!$C$31:$C$42)=$A36))} -> 2629025 | C36: =IF($B$38=0,0,($D$23+'Commission Summary'!$C$33)*B36/$B$38) -> 444222.35 | D36: =MAX(B36-C36,0) -> 2184802.6 | E36: =D36*A36 -> 10924.013
A37: 0.01 | B37: {=SUMPRODUCT((MONTH(CategoryMonthlyRecords[Period])=$K$3)*CategoryMonthlyRecords[Gross Sales]*(SUMIF('%Comm'!$B$31:$B$42,CategoryMonthlyRecords[Category],'%Comm'!$C$31:$C$42)=$A37))} -> 2734093.7 | C37: =IF($B$38=0,0,($D$23+'Commission Summary'!$C$33)*B37/$B$38) -> 461975.64 | D37: =MAX(B37-C37,0) -> 2272118 | E37: =D37*A37 -> 22721.18
A38: TOTAL | B38: =SUM(B36:B37) -> 5363118.7 | C38: =SUM(C36:C37) -> 906198 | D38: =SUM(D36:D37) -> 4456920.7 | E38: =SUM(E36:E37) -> 33645.193
A40: 2. SALES STAFF COMMISSION
A41: Component | B41: Basis | C41: Rate | D41: Amount | E41: Commission
A42: Store Gross Sales qualification | B42: =D21 -> 2848080.1 | C42: =Sales_Staff_Rate -> 0.005 | D42: =IF(AND(D21>Sales_Staff_Threshold,D27>0),MAX(D21-(D23*D21/D27),0),0) -> 2447953.7 | E42: =D42*C42 -> 12239.768
A43: TOTAL | E43: =SUM(E42:E42) -> 12239.768
A45: 3. RAYMART COMMISSION (NET IKOT SALES)
A46: Component | B46: Basis | C46: Rate | D46: Amount | E46: Commission
A47: Raymart Net Ikot Sales | B47: =D25-D26 -> 254202 | C47: =Ikot_Commission_Rate -> 0.01 | D47: =D25-D26 -> 254202 | E47: =D47*C47 -> 2542.02
A48: TOTAL | E48: =E47 -> 2542.02
A50: 4. BACK OFFICE STAFF (BOTTOMLINE QUALIFICATION)
A51: Department | B51: Staff | C51: # Staff | D51: Qualifies? | E51: Total Comm | F51: Per Person
A52: Purchasing | B52: Shiena | C52: 1 | D52: =IF($D$28>Back_Office_Threshold,"Yes","No") -> Yes | E52: =IF(D52="Yes",$D$28*Back_Office_Rate,0) -> 4387.8036 | F52: =E52/C52 -> 4387.8036
A53: Admin | B53: Glydal, Riza | C53: 2 | D53: =IF($D$28>Back_Office_Threshold,"Yes","No") -> Yes | E53: =IF(D53="Yes",$D$28*Back_Office_Rate,0) -> 4387.8036 | F53: =E53/C53 -> 2193.9018
A54: Logistics | B54: Vincent, Jojo, Mark | C54: 3 | D54: =IF($D$28>Back_Office_Threshold,"Yes","No") -> Yes | E54: =IF(D54="Yes",$D$28*Back_Office_Rate,0) -> 4387.8036 | F54: =E54/C54 -> 1462.6012
A55: Marketing | B55: Rod | C55: 1 | D55: =IF($D$28>Back_Office_Threshold,"Yes","No") -> Yes | E55: =IF(D55="Yes",$D$28*Back_Office_Rate,0) -> 4387.8036 | F55: =E55/C55 -> 4387.8036
A56: TOTAL | C56: =SUM(C52:C55) -> 7 | E56: =SUM(E52:E55) -> 17551.214 | F56: =SUM(F52:F55) -> 12432.11
A60: 📋 NOTES:
A61: ="• Manager: "&TEXT(Manager_High_Rate,"0.0%")&" if overall gross sales ≥ "&TEXT(Manager_Sales_Threshold,"₱#,##0")&"; otherwise "&TEXT(Manager_Base_Rate,"0.0%")&", after monthly expenses" -> • Manager: Executive Summary!B3 if overall gross sales ≥ %Comm!B31:C42; otherwise Gross sales ratio, after monthly expenses
A62: ="• Sales Staff: "&TEXT(Sales_Staff_Rate,"0.0%")&" of eligible net store basis if Store gross > "&TEXT(Sales_Staff_Threshold,"₱#,##0") -> • Sales Staff: 0.5% of eligible net store basis if Store gross > ₱1,500,000
A63: ="• Raymart: "&TEXT(Ikot_Commission_Rate,"0.0%")&" of Net Ikot Sales (Ikot Sales − Ikot Expenses)" -> • Raymart: 1.0% of Net Ikot Sales (Ikot Sales − Ikot Expenses)
A64: ="• Back Office staff: "&TEXT(Back_Office_Rate,"0.0%")&" departmental pool if pre-commission Bottomline > "&TEXT(Back_Office_Threshold,"₱#,##0") -> • Back Office staff: 1.0% departmental pool if pre-commission Bottomline > ₱300,000
A65: ="• Tithes: "&TEXT(Tithes_Rate,"0.0%")&" of true Bottomline; Offering: "&TEXT(Offering_Multiplier,"0%")&" of tithes" -> • Tithes: 10.0% of true Bottomline; Offering: 100% of tithes

Sheet ItemReportsCategory
A1: MONTHLY CATEGORY RECORDS | F1: ➤ Executive Summary
A2: Recommended layout: append one row per category per month; enter only the input columns and let calculated columns update automatically.
A4: INPUTS: Period, Category, Quantity, Gross Sales, Base Cost, Add-on %, Channel, Commission Rate, Notes | CALCULATED: Add-on Amount, Capital, Markup, Agent Commission, Net Sales
A6: Period | B6: Category | C6: Quantity | D6: Gross Sales | E6: Base Cost | F6: Add-on % | G6: Add-on Amount | H6: Capital | I6: Markup | J6: Channel | K6: Commission Rate | L6: Agent Commission | M6: Net Sales | N6: Notes
A7: 46174 | B7: BATTERY | C7: 23 | D7: 1540200 | E7: 1284640 | F7: 0.01 | G7: =CategoryMonthlyRecords[[#This Row],[Base Cost]]*CategoryMonthlyRecords[[#This Row],[Add-on %]] -> 12846.4 | H7: =CategoryMonthlyRecords[[#This Row],[Base Cost]]+CategoryMonthlyRecords[[#This Row],[Add-on Amount]] -> 1297486.4 | I7: =CategoryMonthlyRecords[[#This Row],[Gross Sales]]-CategoryMonthlyRecords[[#This Row],[Capital]] -> 242713.6 | J7: Store | K7: 0 | L7: =MAX(0,CategoryMonthlyRecords[[#This Row],[Markup]]*CategoryMonthlyRecords[[#This Row],[Commission Rate]]) -> 0 | M7: =CategoryMonthlyRecords[[#This Row],[Markup]]-CategoryMonthlyRecords[[#This Row],[Agent Commission]]+CategoryMonthlyRecords[[#This Row],[Add-on Amount]] -> 255560 | N7: Imported from ItemReportsCategory
A8: 46174 | B8: CAR AIRCON | C8: 1944 | D8: 751895.6 | E8: 522676.98 | F8: 0.07 | G8: =CategoryMonthlyRecords[[#This Row],[Base Cost]]*CategoryMonthlyRecords[[#This Row],[Add-on %]] -> 36587.389 | H8: =CategoryMonthlyRecords[[#This Row],[Base Cost]]+CategoryMonthlyRecords[[#This Row],[Add-on Amount]] -> 559264.37 | I8: =CategoryMonthlyRecords[[#This Row],[Gross Sales]]-CategoryMonthlyRecords[[#This Row],[Capital]] -> 192631.23 | J8: Agent | K8: 0.15 | L8: =MAX(0,CategoryMonthlyRecords[[#This Row],[Markup]]*CategoryMonthlyRecords[[#This Row],[Commission Rate]]) -> 28894.685 | M8: =CategoryMonthlyRecords[[#This Row],[Markup]]-CategoryMonthlyRecords[[#This Row],[Agent Commission]]+CategoryMonthlyRecords[[#This Row],[Add-on Amount]] -> 200323.94 | N8: Imported from ItemReportsCategory
A9: 46174 | B9: INSTALLATION MATERIALS | C9: 5421.93 | D9: 1012643.2 | E9: 786462.09 | F9: 0.01 | G9: =CategoryMonthlyRecords[[#This Row],[Base Cost]]*CategoryMonthlyRecords[[#This Row],[Add-on %]] -> 7864.6209 | H9: =CategoryMonthlyRecords[[#This Row],[Base Cost]]+CategoryMonthlyRecords[[#This Row],[Add-on Amount]] -> 794326.71 | I9: =CategoryMonthlyRecords[[#This Row],[Gross Sales]]-CategoryMonthlyRecords[[#This Row],[Capital]] -> 218316.48 | J9: Agent | K9: 0.15 | L9: =MAX(0,CategoryMonthlyRecords[[#This Row],[Markup]]*CategoryMonthlyRecords[[#This Row],[Commission Rate]]) -> 32747.472 | M9: =CategoryMonthlyRecords[[#This Row],[Markup]]-CategoryMonthlyRecords[[#This Row],[Agent Commission]]+CategoryMonthlyRecords[[#This Row],[Add-on Amount]] -> 193433.63 | N9: Imported from ItemReportsCategory
A10: 46174 | B10: REFRIGERANTS | C10: 628 | D10: 1531349.1 | E10: 1402649.1 | F10: 0.01 | G10: =CategoryMonthlyRecords[[#This Row],[Base Cost]]*CategoryMonthlyRecords[[#This Row],[Add-on %]] -> 14026.491 | H10: =CategoryMonthlyRecords[[#This Row],[Base Cost]]+CategoryMonthlyRecords[[#This Row],[Add-on Amount]] -> 1416675.6 | I10: =CategoryMonthlyRecords[[#This Row],[Gross Sales]]-CategoryMonthlyRecords[[#This Row],[Capital]] -> 114673.53 | J10: Agent | K10: 0.15 | L10: =MAX(0,CategoryMonthlyRecords[[#This Row],[Markup]]*CategoryMonthlyRecords[[#This Row],[Commission Rate]]) -> 17201.029 | M10: =CategoryMonthlyRecords[[#This Row],[Markup]]-CategoryMonthlyRecords[[#This Row],[Agent Commission]]+CategoryMonthlyRecords[[#This Row],[Add-on Amount]] -> 111498.99 | N10: Imported from ItemReportsCategory
A11: 46174 | B11: PV PANELS | C11: 36 | D11: 309600 | E11: 253368 | F11: 0.01 | G11: =CategoryMonthlyRecords[[#This Row],[Base Cost]]*CategoryMonthlyRecords[[#This Row],[Add-on %]] -> 2533.68 | H11: =CategoryMonthlyRecords[[#This Row],[Base Cost]]+CategoryMonthlyRecords[[#This Row],[Add-on Amount]] -> 255901.68 | I11: =CategoryMonthlyRecords[[#This Row],[Gross Sales]]-CategoryMonthlyRecords[[#This Row],[Capital]] -> 53698.32 | J11: Store | K11: 0 | L11: =MAX(0,CategoryMonthlyRecords[[#This Row],[Markup]]*CategoryMonthlyRecords[[#This Row],[Commission Rate]]) -> 0 | M11: =CategoryMonthlyRecords[[#This Row],[Markup]]-CategoryMonthlyRecords[[#This Row],[Agent Commission]]+CategoryMonthlyRecords[[#This Row],[Add-on Amount]] -> 56232 | N11: Imported from ItemReportsCategory
A12: 46174 | B12: GENERAL | C12: 1454 | D12: 114627.84 | E12: 71853.7 | F12: 0.02 | G12: =CategoryMonthlyRecords[[#This Row],[Base Cost]]*CategoryMonthlyRecords[[#This Row],[Add-on %]] -> 1437.074 | H12: =CategoryMonthlyRecords[[#This Row],[Base Cost]]+CategoryMonthlyRecords[[#This Row],[Add-on Amount]] -> 73290.774 | I12: =CategoryMonthlyRecords[[#This Row],[Gross Sales]]-CategoryMonthlyRecords[[#This Row],[Capital]] -> 41337.066 | J12: Agent | K12: 0.3 | L12: =MAX(0,CategoryMonthlyRecords[[#This Row],[Markup]]*CategoryMonthlyRecords[[#This Row],[Commission Rate]]) -> 12401.12 | M12: =CategoryMonthlyRecords[[#This Row],[Markup]]-CategoryMonthlyRecords[[#This Row],[Agent Commission]]+CategoryMonthlyRecords[[#This Row],[Add-on Amount]] -> 30373.02 | N12: Imported from ItemReportsCategory
A13: 46174 | B13: AIRCON UNIT | C13: 2 | D13: 135760 | E13: 115720.93 | F13: 0 | G13: =CategoryMonthlyRecords[[#This Row],[Base Cost]]*CategoryMonthlyRecords[[#This Row],[Add-on %]] -> 0 | H13: =CategoryMonthlyRecords[[#This Row],[Base Cost]]+CategoryMonthlyRecords[[#This Row],[Add-on Amount]] -> 115720.93 | I13: =CategoryMonthlyRecords[[#This Row],[Gross Sales]]-CategoryMonthlyRecords[[#This Row],[Capital]] -> 20039.07 | J13: Store | K13: 0 | L13: =MAX(0,CategoryMonthlyRecords[[#This Row],[Markup]]*CategoryMonthlyRecords[[#This Row],[Commission Rate]]) -> 0 | M13: =CategoryMonthlyRecords[[#This Row],[Markup]]-CategoryMonthlyRecords[[#This Row],[Agent Commission]]+CategoryMonthlyRecords[[#This Row],[Add-on Amount]] -> 20039.07 | N13: Imported from ItemReportsCategory
A14: 46174 | B14: TOOLS | C14: 80 | D14: 45818.5 | E14: 25873.14 | F14: 0.03 | G14: =CategoryMonthlyRecords[[#This Row],[Base Cost]]*CategoryMonthlyRecords[[#This Row],[Add-on %]] -> 776.1942 | H14: =CategoryMonthlyRecords[[#This Row],[Base Cost]]+CategoryMonthlyRecords[[#This Row],[Add-on Amount]] -> 26649.334 | I14: =CategoryMonthlyRecords[[#This Row],[Gross Sales]]-CategoryMonthlyRecords[[#This Row],[Capital]] -> 19169.166 | J14: Agent | K14: 0.3 | L14: =MAX(0,CategoryMonthlyRecords[[#This Row],[Markup]]*CategoryMonthlyRecords[[#This Row],[Commission Rate]]) -> 5750.7497 | M14: =CategoryMonthlyRecords[[#This Row],[Markup]]-CategoryMonthlyRecords[[#This Row],[Agent Commission]]+CategoryMonthlyRecords[[#This Row],[Add-on Amount]] -> 14194.61 | N14: Imported from ItemReportsCategory
A15: 46174 | B15: ELECTRICAL | C15: 222 | D15: 56748.03 | E15: 42979.57 | F15: 0.03 | G15: =CategoryMonthlyRecords[[#This Row],[Base Cost]]*CategoryMonthlyRecords[[#This Row],[Add-on %]] -> 1289.3871 | H15: =CategoryMonthlyRecords[[#This Row],[Base Cost]]+CategoryMonthlyRecords[[#This Row],[Add-on Amount]] -> 44268.957 | I15: =CategoryMonthlyRecords[[#This Row],[Gross Sales]]-CategoryMonthlyRecords[[#This Row],[Capital]] -> 12479.073 | J15: Agent | K15: 0.3 | L15: =MAX(0,CategoryMonthlyRecords[[#This Row],[Markup]]*CategoryMonthlyRecords[[#This Row],[Commission Rate]]) -> 3743.7219 | M15: =CategoryMonthlyRecords[[#This Row],[Markup]]-CategoryMonthlyRecords[[#This Row],[Agent Commission]]+CategoryMonthlyRecords[[#This Row],[Add-on Amount]] -> 10024.738 | N15: Imported from ItemReportsCategory
A16: 46174 | B16: AIRCON PARTS | C16: 20 | D16: 46840 | E16: 33964 | F16: 0.03 | G16: =CategoryMonthlyRecords[[#This Row],[Base Cost]]*CategoryMonthlyRecords[[#This Row],[Add-on %]] -> 1018.92 | H16: =CategoryMonthlyRecords[[#This Row],[Base Cost]]+CategoryMonthlyRecords[[#This Row],[Add-on Amount]] -> 34982.92 | I16: =CategoryMonthlyRecords[[#This Row],[Gross Sales]]-CategoryMonthlyRecords[[#This Row],[Capital]] -> 11857.08 | J16: Agent | K16: 0.3 | L16: =MAX(0,CategoryMonthlyRecords[[#This Row],[Markup]]*CategoryMonthlyRecords[[#This Row],[Commission Rate]]) -> 3557.124 | M16: =CategoryMonthlyRecords[[#This Row],[Markup]]-CategoryMonthlyRecords[[#This Row],[Agent Commission]]+CategoryMonthlyRecords[[#This Row],[Add-on Amount]] -> 9318.876 | N16: Imported from ItemReportsCategory
A17: 46174 | B17: INVERTER | C17: 5 | D17: 2040 | E17: 1560 | F17: 0.01 | G17: =CategoryMonthlyRecords[[#This Row],[Base Cost]]*CategoryMonthlyRecords[[#This Row],[Add-on %]] -> 15.6 | H17: =CategoryMonthlyRecords[[#This Row],[Base Cost]]+CategoryMonthlyRecords[[#This Row],[Add-on Amount]] -> 1575.6 | I17: =CategoryMonthlyRecords[[#This Row],[Gross Sales]]-CategoryMonthlyRecords[[#This Row],[Capital]] -> 464.4 | J17: Store | K17: 0 | L17: =MAX(0,CategoryMonthlyRecords[[#This Row],[Markup]]*CategoryMonthlyRecords[[#This Row],[Commission Rate]]) -> 0 | M17: =CategoryMonthlyRecords[[#This Row],[Markup]]-CategoryMonthlyRecords[[#This Row],[Agent Commission]]+CategoryMonthlyRecords[[#This Row],[Add-on Amount]] -> 480 | N17: Imported from ItemReportsCategory
A18: 46174 | B18: CONSTRUCTION | C18: 2 | D18: 550 | E18: 301 | F18: 0.03 | G18: =CategoryMonthlyRecords[[#This Row],[Base Cost]]*CategoryMonthlyRecords[[#This Row],[Add-on %]] -> 9.03 | H18: =CategoryMonthlyRecords[[#This Row],[Base Cost]]+CategoryMonthlyRecords[[#This Row],[Add-on Amount]] -> 310.03 | I18: =CategoryMonthlyRecords[[#This Row],[Gross Sales]]-CategoryMonthlyRecords[[#This Row],[Capital]] -> 239.97 | J18: Agent | K18: 0.3 | L18: =MAX(0,CategoryMonthlyRecords[[#This Row],[Markup]]*CategoryMonthlyRecords[[#This Row],[Commission Rate]]) -> 71.991 | M18: =CategoryMonthlyRecords[[#This Row],[Markup]]-CategoryMonthlyRecords[[#This Row],[Agent Commission]]+CategoryMonthlyRecords[[#This Row],[Add-on Amount]] -> 177.009 | N18: Imported from ItemReportsCategory
... A34: 46235 | B34: ELECTRICAL | C34: 46 | D34: 59985.68 | E34: 41719.3 | F34: 0.03 | G34: =CategoryMonthlyRecords[[#This Row],[Base Cost]]*CategoryMonthlyRecords[[#This Row],[Add-on %]] -> 1251.579 | H34: =CategoryMonthlyRecords[[#This Row],[Base Cost]]+CategoryMonthlyRecords[[#This Row],[Add-on Amount]] -> 42970.879 | I34: =CategoryMonthlyRecords[[#This Row],[Gross Sales]]-CategoryMonthlyRecords[[#This Row],[Capital]] -> 17014.801 | J34: Agent | K34: 0.3 | L34: =MAX(0,CategoryMonthlyRecords[[#This Row],[Markup]]*CategoryMonthlyRecords[[#This Row],[Commission Rate]]) -> 5104.4403 | M34: =CategoryMonthlyRecords[[#This Row],[Markup]]-CategoryMonthlyRecords[[#This Row],[Agent Commission]]+CategoryMonthlyRecords[[#This Row],[Add-on Amount]] -> 13161.94 | N34: Imported from August 2026 sales report
A35: 46235 | B35: AIRCON UNIT | C35: 13 | D35: 1058025 | E35: 715429 | F35: 0 | G35: =CategoryMonthlyRecords[[#This Row],[Base Cost]]*CategoryMonthlyRecords[[#This Row],[Add-on %]] -> 0 | H35: =CategoryMonthlyRecords[[#This Row],[Base Cost]]+CategoryMonthlyRecords[[#This Row],[Add-on Amount]] -> 715429 | I35: =CategoryMonthlyRecords[[#This Row],[Gross Sales]]-CategoryMonthlyRecords[[#This Row],[Capital]] -> 342596 | J35: Store | K35: 0 | L35: =MAX(0,CategoryMonthlyRecords[[#This Row],[Markup]]*CategoryMonthlyRecords[[#This Row],[Commission Rate]]) -> 0 | M35: =CategoryMonthlyRecords[[#This Row],[Markup]]-CategoryMonthlyRecords[[#This Row],[Agent Commission]]+CategoryMonthlyRecords[[#This Row],[Add-on Amount]] -> 342596
A36: 46235 | B36: TOOLS | C36: 26 | D36: 18235.76 | E36: 12498.88 | F36: 0.03 | G36: =CategoryMonthlyRecords[[#This Row],[Base Cost]]*CategoryMonthlyRecords[[#This Row],[Add-on %]] -> 374.9664 | H36: =CategoryMonthlyRecords[[#This Row],[Base Cost]]+CategoryMonthlyRecords[[#This Row],[Add-on Amount]] -> 12873.846 | I36: =CategoryMonthlyRecords[[#This Row],[Gross Sales]]-CategoryMonthlyRecords[[#This Row],[Capital]] -> 5361.9136 | J36: Agent | K36: 0.3 | L36: =MAX(0,CategoryMonthlyRecords[[#This Row],[Markup]]*CategoryMonthlyRecords[[#This Row],[Commission Rate]]) -> 1608.5741 | M36: =CategoryMonthlyRecords[[#This Row],[Markup]]-CategoryMonthlyRecords[[#This Row],[Agent Commission]]+CategoryMonthlyRecords[[#This Row],[Add-on Amount]] -> 4128.3059
A37: 46235 | B37: CONSTRUCTION | C37: 6 | D37: 1670 | E37: 1104.89 | F37: 0.03 | G37: =CategoryMonthlyRecords[[#This Row],[Base Cost]]*CategoryMonthlyRecords[[#This Row],[Add-on %]] -> 33.1467 | H37: =CategoryMonthlyRecords[[#This Row],[Base Cost]]+CategoryMonthlyRecords[[#This Row],[Add-on Amount]] -> 1138.0367 | I37: =CategoryMonthlyRecords[[#This Row],[Gross Sales]]-CategoryMonthlyRecords[[#This Row],[Capital]] -> 531.9633 | J37: Agent | K37: 0.3 | L37: =MAX(0,CategoryMonthlyRecords[[#This Row],[Markup]]*CategoryMonthlyRecords[[#This Row],[Commission Rate]]) -> 159.58899 | M37: =CategoryMonthlyRecords[[#This Row],[Markup]]-CategoryMonthlyRecords[[#This Row],[Agent Commission]]+CategoryMonthlyRecords[[#This Row],[Add-on Amount]] -> 405.52101
A38: 46235 | B38: PV PANELS | F38: 0.01 | G38: =CategoryMonthlyRecords[[#This Row],[Base Cost]]*CategoryMonthlyRecords[[#This Row],[Add-on %]] -> 0 | H38: =CategoryMonthlyRecords[[#This Row],[Base Cost]]+CategoryMonthlyRecords[[#This Row],[Add-on Amount]] -> 0 | I38: =CategoryMonthlyRecords[[#This Row],[Gross Sales]]-CategoryMonthlyRecords[[#This Row],[Capital]] -> 0 | J38: Store | K38: 0 | L38: =MAX(0,CategoryMonthlyRecords[[#This Row],[Markup]]*CategoryMonthlyRecords[[#This Row],[Commission Rate]]) -> 0 | M38: =CategoryMonthlyRecords[[#This Row],[Markup]]-CategoryMonthlyRecords[[#This Row],[Agent Commission]]+CategoryMonthlyRecords[[#This Row],[Add-on Amount]] -> 0 | N38: No August activity — zero record
A39: 46235 | B39: INVERTER | F39: 0.01 | G39: =CategoryMonthlyRecords[[#This Row],[Base Cost]]*CategoryMonthlyRecords[[#This Row],[Add-on %]] -> 0 | H39: =CategoryMonthlyRecords[[#This Row],[Base Cost]]+CategoryMonthlyRecords[[#This Row],[Add-on Amount]] -> 0 | I39: =CategoryMonthlyRecords[[#This Row],[Gross Sales]]-CategoryMonthlyRecords[[#This Row],[Capital]] -> 0 | J39: Store | K39: 0 | L39: =MAX(0,CategoryMonthlyRecords[[#This Row],[Markup]]*CategoryMonthlyRecords[[#This Row],[Commission Rate]]) -> 0 | M39: =CategoryMonthlyRecords[[#This Row],[Markup]]-CategoryMonthlyRecords[[#This Row],[Agent Commission]]+CategoryMonthlyRecords[[#This Row],[Add-on Amount]] -> 0 | N39: No August activity — zero record
A40: 46266 | B40: BATTERY | F40: 0.01 | G40: =CategoryMonthlyRecords[[#This Row],[Base Cost]]*CategoryMonthlyRecords[[#This Row],[Add-on %]] -> 0 | H40: =CategoryMonthlyRecords[[#This Row],[Base Cost]]+CategoryMonthlyRecords[[#This Row],[Add-on Amount]] -> 0 | I40: =CategoryMonthlyRecords[[#This Row],[Gross Sales]]-CategoryMonthlyRecords[[#This Row],[Capital]] -> 0 | J40: Store | K40: 0 | L40: =MAX(0,CategoryMonthlyRecords[[#This Row],[Markup]]*CategoryMonthlyRecords[[#This Row],[Commission Rate]]) -> 0 | M40: =CategoryMonthlyRecords[[#This Row],[Markup]]-CategoryMonthlyRecords[[#This Row],[Agent Commission]]+CategoryMonthlyRecords[[#This Row],[Add-on Amount]] -> 0 | N40: Template for September 2026 — enter input columns
A41: 46266 | B41: CAR AIRCON | F41: 0.07 | G41: =CategoryMonthlyRecords[[#This Row],[Base Cost]]*CategoryMonthlyRecords[[#This Row],[Add-on %]] -> 0 | H41: =CategoryMonthlyRecords[[#This Row],[Base Cost]]+CategoryMonthlyRecords[[#This Row],[Add-on Amount]] -> 0 | I41: =CategoryMonthlyRecords[[#This Row],[Gross Sales]]-CategoryMonthlyRecords[[#This Row],[Capital]] -> 0 | J41: Agent | K41: 0.15 | L41: =MAX(0,CategoryMonthlyRecords[[#This Row],[Markup]]*CategoryMonthlyRecords[[#This Row],[Commission Rate]]) -> 0 | M41: =CategoryMonthlyRecords[[#This Row],[Markup]]-CategoryMonthlyRecords[[#This Row],[Agent Commission]]+CategoryMonthlyRecords[[#This Row],[Add-on Amount]] -> 0 | N41: Template for September 2026 — enter input columns
A42: 46266 | B42: INSTALLATION MATERIALS | F42: 0.01 | G42: =CategoryMonthlyRecords[[#This Row],[Base Cost]]*CategoryMonthlyRecords[[#This Row],[Add-on %]] -> 0 | H42: =CategoryMonthlyRecords[[#This Row],[Base Cost]]+CategoryMonthlyRecords[[#This Row],[Add-on Amount]] -> 0 | I42: =CategoryMonthlyRecords[[#This Row],[Gross Sales]]-CategoryMonthlyRecords[[#This Row],[Capital]] -> 0 | J42: Agent | K42: 0.15 | L42: =MAX(0,CategoryMonthlyRecords[[#This Row],[Markup]]*CategoryMonthlyRecords[[#This Row],[Commission Rate]]) -> 0 | M42: =CategoryMonthlyRecords[[#This Row],[Markup]]-CategoryMonthlyRecords[[#This Row],[Agent Commission]]+CategoryMonthlyRecords[[#This Row],[Add-on Amount]] -> 0 | N42: Template for September 2026 — enter input columns
A43: 46266 | B43: REFRIGERANTS | F43: 0.01 | G43: =CategoryMonthlyRecords[[#This Row],[Base Cost]]*CategoryMonthlyRecords[[#This Row],[Add-on %]] -> 0 | H43: =CategoryMonthlyRecords[[#This Row],[Base Cost]]+CategoryMonthlyRecords[[#This Row],[Add-on Amount]] -> 0 | I43: =CategoryMonthlyRecords[[#This Row],[Gross Sales]]-CategoryMonthlyRecords[[#This Row],[Capital]] -> 0 | J43: Agent | K43: 0.15 | L43: =MAX(0,CategoryMonthlyRecords[[#This Row],[Markup]]*CategoryMonthlyRecords[[#This Row],[Commission Rate]]) -> 0 | M43: =CategoryMonthlyRecords[[#This Row],[Markup]]-CategoryMonthlyRecords[[#This Row],[Agent Commission]]+CategoryMonthlyRecords[[#This Row],[Add-on Amount]] -> 0 | N43: Template for September 2026 — enter input columns
A44: 46266 | B44: PV PANELS | F44: 0.01 | G44: =CategoryMonthlyRecords[[#This Row],[Base Cost]]*CategoryMonthlyRecords[[#This Row],[Add-on %]] -> 0 | H44: =CategoryMonthlyRecords[[#This Row],[Base Cost]]+CategoryMonthlyRecords[[#This Row],[Add-on Amount]] -> 0 | I44: =CategoryMonthlyRecords[[#This Row],[Gross Sales]]-CategoryMonthlyRecords[[#This Row],[Capital]] -> 0 | J44: Store | K44: 0 | L44: =MAX(0,CategoryMonthlyRecords[[#This Row],[Markup]]*CategoryMonthlyRecords[[#This Row],[Commission Rate]]) -> 0 | M44: =CategoryMonthlyRecords[[#This Row],[Markup]]-CategoryMonthlyRecords[[#This Row],[Agent Commission]]+CategoryMonthlyRecords[[#This Row],[Add-on Amount]] -> 0 | N44: Template for September 2026 — enter input columns
A45: 46266 | B45: GENERAL | F45: 0.02 | G45: =CategoryMonthlyRecords[[#This Row],[Base Cost]]*CategoryMonthlyRecords[[#This Row],[Add-on %]] -> 0 | H45: =CategoryMonthlyRecords[[#This Row],[Base Cost]]+CategoryMonthlyRecords[[#This Row],[Add-on Amount]] -> 0 | I45: =CategoryMonthlyRecords[[#This Row],[Gross Sales]]-CategoryMonthlyRecords[[#This Row],[Capital]] -> 0 | J45: Agent | K45: 0.3 | L45: =MAX(0,CategoryMonthlyRecords[[#This Row],[Markup]]*CategoryMonthlyRecords[[#This Row],[Commission Rate]]) -> 0 | M45: =CategoryMonthlyRecords[[#This Row],[Markup]]-CategoryMonthlyRecords[[#This Row],[Agent Commission]]+CategoryMonthlyRecords[[#This Row],[Add-on Amount]] -> 0 | N45: Template for September 2026 — enter input columns
A46: 46266 | B46: AIRCON UNIT | F46: 0 | G46: =CategoryMonthlyRecords[[#This Row],[Base Cost]]*CategoryMonthlyRecords[[#This Row],[Add-on %]] -> 0 | H46: =CategoryMonthlyRecords[[#This Row],[Base Cost]]+CategoryMonthlyRecords[[#This Row],[Add-on Amount]] -> 0 | I46: =CategoryMonthlyRecords[[#This Row],[Gross Sales]]-CategoryMonthlyRecords[[#This Row],[Capital]] -> 0 | J46: Store | K46: 0 | L46: =MAX(0,CategoryMonthlyRecords[[#This Row],[Markup]]*CategoryMonthlyRecords[[#This Row],[Commission Rate]]) -> 0 | M46: =CategoryMonthlyRecords[[#This Row],[Markup]]-CategoryMonthlyRecords[[#This Row],[Agent Commission]]+CategoryMonthlyRecords[[#This Row],[Add-on Amount]] -> 0 | N46: Template for September 2026 — enter input columns
A47: 46266 | B47: TOOLS | F47: 0.03 | G47: =CategoryMonthlyRecords[[#This Row],[Base Cost]]*CategoryMonthlyRecords[[#This Row],[Add-on %]] -> 0 | H47: =CategoryMonthlyRecords[[#This Row],[Base Cost]]+CategoryMonthlyRecords[[#This Row],[Add-on Amount]] -> 0 | I47: =CategoryMonthlyRecords[[#This Row],[Gross Sales]]-CategoryMonthlyRecords[[#This Row],[Capital]] -> 0 | J47: Agent | K47: 0.3 | L47: =MAX(0,CategoryMonthlyRecords[[#This Row],[Markup]]*CategoryMonthlyRecords[[#This Row],[Commission Rate]]) -> 0 | M47: =CategoryMonthlyRecords[[#This Row],[Markup]]-CategoryMonthlyRecords[[#This Row],[Agent Commission]]+CategoryMonthlyRecords[[#This Row],[Add-on Amount]] -> 0 | N47: Template for September 2026 — enter input columns
A48: 46266 | B48: ELECTRICAL | F48: 0.03 | G48: =CategoryMonthlyRecords[[#This Row],[Base Cost]]*CategoryMonthlyRecords[[#This Row],[Add-on %]] -> 0 | H48: =CategoryMonthlyRecords[[#This Row],[Base Cost]]+CategoryMonthlyRecords[[#This Row],[Add-on Amount]] -> 0 | I48: =CategoryMonthlyRecords[[#This Row],[Gross Sales]]-CategoryMonthlyRecords[[#This Row],[Capital]] -> 0 | J48: Agent | K48: 0.3 | L48: =MAX(0,CategoryMonthlyRecords[[#This Row],[Markup]]*CategoryMonthlyRecords[[#This Row],[Commission Rate]]) -> 0 | M48: =CategoryMonthlyRecords[[#This Row],[Markup]]-CategoryMonthlyRecords[[#This Row],[Agent Commission]]+CategoryMonthlyRecords[[#This Row],[Add-on Amount]] -> 0 | N48: Template for September 2026 — enter input columns
A49: 46266 | B49: AIRCON PARTS | F49: 0.03 | G49: =CategoryMonthlyRecords[[#This Row],[Base Cost]]*CategoryMonthlyRecords[[#This Row],[Add-on %]] -> 0 | H49: =CategoryMonthlyRecords[[#This Row],[Base Cost]]+CategoryMonthlyRecords[[#This Row],[Add-on Amount]] -> 0 | I49: =CategoryMonthlyRecords[[#This Row],[Gross Sales]]-CategoryMonthlyRecords[[#This Row],[Capital]] -> 0 | J49: Agent | K49: 0.3 | L49: =MAX(0,CategoryMonthlyRecords[[#This Row],[Markup]]*CategoryMonthlyRecords[[#This Row],[Commission Rate]]) -> 0 | M49: =CategoryMonthlyRecords[[#This Row],[Markup]]-CategoryMonthlyRecords[[#This Row],[Agent Commission]]+CategoryMonthlyRecords[[#This Row],[Add-on Amount]] -> 0 | N49: Template for September 2026 — enter input columns
... A87: 46357 | B87: CONSTRUCTION | F87: 0.03 | G87: =CategoryMonthlyRecords[[#This Row],[Base Cost]]*CategoryMonthlyRecords[[#This Row],[Add-on %]] -> 0 | H87: =CategoryMonthlyRecords[[#This Row],[Base Cost]]+CategoryMonthlyRecords[[#This Row],[Add-on Amount]] -> 0 | I87: =CategoryMonthlyRecords[[#This Row],[Gross Sales]]-CategoryMonthlyRecords[[#This Row],[Capital]] -> 0 | J87: Agent | K87: 0.3 | L87: =MAX(0,CategoryMonthlyRecords[[#This Row],[Markup]]*CategoryMonthlyRecords[[#This Row],[Commission Rate]]) -> 0 | M87: =CategoryMonthlyRecords[[#This Row],[Markup]]-CategoryMonthlyRecords[[#This Row],[Agent Commission]]+CategoryMonthlyRecords[[#This Row],[Add-on Amount]] -> 0 | N87: Template for December 2026 — enter input columns

Sheet AgentYearlySales
E1: ➤ Executive Summary
A3: ISHABELLA AIRCON AND REFRIGERATION PARTS TRADING
A4: NON-VAT REG TIN 245-311-904-000
A5: 78 MAIN AVE. SOCORRO CUBAO QUEZON CITY
A6: 09665212881
A7: YEARLY SALES AND COMMISSION FOR THE YEAR 2026
A9: DESCRIPTION | C9: JANUARY | I9: FEBRUARY | P9: MARCH | V9: APRIL | AB9: MAY | AH9: JUNE | AN9: JULY | AT9: AUGUST | AZ9: SEPTEMBER | BF9: OCTOBER | BL9: NOVEMBER | BR9: DECEMBER | BX9: TOTAL
C10: SALES | D10: CAPITAL | E10: EXPENSES | F10: NET SALES | G10: % | H10: COMMISSION | I10: SALES | J10: CAPITAL | K10: EXPENSES | L10: NET SALES | N10: % | O10: COMMISSION | P10: SALES | Q10: CAPITAL | R10: EXPENSES | S10: NET SALES | T10: % | U10: COMMISSION | V10: SALES | W10: CAPITAL | X10: EXPENSES | Y10: NET SALES | Z10: % | AA10: COMMISSION | AB10: SALES | AC10: CAPITAL | AD10: EXPENSES | AE10: NET SALES | AF10: % | AG10: COMMISSION | AH10: SALES | AI10: CAPITAL | AJ10: EXPENSES | AK10: NET SALES | AL10: % | AM10: COMMISSION | AN10: SALES | AO10: CAPITAL | AP10: EXPENSES | AQ10: NET SALES | AR10: % | AS10: COMMISSION | AT10: SALES | AU10: CAPITAL | AV10: EXPENSES | AW10: NET SALES | AX10: % | AY10: COMMISSION | AZ10: SALES | BA10: CAPITAL | BB10: EXPENSES | BC10: NET SALES | BD10: % | BE10: COMMISSION | BF10: SALES | BG10: CAPITAL | BH10: EXPENSES | BI10: NET SALES | BJ10: % | BK10: COMMISSION | BL10: SALES | BM10: CAPITAL | BN10: EXPENSES | BO10: NET SALES | BP10: % | BQ10: COMMISSION | BR10: SALES | BS10: CAPITAL | BT10: EXPENSES | BU10: NET SALES | BV10: % | BW10: COMMISSION | BX10: SALES | BY10: CAPITAL | BZ10: EXPENSES | CA10: NET SALES | CB10: COMMISSION
A11: 1. ARNOLD ORTIZ | AB11: 8,700.00 | AC11: 5,800.00 | AD11: 0.00 | AE11: 2,900.00 | AF11: 20 | AG11: 580.00 | AH11: 385,266.32 | AI11: 318,350.44 | AK11: 66,915.88 | AL11: 30 | AM11: 20,074.76 | AN11: 468723.72 | AO11: 335180.17 | AP11: 0 | AQ11: =IF(COUNTA(AN11:AO11)=0,"",AN11-AO11) -> 133543.55 | AR11: 0.2 | AS11: =IF(OR(AQ11="",AR11=""),"",AQ11*AR11) -> 26708.71 | AT11: 113401 | AU11: 87333.6 | AW11: 26067.4 | AX11: 0.2 | AY11: =IF(OR(AW11="",AX11=""),"",AW11*AX11) -> 5213.48 | BX11: =IFERROR(VALUE(C11),0)+IFERROR(VALUE(I11),0)+IFERROR(VALUE(P11),0)+IFERROR(VALUE(V11),0)+IFERROR(VALUE(AB11),0)+IFERROR(VALUE(AH11),0)+IFERROR(VALUE(AN11),0)+IFERROR(VALUE(AT11),0)+IFERROR(VALUE(AZ11),0)+IFERROR(VALUE(BF11),0)+IFERROR(VALUE(BL11),0)+IFERROR(VALUE(BR11),0) -> 976091.04 | BY11: =IFERROR(VALUE(D11),0)+IFERROR(VALUE(J11),0)+IFERROR(VALUE(Q11),0)+IFERROR(VALUE(W11),0)+IFERROR(VALUE(AC11),0)+IFERROR(VALUE(AI11),0)+IFERROR(VALUE(AO11),0)+IFERROR(VALUE(AU11),0)+IFERROR(VALUE(BA11),0)+IFERROR(VALUE(BG11),0)+IFERROR(VALUE(BM11),0)+IFERROR(VALUE(BS11),0) -> 746664.21 | BZ11: =IFERROR(VALUE(E11),0)+IFERROR(VALUE(K11),0)+IFERROR(VALUE(R11),0)+IFERROR(VALUE(X11),0)+IFERROR(VALUE(AD11),0)+IFERROR(VALUE(AJ11),0)+IFERROR(VALUE(AP11),0)+IFERROR(VALUE(AV11),0)+IFERROR(VALUE(BB11),0)+IFERROR(VALUE(BH11),0)+IFERROR(VALUE(BN11),0)+IFERROR(VALUE(BT11),0) -> 0 | CA11: =IFERROR(VALUE(F11),0)+IFERROR(VALUE(L11),0)+IFERROR(VALUE(S11),0)+IFERROR(VALUE(Y11),0)+IFERROR(VALUE(AE11),0)+IFERROR(VALUE(AK11),0)+IFERROR(VALUE(AQ11),0)+IFERROR(VALUE(AW11),0)+IFERROR(VALUE(BC11),0)+IFERROR(VALUE(BI11),0)+IFERROR(VALUE(BO11),0)+IFERROR(VALUE(BU11),0) -> 229426.83 | CB11: =IFERROR(VALUE(H11),0)+IFERROR(VALUE(O11),0)+IFERROR(VALUE(U11),0)+IFERROR(VALUE(AA11),0)+IFERROR(VALUE(AG11),0)+IFERROR(VALUE(AM11),0)+IFERROR(VALUE(AS11),0)+IFERROR(VALUE(AY11),0)+IFERROR(VALUE(BE11),0)+IFERROR(VALUE(BK11),0)+IFERROR(VALUE(BQ11),0)+IFERROR(VALUE(BW11),0) -> 52576.95
A12: 2. JENNIFER DUM-OGAN - ONLINE | AH12: 92,977.30 | AI12: 54,585.61 | AK12: 38,391.69 | AL12: 20 | AM12: 7,678.34 | AN12: 49567.51 | AO12: 32264.51 | AP12: 0 | AQ12: =IF(COUNTA(AN12:AO12)=0,"",AN12-AO12) -> 17303 | AR12: 0.2 | AS12: =IF(OR(AQ12="",AR12=""),"",AQ12*AR12) -> 3460.6 | AT12: 23556.88 | AU12: 16065.51 | AW12: 7491.37 | AX12: 0.2 | AY12: =IF(OR(AW12="",AX12=""),"",AW12*AX12) -> 1498.274 | BX12: =IFERROR(VALUE(C12),0)+IFERROR(VALUE(I12),0)+IFERROR(VALUE(P12),0)+IFERROR(VALUE(V12),0)+IFERROR(VALUE(AB12),0)+IFERROR(VALUE(AH12),0)+IFERROR(VALUE(AN12),0)+IFERROR(VALUE(AT12),0)+IFERROR(VALUE(AZ12),0)+IFERROR(VALUE(BF12),0)+IFERROR(VALUE(BL12),0)+IFERROR(VALUE(BR12),0) -> 166101.69 | BY12: =IFERROR(VALUE(D12),0)+IFERROR(VALUE(J12),0)+IFERROR(VALUE(Q12),0)+IFERROR(VALUE(W12),0)+IFERROR(VALUE(AC12),0)+IFERROR(VALUE(AI12),0)+IFERROR(VALUE(AO12),0)+IFERROR(VALUE(AU12),0)+IFERROR(VALUE(BA12),0)+IFERROR(VALUE(BG12),0)+IFERROR(VALUE(BM12),0)+IFERROR(VALUE(BS12),0) -> 102915.63 | BZ12: =IFERROR(VALUE(E12),0)+IFERROR(VALUE(K12),0)+IFERROR(VALUE(R12),0)+IFERROR(VALUE(X12),0)+IFERROR(VALUE(AD12),0)+IFERROR(VALUE(AJ12),0)+IFERROR(VALUE(AP12),0)+IFERROR(VALUE(AV12),0)+IFERROR(VALUE(BB12),0)+IFERROR(VALUE(BH12),0)+IFERROR(VALUE(BN12),0)+IFERROR(VALUE(BT12),0) -> 0 | CA12: =IFERROR(VALUE(F12),0)+IFERROR(VALUE(L12),0)+IFERROR(VALUE(S12),0)+IFERROR(VALUE(Y12),0)+IFERROR(VALUE(AE12),0)+IFERROR(VALUE(AK12),0)+IFERROR(VALUE(AQ12),0)+IFERROR(VALUE(AW12),0)+IFERROR(VALUE(BC12),0)+IFERROR(VALUE(BI12),0)+IFERROR(VALUE(BO12),0)+IFERROR(VALUE(BU12),0) -> 63186.06 | CB12: =IFERROR(VALUE(H12),0)+IFERROR(VALUE(O12),0)+IFERROR(VALUE(U12),0)+IFERROR(VALUE(AA12),0)+IFERROR(VALUE(AG12),0)+IFERROR(VALUE(AM12),0)+IFERROR(VALUE(AS12),0)+IFERROR(VALUE(AY12),0)+IFERROR(VALUE(BE12),0)+IFERROR(VALUE(BK12),0)+IFERROR(VALUE(BQ12),0)+IFERROR(VALUE(BW12),0) -> 12637.214
A13: 3. JOVY VILLANUEVA | AH13: 85,700.00 | AI13: 66,701.05 | AK13: 18,998.95 | AL13: 20 | AM13: 3,799.79 | AN13: 226674 | AO13: 182345.57 | AP13: 0 | AQ13: =IF(COUNTA(AN13:AO13)=0,"",AN13-AO13) -> 44328.43 | AR13: 0.2 | AS13: =IF(OR(AQ13="",AR13=""),"",AQ13*AR13) -> 8865.686 | AT13: 33922 | AU13: 27817.76 | AW13: 6104.24 | AX13: 0.2 | AY13: =IF(OR(AW13="",AX13=""),"",AW13*AX13) -> 1220.848 | BX13: =IFERROR(VALUE(C13),0)+IFERROR(VALUE(I13),0)+IFERROR(VALUE(P13),0)+IFERROR(VALUE(V13),0)+IFERROR(VALUE(AB13),0)+IFERROR(VALUE(AH13),0)+IFERROR(VALUE(AN13),0)+IFERROR(VALUE(AT13),0)+IFERROR(VALUE(AZ13),0)+IFERROR(VALUE(BF13),0)+IFERROR(VALUE(BL13),0)+IFERROR(VALUE(BR13),0) -> 346296 | BY13: =IFERROR(VALUE(D13),0)+IFERROR(VALUE(J13),0)+IFERROR(VALUE(Q13),0)+IFERROR(VALUE(W13),0)+IFERROR(VALUE(AC13),0)+IFERROR(VALUE(AI13),0)+IFERROR(VALUE(AO13),0)+IFERROR(VALUE(AU13),0)+IFERROR(VALUE(BA13),0)+IFERROR(VALUE(BG13),0)+IFERROR(VALUE(BM13),0)+IFERROR(VALUE(BS13),0) -> 276864.38 | BZ13: =IFERROR(VALUE(E13),0)+IFERROR(VALUE(K13),0)+IFERROR(VALUE(R13),0)+IFERROR(VALUE(X13),0)+IFERROR(VALUE(AD13),0)+IFERROR(VALUE(AJ13),0)+IFERROR(VALUE(AP13),0)+IFERROR(VALUE(AV13),0)+IFERROR(VALUE(BB13),0)+IFERROR(VALUE(BH13),0)+IFERROR(VALUE(BN13),0)+IFERROR(VALUE(BT13),0) -> 0 | CA13: =IFERROR(VALUE(F13),0)+IFERROR(VALUE(L13),0)+IFERROR(VALUE(S13),0)+IFERROR(VALUE(Y13),0)+IFERROR(VALUE(AE13),0)+IFERROR(VALUE(AK13),0)+IFERROR(VALUE(AQ13),0)+IFERROR(VALUE(AW13),0)+IFERROR(VALUE(BC13),0)+IFERROR(VALUE(BI13),0)+IFERROR(VALUE(BO13),0)+IFERROR(VALUE(BU13),0) -> 69431.62 | CB13: =IFERROR(VALUE(H13),0)+IFERROR(VALUE(O13),0)+IFERROR(VALUE(U13),0)+IFERROR(VALUE(AA13),0)+IFERROR(VALUE(AG13),0)+IFERROR(VALUE(AM13),0)+IFERROR(VALUE(AS13),0)+IFERROR(VALUE(AY13),0)+IFERROR(VALUE(BE13),0)+IFERROR(VALUE(BK13),0)+IFERROR(VALUE(BQ13),0)+IFERROR(VALUE(BW13),0) -> 13886.324
A14: 4. MARIVIC BRILLANTES | AH14: 2,800.00 | AI14: 1,895.80 | AK14: 904.20 | AL14: 20 | AM14: 180.84 | AP14: 0 | AQ14: =IF(COUNTA(AN14:AO14)=0,"",AN14-AO14) | AR14: 0.2 | AS14: =IF(OR(AQ14="",AR14=""),"",AQ14*AR14) | AY14: =IF(OR(AW14="",AX14=""),"",AW14*AX14) | BX14: =IFERROR(VALUE(C14),0)+IFERROR(VALUE(I14),0)+IFERROR(VALUE(P14),0)+IFERROR(VALUE(V14),0)+IFERROR(VALUE(AB14),0)+IFERROR(VALUE(AH14),0)+IFERROR(VALUE(AN14),0)+IFERROR(VALUE(AT14),0)+IFERROR(VALUE(AZ14),0)+IFERROR(VALUE(BF14),0)+IFERROR(VALUE(BL14),0)+IFERROR(VALUE(BR14),0) -> 2800 | BY14: =IFERROR(VALUE(D14),0)+IFERROR(VALUE(J14),0)+IFERROR(VALUE(Q14),0)+IFERROR(VALUE(W14),0)+IFERROR(VALUE(AC14),0)+IFERROR(VALUE(AI14),0)+IFERROR(VALUE(AO14),0)+IFERROR(VALUE(AU14),0)+IFERROR(VALUE(BA14),0)+IFERROR(VALUE(BG14),0)+IFERROR(VALUE(BM14),0)+IFERROR(VALUE(BS14),0) -> 1895.8 | BZ14: =IFERROR(VALUE(E14),0)+IFERROR(VALUE(K14),0)+IFERROR(VALUE(R14),0)+IFERROR(VALUE(X14),0)+IFERROR(VALUE(AD14),0)+IFERROR(VALUE(AJ14),0)+IFERROR(VALUE(AP14),0)+IFERROR(VALUE(AV14),0)+IFERROR(VALUE(BB14),0)+IFERROR(VALUE(BH14),0)+IFERROR(VALUE(BN14),0)+IFERROR(VALUE(BT14),0) -> 0 | CA14: =IFERROR(VALUE(F14),0)+IFERROR(VALUE(L14),0)+IFERROR(VALUE(S14),0)+IFERROR(VALUE(Y14),0)+IFERROR(VALUE(AE14),0)+IFERROR(VALUE(AK14),0)+IFERROR(VALUE(AQ14),0)+IFERROR(VALUE(AW14),0)+IFERROR(VALUE(BC14),0)+IFERROR(VALUE(BI14),0)+IFERROR(VALUE(BO14),0)+IFERROR(VALUE(BU14),0) -> 904.2 | CB14: =IFERROR(VALUE(H14),0)+IFERROR(VALUE(O14),0)+IFERROR(VALUE(U14),0)+IFERROR(VALUE(AA14),0)+IFERROR(VALUE(AG14),0)+IFERROR(VALUE(AM14),0)+IFERROR(VALUE(AS14),0)+IFERROR(VALUE(AY14),0)+IFERROR(VALUE(BE14),0)+IFERROR(VALUE(BK14),0)+IFERROR(VALUE(BQ14),0)+IFERROR(VALUE(BW14),0) -> 180.84
A15: 5. MICHAEL PLAZA | AH15: 494,714.01 | AI15: 398,088.74 | AK15: 96,625.27 | AL15: 30 | AM15: 28,987.58 | AN15: 592443.9 | AO15: 497396.01 | AP15: 0 | AQ15: =IF(COUNTA(AN15:AO15)=0,"",AN15-AO15) -> 95047.89 | AR15: 0.3 | AS15: =IF(OR(AQ15="",AR15=""),"",AQ15*AR15) -> 28514.367 | AT15: 817590.78 | AU15: 593990.02 | AW15: 223600.76 | AX15: 0.3 | AY15: =IF(OR(AW15="",AX15=""),"",AW15*AX15) -> 67080.228 | BX15: =IFERROR(VALUE(C15),0)+IFERROR(VALUE(I15),0)+IFERROR(VALUE(P15),0)+IFERROR(VALUE(V15),0)+IFERROR(VALUE(AB15),0)+IFERROR(VALUE(AH15),0)+IFERROR(VALUE(AN15),0)+IFERROR(VALUE(AT15),0)+IFERROR(VALUE(AZ15),0)+IFERROR(VALUE(BF15),0)+IFERROR(VALUE(BL15),0)+IFERROR(VALUE(BR15),0) -> 1904748.7 | BY15: =IFERROR(VALUE(D15),0)+IFERROR(VALUE(J15),0)+IFERROR(VALUE(Q15),0)+IFERROR(VALUE(W15),0)+IFERROR(VALUE(AC15),0)+IFERROR(VALUE(AI15),0)+IFERROR(VALUE(AO15),0)+IFERROR(VALUE(AU15),0)+IFERROR(VALUE(BA15),0)+IFERROR(VALUE(BG15),0)+IFERROR(VALUE(BM15),0)+IFERROR(VALUE(BS15),0) -> 1489474.8 | BZ15: =IFERROR(VALUE(E15),0)+IFERROR(VALUE(K15),0)+IFERROR(VALUE(R15),0)+IFERROR(VALUE(X15),0)+IFERROR(VALUE(AD15),0)+IFERROR(VALUE(AJ15),0)+IFERROR(VALUE(AP15),0)+IFERROR(VALUE(AV15),0)+IFERROR(VALUE(BB15),0)+IFERROR(VALUE(BH15),0)+IFERROR(VALUE(BN15),0)+IFERROR(VALUE(BT15),0) -> 0 | CA15: =IFERROR(VALUE(F15),0)+IFERROR(VALUE(L15),0)+IFERROR(VALUE(S15),0)+IFERROR(VALUE(Y15),0)+IFERROR(VALUE(AE15),0)+IFERROR(VALUE(AK15),0)+IFERROR(VALUE(AQ15),0)+IFERROR(VALUE(AW15),0)+IFERROR(VALUE(BC15),0)+IFERROR(VALUE(BI15),0)+IFERROR(VALUE(BO15),0)+IFERROR(VALUE(BU15),0) -> 415273.92 | CB15: =IFERROR(VALUE(H15),0)+IFERROR(VALUE(O15),0)+IFERROR(VALUE(U15),0)+IFERROR(VALUE(AA15),0)+IFERROR(VALUE(AG15),0)+IFERROR(VALUE(AM15),0)+IFERROR(VALUE(AS15),0)+IFERROR(VALUE(AY15),0)+IFERROR(VALUE(BE15),0)+IFERROR(VALUE(BK15),0)+IFERROR(VALUE(BQ15),0)+IFERROR(VALUE(BW15),0) -> 124582.18
A16: 6. MODESTO PAG-ARIGON | AH16: 45,805.00 | AI16: 38,466.37 | AK16: 7,338.63 | AL16: 20 | AM16: 1,467.73 | AN16: 12460 | AO16: 10545.3 | AP16: 0 | AQ16: =IF(COUNTA(AN16:AO16)=0,"",AN16-AO16) -> 1914.7 | AR16: 0.2 | AS16: =IF(OR(AQ16="",AR16=""),"",AQ16*AR16) -> 382.94 | AY16: =IF(OR(AW16="",AX16=""),"",AW16*AX16) | BX16: =IFERROR(VALUE(C16),0)+IFERROR(VALUE(I16),0)+IFERROR(VALUE(P16),0)+IFERROR(VALUE(V16),0)+IFERROR(VALUE(AB16),0)+IFERROR(VALUE(AH16),0)+IFERROR(VALUE(AN16),0)+IFERROR(VALUE(AT16),0)+IFERROR(VALUE(AZ16),0)+IFERROR(VALUE(BF16),0)+IFERROR(VALUE(BL16),0)+IFERROR(VALUE(BR16),0) -> 58265 | BY16: =IFERROR(VALUE(D16),0)+IFERROR(VALUE(J16),0)+IFERROR(VALUE(Q16),0)+IFERROR(VALUE(W16),0)+IFERROR(VALUE(AC16),0)+IFERROR(VALUE(AI16),0)+IFERROR(VALUE(AO16),0)+IFERROR(VALUE(AU16),0)+IFERROR(VALUE(BA16),0)+IFERROR(VALUE(BG16),0)+IFERROR(VALUE(BM16),0)+IFERROR(VALUE(BS16),0) -> 49011.67 | BZ16: =IFERROR(VALUE(E16),0)+IFERROR(VALUE(K16),0)+IFERROR(VALUE(R16),0)+IFERROR(VALUE(X16),0)+IFERROR(VALUE(AD16),0)+IFERROR(VALUE(AJ16),0)+IFERROR(VALUE(AP16),0)+IFERROR(VALUE(AV16),0)+IFERROR(VALUE(BB16),0)+IFERROR(VALUE(BH16),0)+IFERROR(VALUE(BN16),0)+IFERROR(VALUE(BT16),0) -> 0 | CA16: =IFERROR(VALUE(F16),0)+IFERROR(VALUE(L16),0)+IFERROR(VALUE(S16),0)+IFERROR(VALUE(Y16),0)+IFERROR(VALUE(AE16),0)+IFERROR(VALUE(AK16),0)+IFERROR(VALUE(AQ16),0)+IFERROR(VALUE(AW16),0)+IFERROR(VALUE(BC16),0)+IFERROR(VALUE(BI16),0)+IFERROR(VALUE(BO16),0)+IFERROR(VALUE(BU16),0) -> 9253.33 | CB16: =IFERROR(VALUE(H16),0)+IFERROR(VALUE(O16),0)+IFERROR(VALUE(U16),0)+IFERROR(VALUE(AA16),0)+IFERROR(VALUE(AG16),0)+IFERROR(VALUE(AM16),0)+IFERROR(VALUE(AS16),0)+IFERROR(VALUE(AY16),0)+IFERROR(VALUE(BE16),0)+IFERROR(VALUE(BK16),0)+IFERROR(VALUE(BQ16),0)+IFERROR(VALUE(BW16),0) -> 1850.67
A17: 7. MODESTO PAG-ARIGON - ONLINE | AH17: 162,003.01 | AI17: 110,493.80 | AK17: 51,509.21 | AL17: 20 | AM17: 10,301.84 | AN17: 89099.68 | AO17: 70549.92 | AP17: 0 | AQ17: =IF(COUNTA(AN17:AO17)=0,"",AN17-AO17) -> 18549.76 | AR17: 0.2 | AS17: =IF(OR(AQ17="",AR17=""),"",AQ17*AR17) -> 3709.952 | AT17: 48611.93 | AU17: 33254.19 | AW17: 15357.74 | AX17: 0.2 | AY17: =IF(OR(AW17="",AX17=""),"",AW17*AX17) -> 3071.548 | BX17: =IFERROR(VALUE(C17),0)+IFERROR(VALUE(I17),0)+IFERROR(VALUE(P17),0)+IFERROR(VALUE(V17),0)+IFERROR(VALUE(AB17),0)+IFERROR(VALUE(AH17),0)+IFERROR(VALUE(AN17),0)+IFERROR(VALUE(AT17),0)+IFERROR(VALUE(AZ17),0)+IFERROR(VALUE(BF17),0)+IFERROR(VALUE(BL17),0)+IFERROR(VALUE(BR17),0) -> 299714.62 | BY17: =IFERROR(VALUE(D17),0)+IFERROR(VALUE(J17),0)+IFERROR(VALUE(Q17),0)+IFERROR(VALUE(W17),0)+IFERROR(VALUE(AC17),0)+IFERROR(VALUE(AI17),0)+IFERROR(VALUE(AO17),0)+IFERROR(VALUE(AU17),0)+IFERROR(VALUE(BA17),0)+IFERROR(VALUE(BG17),0)+IFERROR(VALUE(BM17),0)+IFERROR(VALUE(BS17),0) -> 214297.91 | BZ17: =IFERROR(VALUE(E17),0)+IFERROR(VALUE(K17),0)+IFERROR(VALUE(R17),0)+IFERROR(VALUE(X17),0)+IFERROR(VALUE(AD17),0)+IFERROR(VALUE(AJ17),0)+IFERROR(VALUE(AP17),0)+IFERROR(VALUE(AV17),0)+IFERROR(VALUE(BB17),0)+IFERROR(VALUE(BH17),0)+IFERROR(VALUE(BN17),0)+IFERROR(VALUE(BT17),0) -> 0 | CA17: =IFERROR(VALUE(F17),0)+IFERROR(VALUE(L17),0)+IFERROR(VALUE(S17),0)+IFERROR(VALUE(Y17),0)+IFERROR(VALUE(AE17),0)+IFERROR(VALUE(AK17),0)+IFERROR(VALUE(AQ17),0)+IFERROR(VALUE(AW17),0)+IFERROR(VALUE(BC17),0)+IFERROR(VALUE(BI17),0)+IFERROR(VALUE(BO17),0)+IFERROR(VALUE(BU17),0) -> 85416.71 | CB17: =IFERROR(VALUE(H17),0)+IFERROR(VALUE(O17),0)+IFERROR(VALUE(U17),0)+IFERROR(VALUE(AA17),0)+IFERROR(VALUE(AG17),0)+IFERROR(VALUE(AM17),0)+IFERROR(VALUE(AS17),0)+IFERROR(VALUE(AY17),0)+IFERROR(VALUE(BE17),0)+IFERROR(VALUE(BK17),0)+IFERROR(VALUE(BQ17),0)+IFERROR(VALUE(BW17),0) -> 17083.34
A18: 8. RAMONITO VILLANUEVA - ONLINE | AH18: 69,472.78 | AI18: 47,749.20 | AK18: 21,723.58 | AL18: 20 | AM18: 4,344.72 | AN18: 42520.45 | AO18: 31779.18 | AP18: 0 | AQ18: =IF(COUNTA(AN18:AO18)=0,"",AN18-AO18) -> 10741.27 | AR18: 0.2 | AS18: =IF(OR(AQ18="",AR18=""),"",AQ18*AR18) -> 2148.254 | AT18: 44225.99 | AU18: 29994.11 | AW18: 14231.88 | AX18: 0.2 | AY18: =IF(OR(AW18="",AX18=""),"",AW18*AX18) -> 2846.376 | BX18: =IFERROR(VALUE(C18),0)+IFERROR(VALUE(I18),0)+IFERROR(VALUE(P18),0)+IFERROR(VALUE(V18),0)+IFERROR(VALUE(AB18),0)+IFERROR(VALUE(AH18),0)+IFERROR(VALUE(AN18),0)+IFERROR(VALUE(AT18),0)+IFERROR(VALUE(AZ18),0)+IFERROR(VALUE(BF18),0)+IFERROR(VALUE(BL18),0)+IFERROR(VALUE(BR18),0) -> 156219.22 | BY18: =IFERROR(VALUE(D18),0)+IFERROR(VALUE(J18),0)+IFERROR(VALUE(Q18),0)+IFERROR(VALUE(W18),0)+IFERROR(VALUE(AC18),0)+IFERROR(VALUE(AI18),0)+IFERROR(VALUE(AO18),0)+IFERROR(VALUE(AU18),0)+IFERROR(VALUE(BA18),0)+IFERROR(VALUE(BG18),0)+IFERROR(VALUE(BM18),0)+IFERROR(VALUE(BS18),0) -> 109522.49 | BZ18: =IFERROR(VALUE(E18),0)+IFERROR(VALUE(K18),0)+IFERROR(VALUE(R18),0)+IFERROR(VALUE(X18),0)+IFERROR(VALUE(AD18),0)+IFERROR(VALUE(AJ18),0)+IFERROR(VALUE(AP18),0)+IFERROR(VALUE(AV18),0)+IFERROR(VALUE(BB18),0)+IFERROR(VALUE(BH18),0)+IFERROR(VALUE(BN18),0)+IFERROR(VALUE(BT18),0) -> 0 | CA18: =IFERROR(VALUE(F18),0)+IFERROR(VALUE(L18),0)+IFERROR(VALUE(S18),0)+IFERROR(VALUE(Y18),0)+IFERROR(VALUE(AE18),0)+IFERROR(VALUE(AK18),0)+IFERROR(VALUE(AQ18),0)+IFERROR(VALUE(AW18),0)+IFERROR(VALUE(BC18),0)+IFERROR(VALUE(BI18),0)+IFERROR(VALUE(BO18),0)+IFERROR(VALUE(BU18),0) -> 46696.73 | CB18: =IFERROR(VALUE(H18),0)+IFERROR(VALUE(O18),0)+IFERROR(VALUE(U18),0)+IFERROR(VALUE(AA18),0)+IFERROR(VALUE(AG18),0)+IFERROR(VALUE(AM18),0)+IFERROR(VALUE(AS18),0)+IFERROR(VALUE(AY18),0)+IFERROR(VALUE(BE18),0)+IFERROR(VALUE(BK18),0)+IFERROR(VALUE(BQ18),0)+IFERROR(VALUE(BW18),0) -> 9339.35
A19: 9. ROCKY DELA PENA | AH19: 71,908.00 | AI19: 48,012.06 | AK19: 23,895.94 | AL19: 20 | AM19: 4,779.19 | AN19: 27180 | AO19: 20642.06 | AP19: 0 | AQ19: =IF(COUNTA(AN19:AO19)=0,"",AN19-AO19) -> 6537.94 | AR19: 0.2 | AS19: =IF(OR(AQ19="",AR19=""),"",AQ19*AR19) -> 1307.588 | AT19: 45600 | AU19: 23561.69 | AW19: 22038.31 | AX19: 0.2 | AY19: =IF(OR(AW19="",AX19=""),"",AW19*AX19) -> 4407.662 | BX19: =IFERROR(VALUE(C19),0)+IFERROR(VALUE(I19),0)+IFERROR(VALUE(P19),0)+IFERROR(VALUE(V19),0)+IFERROR(VALUE(AB19),0)+IFERROR(VALUE(AH19),0)+IFERROR(VALUE(AN19),0)+IFERROR(VALUE(AT19),0)+IFERROR(VALUE(AZ19),0)+IFERROR(VALUE(BF19),0)+IFERROR(VALUE(BL19),0)+IFERROR(VALUE(BR19),0) -> 144688 | BY19: =IFERROR(VALUE(D19),0)+IFERROR(VALUE(J19),0)+IFERROR(VALUE(Q19),0)+IFERROR(VALUE(W19),0)+IFERROR(VALUE(AC19),0)+IFERROR(VALUE(AI19),0)+IFERROR(VALUE(AO19),0)+IFERROR(VALUE(AU19),0)+IFERROR(VALUE(BA19),0)+IFERROR(VALUE(BG19),0)+IFERROR(VALUE(BM19),0)+IFERROR(VALUE(BS19),0) -> 92215.81 | BZ19: =IFERROR(VALUE(E19),0)+IFERROR(VALUE(K19),0)+IFERROR(VALUE(R19),0)+IFERROR(VALUE(X19),0)+IFERROR(VALUE(AD19),0)+IFERROR(VALUE(AJ19),0)+IFERROR(VALUE(AP19),0)+IFERROR(VALUE(AV19),0)+IFERROR(VALUE(BB19),0)+IFERROR(VALUE(BH19),0)+IFERROR(VALUE(BN19),0)+IFERROR(VALUE(BT19),0) -> 0 | CA19: =IFERROR(VALUE(F19),0)+IFERROR(VALUE(L19),0)+IFERROR(VALUE(S19),0)+IFERROR(VALUE(Y19),0)+IFERROR(VALUE(AE19),0)+IFERROR(VALUE(AK19),0)+IFERROR(VALUE(AQ19),0)+IFERROR(VALUE(AW19),0)+IFERROR(VALUE(BC19),0)+IFERROR(VALUE(BI19),0)+IFERROR(VALUE(BO19),0)+IFERROR(VALUE(BU19),0) -> 52472.19 | CB19: =IFERROR(VALUE(H19),0)+IFERROR(VALUE(O19),0)+IFERROR(VALUE(U19),0)+IFERROR(VALUE(AA19),0)+IFERROR(VALUE(AG19),0)+IFERROR(VALUE(AM19),0)+IFERROR(VALUE(AS19),0)+IFERROR(VALUE(AY19),0)+IFERROR(VALUE(BE19),0)+IFERROR(VALUE(BK19),0)+IFERROR(VALUE(BQ19),0)+IFERROR(VALUE(BW19),0) -> 10494.44
A20: 10. ROD SANTIAGO | AH20: 457,315.00 | AI20: 433,299.31 | AK20: 24,015.69 | AL20: 30 | AM20: 7,204.71 | AN20: 319200 | AO20: 285809.25 | AP20: 0 | AQ20: =IF(COUNTA(AN20:AO20)=0,"",AN20-AO20) -> 33390.75 | AR20: 0.2 | AS20: =IF(OR(AQ20="",AR20=""),"",AQ20*AR20) -> 6678.15 | AT20: 1354410 | AU20: 1129757.5 | AW20: 224652.49 | AX20: 0.3 | AY20: =IF(OR(AW20="",AX20=""),"",AW20*AX20) -> 67395.747 | BX20: =IFERROR(VALUE(C20),0)+IFERROR(VALUE(I20),0)+IFERROR(VALUE(P20),0)+IFERROR(VALUE(V20),0)+IFERROR(VALUE(AB20),0)+IFERROR(VALUE(AH20),0)+IFERROR(VALUE(AN20),0)+IFERROR(VALUE(AT20),0)+IFERROR(VALUE(AZ20),0)+IFERROR(VALUE(BF20),0)+IFERROR(VALUE(BL20),0)+IFERROR(VALUE(BR20),0) -> 2130925 | BY20: =IFERROR(VALUE(D20),0)+IFERROR(VALUE(J20),0)+IFERROR(VALUE(Q20),0)+IFERROR(VALUE(W20),0)+IFERROR(VALUE(AC20),0)+IFERROR(VALUE(AI20),0)+IFERROR(VALUE(AO20),0)+IFERROR(VALUE(AU20),0)+IFERROR(VALUE(BA20),0)+IFERROR(VALUE(BG20),0)+IFERROR(VALUE(BM20),0)+IFERROR(VALUE(BS20),0) -> 1848866.1 | BZ20: =IFERROR(VALUE(E20),0)+IFERROR(VALUE(K20),0)+IFERROR(VALUE(R20),0)+IFERROR(VALUE(X20),0)+IFERROR(VALUE(AD20),0)+IFERROR(VALUE(AJ20),0)+IFERROR(VALUE(AP20),0)+IFERROR(VALUE(AV20),0)+IFERROR(VALUE(BB20),0)+IFERROR(VALUE(BH20),0)+IFERROR(VALUE(BN20),0)+IFERROR(VALUE(BT20),0) -> 0 | CA20: =IFERROR(VALUE(F20),0)+IFERROR(VALUE(L20),0)+IFERROR(VALUE(S20),0)+IFERROR(VALUE(Y20),0)+IFERROR(VALUE(AE20),0)+IFERROR(VALUE(AK20),0)+IFERROR(VALUE(AQ20),0)+IFERROR(VALUE(AW20),0)+IFERROR(VALUE(BC20),0)+IFERROR(VALUE(BI20),0)+IFERROR(VALUE(BO20),0)+IFERROR(VALUE(BU20),0) -> 282058.93 | CB20: =IFERROR(VALUE(H20),0)+IFERROR(VALUE(O20),0)+IFERROR(VALUE(U20),0)+IFERROR(VALUE(AA20),0)+IFERROR(VALUE(AG20),0)+IFERROR(VALUE(AM20),0)+IFERROR(VALUE(AS20),0)+IFERROR(VALUE(AY20),0)+IFERROR(VALUE(BE20),0)+IFERROR(VALUE(BK20),0)+IFERROR(VALUE(BQ20),0)+IFERROR(VALUE(BW20),0) -> 81278.607
A21: 11. STORE | C21: 1,557.00 | D21: 494.40 | E21: =IF(VALUE(C21)>0,'Store Expenses'!D34,0) -> 702225.05 | F21: 1,062.60 | G21: 20 | H21: 212.52 | K21: =IF(VALUE(I21)>0,'Store Expenses'!E34,0) -> 0 | R21: =IF(VALUE(P21)>0,'Store Expenses'!F34,0) -> 0 | X21: =IF(VALUE(V21)>0,'Store Expenses'!G34,0) -> 0 | AB21: 37,040.00 | AC21: 33,552.20 | AD21: =IF(VALUE(AB21)>0,'Store Expenses'!H34,0) -> 1005820.9 | AE21: 3,487.80 | AF21: 20 | AG21: 697.56 | AH21: 2,807,555.39 | AI21: 2,292,906.95 | AJ21: =IF(VALUE(AH21)>0,'Store Expenses'!I34,0) -> 778781.08 | AK21: 514,648.44 | AL21: 30 | AM21: 154,394.53 | AN21: 3234973.3 | AO21: 2685993.5 | AP21: =IF(VALUE(AN21)>0,'Store Expenses'!J34,0) -> 754819.77 | AQ21: =IF(COUNTA(AN21:AO21)=0,"",AN21-AO21) -> 548979.8 | AR21: 0.3 | AS21: =IF(OR(AQ21="",AR21=""),"",AQ21*AR21) -> 164693.94 | AT21: 2848080.1 | AU21: 2094480.2 | AV21: =IF(VALUE(AT21)>0,'Store Expenses'!K34,0) -> 753463.83 | AW21: =IF(AT21=0,"",AT21-AU21) -> 753599.85 | AX21: 0.3 | AY21: =IF(OR(AW21="",AX21=""),"",AW21*AX21) -> 226079.96 | BB21: =IF(VALUE(AZ21)>0,'Store Expenses'!L34,0) -> 0 | BH21: =IF(VALUE(BF21)>0,'Store Expenses'!M34,0) -> 0 | BN21: =IF(VALUE(BL21)>0,'Store Expenses'!N34,0) -> 0 | BT21: =IF(VALUE(BR21)>0,'Store Expenses'!O34,0) -> 0 | BX21: =IFERROR(VALUE(C21),0)+IFERROR(VALUE(I21),0)+IFERROR(VALUE(P21),0)+IFERROR(VALUE(V21),0)+IFERROR(VALUE(AB21),0)+IFERROR(VALUE(AH21),0)+IFERROR(VALUE(AN21),0)+IFERROR(VALUE(AT21),0)+IFERROR(VALUE(AZ21),0)+IFERROR(VALUE(BF21),0)+IFERROR(VALUE(BL21),0)+IFERROR(VALUE(BR21),0) -> 8929205.8 | BY21: =IFERROR(VALUE(D21),0)+IFERROR(VALUE(J21),0)+IFERROR(VALUE(Q21),0)+IFERROR(VALUE(W21),0)+IFERROR(VALUE(AC21),0)+IFERROR(VALUE(AI21),0)+IFERROR(VALUE(AO21),0)+IFERROR(VALUE(AU21),0)+IFERROR(VALUE(BA21),0)+IFERROR(VALUE(BG21),0)+IFERROR(VALUE(BM21),0)+IFERROR(VALUE(BS21),0) -> 7107427.3 | BZ21: =E21+K21+R21+X21+AD21+AJ21+AP21+AV21+BB21+BH21+BN21+BT21 -> 3995110.6 | CA21: =BX21-BY21-BZ21 -> -2173332.1 | CB21: =IFERROR(VALUE(H21),0)+IFERROR(VALUE(O21),0)+IFERROR(VALUE(U21),0)+IFERROR(VALUE(AA21),0)+IFERROR(VALUE(AG21),0)+IFERROR(VALUE(AM21),0)+IFERROR(VALUE(AS21),0)+IFERROR(VALUE(AY21),0)+IFERROR(VALUE(BE21),0)+IFERROR(VALUE(BK21),0)+IFERROR(VALUE(BQ21),0)+IFERROR(VALUE(BW21),0) -> 546078.51
C22: 1,557.00 | D22: 494.40 | E22: 0.00 | F22: 1,062.60 | H22: 212.52 | I22: 0.00 | J22: 0.00 | K22: 0.00 | L22: 0.00 | O22: 0.00 | P22: 0.00 | Q22: 0.00 | R22: 0.00 | S22: 0.00 | U22: 0.00 | V22: 0.00 | W22: 0.00 | X22: 0.00 | Y22: 0.00 | AA22: 0.00 | AB22: 45,740.00 | AC22: 39,352.20 | AD22: 0.00 | AE22: 6,387.80 | AG22: 1,277.56 | AH22: 4,675,516.81 | AI22: 3,810,549.33 | AK22: 864,967.48 | AM22: 243,214.02 | AN22: =SUM(AN11:AN21) -> 5062842.6 | AO22: =SUM(AO11:AO21) -> 4152505.5 | AP22: =SUM(AP11:AP20) -> 0 | AQ22: =SUM(AQ11:AQ21) -> 910337.09 | AS22: =SUM(AS11:AS21) -> 246470.19 | AT22: =SUM(AT11:AT21) -> 5329398.7 | AU22: =SUM(AU11:AU21) -> 4036254.6 | AV22: =SUM(AV11:AV20) -> 0 | AW22: =SUM(AW11:AW21) -> 1293144 | AY22: =SUM(AY11:AY21) -> 378814.12 | AZ22: 0.00 | BA22: 0.00 | BB22: 0.00 | BC22: 0.00 | BE22: 0.00 | BF22: 0.00 | BG22: 0.00 | BH22: 0.00 | BI22: 0.00 | BK22: 0.00 | BL22: 0.00 | BM22: 0.00 | BN22: 0.00 | BO22: 0.00 | BQ22: 0.00 | BR22: 0.00 | BS22: 0.00 | BT22: 0.00 | BU22: 0.00 | BW22: 0.00 | BX22: =SUM(BX11:BX21) -> 15115055 | BY22: =SUM(BY11:BY21) -> 12039156 | BZ22: =SUM(BZ11:BZ21) -> 3995110.6 | CA22: =SUM(CA11:CA21) -> -919211.62 | CB22: =SUM(CB11:CB21) -> 869988.42
A23: BOTTOMLINE | F23: =IF(IFERROR(VALUE(F22),0)>0,IFERROR(VALUE(F22),0)-'Store Expenses'!D34,0) -> -701162.45 | L23: =IF(IFERROR(VALUE(L22),0)>0,IFERROR(VALUE(L22),0)-'Store Expenses'!E34,0) -> 0 | S23: =IF(IFERROR(VALUE(S22),0)>0,IFERROR(VALUE(S22),0)-'Store Expenses'!F34,0) -> 0 | Y23: =IF(IFERROR(VALUE(Y22),0)>0,IFERROR(VALUE(Y22),0)-'Store Expenses'!G34,0) -> 0 | AE23: =IF(IFERROR(VALUE(AE22),0)>0,IFERROR(VALUE(AE22),0)-'Store Expenses'!H34,0) -> -999433.09 | AK23: =IF(IFERROR(VALUE(AK22),0)>0,IFERROR(VALUE(AK22),0)-'Store Expenses'!I34,0) -> 86186.397 | AQ23: =IF(IFERROR(VALUE(AQ22),0)>0,IFERROR(VALUE(AQ22),0)-'Store Expenses'!J34,0) -> 155517.32 | AW23: =IF(IFERROR(VALUE(AW22),0)>0,IFERROR(VALUE(AW22),0)-'Store Expenses'!K34,0) -> 539680.21 | BC23: =IF(IFERROR(VALUE(BC22),0)>0,IFERROR(VALUE(BC22),0)-'Store Expenses'!L34,0) -> 0 | BI23: =IF(IFERROR(VALUE(BI22),0)>0,IFERROR(VALUE(BI22),0)-'Store Expenses'!M34,0) -> 0 | BO23: =IF(IFERROR(VALUE(BO22),0)>0,IFERROR(VALUE(BO22),0)-'Store Expenses'!N34,0) -> 0 | BU23: =IF(IFERROR(VALUE(BU22),0)>0,IFERROR(VALUE(BU22),0)-'Store Expenses'!O34,0) -> 0 | CA23: =F23+L23+S23+Y23+AE23+AK23+AQ23+AW23+BC23+BI23+BO23+BU23 -> -919211.62

Sheet Store Expenses
K1: ➤ Executive Summary
B3: MONTHLY EXPENSES | C3: Annualized | D3: January | E3: February | F3: March | G3: April | H3: May | I3: June | J3: July | K3: Aug. | L3: Sept. | M3: Oct. | N3: Nov. | O3: Dec.
B4: Description
B5: 13th Month Pay | C5: 200000 | D5: =Table9[[#This Row],[Annualized]]/12 -> 16666.667 | E5: =Table9[[#This Row],[Annualized]]/12 -> 16666.667 | F5: 16666.67 | G5: 16666.67 | H5: 16666.67 | I5: 16666.67 | J5: 16666.67 | K5: 16666.67 | L5: 16666.67 | M5: 16666.67 | N5: 16666.67 | O5: 16666.67
B6: Mayor's Permit | C6: 200000 | D6: =Table9[[#This Row],[Annualized]]/12 -> 16666.667 | E6: =Table9[[#This Row],[Annualized]]/12 -> 16666.667 | F6: =Table9[[#This Row],[Annualized]]/12 -> 16666.667 | G6: 16667.67 | H6: 16667.67 | I6: 16667.67 | J6: 16667.67 | K6: 16667.67 | L6: 16667.67 | M6: 16667.67 | N6: 16667.67 | O6: 16667.67 | Y6: GO SOLAR
B7: Ishabella 5th Anniv. | C7: 50000 | D7: =Table9[[#This Row],[Annualized]]/12 -> 4166.6667 | E7: =Table9[[#This Row],[Annualized]]/12 -> 4166.6667 | F7: 4166.67 | G7: 4166.67 | H7: 4166.67 | I7: 4166.67 | J7: 4166.67 | K7: 4166.67 | L7: 4166.67 | M7: 4166.67 | N7: 4166.67 | O7: 4166.67
B8: Solar | C8: 50000 | D8: 25000 | E8: 25000 | Y8: Payment | Z8: 185400
B9: Solar hulugan | C9: 16166 | E9: 16166 | F9: 16166 | G9: 16166 | H9: 13984.91 | I9: 13984.91 | J9: 13984.91 | K9: 13984.91 | L9: 13984.91 | M9: 13984.91 | N9: 13984.91 | O9: 13984.91 | Y9: Capital | Z9: 169200
Y10: INCOME | Z10: =Z8-Z9 -> 16200
B11: NEW BODEGA RENTAL | C11: 102100 | D11: 72100 | E11: 72100 | F11: 92100 | G11: 92100 | H11: 92100 | I11: 92100 | J11: 92100 | K11: 92100 | L11: 92100 | M11: 92100 | N11: 92100 | O11: 92100
F12: 40000 | Y12: Payment | Z12: 1236000
B13: Wigo Monthly | C13: 13844 | D13: 13844 | E13: 13844 | F13: 13844 | G13: 13844 | H13: 13844 | I13: 13844 | J13: 13844 | K13: 13844 | L13: 13844 | M13: 13844 | N13: 13844 | O13: 13844 | Y13: Capital | Z13: 1128000
B14: HINO | C14: 36604 | H14: 37000 | I14: 36604 | J14: 36604 | K14: 36604 | L14: 36604 | M14: 36604 | N14: 36604 | O14: 36604
B15: Prof. Fee Nang nine | C15: 10000 | D15: 10000 | E15: 10000
B17: OWNER EXPENSES | C17: 60000 | D17: 60000 | E17: 60000 | F17: 60000 | G17: 60000 | H17: 60000 | I17: 60000 | J17: 60000 | K17: 60000 | L17: 60000 | M17: 60000 | N17: 60000 | O17: 60000 | Y17: INCOME | Z17: =Z12-Z13 -> 108000
B18: OWNER ALLOWANCE | C18: 50000 | D18: 50000 | E18: 50000 | F18: 50000 | G18: 50000 | H18: 50000 | I18: 50000 | J18: 50000 | K18: 50000 | L18: 50000 | M18: 50000 | N18: 50000 | O18: 50000
B19: Salary 15th | D19: 75339.93 | E19: 94491.54 | F19: 101451.72 | G19: 102349.44 | H19: 95214.51 | I19: 113569.74 | J19: 93852.85 | K19: 105051.56
B20: Salary 30th | D20: 99491.54 | E20: 99385.54 | F20: 103932.6 | G20: 107109.29 | H20: 102566.28 | I20: 102097.54 | J20: 102304.78 | K20: 105311.03
B21: MANDATORIES | D21: 40000 | E21: 40000 | F21: 40000 | G21: 40000 | H21: 40000 | I21: 40000 | J21: 40000 | K21: 40000 | L21: 40000 | M21: 40000 | N21: 40000 | O21: 40000 | Y21: JBB | Z21: MARK UP | AA21: Remarks
B22: Others | D22: 40000 | E22: 40000 | F22: 40000 | G22: 40000 | I22: =12000+8000 -> 20000 | J22: 4000 | Y22: JBB | Z22: MARK UP | AA22: Remarks
B23: STORE EVERY DAY EXPENSES | D23: 36055.65 | E23: 36598.45 | F23: 49000 | G23: 47148 | H23: 81934.4 | I23: 56236.75 | J23: 58262.67 | K23: 61027.79 | Y23: 46129 | Z23: 80250 | AA23: Materials
B24: STORE BILLS | D24: 30215 | E24: 16965.83 | F24: 14829.47 | G24: 25791.34 | H24: 35960.71 | I24: 33278.3 | J24: 26717.66 | K24: 28348.7
B25: Store - Ikot Expenses | D25: 17621.43 | E25: 22695.63 | F25: 25593.14 | G25: 32802 | H25: 25618.08 | J25: 22646.06 | K25: 11048
B26: Zambales/Lipa Arnold 50% | D26: 5057.5 | E26: 1940 | F26: 2003 | G26: 4632 | H26: 4164 | I26: 8376 | J26: 4613 | K26: 2454 | Z26: =SUM(Z22:Z25) -> 80250
B27: Mariosoft | C27: 39627.77 | I27: =Table9[[#This Row],[Annualized]]*3% -> 1188.8331 | J27: =Table9[[#This Row],[Annualized]]*3% -> 1188.8331 | K27: =Table9[[#This Row],[Annualized]]*3% -> 1188.8331 | L27: =Table9[[#This Row],[Annualized]]*3% -> 1188.8331 | M27: =Table9[[#This Row],[Annualized]]*3% -> 1188.8331 | N27: =Table9[[#This Row],[Annualized]]*3% -> 1188.8331 | O27: =Table9[[#This Row],[Annualized]]*3% -> 1188.8331
B28: MARKETING | I28: 10000 | J28: 5000 | K28: 5000 | L28: 5000
B29: ADDITONAL FEES | F29: 11503.386
B30: Client Commission-Materials (S.I) | D30: 0 | E30: 7088.4 | F30: 0 | G30: 196504.74 | H30: 51370
B31: Client Commission-Aircon units (S.I) | D31: 0 | F31: 0 | G31: 311471.35 | H31: 174562.99
B32: BANK FEE (BOUNCE CHECK) | D32: 0 | F32: 7050 | G32: 500 | J32: 2200
B33: Bad Debt Repayment | C33: =SUM(D33:O33) -> 1080000 | D33: 90000 | E33: 90000 | F33: 90000 | G33: 90000 | H33: 90000 | I33: 90000 | J33: 90000 | K33: 90000 | L33: 90000 | M33: 90000 | N33: 90000 | O33: 90000
B34: TOTAL | D34: =SUM(D4:D33) -> 702225.05 | E34: =SUM(E4:E33) -> 733775.39 | F34: =SUM(F4:F33) -> 794973.32 | G34: =SUM(G4:G33) -> 1267919.2 | H34: =SUM(H4:H33) -> 1005820.9 | I34: =SUM(I4:I33) -> 778781.08 | J34: =SUM(J4:J33) -> 754819.77 | K34: =SUM(K4:K33) -> 753463.83 | ... O34: =SUM(O4:O33) -> 435222.75
E36: Banana boat | F36: 0
F37: =SUM(F36:F36) -> 0

Sheet Ikot Sales
A1: Agent | B1: Date | C1: Month | D1: Year | E1: Sales | F1: Cash Collected | G1: G-Cash | H1: Total Collected | I1: Expenses | J1: PDC | K1: Location | L1: Gas Top Up | M1: Net Sales | N1: Collection Rate % | O1: Old balance | P1: New Balance | R1: ➤ Executive Summary
A2: ARNOLD | B2: 46073 | C2: February | D2: 2026 | E2: 337400 | F2: 316700 | G2: 9930 | H2: =F2+G2 -> 326630 | I2: 967.58 | J2: 0 | K2: Cubao/Pasig/Antipolo | L2: 1500 | M2: =E2-I2 -> 336432.42 | N2: =IF(E2>0,H2/E2,0) -> 0.96807943 | P2: =E2-ikot[[#This Row],[Total Collected]] -> 10770
A3: ARNOLD | B3: 46108 | C3: March | D3: 2026 | E3: 44240 | F3: 20000 | G3: 0 | H3: =F3+G3 -> 20000 | I3: 4696.93 | J3: 0 | K3: Pangasinan | L3: 0 | M3: =E3-I3 -> 39543.07 | N3: =IF(E3>0,H3/E3,0) -> 0.45207957 | P3: =E3-ikot[[#This Row],[Total Collected]] -> 24240
A4: ARNOLD | B4: 46129 | C4: April | D4: 2026 | E4: 62240 | F4: 21000 | G4: 2500 | H4: =F4+G4 -> 23500 | I4: 2088 | J4: 0 | K4: Nasugbo | L4: 1270 | M4: =E4-I4 -> 60152 | N4: =IF(E4>0,H4/E4,0) -> 0.37757069 | P4: =E4-ikot[[#This Row],[Total Collected]] -> 38740
A5: ARNOLD | B5: 46141 | C5: April | D5: 2026 | E5: 63454 | F5: 22900 | G5: 4750 | H5: =F5+G5 -> 27650 | I5: 900 | J5: 0 | K5: Cubao/Pasig/Antipolo | L5: 0 | M5: =E5-I5 -> 62554 | N5: =IF(E5>0,H5/E5,0) -> 0.43574873 | P5: =E5-ikot[[#This Row],[Total Collected]] -> 35804
A6: ARNOLD | B6: 46155 | C6: May | D6: 2026 | E6: 135590 | F6: 85770 | G6: 0 | H6: =F6+G6 -> 85770 | I6: 2554 | J6: 0 | K6: Nueva Ecija | L6: 0 | M6: =E6-I6 -> 133036 | N6: =IF(E6>0,H6/E6,0) -> 0.63256877 | P6: =E6-ikot[[#This Row],[Total Collected]] -> 49820
A7: ARNOLD | B7: 46163 | C7: May | D7: 2026 | E7: 216600 | F7: 182350 | G7: 4660 | H7: =F7+G7 -> 187010 | I7: 1104 | J7: 0 | K7: Cubao/Pasig/Antipolo | L7: 0 | M7: =E7-I7 -> 215496 | N7: =IF(E7>0,H7/E7,0) -> 0.86338873 | P7: =E7-ikot[[#This Row],[Total Collected]] -> 29590
A8: ARNOLD | B8: 46178 | C8: June | D8: 2026 | E8: 112860 | F8: 66370 | G8: 4500 | H8: =F8+G8 -> 70870 | I8: 4519.92 | J8: 0 | K8: Pangasinan | L8: 0 | M8: =E8-I8 -> 108340.08 | N8: =IF(E8>0,H8/E8,0) -> 0.62794613 | P8: =E8-ikot[[#This Row],[Total Collected]] -> 41990
A9: ARNOLD | B9: 46191 | C9: June | D9: 2026 | E9: 221262 | F9: 148960 | G9: 7100 | H9: =F9+G9 -> 156060 | I9: 791 | J9: 0 | K9: Cubao/Pasig/Antipolo | L9: 0 | M9: =E9-I9 -> 220471 | N9: =IF(E9>0,H9/E9,0) -> 0.70531768 | P9: =E9-ikot[[#This Row],[Total Collected]] -> 65202
A10: ARNOLD | B10: 46192 | C10: June | D10: 2026 | E10: 81080 | F10: 43670 | G10: 2080 | H10: =F10+G10 -> 45750 | I10: 830 | J10: 0 | K10: Cubao/Pasig/Antipolo | L10: 0 | M10: =E10-I10 -> 80250 | N10: =IF(E10>0,H10/E10,0) -> 0.56425752 | P10: =E10-ikot[[#This Row],[Total Collected]] -> 35330
A11: ARNOLD | B11: 46206 | C11: July | D11: 2026 | E11: 88200 | F11: 77250 | G11: 7500 | H11: =F11+G11 -> 84750 | I11: 4690 | J11: 0 | K11: Nasugbo | L11: 2500 | M11: =E11-I11 -> 83510 | N11: =IF(E11>0,H11/E11,0) -> 0.96088435 | P11: =E11-ikot[[#This Row],[Total Collected]] -> 3450
A12: ARNOLD | B12: 46227 | C12: July | D12: 2026 | E12: 234030 | F12: 181720 | G12: 15200 | H12: =F12+G12 -> 196920 | I12: 4333 | J12: 0 | K12: Pangasinan | L12: 0 | M12: =E12-I12 -> 229697 | N12: =IF(E12>0,H12/E12,0) -> 0.84143059 | P12: =E12-ikot[[#This Row],[Total Collected]] -> 37110
A13: RAYMART | B13: 46029 | C13: January | D13: 2026 | E13: 23740 | F13: 11600 | G13: 4700 | H13: =F13+G13 -> 16300 | I13: 1300 | J13: 0 | K13: Cubao/Pasig/Antipolo | L13: 0 | M13: =E13-I13 -> 22440 | N13: =IF(E13>0,H13/E13,0) -> 0.68660489 | P13: =E13-ikot[[#This Row],[Total Collected]] -> 7440
... A76: RAYMART | B76: 46260 | C76: August | D76: 2026 | E76: 43080 | F76: 26610 | G76: 17675 | H76: =F76+G76 -> 44285 | I76: 1000 | J76: 0 | K76: Cubao | L76: 3524.71 | M76: =E76-I76 -> 42080 | N76: =IF(E76>0,H76/E76,0) -> 1.0279712 | P76: =E76-ikot[[#This Row],[Total Collected]] -> -1205
A77: ARNOLD | B77: 46262 | C77: August | D77: 2026 | E77: 68439 | F77: 41570 | G77: 0 | H77: =F77+G77 -> 41570 | I77: 4908 | J77: 20500 | K77: Lucena | M77: =E77-I77 -> 63531 | N77: =IF(E77>0,H77/E77,0) -> 0.60740221 | P77: =E77-ikot[[#This Row],[Total Collected]] -> 26869

Sheet Ikot Summary
A1: IKOT SALES SUMMARY - 2026 | E1: ➤ Executive Summary
A3: AGENT SUMMARY
A4: Agent | B4: Sales | C4: Cash Collected | D4: G-Cash | E4: Expenses | F4: Net Sales | G4: Collection Rate
A5: ARNOLD | B5: =SUMIF('Ikot Sales'!A:A,A5,'Ikot Sales'!E:E) -> 1665395 | C5: =SUMIF('Ikot Sales'!A:A,A5,'Ikot Sales'!F:F) -> 1208260 | D5: =SUMIF('Ikot Sales'!A:A,A5,'Ikot Sales'!G:G) -> 58220 | E5: =SUMIF('Ikot Sales'!A:A,A5,'Ikot Sales'!I:I) -> 32382.43 | F5: =SUMIF('Ikot Sales'!A:A,A5,'Ikot Sales'!M:M) -> 1633012.6 | G5: =IF(B5>0,C5/B5,0) -> 0.72550956
A6: RAYMART | B6: =SUMIF('Ikot Sales'!A:A,A6,'Ikot Sales'!E:E) -> 3498999 | C6: =SUMIF('Ikot Sales'!A:A,A6,'Ikot Sales'!F:F) -> 2455149 | D6: =SUMIF('Ikot Sales'!A:A,A6,'Ikot Sales'!G:G) -> 393340 | E6: =SUMIF('Ikot Sales'!A:A,A6,'Ikot Sales'!I:I) -> 180224.5 | F6: =SUMIF('Ikot Sales'!A:A,A6,'Ikot Sales'!M:M) -> 3318774.5 | G6: =IF(B6>0,C6/B6,0) -> 0.70167182
A7: TOTAL | B7: =SUM(B5:B6) -> 5164394 | C7: =SUM(C5:C6) -> 3663409 | D7: =SUM(D5:D6) -> 451560 | E7: =SUM(E5:E6) -> 212606.93 | F7: =SUM(F5:F6) -> 4951787.1 | G7: =IF(B7>0,C7/B7,0) -> 0.70935893
A9: MONTHLY SUMMARY
A10: Month | B10: Sales | C10: Cash Collected | D10: G-Cash | E10: Expenses | F10: Net Sales | G10: Collection Rate
A11: January | B11: =SUMIF('Ikot Sales'!C:C,"January",'Ikot Sales'!E:E) -> 316420 | C11: =SUMIF('Ikot Sales'!C:C,"January",'Ikot Sales'!F:F) -> 252960 | D11: =SUMIF('Ikot Sales'!C:C,"January",'Ikot Sales'!G:G) -> 94575 | E11: =SUMIF('Ikot Sales'!C:C,"January",'Ikot Sales'!I:I) -> 19722.53 | F11: =SUMIF('Ikot Sales'!C:C,"January",'Ikot Sales'!M:M) -> 296697.47 | G11: =IF(B11>0,(C11+D11)/B11,0) -> 1.0983345
A12: February | B12: =SUMIF('Ikot Sales'!C:C,"February",'Ikot Sales'!E:E) -> 876445 | C12: =SUMIF('Ikot Sales'!C:C,"February",'Ikot Sales'!F:F) -> 671700 | D12: =SUMIF('Ikot Sales'!C:C,"February",'Ikot Sales'!G:G) -> 61355 | E12: =SUMIF('Ikot Sales'!C:C,"February",'Ikot Sales'!I:I) -> 27566.72 | F12: =SUMIF('Ikot Sales'!C:C,"February",'Ikot Sales'!M:M) -> 848878.28 | G12: =IF(B12>0,(C12+D12)/B12,0) -> 0.83639589
A13: March | B13: =SUMIF('Ikot Sales'!C:C,"March",'Ikot Sales'!E:E) -> 693275 | C13: =SUMIF('Ikot Sales'!C:C,"March",'Ikot Sales'!F:F) -> 589300 | D13: =SUMIF('Ikot Sales'!C:C,"March",'Ikot Sales'!G:G) -> 58400 | E13: =SUMIF('Ikot Sales'!C:C,"March",'Ikot Sales'!I:I) -> 42080.93 | F13: =SUMIF('Ikot Sales'!C:C,"March",'Ikot Sales'!M:M) -> 651194.07 | G13: =IF(B13>0,(C13+D13)/B13,0) -> 0.9342613
A14: April | B14: =SUMIF('Ikot Sales'!C:C,"April",'Ikot Sales'!E:E) -> 651781 | C14: =SUMIF('Ikot Sales'!C:C,"April",'Ikot Sales'!F:F) -> 464150 | D14: =SUMIF('Ikot Sales'!C:C,"April",'Ikot Sales'!G:G) -> 45510 | E14: =SUMIF('Ikot Sales'!C:C,"April",'Ikot Sales'!I:I) -> 31892.08 | F14: =SUMIF('Ikot Sales'!C:C,"April",'Ikot Sales'!M:M) -> 619888.92 | G14: =IF(B14>0,(C14+D14)/B14,0) -> 0.78194977
A15: May | B15: =SUMIF('Ikot Sales'!C:C,"May",'Ikot Sales'!E:E) -> 646405 | C15: =SUMIF('Ikot Sales'!C:C,"May",'Ikot Sales'!F:F) -> 516205 | D15: =SUMIF('Ikot Sales'!C:C,"May",'Ikot Sales'!G:G) -> 61980 | E15: =SUMIF('Ikot Sales'!C:C,"May",'Ikot Sales'!I:I) -> 26012.41 | F15: =SUMIF('Ikot Sales'!C:C,"May",'Ikot Sales'!M:M) -> 620392.59 | G15: =IF(B15>0,(C15+D15)/B15,0) -> 0.89446245
A16: June | B16: =SUMIF('Ikot Sales'!C:C,"June",'Ikot Sales'!E:E) -> 846911 | C16: =SUMIF('Ikot Sales'!C:C,"June",'Ikot Sales'!F:F) -> 546199 | D16: =SUMIF('Ikot Sales'!C:C,"June",'Ikot Sales'!G:G) -> 51765 | E16: =SUMIF('Ikot Sales'!C:C,"June",'Ikot Sales'!I:I) -> 40353.26 | F16: =SUMIF('Ikot Sales'!C:C,"June",'Ikot Sales'!M:M) -> 806557.74 | G16: =IF(B16>0,(C16+D16)/B16,0) -> 0.70605294
A17: July | B17: =SUMIF('Ikot Sales'!C:C,"July",'Ikot Sales'!E:E) -> 799468 | C17: =SUMIF('Ikot Sales'!C:C,"July",'Ikot Sales'!F:F) -> 361245 | D17: =SUMIF('Ikot Sales'!C:C,"July",'Ikot Sales'!G:G) -> 34700 | E17: =SUMIF('Ikot Sales'!C:C,"July",'Ikot Sales'!I:I) -> 9023 | F17: =SUMIF('Ikot Sales'!C:C,"July",'Ikot Sales'!M:M) -> 790445 | G17: =IF(B17>0,(C17+D17)/B17,0) -> 0.4952606
A18: August | B18: =SUMIF('Ikot Sales'!C:C,"August",'Ikot Sales'!E:E) -> 333689 | C18: =SUMIF('Ikot Sales'!C:C,"August",'Ikot Sales'!F:F) -> 261650 | D18: =SUMIF('Ikot Sales'!C:C,"August",'Ikot Sales'!G:G) -> 43275 | E18: =SUMIF('Ikot Sales'!C:C,"August",'Ikot Sales'!I:I) -> 15956 | F18: =SUMIF('Ikot Sales'!C:C,"August",'Ikot Sales'!M:M) -> 317733 | G18: =IF(B18>0,(C18+D18)/B18,0) -> 0.91379998
A19: September | B19: =SUMIF('Ikot Sales'!C:C,"September",'Ikot Sales'!E:E) -> 0 | C19: =SUMIF('Ikot Sales'!C:C,"September",'Ikot Sales'!F:F) -> 0 | D19: =SUMIF('Ikot Sales'!C:C,"September",'Ikot Sales'!G:G) -> 0 | E19: =SUMIF('Ikot Sales'!C:C,"September",'Ikot Sales'!I:I) -> 0 | F19: =SUMIF('Ikot Sales'!C:C,"September",'Ikot Sales'!M:M) -> 0 | G19: =IF(B19>0,(C19+D19)/B19,0) -> 0
A20: October | B20: =SUMIF('Ikot Sales'!C:C,"October",'Ikot Sales'!E:E) -> 0 | C20: =SUMIF('Ikot Sales'!C:C,"October",'Ikot Sales'!F:F) -> 0 | D20: =SUMIF('Ikot Sales'!C:C,"October",'Ikot Sales'!G:G) -> 0 | E20: =SUMIF('Ikot Sales'!C:C,"October",'Ikot Sales'!I:I) -> 0 | F20: =SUMIF('Ikot Sales'!C:C,"October",'Ikot Sales'!M:M) -> 0 | G20: =IF(B20>0,(C20+D20)/B20,0) -> 0
A21: November | B21: =SUMIF('Ikot Sales'!C:C,"November",'Ikot Sales'!E:E) -> 0 | C21: =SUMIF('Ikot Sales'!C:C,"November",'Ikot Sales'!F:F) -> 0 | D21: =SUMIF('Ikot Sales'!C:C,"November",'Ikot Sales'!G:G) -> 0 | E21: =SUMIF('Ikot Sales'!C:C,"November",'Ikot Sales'!I:I) -> 0 | F21: =SUMIF('Ikot Sales'!C:C,"November",'Ikot Sales'!M:M) -> 0 | G21: =IF(B21>0,(C21+D21)/B21,0) -> 0
A22: December | B22: =SUMIF('Ikot Sales'!C:C,"December",'Ikot Sales'!E:E) -> 0 | C22: =SUMIF('Ikot Sales'!C:C,"December",'Ikot Sales'!F:F) -> 0 | D22: =SUMIF('Ikot Sales'!C:C,"December",'Ikot Sales'!G:G) -> 0 | E22: =SUMIF('Ikot Sales'!C:C,"December",'Ikot Sales'!I:I) -> 0 | F22: =SUMIF('Ikot Sales'!C:C,"December",'Ikot Sales'!M:M) -> 0 | G22: =IF(B22>0,(C22+D22)/B22,0) -> 0
A23: TOTAL | B23: =SUM(B11:B22) -> 5164394 | C23: =SUM(C11:C22) -> 3663409 | D23: =SUM(D11:D22) -> 451560 | E23: =SUM(E11:E22) -> 212606.93 | F23: =SUM(F11:F22) -> 4951787.1 | G23: =IF(B23>0,C23/B23,0) -> 0.70935893
A25: AGENT SALES PER MONTH
A26: Agent | B26: Jan | C26: Feb | D26: Mar | E26: Apr | F26: May | G26: Jun | H26: Jul | I26: Aug | J26: Sep | K26: Oct | L26: Nov | M26: Dec | N26: TOTAL
A27: ARNOLD | B27: =SUMIFS('Ikot Sales'!E:E,'Ikot Sales'!A:A,"ARNOLD",'Ikot Sales'!C:C,"January") -> 0 | C27: =SUMIFS('Ikot Sales'!E:E,'Ikot Sales'!A:A,"ARNOLD",'Ikot Sales'!C:C,"February") -> 337400 | D27: =SUMIFS('Ikot Sales'!E:E,'Ikot Sales'!A:A,"ARNOLD",'Ikot Sales'!C:C,"March") -> 44240 | E27: =SUMIFS('Ikot Sales'!E:E,'Ikot Sales'!A:A,"ARNOLD",'Ikot Sales'!C:C,"April") -> 125694 | F27: =SUMIFS('Ikot Sales'!E:E,'Ikot Sales'!A:A,"ARNOLD",'Ikot Sales'!C:C,"May") -> 352190 | G27: =SUMIFS('Ikot Sales'!E:E,'Ikot Sales'!A:A,"ARNOLD",'Ikot Sales'!C:C,"June") -> 415202 | H27: =SUMIFS('Ikot Sales'!E:E,'Ikot Sales'!A:A,"ARNOLD",'Ikot Sales'!C:C,"July") -> 322230 | I27: =SUMIFS('Ikot Sales'!E:E,'Ikot Sales'!A:A,"ARNOLD",'Ikot Sales'!C:C,"August") -> 68439 | J27: =SUMIFS('Ikot Sales'!E:E,'Ikot Sales'!A:A,"ARNOLD",'Ikot Sales'!C:C,"September") -> 0 | K27: =SUMIFS('Ikot Sales'!E:E,'Ikot Sales'!A:A,"ARNOLD",'Ikot Sales'!C:C,"October") -> 0 | L27: =SUMIFS('Ikot Sales'!E:E,'Ikot Sales'!A:A,"ARNOLD",'Ikot Sales'!C:C,"November") -> 0 | M27: =SUMIFS('Ikot Sales'!E:E,'Ikot Sales'!A:A,"ARNOLD",'Ikot Sales'!C:C,"December") -> 0 | N27: =SUM(B27:M27) -> 1665395
A28: RAYMART | B28: =SUMIFS('Ikot Sales'!E:E,'Ikot Sales'!A:A,"RAYMART",'Ikot Sales'!C:C,"January") -> 316420 | C28: =SUMIFS('Ikot Sales'!E:E,'Ikot Sales'!A:A,"RAYMART",'Ikot Sales'!C:C,"February") -> 539045 | D28: =SUMIFS('Ikot Sales'!E:E,'Ikot Sales'!A:A,"RAYMART",'Ikot Sales'!C:C,"March") -> 649035 | E28: =SUMIFS('Ikot Sales'!E:E,'Ikot Sales'!A:A,"RAYMART",'Ikot Sales'!C:C,"April") -> 526087 | F28: =SUMIFS('Ikot Sales'!E:E,'Ikot Sales'!A:A,"RAYMART",'Ikot Sales'!C:C,"May") -> 294215 | G28: =SUMIFS('Ikot Sales'!E:E,'Ikot Sales'!A:A,"RAYMART",'Ikot Sales'!C:C,"June") -> 431709 | H28: =SUMIFS('Ikot Sales'!E:E,'Ikot Sales'!A:A,"RAYMART",'Ikot Sales'!C:C,"July") -> 477238 | I28: =SUMIFS('Ikot Sales'!E:E,'Ikot Sales'!A:A,"RAYMART",'Ikot Sales'!C:C,"August") -> 265250 | J28: =SUMIFS('Ikot Sales'!E:E,'Ikot Sales'!A:A,"RAYMART",'Ikot Sales'!C:C,"September") -> 0 | K28: =SUMIFS('Ikot Sales'!E:E,'Ikot Sales'!A:A,"RAYMART",'Ikot Sales'!C:C,"October") -> 0 | L28: =SUMIFS('Ikot Sales'!E:E,'Ikot Sales'!A:A,"RAYMART",'Ikot Sales'!C:C,"November") -> 0 | M28: =SUMIFS('Ikot Sales'!E:E,'Ikot Sales'!A:A,"RAYMART",'Ikot Sales'!C:C,"December") -> 0 | N28: =SUM(B28:M28) -> 3498999
A29: TOTAL | B29: =SUM(B27:B28) -> 316420 | C29: =SUM(C27:C28) -> 876445 | D29: =SUM(D27:D28) -> 693275 | E29: =SUM(E27:E28) -> 651781 | F29: =SUM(F27:F28) -> 646405 | G29: =SUM(G27:G28) -> 846911 | H29: =SUM(H27:H28) -> 799468 | I29: =SUM(I27:I28) -> 333689 | ... M29: =SUM(M27:M28) -> 0 | N29: =SUM(B29:M29) -> 5164394
A31: LOCATION SUMMARY
A32: Location | B32: Trips | C32: Sales | D32: Net Sales | E32: Collection Rate
A33: Cubao/Pasig/Antipolo | B33: =COUNTIF('Ikot Sales'!K:K,"Cubao/Pasig/Antipolo") -> 12 | C33: =SUMIF('Ikot Sales'!K:K,"Cubao/Pasig/Antipolo",'Ikot Sales'!E:E) -> 1120385 | D33: =SUMIF('Ikot Sales'!K:K,"Cubao/Pasig/Antipolo",'Ikot Sales'!M:M) -> 1105072.4 | E33: =IF(C33>0,SUMIF('Ikot Sales'!K:K,"Cubao/Pasig/Antipolo",'Ikot Sales'!H:H)/C33,0) -> 0.83092419
A34: Pangasinan | B34: =COUNTIF('Ikot Sales'!K:K,"Pangasinan") -> 15 | C34: =SUMIF('Ikot Sales'!K:K,"Pangasinan",'Ikot Sales'!E:E) -> 1150514 | D34: =SUMIF('Ikot Sales'!K:K,"Pangasinan",'Ikot Sales'!M:M) -> 1077005.9 | E34: =IF(C34>0,SUMIF('Ikot Sales'!K:K,"Pangasinan",'Ikot Sales'!H:H)/C34,0) -> 0.81726428
A35: Nueva Ecija | B35: =COUNTIF('Ikot Sales'!K:K,"Nueva Ecija") -> 8 | C35: =SUMIF('Ikot Sales'!K:K,"Nueva Ecija",'Ikot Sales'!E:E) -> 638795 | D35: =SUMIF('Ikot Sales'!K:K,"Nueva Ecija",'Ikot Sales'!M:M) -> 612279.73 | E35: =IF(C35>0,SUMIF('Ikot Sales'!K:K,"Nueva Ecija",'Ikot Sales'!H:H)/C35,0) -> 0.85788868
A36: Nasugbo | B36: =COUNTIF('Ikot Sales'!K:K,"Nasugbo") -> 4 | C36: =SUMIF('Ikot Sales'!K:K,"Nasugbo",'Ikot Sales'!E:E) -> 294111 | D36: =SUMIF('Ikot Sales'!K:K,"Nasugbo",'Ikot Sales'!M:M) -> 279586 | E36: =IF(C36>0,SUMIF('Ikot Sales'!K:K,"Nasugbo",'Ikot Sales'!H:H)/C36,0) -> 0.6859655
A37: Lucena | B37: =COUNTIF('Ikot Sales'!K:K,"Lucena") -> 8 | C37: =SUMIF('Ikot Sales'!K:K,"Lucena",'Ikot Sales'!E:E) -> 398847 | D37: =SUMIF('Ikot Sales'!K:K,"Lucena",'Ikot Sales'!M:M) -> 372655 | E37: =IF(C37>0,SUMIF('Ikot Sales'!K:K,"Lucena",'Ikot Sales'!H:H)/C37,0) -> 0.65986456
A38: Batangas | B38: =COUNTIF('Ikot Sales'!K:K,"Batangas") -> 3 | C38: =SUMIF('Ikot Sales'!K:K,"Batangas",'Ikot Sales'!E:E) -> 194805 | D38: =SUMIF('Ikot Sales'!K:K,"Batangas",'Ikot Sales'!M:M) -> 190221.47 | E38: =IF(C38>0,SUMIF('Ikot Sales'!K:K,"Batangas",'Ikot Sales'!H:H)/C38,0) -> 0.33492467
A39: Lipa | B39: =COUNTIF('Ikot Sales'!K:K,"Lipa") -> 1 | C39: =SUMIF('Ikot Sales'!K:K,"Lipa",'Ikot Sales'!E:E) -> 30090 | D39: =SUMIF('Ikot Sales'!K:K,"Lipa",'Ikot Sales'!M:M) -> 25944 | E39: =IF(C39>0,SUMIF('Ikot Sales'!K:K,"Lipa",'Ikot Sales'!H:H)/C39,0) -> 1.0631439
A40: Lipa/Lucena | B40: =COUNTIF('Ikot Sales'!K:K,"Lipa/Lucena") -> 1 | C40: =SUMIF('Ikot Sales'!K:K,"Lipa/Lucena",'Ikot Sales'!E:E) -> 12535 | D40: =SUMIF('Ikot Sales'!K:K,"Lipa/Lucena",'Ikot Sales'!M:M) -> 7071 | E40: =IF(C40>0,SUMIF('Ikot Sales'!K:K,"Lipa/Lucena",'Ikot Sales'!H:H)/C40,0) -> 1.6114878
A41: Pampanga | B41: =COUNTIF('Ikot Sales'!K:K,"Pampanga") -> 5 | C41: =SUMIF('Ikot Sales'!K:K,"Pampanga",'Ikot Sales'!E:E) -> 327875 | D41: =SUMIF('Ikot Sales'!K:K,"Pampanga",'Ikot Sales'!M:M) -> 317038.35 | E41: =IF(C41>0,SUMIF('Ikot Sales'!K:K,"Pampanga",'Ikot Sales'!H:H)/C41,0) -> 0.91354937
A42: Zambales | B42: =COUNTIF('Ikot Sales'!K:K,"Zambales") -> 2 | C42: =SUMIF('Ikot Sales'!K:K,"Zambales",'Ikot Sales'!E:E) -> 240880 | D42: =SUMIF('Ikot Sales'!K:K,"Zambales",'Ikot Sales'!M:M) -> 229540 | E42: =IF(C42>0,SUMIF('Ikot Sales'!K:K,"Zambales",'Ikot Sales'!H:H)/C42,0) -> 0.83846729
A43: Cubao | B43: =COUNTIF('Ikot Sales'!K:K,"Cubao") -> 17 | C43: =SUMIF('Ikot Sales'!K:K,"Cubao",'Ikot Sales'!E:E) -> 755557 | D43: =SUMIF('Ikot Sales'!K:K,"Cubao",'Ikot Sales'!M:M) -> 735373.19 | E43: =IF(C43>0,SUMIF('Ikot Sales'!K:K,"Cubao",'Ikot Sales'!H:H)/C43,0) -> 0.80980654
A44: TOTAL | B44: =COUNTA('Ikot Sales'!K2:K200) -> 76 | C44: =SUM('Ikot Sales'!E2:E200) -> 5164394 | D44: =SUM('Ikot Sales'!M2:M200) -> 4951787.1 | E44: =IF(C44>0,SUM('Ikot Sales'!H2:H200)/C44,0) -> 0.7967961

Sheet Payslips 1-4
A1: COMMISSION PAYSLIP | G1: ✂ | H1: COMMISSION PAYSLIP | O1: ➤ Executive Summary
A2: ISHABELLA AIRCON AND REFRIGERATION PARTS TRADING | H2: ISHABELLA AIRCON AND REFRIGERATION PARTS TRADING
A3: 78 MAIN AVE. SOCORRO CUBAO QUEZON CITY | H3: 78 MAIN AVE. SOCORRO CUBAO QUEZON CITY
A4: ="Commission Period: "&'Executive Summary'!$B$3&" 2026" -> Commission Period: August 2026 | H4: ="Commission Period: "&'Executive Summary'!$B$3&" 2026" -> Commission Period: August 2026
A6: Agent Name | B6: ='Commission Summary'!$A$7 -> ARNOLD ORTIZ | H6: Agent Name | I6: ='Commission Summary'!$A$8 -> JENNIFER DUM-OGAN - ONLINE
A7: Mode | B7: ='Commission Summary'!$B$7 -> direct | D7: Date Issued | E7: =TODAY() -> 46280 | H7: Mode | I7: ='Commission Summary'!$B$8 -> online | K7: Date Issued | L7: =TODAY() -> 46280
A8: Pay Period | B8: ='Executive Summary'!$B$3&" 2026" -> August 2026 | D8: Currency | E8: PHP | H8: Pay Period | I8: ='Executive Summary'!$B$3&" 2026" -> August 2026 | K8: Currency | L8: PHP
A10: EARNINGS AND DEDUCTIONS | H10: EARNINGS AND DEDUCTIONS
A11: Description | D11: Amount | H11: Description | K11: Amount
A12: Paid Gross Sales | D12: ='Commission Summary'!$C$7 -> 113401 | H12: Paid Gross Sales | K12: ='Commission Summary'!$C$8 -> 23556.88
A13: Net Sales (Commission Basis) | D13: ='Commission Summary'!$D$7 -> 26067.4 | H13: Net Sales (Commission Basis) | K13: ='Commission Summary'!$D$8 -> 7491.37
A14: Commission Rate | D14: ='Commission Summary'!$E$7 -> 0.2 | H14: Commission Rate | K14: ='Commission Summary'!$E$8 -> 0.2
A15: Gross Commission | D15: ='Commission Summary'!$F$7 -> 5213.48 | H15: Gross Commission | K15: ='Commission Summary'!$F$8 -> 1498.274
A17: Less: Agent Expense | D17: ='Commission Summary'!$G$7 -> 2454 | H17: Less: Agent Expense | K17: ='Commission Summary'!$G$8 -> 1000
A18: Less: 5% Savings | D18: ='Commission Summary'!$I$7 -> 137.974 | H18: Less: 5% Savings | K18: ='Commission Summary'!$I$8 -> 0
A20: FINAL COMMISSION | D20: ='Commission Summary'!$J$7 -> 2621.506 | H20: FINAL COMMISSION | K20: ='Commission Summary'!$J$8 -> 498.274
A23: Prepared by | D23: Received by | H23: Prepared by | K23: Received by
A26: This payslip updates automatically when the month is changed in Executive Summary. | H26: This payslip updates automatically when the month is changed in Executive Summary.
A27: ✂ CUT | H27: ✂ CUT
A28: COMMISSION PAYSLIP | G28: ✂ | H28: COMMISSION PAYSLIP
A29: ISHABELLA AIRCON AND REFRIGERATION PARTS TRADING | H29: ISHABELLA AIRCON AND REFRIGERATION PARTS TRADING
A30: 78 MAIN AVE. SOCORRO CUBAO QUEZON CITY | H30: 78 MAIN AVE. SOCORRO CUBAO QUEZON CITY
A31: ="Commission Period: "&'Executive Summary'!$B$3&" 2026" -> Commission Period: August 2026 | H31: ="Commission Period: "&'Executive Summary'!$B$3&" 2026" -> Commission Period: August 2026
A33: Agent Name | B33: ='Commission Summary'!$A$9 -> JOVY VILLANUEVA | H33: Agent Name | I33: ='Commission Summary'!$A$10 -> MARIVIC BRILLANTES
A34: Mode | B34: ='Commission Summary'!$B$9 -> direct | D34: Date Issued | E34: =TODAY() -> 46280 | H34: Mode | I34: ='Commission Summary'!$B$10 -> direct | K34: Date Issued | L34: =TODAY() -> 46280
A35: Pay Period | B35: ='Executive Summary'!$B$3&" 2026" -> August 2026 | D35: Currency | E35: PHP | H35: Pay Period | I35: ='Executive Summary'!$B$3&" 2026" -> August 2026 | K35: Currency | L35: PHP
A37: EARNINGS AND DEDUCTIONS | H37: EARNINGS AND DEDUCTIONS
A38: Description | D38: Amount | H38: Description | K38: Amount
A39: Paid Gross Sales | D39: ='Commission Summary'!$C$9 -> 33922 | H39: Paid Gross Sales | K39: ='Commission Summary'!$C$10 -> 0
A40: Net Sales (Commission Basis) | D40: ='Commission Summary'!$D$9 -> 6104.24 | H40: Net Sales (Commission Basis) | K40: ='Commission Summary'!$D$10 -> 0
A41: Commission Rate | D41: ='Commission Summary'!$E$9 -> 0.2 | H41: Commission Rate | K41: ='Commission Summary'!$E$10
A42: Gross Commission | D42: ='Commission Summary'!$F$9 -> 1220.848 | H42: Gross Commission | K42: ='Commission Summary'!$F$10 -> 0
A44: Less: Agent Expense | D44: ='Commission Summary'!$G$9 -> 0 | H44: Less: Agent Expense | K44: ='Commission Summary'!$G$10 -> 0
A45: Less: 5% Savings | D45: ='Commission Summary'!$I$9 -> 61.0424 | H45: Less: 5% Savings | K45: ='Commission Summary'!$I$10 -> 0
A47: FINAL COMMISSION | D47: ='Commission Summary'!$J$9 -> 1159.8056 | H47: FINAL COMMISSION | K47: ='Commission Summary'!$J$10 -> 0
A50: Prepared by | D50: Received by | H50: Prepared by | K50: Received by
A53: This payslip updates automatically when the month is changed in Executive Summary. | H53: This payslip updates automatically when the month is changed in Executive Summary.

Sheet Payslips 5-8
A1: COMMISSION PAYSLIP | G1: ✂ | H1: COMMISSION PAYSLIP | O1: ➤ Executive Summary
A2: ISHABELLA AIRCON AND REFRIGERATION PARTS TRADING | H2: ISHABELLA AIRCON AND REFRIGERATION PARTS TRADING
A3: 78 MAIN AVE. SOCORRO CUBAO QUEZON CITY | H3: 78 MAIN AVE. SOCORRO CUBAO QUEZON CITY
A4: ="Commission Period: "&'Executive Summary'!$B$3&" 2026" -> Commission Period: August 2026 | H4: ="Commission Period: "&'Executive Summary'!$B$3&" 2026" -> Commission Period: August 2026
A6: Agent Name | B6: ='Commission Summary'!$A$11 -> MICHAEL PLAZA | H6: Agent Name | I6: ='Commission Summary'!$A$12 -> MODESTO PAG-ARIGON
A7: Mode | B7: ='Commission Summary'!$B$11 -> direct | D7: Date Issued | E7: =TODAY() -> 46280 | H7: Mode | I7: ='Commission Summary'!$B$12 -> direct | K7: Date Issued | L7: =TODAY() -> 46280
A8: Pay Period | B8: ='Executive Summary'!$B$3&" 2026" -> August 2026 | D8: Currency | E8: PHP | H8: Pay Period | I8: ='Executive Summary'!$B$3&" 2026" -> August 2026 | K8: Currency | L8: PHP
A10: EARNINGS AND DEDUCTIONS | H10: EARNINGS AND DEDUCTIONS
A11: Description | D11: Amount | H11: Description | K11: Amount
A12: Paid Gross Sales | D12: ='Commission Summary'!$C$11 -> 817590.78 | H12: Paid Gross Sales | K12: ='Commission Summary'!$C$12 -> 0
A13: Net Sales (Commission Basis) | D13: ='Commission Summary'!$D$11 -> 223600.76 | H13: Net Sales (Commission Basis) | K13: ='Commission Summary'!$D$12 -> 0
A14: Commission Rate | D14: ='Commission Summary'!$E$11 -> 0.3 | H14: Commission Rate | K14: ='Commission Summary'!$E$12
A15: Gross Commission | D15: ='Commission Summary'!$F$11 -> 67080.228 | H15: Gross Commission | K15: ='Commission Summary'!$F$12 -> 0
A17: Less: Agent Expense | D17: ='Commission Summary'!$G$11 -> 0 | H17: Less: Agent Expense | K17: ='Commission Summary'!$G$12 -> 0
A18: Less: 5% Savings | D18: ='Commission Summary'!$I$11 -> 3354.0114 | H18: Less: 5% Savings | K18: ='Commission Summary'!$I$12 -> 0
A20: FINAL COMMISSION | D20: ='Commission Summary'!$J$11 -> 63726.217 | H20: FINAL COMMISSION | K20: ='Commission Summary'!$J$12 -> 0
A23: Prepared by | D23: Received by | H23: Prepared by | K23: Received by
A26: This payslip updates automatically when the month is changed in Executive Summary. | H26: This payslip updates automatically when the month is changed in Executive Summary.
A27: ✂ CUT | H27: ✂ CUT
A28: COMMISSION PAYSLIP | G28: ✂ | H28: COMMISSION PAYSLIP
A29: ISHABELLA AIRCON AND REFRIGERATION PARTS TRADING | H29: ISHABELLA AIRCON AND REFRIGERATION PARTS TRADING
A30: 78 MAIN AVE. SOCORRO CUBAO QUEZON CITY | H30: 78 MAIN AVE. SOCORRO CUBAO QUEZON CITY
A31: ="Commission Period: "&'Executive Summary'!$B$3&" 2026" -> Commission Period: August 2026 | H31: ="Commission Period: "&'Executive Summary'!$B$3&" 2026" -> Commission Period: August 2026
A33: Agent Name | B33: ='Commission Summary'!$A$13 -> MODESTO PAG-ARIGON - ONLINE | H33: Agent Name | I33: ='Commission Summary'!$A$14 -> RAMONITO VILLANUEVA - ONLINE
A34: Mode | B34: ='Commission Summary'!$B$13 -> online | D34: Date Issued | E34: =TODAY() -> 46280 | H34: Mode | I34: ='Commission Summary'!$B$14 -> online | K34: Date Issued | L34: =TODAY() -> 46280
A35: Pay Period | B35: ='Executive Summary'!$B$3&" 2026" -> August 2026 | D35: Currency | E35: PHP | H35: Pay Period | I35: ='Executive Summary'!$B$3&" 2026" -> August 2026 | K35: Currency | L35: PHP
A37: EARNINGS AND DEDUCTIONS | H37: EARNINGS AND DEDUCTIONS
A38: Description | D38: Amount | H38: Description | K38: Amount
A39: Paid Gross Sales | D39: ='Commission Summary'!$C$13 -> 48611.93 | H39: Paid Gross Sales | K39: ='Commission Summary'!$C$14 -> 44225.99
A40: Net Sales (Commission Basis) | D40: ='Commission Summary'!$D$13 -> 15357.74 | H40: Net Sales (Commission Basis) | K40: ='Commission Summary'!$D$14 -> 14231.88
A41: Commission Rate | D41: ='Commission Summary'!$E$13 -> 0.2 | H41: Commission Rate | K41: ='Commission Summary'!$E$14 -> 0.2
A42: Gross Commission | D42: ='Commission Summary'!$F$13 -> 3071.548 | H42: Gross Commission | K42: ='Commission Summary'!$F$14 -> 2846.376
A44: Less: Agent Expense | D44: ='Commission Summary'!$G$13 -> 1000 | H44: Less: Agent Expense | K44: ='Commission Summary'!$G$14 -> 1000
A45: Less: 5% Savings | D45: ='Commission Summary'!$I$13 -> 0 | H45: Less: 5% Savings | K45: ='Commission Summary'!$I$14 -> 0
A47: FINAL COMMISSION | D47: ='Commission Summary'!$J$13 -> 2071.548 | H47: FINAL COMMISSION | K47: ='Commission Summary'!$J$14 -> 1846.376
A50: Prepared by | D50: Received by | H50: Prepared by | K50: Received by
A53: This payslip updates automatically when the month is changed in Executive Summary. | H53: This payslip updates automatically when the month is changed in Executive Summary.

Sheet Payslips 9-10
A1: COMMISSION PAYSLIP | G1: ✂ | H1: COMMISSION PAYSLIP | O1: ➤ Executive Summary
A2: ISHABELLA AIRCON AND REFRIGERATION PARTS TRADING | H2: ISHABELLA AIRCON AND REFRIGERATION PARTS TRADING
A3: 78 MAIN AVE. SOCORRO CUBAO QUEZON CITY | H3: 78 MAIN AVE. SOCORRO CUBAO QUEZON CITY
A4: ="Commission Period: "&'Executive Summary'!$B$3&" 2026" -> Commission Period: August 2026 | H4: ="Commission Period: "&'Executive Summary'!$B$3&" 2026" -> Commission Period: August 2026
A6: Agent Name | B6: ='Commission Summary'!$A$15 -> ROCKY DELA PENA | H6: Agent Name | I6: ='Commission Summary'!$A$16 -> ROD SANTIAGO
A7: Mode | B7: ='Commission Summary'!$B$15 -> direct | D7: Date Issued | E7: =TODAY() -> 46280 | H7: Mode | I7: ='Commission Summary'!$B$16 -> direct | K7: Date Issued | L7: =TODAY() -> 46280
A8: Pay Period | B8: ='Executive Summary'!$B$3&" 2026" -> August 2026 | D8: Currency | E8: PHP | H8: Pay Period | I8: ='Executive Summary'!$B$3&" 2026" -> August 2026 | K8: Currency | L8: PHP
A10: EARNINGS AND DEDUCTIONS | H10: EARNINGS AND DEDUCTIONS
A11: Description | D11: Amount | H11: Description | K11: Amount
A12: Paid Gross Sales | D12: ='Commission Summary'!$C$15 -> 45600 | H12: Paid Gross Sales | K12: ='Commission Summary'!$C$16 -> 1354410
A13: Net Sales (Commission Basis) | D13: ='Commission Summary'!$D$15 -> 22038.31 | H13: Net Sales (Commission Basis) | K13: ='Commission Summary'!$D$16 -> 224652.49
A14: Commission Rate | D14: ='Commission Summary'!$E$15 -> 0.2 | H14: Commission Rate | K14: ='Commission Summary'!$E$16 -> 0.3
A15: Gross Commission | D15: ='Commission Summary'!$F$15 -> 4407.662 | H15: Gross Commission | K15: ='Commission Summary'!$F$16 -> 67395.747
A17: Less: Agent Expense | D17: ='Commission Summary'!$G$15 -> 0 | H17: Less: Agent Expense | K17: ='Commission Summary'!$G$16 -> 0
A18: Less: 5% Savings | D18: ='Commission Summary'!$I$15 -> 220.3831 | H18: Less: 5% Savings | K18: ='Commission Summary'!$I$16 -> 3369.7873
A20: FINAL COMMISSION | D20: ='Commission Summary'!$J$15 -> 4187.2789 | H20: FINAL COMMISSION | K20: ='Commission Summary'!$J$16 -> 64025.96
A23: Prepared by | D23: Received by | H23: Prepared by | K23: Received by
A26: This payslip updates automatically when the month is changed in Executive Summary. | H26: This payslip updates automatically when the month is changed in Executive Summary.

Sheet %Comm
D1: ➤ Executive Summary
B4: Agent | C4: Mode | D4: 199999 | E4: 200001
B5: 1. ARNOLD ORTIZ | C5: =IF(B5="online",Agent_Online_Rate,Agent_Base_Rate) -> 0.2 | D5: =IF(B5="online",Agent_Online_Rate,Agent_High_Rate) -> 0.3 | E5: 0.3 | F5: commission based on net sales
B6: 2. JENNIFER DUM-OGAN - ONLINE | C6: =IF(B6="online",Agent_Online_Rate,Agent_Base_Rate) -> 0.2 | D6: =IF(B6="online",Agent_Online_Rate,Agent_High_Rate) -> 0.3 | E6: 0.2 | F6: commission based on net sales
B7: 3. JOVY VILLANUEVA | C7: =IF(B7="online",Agent_Online_Rate,Agent_Base_Rate) -> 0.2 | D7: =IF(B7="online",Agent_Online_Rate,Agent_High_Rate) -> 0.3 | E7: 0.3 | F7: commission based on net sales
B8: 4. MARIVIC BRILLANTES | C8: =IF(B8="online",Agent_Online_Rate,Agent_Base_Rate) -> 0.2 | D8: =IF(B8="online",Agent_Online_Rate,Agent_High_Rate) -> 0.3 | E8: 0.3 | F8: commission based on net sales
B9: 5. MICHAEL PLAZA | C9: =IF(B9="online",Agent_Online_Rate,Agent_Base_Rate) -> 0.2 | D9: =IF(B9="online",Agent_Online_Rate,Agent_High_Rate) -> 0.3 | E9: 0.3 | F9: commission based on net sales
B10: 6. MODESTO PAG-ARIGON | C10: =IF(B10="online",Agent_Online_Rate,Agent_Base_Rate) -> 0.2 | D10: =IF(B10="online",Agent_Online_Rate,Agent_High_Rate) -> 0.3 | E10: 0.3 | F10: commission based on net sales
B11: 7. MODESTO PAG-ARIGON - ONLINE | C11: =IF(B11="online",Agent_Online_Rate,Agent_Base_Rate) -> 0.2 | D11: =IF(B11="online",Agent_Online_Rate,Agent_High_Rate) -> 0.3 | E11: 0.2 | F11: commission based on net sales
B12: 8. RAMONITO VILLANUEVA - ONLINE | C12: =IF(B12="online",Agent_Online_Rate,Agent_Base_Rate) -> 0.2 | D12: =IF(B12="online",Agent_Online_Rate,Agent_High_Rate) -> 0.3 | E12: 0.2 | F12: commission based on net sales
B13: 9. ROCKY DELA PENA | C13: =IF(B13="online",Agent_Online_Rate,Agent_Base_Rate) -> 0.2 | D13: =IF(B13="online",Agent_Online_Rate,Agent_High_Rate) -> 0.3 | E13: 0.3 | F13: commission based on net sales
B14: 10. ROD SANTIAGO | C14: =IF(B14="online",Agent_Online_Rate,Agent_Base_Rate) -> 0.2 | D14: =IF(B14="online",Agent_Online_Rate,Agent_High_Rate) -> 0.3 | E14: 0.3 | F14: commission based on net sales
A17: Manager (Bert) | B17: Category-specific rates in the selected table below | D17: Basis: category gross less allocated monthly expenses and agent commission | F17: Allocation pool = monthly expenses + total agent commission; distributed by gross-sales ratio
A18: Sales Staff | B18: Command Center: store threshold and staff rate | D18: Basis: Store gross less allocated expense
A19: Raymart | B19: Command Center: Ikot rate | D19: Basis: Ikot Sales less Ikot Expenses | F19: less expense
A20: Purchasing | B20: Command Center: Back Office threshold and pool rate | D20: Shiena | F20: Shiena
A21: Admin | B21: Command Center: Back Office threshold and pool rate | D21: Riza, Glydal | F21: Riza, glydal
A22: Logistics | B22: Command Center: Back Office threshold and pool rate | D22: Vincent, Jojo, Mark | F22: vincent, Jojo, mark
A23: Marketing | B23: Command Center: Back Office threshold and pool rate | D23: Rod | F23: Rod
A24: Tithes | B24: Command Center: tithes rate | D24: True bottomline after BO commission
A25: Offering | B25: Command Center: offering multiplier | D25: Applied to calculated tithes
B30: Category | C30: Manager commission
B31: BATTERY | C31: 0.005
B32: CAR AIRCON | C32: 0.01
B33: INSTALLATION MATERIALS | C33: 0.01
B34: REFRIGERANTS | C34: 0.01
B35: PV PANELS | C35: 0.005
B36: GENERAL | C36: 0.01
B37: AIRCON UNIT | C37: 0.005
B38: TOOLS | C38: 0.01
B39: ELECTRICAL | C39: 0.01
B40: AIRCON PARTS | C40: 0.01
B41: INVERTER | C41: 0.005
B42: CONSTRUCTION | C42: 0.01

Sheet Agent Savings
A1: ➤ Executive Summary
A4: Agent | B4: YTD | C4: January | D4: February | E4: March | F4: April | G4: May | H4: June | I4: July | J4: August | K4: September | L4: October | M4: November | N4: December
A5: ARNOLD ORTIZ | B5: =SUM(C5:N5) -> 137.974 | J5: ='Commission Summary'!I7 -> 137.974
A6: JENNIFER DUM-OGAN - ONLINE | B6: =SUM(C6:N6) -> 0 | J6: ='Commission Summary'!I8 -> 0
A7: JOVY VILLANUEVA | B7: =SUM(C7:N7) -> 61.0424 | J7: ='Commission Summary'!I9 -> 61.0424
A8: MARIVIC BRILLANTES | B8: =SUM(C8:N8) -> 0 | J8: ='Commission Summary'!I10 -> 0
A9: MICHAEL PLAZA | B9: =SUM(C9:N9) -> 3354.0114 | J9: ='Commission Summary'!I11 -> 3354.0114
A10: MODESTO PAG-ARIGON | B10: =SUM(C10:N10) -> 0 | J10: ='Commission Summary'!I12 -> 0
A11: MODESTO PAG-ARIGON - ONLINE | B11: =SUM(C11:N11) -> 0 | J11: ='Commission Summary'!I13 -> 0
A12: RAMONITO VILLANUEVA - ONLINE | B12: =SUM(C12:N12) -> 0 | J12: ='Commission Summary'!I14 -> 0
A13: ROCKY DELA PENA | B13: =SUM(C13:N13) -> 220.3831 | J13: ='Commission Summary'!I15 -> 220.3831
A14: ROD SANTIAGO | B14: =SUM(C14:N14) -> 3369.7873 | J14: ='Commission Summary'!I16 -> 3369.7873

Sheet Agent Expense
A1: ➤ Executive Summary
A4: Agent | B4: January | C4: February | D4: March | E4: April | F4: May | G4: June | H4: July | I4: August | J4: September | K4: October | L4: November | M4: December
A5: ARNOLD ORTIZ | I5: 2454
A6: JENNIFER DUM-OGAN - ONLINE | I6: 1000
A7: JOVY VILLANUEVA | I7: 0
A8: MARIVIC BRILLANTES | I8: 0
A9: MICHAEL PLAZA | I9: 0
A10: MODESTO PAG-ARIGON | I10: 0
A11: MODESTO PAG-ARIGON - ONLINE | I11: 1000
A12: RAMONITO VILLANUEVA - ONLINE | I12: 1000
A13: ROCKY DELA PENA | I13: 0
A14: ROD SANTIAGO | I14: 0
